Workbook
Name L_Nature: 'Paramètres'!$D$70:$D$77
Name L_Notes: 'Paramètres'!$B$70:$B$74
Name L_OuiNon: 'Paramètres'!$A$70:$A$71
Name L_Periodicite: 'Paramètres'!$C$70:$C$72
Name L_QualAch: 'Paramètres'!$E$70:$E$72
Name P_Ancre_C: 'Paramètres'!$C$63
Name P_Ancre_F: 'Paramètres'!$C$61
Name P_Ancre_TF: 'Paramètres'!$C$60
Name P_Ancre_V: 'Paramètres'!$C$62
Name P_C10: 'Paramètres'!$J$55
Name P_C13: 'Paramètres'!$J$56
Name P_C1: 'Paramètres'!$J$48
Name P_C3: 'Paramètres'!$J$49
Name P_C4: 'Paramètres'!$J$50
Name P_C6: 'Paramètres'!$J$51
Name P_C7: 'Paramètres'!$J$52
Name P_C8: 'Paramètres'!$J$53
Name P_C9: 'Paramètres'!$J$54
Name P_ConvLib: 'Paramètres'!$J$6:$J$15
Name P_ConvNote: 'Paramètres'!$I$6:$I$15
Name P_ConvOrient: 'Paramètres'!$K$6:$K$15
Name P_ConvSeuil: 'Paramètres'!$H$6:$H$15
Name P_COUV: 'Paramètres'!$J$57
Name P_Crit: 'Paramètres'!$C$6:$C$9
Name P_DomCodes: 'Paramètres'!$A$37:$A$45
Name P_DomLib: 'Paramètres'!$B$37:$B$45
Name P_Fav: 'Paramètres'!$E$6:$E$9
Name P_InfoInsuff: 'Paramètres'!$C$64
Name P_L_CAPEX: 'Paramètres'!$J$42
Name P_L_EXPO: 'Paramètres'!$J$43
Name P_L_NBCP: 'Paramètres'!$J$44
Name P_N3_F: 'Paramètres'!$J$46
Name P_N3_TF: 'Paramètres'!$J$45
Name P_N3_V: 'Paramètres'!$J$47
Name P_PhaseCodes: 'Paramètres'!$A$30:$A$32
Name P_PhaseLib: 'Paramètres'!$B$30:$B$32
Name P_PhaseMaj: 'Paramètres'!$C$30:$C$32
Name P_PlafCode: 'Paramètres'!$H$20:$H$34
Name P_PlafFait: 'Paramètres'!$I$20:$I$34
Name P_PlafNiv: 'Paramètres'!$J$20:$J$34
Name P_PoidsDom: 'Paramètres'!$C$37:$E$45
Name P_PoidsHdr: 'Paramètres'!$C$36:$E$36
Name P_PoidsN: 'Paramètres'!$C$50:$C$55
Name P_Regimes: 'Paramètres'!$A$6:$A$9
Name P_RegLib: 'Paramètres'!$B$6:$B$9
Name P_S_CAPEX: 'Paramètres'!$J$39
Name P_S_DUREE: 'Paramètres'!$J$41
Name P_S_EXPO: 'Paramètres'!$J$40
Name P_SCCle: 'Paramètres'!$H$62:$H$86
Name P_SCPoids: 'Paramètres'!$J$62:$J$86
Name P_SecCodes: 'Paramètres'!$A$14:$A$25
Name P_SecDelta: 'Paramètres'!$C$14:$C$25
Name P_SecLib: 'Paramètres'!$B$14:$B$25
Name P_Vig: 'Paramètres'!$D$6:$D$9

Sheet Accueil
B2: Outil de scoring Project Finance — modèle V8
B3: Version 2 de l'outil · notes calculées par formules, macros pour créer, contrôler, imprimer et tracer.
B5: SCORER UN PROJET EN 5 ÉTAPES
B6: 1. Cliquez « Nouveau dossier » (à droite) et donnez un nom court à l'onglet, par exemple PORT-NADOR.
B7: 2. Remplissez les cellules ORANGE : ce sont les saisies obligatoires encore vides. Elles deviennent jaunes une fois remplies. Sélectionnez une cellule pour lire l'aide qui s'affiche ; les listes déroulantes évitent les fautes de frappe.
B8: 3. Suivez la ligne « À SAISIR » en haut du dossier : elle compte ce qui manque et donne un lien vers la prochaine cellule à remplir. La barre « Aller à la section » permet de circuler dans le dossier.
B9: 4. Lisez le tableau de bord : note approuvée, plafonds et verrous actifs, statut. La note se recalcule à chaque saisie.
B10: 5. Cliquez « Contrôler la saisie », puis « Fiche comité » pour imprimer la page de synthèse ou l'exporter en PDF.
B12: LÉGENDE
B13: Saisie | C13: Saisie obligatoire manquante | D13: Calcul | E13: Note ≥ 8 | F13: Note 6 ou 7 — Vigilance | G13: Note ≤ 5
B14: Les cellules de calcul sont protégées (sans mot de passe) pour éviter d'écraser une formule par erreur. Pour modifier la structure : onglet Révision › Ôter la protection de la feuille.
B16: VOS DOSSIERS — cliquez sur un nom pour ouvrir le dossier
B17: Onglet | C17: Intitulé | D17: Phase | E17: Note approuvée | F17: Statut | G17: Saisies manquantes
B18: =IF('Synthèse'!$B$4="","",HYPERLINK("#'"&'Synthèse'!$B$4&"'!A1",'Synthèse'!$B$4)) -> 0 | C18: =IF('Synthèse'!$B$4="","",'Synthèse'!$B$5) -> 0 | D18: =IF('Synthèse'!$B$4="","",'Synthèse'!$B$8) -> 0 | E18: =IF('Synthèse'!$B$4="","",'Synthèse'!$B$20) -> 0 | F18: =IF('Synthèse'!$B$4="","",'Synthèse'!$B$21) -> 0 | G18: =IF('Synthèse'!$B$4="","",'Synthèse'!$B$22) -> 0
B19: =IF('Synthèse'!$C$4="","",HYPERLINK("#'"&'Synthèse'!$C$4&"'!A1",'Synthèse'!$C$4)) -> 0 | C19: =IF('Synthèse'!$C$4="","",'Synthèse'!$C$5) -> 0 | D19: =IF('Synthèse'!$C$4="","",'Synthèse'!$C$8) -> 0 | E19: =IF('Synthèse'!$C$4="","",'Synthèse'!$C$20) -> 0 | F19: =IF('Synthèse'!$C$4="","",'Synthèse'!$C$21) -> 0 | G19: =IF('Synthèse'!$C$4="","",'Synthèse'!$C$22) -> 0
B20: =IF('Synthèse'!$D$4="","",HYPERLINK("#'"&'Synthèse'!$D$4&"'!A1",'Synthèse'!$D$4)) -> 0 | C20: =IF('Synthèse'!$D$4="","",'Synthèse'!$D$5) -> 0 | D20: =IF('Synthèse'!$D$4="","",'Synthèse'!$D$8) -> 0 | E20: =IF('Synthèse'!$D$4="","",'Synthèse'!$D$20) -> 0 | F20: =IF('Synthèse'!$D$4="","",'Synthèse'!$D$21) -> 0 | G20: =IF('Synthèse'!$D$4="","",'Synthèse'!$D$22) -> 0
B21: =IF('Synthèse'!$E$4="","",HYPERLINK("#'"&'Synthèse'!$E$4&"'!A1",'Synthèse'!$E$4)) -> 0 | C21: =IF('Synthèse'!$E$4="","",'Synthèse'!$E$5) -> 0 | D21: =IF('Synthèse'!$E$4="","",'Synthèse'!$E$8) -> 0 | E21: =IF('Synthèse'!$E$4="","",'Synthèse'!$E$20) -> 0 | F21: =IF('Synthèse'!$E$4="","",'Synthèse'!$E$21) -> 0 | G21: =IF('Synthèse'!$E$4="","",'Synthèse'!$E$22) -> 0
B22: =IF('Synthèse'!$F$4="","",HYPERLINK("#'"&'Synthèse'!$F$4&"'!A1",'Synthèse'!$F$4)) -> 0 | C22: =IF('Synthèse'!$F$4="","",'Synthèse'!$F$5) -> 0 | D22: =IF('Synthèse'!$F$4="","",'Synthèse'!$F$8) -> 0 | E22: =IF('Synthèse'!$F$4="","",'Synthèse'!$F$20) -> 0 | F22: =IF('Synthèse'!$F$4="","",'Synthèse'!$F$21) -> 0 | G22: =IF('Synthèse'!$F$4="","",'Synthèse'!$F$22) -> 0
B23: =IF('Synthèse'!$G$4="","",HYPERLINK("#'"&'Synthèse'!$G$4&"'!A1",'Synthèse'!$G$4)) -> 0 | C23: =IF('Synthèse'!$G$4="","",'Synthèse'!$G$5) -> 0 | D23: =IF('Synthèse'!$G$4="","",'Synthèse'!$G$8) -> 0 | E23: =IF('Synthèse'!$G$4="","",'Synthèse'!$G$20) -> 0 | F23: =IF('Synthèse'!$G$4="","",'Synthèse'!$G$21) -> 0 | G23: =IF('Synthèse'!$G$4="","",'Synthèse'!$G$22) -> 0
B24: =IF('Synthèse'!$H$4="","",HYPERLINK("#'"&'Synthèse'!$H$4&"'!A1",'Synthèse'!$H$4)) -> 0 | C24: =IF('Synthèse'!$H$4="","",'Synthèse'!$H$5) -> 0 | D24: =IF('Synthèse'!$H$4="","",'Synthèse'!$H$8) -> 0 | E24: =IF('Synthèse'!$H$4="","",'Synthèse'!$H$20) -> 0 | F24: =IF('Synthèse'!$H$4="","",'Synthèse'!$H$21) -> 0 | G24: =IF('Synthèse'!$H$4="","",'Synthèse'!$H$22) -> 0
B25: =IF('Synthèse'!$I$4="","",HYPERLINK("#'"&'Synthèse'!$I$4&"'!A1",'Synthèse'!$I$4)) -> 0 | C25: =IF('Synthèse'!$I$4="","",'Synthèse'!$I$5) -> 0 | D25: =IF('Synthèse'!$I$4="","",'Synthèse'!$I$8) -> 0 | E25: =IF('Synthèse'!$I$4="","",'Synthèse'!$I$20) -> 0 | F25: =IF('Synthèse'!$I$4="","",'Synthèse'!$I$21) -> 0 | G25: =IF('Synthèse'!$I$4="","",'Synthèse'!$I$22) -> 0
B26: =IF('Synthèse'!$J$4="","",HYPERLINK("#'"&'Synthèse'!$J$4&"'!A1",'Synthèse'!$J$4)) -> 0 | C26: =IF('Synthèse'!$J$4="","",'Synthèse'!$J$5) -> 0 | D26: =IF('Synthèse'!$J$4="","",'Synthèse'!$J$8) -> 0 | E26: =IF('Synthèse'!$J$4="","",'Synthèse'!$J$20) -> 0 | F26: =IF('Synthèse'!$J$4="","",'Synthèse'!$J$21) -> 0 | G26: =IF('Synthèse'!$J$4="","",'Synthèse'!$J$22) -> 0
B27: =IF('Synthèse'!$K$4="","",HYPERLINK("#'"&'Synthèse'!$K$4&"'!A1",'Synthèse'!$K$4)) -> 0 | C27: =IF('Synthèse'!$K$4="","",'Synthèse'!$K$5) -> 0 | D27: =IF('Synthèse'!$K$4="","",'Synthèse'!$K$8) -> 0 | E27: =IF('Synthèse'!$K$4="","",'Synthèse'!$K$20) -> 0 | F27: =IF('Synthèse'!$K$4="","",'Synthèse'!$K$21) -> 0 | G27: =IF('Synthèse'!$K$4="","",'Synthèse'!$K$22) -> 0
B28: =IF('Synthèse'!$L$4="","",HYPERLINK("#'"&'Synthèse'!$L$4&"'!A1",'Synthèse'!$L$4)) -> 0 | C28: =IF('Synthèse'!$L$4="","",'Synthèse'!$L$5) -> 0 | D28: =IF('Synthèse'!$L$4="","",'Synthèse'!$L$8) -> 0 | E28: =IF('Synthèse'!$L$4="","",'Synthèse'!$L$20) -> 0 | F28: =IF('Synthèse'!$L$4="","",'Synthèse'!$L$21) -> 0 | G28: =IF('Synthèse'!$L$4="","",'Synthèse'!$L$22) -> 0
B29: =IF('Synthèse'!$M$4="","",HYPERLINK("#'"&'Synthèse'!$M$4&"'!A1",'Synthèse'!$M$4)) -> 0 | C29: =IF('Synthèse'!$M$4="","",'Synthèse'!$M$5) -> 0 | D29: =IF('Synthèse'!$M$4="","",'Synthèse'!$M$8) -> 0 | E29: =IF('Synthèse'!$M$4="","",'Synthèse'!$M$20) -> 0 | F29: =IF('Synthèse'!$M$4="","",'Synthèse'!$M$21) -> 0 | G29: =IF('Synthèse'!$M$4="","",'Synthèse'!$M$22) -> 0
B30: =IF('Synthèse'!$N$4="","",HYPERLINK("#'"&'Synthèse'!$N$4&"'!A1",'Synthèse'!$N$4)) -> 0 | C30: =IF('Synthèse'!$N$4="","",'Synthèse'!$N$5) -> 0 | D30: =IF('Synthèse'!$N$4="","",'Synthèse'!$N$8) -> 0 | E30: =IF('Synthèse'!$N$4="","",'Synthèse'!$N$20) -> 0 | F30: =IF('Synthèse'!$N$4="","",'Synthèse'!$N$21) -> 0 | G30: =IF('Synthèse'!$N$4="","",'Synthèse'!$N$22) -> 0
B31: =IF('Synthèse'!$O$4="","",HYPERLINK("#'"&'Synthèse'!$O$4&"'!A1",'Synthèse'!$O$4)) -> 0 | C31: =IF('Synthèse'!$O$4="","",'Synthèse'!$O$5) -> 0 | D31: =IF('Synthèse'!$O$4="","",'Synthèse'!$O$8) -> 0 | E31: =IF('Synthèse'!$O$4="","",'Synthèse'!$O$20) -> 0 | F31: =IF('Synthèse'!$O$4="","",'Synthèse'!$O$21) -> 0 | G31: =IF('Synthèse'!$O$4="","",'Synthèse'!$O$22) -> 0
B32: =IF('Synthèse'!$P$4="","",HYPERLINK("#'"&'Synthèse'!$P$4&"'!A1",'Synthèse'!$P$4)) -> 0 | C32: =IF('Synthèse'!$P$4="","",'Synthèse'!$P$5) -> 0 | D32: =IF('Synthèse'!$P$4="","",'Synthèse'!$P$8) -> 0 | E32: =IF('Synthèse'!$P$4="","",'Synthèse'!$P$20) -> 0 | F32: =IF('Synthèse'!$P$4="","",'Synthèse'!$P$21) -> 0 | G32: =IF('Synthèse'!$P$4="","",'Synthèse'!$P$22) -> 0
B33: =IF('Synthèse'!$Q$4="","",HYPERLINK("#'"&'Synthèse'!$Q$4&"'!A1",'Synthèse'!$Q$4)) -> 0 | C33: =IF('Synthèse'!$Q$4="","",'Synthèse'!$Q$5) -> 0 | D33: =IF('Synthèse'!$Q$4="","",'Synthèse'!$Q$8) -> 0 | E33: =IF('Synthèse'!$Q$4="","",'Synthèse'!$Q$20) -> 0 | F33: =IF('Synthèse'!$Q$4="","",'Synthèse'!$Q$21) -> 0 | G33: =IF('Synthèse'!$Q$4="","",'Synthèse'!$Q$22) -> 0
B34: =IF('Synthèse'!$R$4="","",HYPERLINK("#'"&'Synthèse'!$R$4&"'!A1",'Synthèse'!$R$4)) -> 0 | C34: =IF('Synthèse'!$R$4="","",'Synthèse'!$R$5) -> 0 | D34: =IF('Synthèse'!$R$4="","",'Synthèse'!$R$8) -> 0 | E34: =IF('Synthèse'!$R$4="","",'Synthèse'!$R$20) -> 0 | F34: =IF('Synthèse'!$R$4="","",'Synthèse'!$R$21) -> 0 | G34: =IF('Synthèse'!$R$4="","",'Synthèse'!$R$22) -> 0
B35: =IF('Synthèse'!$S$4="","",HYPERLINK("#'"&'Synthèse'!$S$4&"'!A1",'Synthèse'!$S$4)) -> 0 | C35: =IF('Synthèse'!$S$4="","",'Synthèse'!$S$5) -> 0 | D35: =IF('Synthèse'!$S$4="","",'Synthèse'!$S$8) -> 0 | E35: =IF('Synthèse'!$S$4="","",'Synthèse'!$S$20) -> 0 | F35: =IF('Synthèse'!$S$4="","",'Synthèse'!$S$21) -> 0 | G35: =IF('Synthèse'!$S$4="","",'Synthèse'!$S$22) -> 0
B36: =IF('Synthèse'!$T$4="","",HYPERLINK("#'"&'Synthèse'!$T$4&"'!A1",'Synthèse'!$T$4)) -> 0 | C36: =IF('Synthèse'!$T$4="","",'Synthèse'!$T$5) -> 0 | D36: =IF('Synthèse'!$T$4="","",'Synthèse'!$T$8) -> 0 | E36: =IF('Synthèse'!$T$4="","",'Synthèse'!$T$20) -> 0 | F36: =IF('Synthèse'!$T$4="","",'Synthèse'!$T$21) -> 0 | G36: =IF('Synthèse'!$T$4="","",'Synthèse'!$T$22) -> 0
B37: =IF('Synthèse'!$U$4="","",HYPERLINK("#'"&'Synthèse'!$U$4&"'!A1",'Synthèse'!$U$4)) -> 0 | C37: =IF('Synthèse'!$U$4="","",'Synthèse'!$U$5) -> 0 | D37: =IF('Synthèse'!$U$4="","",'Synthèse'!$U$8) -> 0 | E37: =IF('Synthèse'!$U$4="","",'Synthèse'!$U$20) -> 0 | F37: =IF('Synthèse'!$U$4="","",'Synthèse'!$U$21) -> 0 | G37: =IF('Synthèse'!$U$4="","",'Synthèse'!$U$22) -> 0
B38: =IF('Synthèse'!$V$4="","",HYPERLINK("#'"&'Synthèse'!$V$4&"'!A1",'Synthèse'!$V$4)) -> 0 | C38: =IF('Synthèse'!$V$4="","",'Synthèse'!$V$5) -> 0 | D38: =IF('Synthèse'!$V$4="","",'Synthèse'!$V$8) -> 0 | E38: =IF('Synthèse'!$V$4="","",'Synthèse'!$V$20) -> 0 | F38: =IF('Synthèse'!$V$4="","",'Synthèse'!$V$21) -> 0 | G38: =IF('Synthèse'!$V$4="","",'Synthèse'!$V$22) -> 0
B39: =IF('Synthèse'!$W$4="","",HYPERLINK("#'"&'Synthèse'!$W$4&"'!A1",'Synthèse'!$W$4)) -> 0 | C39: =IF('Synthèse'!$W$4="","",'Synthèse'!$W$5) -> 0 | D39: =IF('Synthèse'!$W$4="","",'Synthèse'!$W$8) -> 0 | E39: =IF('Synthèse'!$W$4="","",'Synthèse'!$W$20) -> 0 | F39: =IF('Synthèse'!$W$4="","",'Synthèse'!$W$21) -> 0 | G39: =IF('Synthèse'!$W$4="","",'Synthèse'!$W$22) -> 0
B40: =IF('Synthèse'!$X$4="","",HYPERLINK("#'"&'Synthèse'!$X$4&"'!A1",'Synthèse'!$X$4)) -> 0 | C40: =IF('Synthèse'!$X$4="","",'Synthèse'!$X$5) -> 0 | D40: =IF('Synthèse'!$X$4="","",'Synthèse'!$X$8) -> 0 | E40: =IF('Synthèse'!$X$4="","",'Synthèse'!$X$20) -> 0 | F40: =IF('Synthèse'!$X$4="","",'Synthèse'!$X$21) -> 0 | G40: =IF('Synthèse'!$X$4="","",'Synthèse'!$X$22) -> 0
B42: BON À SAVOIR
B43: Les six dossiers fournis (C1 à C5) sont FICTIFS et pédagogiques. Les seuils, poids et plafonds de l'onglet Paramètres sont des paramètres CANDIDATS, non approuvés par le Comité de validation : ne pas les utiliser en production avant validation.
B44: Macros : activez-les à l'ouverture (bandeau « Activer le contenu »). Sans macros, tout se calcule quand même ; seuls les boutons sont inactifs. Pour créer un dossier sans macros : clic droit sur un onglet › Afficher › Modèle, puis clic droit sur Modèle › Déplacer ou copier › Créer une copie ; renommez la copie et tapez son nom en ligne 4 de la Synthèse.
B45: Automatique : seuils DSCR (régime + secteur + phase), DSCR par échéance et stressé, N1 à N3, plafonds C1 à C15, verrous B3 et B7, régime de proportionnalité S / M / L avec escalade, poids des domaines selon la phase.
B46: Onglet Diagnostic : anomalies du classeur d'origine et corrections de la version 2. Onglet Journal : trace des créations, contrôles, exports et changements de routage.

Sheet Synthèse
A1: Synthèse des dossiers
A2: Une colonne par onglet de dossier, lue en direct. Les dossiers créés par « Nouveau dossier » sont ajoutés automatiquement ; sans macros, tapez le nom de l'onglet en ligne 4.
A4: Onglet | B4: C1 | C4: C2 | D4: C3 | E4: C4A | F4: C4B | G4: C5
A5: Intitulé du dossier | B5: =IF(B$4="","",IFERROR(INDIRECT("'"&B$4&"'!"&$Z5),"")) -> 0 | C5: =IF(C$4="","",IFERROR(INDIRECT("'"&C$4&"'!"&$Z5),"")) -> 0 | D5: =IF(D$4="","",IFERROR(INDIRECT("'"&D$4&"'!"&$Z5),"")) -> 0 | E5: =IF(E$4="","",IFERROR(INDIRECT("'"&E$4&"'!"&$Z5),"")) -> 0 | F5: =IF(F$4="","",IFERROR(INDIRECT("'"&F$4&"'!"&$Z5),"")) -> 0 | G5: =IF(G$4="","",IFERROR(INDIRECT("'"&G$4&"'!"&$Z5),"")) -> 0 | H5: =IF(H$4="","",IFERROR(INDIRECT("'"&H$4&"'!"&$Z5),"")) -> 0 | I5: =IF(I$4="","",IFERROR(INDIRECT("'"&I$4&"'!"&$Z5),"")) -> 0 | ... X5: =IF(X$4="","",IFERROR(INDIRECT("'"&X$4&"'!"&$Z5),"")) -> 0 | Z5: A1
A6: Régime de revenus | B6: =IF(B$4="","",IFERROR(INDIRECT("'"&B$4&"'!"&$Z6),"")) -> 0 | C6: =IF(C$4="","",IFERROR(INDIRECT("'"&C$4&"'!"&$Z6),"")) -> 0 | D6: =IF(D$4="","",IFERROR(INDIRECT("'"&D$4&"'!"&$Z6),"")) -> 0 | E6: =IF(E$4="","",IFERROR(INDIRECT("'"&E$4&"'!"&$Z6),"")) -> 0 | F6: =IF(F$4="","",IFERROR(INDIRECT("'"&F$4&"'!"&$Z6),"")) -> 0 | G6: =IF(G$4="","",IFERROR(INDIRECT("'"&G$4&"'!"&$Z6),"")) -> 0 | H6: =IF(H$4="","",IFERROR(INDIRECT("'"&H$4&"'!"&$Z6),"")) -> 0 | I6: =IF(I$4="","",IFERROR(INDIRECT("'"&I$4&"'!"&$Z6),"")) -> 0 | ... X6: =IF(X$4="","",IFERROR(INDIRECT("'"&X$4&"'!"&$Z6),"")) -> 0 | Z6: B15
A7: Secteur | B7: =IF(B$4="","",IFERROR(INDIRECT("'"&B$4&"'!"&$Z7),"")) -> 0 | C7: =IF(C$4="","",IFERROR(INDIRECT("'"&C$4&"'!"&$Z7),"")) -> 0 | D7: =IF(D$4="","",IFERROR(INDIRECT("'"&D$4&"'!"&$Z7),"")) -> 0 | E7: =IF(E$4="","",IFERROR(INDIRECT("'"&E$4&"'!"&$Z7),"")) -> 0 | F7: =IF(F$4="","",IFERROR(INDIRECT("'"&F$4&"'!"&$Z7),"")) -> 0 | G7: =IF(G$4="","",IFERROR(INDIRECT("'"&G$4&"'!"&$Z7),"")) -> 0 | H7: =IF(H$4="","",IFERROR(INDIRECT("'"&H$4&"'!"&$Z7),"")) -> 0 | I7: =IF(I$4="","",IFERROR(INDIRECT("'"&I$4&"'!"&$Z7),"")) -> 0 | ... X7: =IF(X$4="","",IFERROR(INDIRECT("'"&X$4&"'!"&$Z7),"")) -> 0 | Z7: B16
A8: Phase | B8: =IF(B$4="","",IFERROR(INDIRECT("'"&B$4&"'!"&$Z8),"")) -> 0 | C8: =IF(C$4="","",IFERROR(INDIRECT("'"&C$4&"'!"&$Z8),"")) -> 0 | D8: =IF(D$4="","",IFERROR(INDIRECT("'"&D$4&"'!"&$Z8),"")) -> 0 | E8: =IF(E$4="","",IFERROR(INDIRECT("'"&E$4&"'!"&$Z8),"")) -> 0 | F8: =IF(F$4="","",IFERROR(INDIRECT("'"&F$4&"'!"&$Z8),"")) -> 0 | G8: =IF(G$4="","",IFERROR(INDIRECT("'"&G$4&"'!"&$Z8),"")) -> 0 | H8: =IF(H$4="","",IFERROR(INDIRECT("'"&H$4&"'!"&$Z8),"")) -> 0 | I8: =IF(I$4="","",IFERROR(INDIRECT("'"&I$4&"'!"&$Z8),"")) -> 0 | ... X8: =IF(X$4="","",IFERROR(INDIRECT("'"&X$4&"'!"&$Z8),"")) -> 0 | Z8: B17
A9: Régime de proportionnalité retenu | B9: =IF(B$4="","",IFERROR(INDIRECT("'"&B$4&"'!"&$Z9),"")) -> 0 | C9: =IF(C$4="","",IFERROR(INDIRECT("'"&C$4&"'!"&$Z9),"")) -> 0 | D9: =IF(D$4="","",IFERROR(INDIRECT("'"&D$4&"'!"&$Z9),"")) -> 0 | E9: =IF(E$4="","",IFERROR(INDIRECT("'"&E$4&"'!"&$Z9),"")) -> 0 | F9: =IF(F$4="","",IFERROR(INDIRECT("'"&F$4&"'!"&$Z9),"")) -> 0 | G9: =IF(G$4="","",IFERROR(INDIRECT("'"&G$4&"'!"&$Z9),"")) -> 0 | H9: =IF(H$4="","",IFERROR(INDIRECT("'"&H$4&"'!"&$Z9),"")) -> 0 | I9: =IF(I$4="","",IFERROR(INDIRECT("'"&I$4&"'!"&$Z9),"")) -> 0 | ... X9: =IF(X$4="","",IFERROR(INDIRECT("'"&X$4&"'!"&$Z9),"")) -> 0 | Z9: B35
A10: Seuil DSCR critique applicable | B10: =IF(B$4="","",IFERROR(INDIRECT("'"&B$4&"'!"&$Z10),"")) -> 0 | C10: =IF(C$4="","",IFERROR(INDIRECT("'"&C$4&"'!"&$Z10),"")) -> 0 | D10: =IF(D$4="","",IFERROR(INDIRECT("'"&D$4&"'!"&$Z10),"")) -> 0 | E10: =IF(E$4="","",IFERROR(INDIRECT("'"&E$4&"'!"&$Z10),"")) -> 0 | F10: =IF(F$4="","",IFERROR(INDIRECT("'"&F$4&"'!"&$Z10),"")) -> 0 | G10: =IF(G$4="","",IFERROR(INDIRECT("'"&G$4&"'!"&$Z10),"")) -> 0 | H10: =IF(H$4="","",IFERROR(INDIRECT("'"&H$4&"'!"&$Z10),"")) -> 0 | I10: =IF(I$4="","",IFERROR(INDIRECT("'"&I$4&"'!"&$Z10),"")) -> 0 | ... X10: =IF(X$4="","",IFERROR(INDIRECT("'"&X$4&"'!"&$Z10),"")) -> 0 | Z10: B67
A11: DSCR minimum par échéance | B11: =IF(B$4="","",IFERROR(INDIRECT("'"&B$4&"'!"&$Z11),"")) -> 0 | C11: =IF(C$4="","",IFERROR(INDIRECT("'"&C$4&"'!"&$Z11),"")) -> 0 | D11: =IF(D$4="","",IFERROR(INDIRECT("'"&D$4&"'!"&$Z11),"")) -> 0 | E11: =IF(E$4="","",IFERROR(INDIRECT("'"&E$4&"'!"&$Z11),"")) -> 0 | F11: =IF(F$4="","",IFERROR(INDIRECT("'"&F$4&"'!"&$Z11),"")) -> 0 | G11: =IF(G$4="","",IFERROR(INDIRECT("'"&G$4&"'!"&$Z11),"")) -> 0 | H11: =IF(H$4="","",IFERROR(INDIRECT("'"&H$4&"'!"&$Z11),"")) -> 0 | I11: =IF(I$4="","",IFERROR(INDIRECT("'"&I$4&"'!"&$Z11),"")) -> 0 | ... X11: =IF(X$4="","",IFERROR(INDIRECT("'"&X$4&"'!"&$Z11),"")) -> 0 | Z11: D133
A12: DSCR minimum sous stress | B12: =IF(B$4="","",IFERROR(INDIRECT("'"&B$4&"'!"&$Z12),"")) -> 0 | C12: =IF(C$4="","",IFERROR(INDIRECT("'"&C$4&"'!"&$Z12),"")) -> 0 | D12: =IF(D$4="","",IFERROR(INDIRECT("'"&D$4&"'!"&$Z12),"")) -> 0 | E12: =IF(E$4="","",IFERROR(INDIRECT("'"&E$4&"'!"&$Z12),"")) -> 0 | F12: =IF(F$4="","",IFERROR(INDIRECT("'"&F$4&"'!"&$Z12),"")) -> 0 | G12: =IF(G$4="","",IFERROR(INDIRECT("'"&G$4&"'!"&$Z12),"")) -> 0 | H12: =IF(H$4="","",IFERROR(INDIRECT("'"&H$4&"'!"&$Z12),"")) -> 0 | I12: =IF(I$4="","",IFERROR(INDIRECT("'"&I$4&"'!"&$Z12),"")) -> 0 | ... X12: =IF(X$4="","",IFERROR(INDIRECT("'"&X$4&"'!"&$Z12),"")) -> 0 | Z12: D134
A13: DSCR moyen (indicatif) | B13: =IF(B$4="","",IFERROR(INDIRECT("'"&B$4&"'!"&$Z13),"")) -> 0 | C13: =IF(C$4="","",IFERROR(INDIRECT("'"&C$4&"'!"&$Z13),"")) -> 0 | D13: =IF(D$4="","",IFERROR(INDIRECT("'"&D$4&"'!"&$Z13),"")) -> 0 | E13: =IF(E$4="","",IFERROR(INDIRECT("'"&E$4&"'!"&$Z13),"")) -> 0 | F13: =IF(F$4="","",IFERROR(INDIRECT("'"&F$4&"'!"&$Z13),"")) -> 0 | G13: =IF(G$4="","",IFERROR(INDIRECT("'"&G$4&"'!"&$Z13),"")) -> 0 | H13: =IF(H$4="","",IFERROR(INDIRECT("'"&H$4&"'!"&$Z13),"")) -> 0 | I13: =IF(I$4="","",IFERROR(INDIRECT("'"&I$4&"'!"&$Z13),"")) -> 0 | ... X13: =IF(X$4="","",IFERROR(INDIRECT("'"&X$4&"'!"&$Z13),"")) -> 0 | Z13: D135
A14: DSCR annuel minimum (indicatif) | B14: =IF(B$4="","",IFERROR(INDIRECT("'"&B$4&"'!"&$Z14),"")) -> 0 | C14: =IF(C$4="","",IFERROR(INDIRECT("'"&C$4&"'!"&$Z14),"")) -> 0 | D14: =IF(D$4="","",IFERROR(INDIRECT("'"&D$4&"'!"&$Z14),"")) -> 0 | E14: =IF(E$4="","",IFERROR(INDIRECT("'"&E$4&"'!"&$Z14),"")) -> 0 | F14: =IF(F$4="","",IFERROR(INDIRECT("'"&F$4&"'!"&$Z14),"")) -> 0 | G14: =IF(G$4="","",IFERROR(INDIRECT("'"&G$4&"'!"&$Z14),"")) -> 0 | H14: =IF(H$4="","",IFERROR(INDIRECT("'"&H$4&"'!"&$Z14),"")) -> 0 | I14: =IF(I$4="","",IFERROR(INDIRECT("'"&I$4&"'!"&$Z14),"")) -> 0 | ... X14: =IF(X$4="","",IFERROR(INDIRECT("'"&X$4&"'!"&$Z14),"")) -> 0 | Z14: D136
A15: D7 — noyau financier | B15: =IF(B$4="","",IFERROR(INDIRECT("'"&B$4&"'!"&$Z15),"")) -> 0 | C15: =IF(C$4="","",IFERROR(INDIRECT("'"&C$4&"'!"&$Z15),"")) -> 0 | D15: =IF(D$4="","",IFERROR(INDIRECT("'"&D$4&"'!"&$Z15),"")) -> 0 | E15: =IF(E$4="","",IFERROR(INDIRECT("'"&E$4&"'!"&$Z15),"")) -> 0 | F15: =IF(F$4="","",IFERROR(INDIRECT("'"&F$4&"'!"&$Z15),"")) -> 0 | G15: =IF(G$4="","",IFERROR(INDIRECT("'"&G$4&"'!"&$Z15),"")) -> 0 | H15: =IF(H$4="","",IFERROR(INDIRECT("'"&H$4&"'!"&$Z15),"")) -> 0 | I15: =IF(I$4="","",IFERROR(INDIRECT("'"&I$4&"'!"&$Z15),"")) -> 0 | ... X15: =IF(X$4="","",IFERROR(INDIRECT("'"&X$4&"'!"&$Z15),"")) -> 0 | Z15: D148
A16: Score global sur 100 | B16: =IF(B$4="","",IFERROR(INDIRECT("'"&B$4&"'!"&$Z16),"")) -> 0 | C16: =IF(C$4="","",IFERROR(INDIRECT("'"&C$4&"'!"&$Z16),"")) -> 0 | D16: =IF(D$4="","",IFERROR(INDIRECT("'"&D$4&"'!"&$Z16),"")) -> 0 | E16: =IF(E$4="","",IFERROR(INDIRECT("'"&E$4&"'!"&$Z16),"")) -> 0 | F16: =IF(F$4="","",IFERROR(INDIRECT("'"&F$4&"'!"&$Z16),"")) -> 0 | G16: =IF(G$4="","",IFERROR(INDIRECT("'"&G$4&"'!"&$Z16),"")) -> 0 | H16: =IF(H$4="","",IFERROR(INDIRECT("'"&H$4&"'!"&$Z16),"")) -> 0 | I16: =IF(I$4="","",IFERROR(INDIRECT("'"&I$4&"'!"&$Z16),"")) -> 0 | ... X16: =IF(X$4="","",IFERROR(INDIRECT("'"&X$4&"'!"&$Z16),"")) -> 0 | Z16: B217
... A23: Prochaine saisie | B23: =IF(B$4="","",IFERROR(INDIRECT("'"&B$4&"'!"&$Z23),"")) -> 0 | C23: =IF(C$4="","",IFERROR(INDIRECT("'"&C$4&"'!"&$Z23),"")) -> 0 | D23: =IF(D$4="","",IFERROR(INDIRECT("'"&D$4&"'!"&$Z23),"")) -> 0 | E23: =IF(E$4="","",IFERROR(INDIRECT("'"&E$4&"'!"&$Z23),"")) -> 0 | F23: =IF(F$4="","",IFERROR(INDIRECT("'"&F$4&"'!"&$Z23),"")) -> 0 | G23: =IF(G$4="","",IFERROR(INDIRECT("'"&G$4&"'!"&$Z23),"")) -> 0 | H23: =IF(H$4="","",IFERROR(INDIRECT("'"&H$4&"'!"&$Z23),"")) -> 0 | I23: =IF(I$4="","",IFERROR(INDIRECT("'"&I$4&"'!"&$Z23),"")) -> 0 | ... X23: =IF(X$4="","",IFERROR(INDIRECT("'"&X$4&"'!"&$Z23),"")) -> 0 | Z23: C4
A26: Les trois démonstrations à retenir
A27: CAS 3 — Anti-compensation : un score de 73,7 (note 7) ramené à 4 par les plafonds C2 et C3. Un sponsor à 100 et une documentation à 100 ne compensent pas un DSCR de 1,06 sur le creux estival.
A28: CAS 4A vs 4B — Le ratio annuel trompe : 1,53 en annuel, 0,59 par échéance. Après sculpture de l'amortissement, apport complémentaire et couverture de change, la note passe de 3 à 6 sans que le marché ait changé.
A29: CAS 5 — Proportionnalité : le régime simplifié allège la grille de jugement, jamais les plafonds. Un noyau financier à 97 reste plafonné à 6 par la concentration sur un acheteur unique non noté.

Sheet Fiche comité
A1: Fiche comité — notation Project Finance (modèle V8)
A2: Choisissez le dossier dans la cellule jaune. Tout est lu dans l'onglet du dossier ; imprimez la page ou utilisez « Exporter en PDF ».
A4: Dossier (nom de l'onglet) | B4: C3 | D4: Édité le | E4: =TODAY() -> 0
A6: IDENTIFICATION
A7: Intitulé | B7: =IF($B$4="","",IFERROR(IF(INDIRECT("'"&$B$4&"'!A1")="","",INDIRECT("'"&$B$4&"'!A1")),"")) -> 0
A8: Société de projet — localisation | B8: =IF($B$4="","",IFERROR(IF(INDIRECT("'"&$B$4&"'!A2")="","",INDIRECT("'"&$B$4&"'!A2")),"")) -> 0
A9: Résumé | B9: =IF($B$4="","",IFERROR(IF(INDIRECT("'"&$B$4&"'!A3")="","",INDIRECT("'"&$B$4&"'!A3")),"")) -> 0
A11: NOTATION
A12: NOTE APPROUVÉE (1 à 10) | B12: =IF($B$4="","",IFERROR(IF(INDIRECT("'"&$B$4&"'!B255")="","",INDIRECT("'"&$B$4&"'!B255")),"")) -> 0 | C12: =IF($B$4="","",IFERROR(IF(INDIRECT("'"&$B$4&"'!D6")="","",INDIRECT("'"&$B$4&"'!D6")),"")) -> 0
A13: Statut | B13: =IF($B$4="","",IFERROR(IF(INDIRECT("'"&$B$4&"'!B256")="","",INDIRECT("'"&$B$4&"'!B256")),"")) -> 0
A14: Orientation | B14: =IF($B$4="","",IFERROR(IF(INDIRECT("'"&$B$4&"'!F11")="","",INDIRECT("'"&$B$4&"'!F11")),"")) -> 0
A15: Score global (sur 100) | B15: =IF($B$4="","",IFERROR(IF(INDIRECT("'"&$B$4&"'!B217")="","",INDIRECT("'"&$B$4&"'!B217")),"")) -> 0 | C15: Note calculée | D15: =IF($B$4="","",IFERROR(IF(INDIRECT("'"&$B$4&"'!B218")="","",INDIRECT("'"&$B$4&"'!B218")),"")) -> 0 | E15: Plafond | F15: =IF($B$4="","",IFERROR(IF(INDIRECT("'"&$B$4&"'!F7")="","",INDIRECT("'"&$B$4&"'!F7")),"")) -> 0
A16: Plafonds actifs | B16: =IF($B$4="","",IFERROR(IF(INDIRECT("'"&$B$4&"'!B8")="","",INDIRECT("'"&$B$4&"'!B8")),"")) -> 0
A17: Verrous actifs (X, B) | B17: =IF($B$4="","",IFERROR(IF(INDIRECT("'"&$B$4&"'!B9")="","",INDIRECT("'"&$B$4&"'!B9")),"")) -> 0
A18: Saisies obligatoires manquantes | B18: =IF($B$4="","",IFERROR(IF(INDIRECT("'"&$B$4&"'!B4")="","",INDIRECT("'"&$B$4&"'!B4")),"")) -> 0 | C18: =IF($B$4="","",IFERROR(IF(INDIRECT("'"&$B$4&"'!C4")="","",INDIRECT("'"&$B$4&"'!C4")),"")) -> 0
A20: ROUTAGE ET PROPORTIONNALITÉ
A21: Régime de revenus | B21: =IF($B$4="","",IFERROR(IF(INDIRECT("'"&$B$4&"'!B15")="","",INDIRECT("'"&$B$4&"'!B15")),"")) -> 0 | C21: =IF($B$4="","",IFERROR(IF(INDIRECT("'"&$B$4&"'!C15")="","",INDIRECT("'"&$B$4&"'!C15")),"")) -> 0
A22: Secteur | B22: =IF($B$4="","",IFERROR(IF(INDIRECT("'"&$B$4&"'!B16")="","",INDIRECT("'"&$B$4&"'!B16")),"")) -> 0 | C22: =IF($B$4="","",IFERROR(IF(INDIRECT("'"&$B$4&"'!C16")="","",INDIRECT("'"&$B$4&"'!C16")),"")) -> 0
A23: Phase | B23: =IF($B$4="","",IFERROR(IF(INDIRECT("'"&$B$4&"'!B17")="","",INDIRECT("'"&$B$4&"'!B17")),"")) -> 0 | C23: =IF($B$4="","",IFERROR(IF(INDIRECT("'"&$B$4&"'!C17")="","",INDIRECT("'"&$B$4&"'!C17")),"")) -> 0
A24: Régime de proportionnalité (S / M / L) | B24: =IF($B$4="","",IFERROR(IF(INDIRECT("'"&$B$4&"'!B35")="","",INDIRECT("'"&$B$4&"'!B35")),"")) -> 0 | C24: =IF($B$4="","",IFERROR(IF(INDIRECT("'"&$B$4&"'!C35")="","",INDIRECT("'"&$B$4&"'!C35")),"")) -> 0
A26: INDICATEURS FINANCIERS
A27: Indicateur | B27: Valeur | C27: Repère | D27: Appréciation
A28: DSCR minimum par échéance (retenu) | B28: =IF($B$4="","",IFERROR(IF(INDIRECT("'"&$B$4&"'!D133")="","",INDIRECT("'"&$B$4&"'!D133")),"")) -> 0 | C28: =IF($B$4="","",IFERROR(IF(INDIRECT("'"&$B$4&"'!B67")="","",INDIRECT("'"&$B$4&"'!B67")),"")) -> 0 | D28: =IF($B$4="","",IFERROR(IF(INDIRECT("'"&$B$4&"'!E133")="","",INDIRECT("'"&$B$4&"'!E133")),"")) -> 0
A29: DSCR minimum sous scénario défavorable | B29: =IF($B$4="","",IFERROR(IF(INDIRECT("'"&$B$4&"'!D134")="","",INDIRECT("'"&$B$4&"'!D134")),"")) -> 0 | D29: =IF($B$4="","",IFERROR(IF(INDIRECT("'"&$B$4&"'!E134")="","",INDIRECT("'"&$B$4&"'!E134")),"")) -> 0
A30: DSCR moyen (indicatif) | B30: =IF($B$4="","",IFERROR(IF(INDIRECT("'"&$B$4&"'!D135")="","",INDIRECT("'"&$B$4&"'!D135")),"")) -> 0
A31: DSCR annuel minimum (indicatif) | B31: =IF($B$4="","",IFERROR(IF(INDIRECT("'"&$B$4&"'!D136")="","",INDIRECT("'"&$B$4&"'!D136")),"")) -> 0
A32: Couverture du besoin à terminaison | B32: =IF($B$4="","",IFERROR(IF(INDIRECT("'"&$B$4&"'!B48")="","",INDIRECT("'"&$B$4&"'!B48")),"")) -> 0
A33: Quote-part de dette | B33: =IF($B$4="","",IFERROR(IF(INDIRECT("'"&$B$4&"'!B49")="","",INDIRECT("'"&$B$4&"'!B49")),"")) -> 0 | C33: =P_C9 -> 0
A34: LLCR | B34: =IF($B$4="","",IFERROR(IF(INDIRECT("'"&$B$4&"'!B151")="","",INDIRECT("'"&$B$4&"'!B151")),"")) -> 0 | C34: =P_C4 -> 0
A35: DSRA (mois de service) | B35: =IF($B$4="","",IFERROR(IF(INDIRECT("'"&$B$4&"'!B152")="","",INDIRECT("'"&$B$4&"'!B152")),"")) -> 0 | C35: =P_C7 -> 0
A36: CAPEX du projet (MMAD) | B36: =IF($B$4="","",IFERROR(IF(INDIRECT("'"&$B$4&"'!B22")="","",INDIRECT("'"&$B$4&"'!B22")),"")) -> 0
A37: Exposition de la banque (MMAD) | B37: =IF($B$4="","",IFERROR(IF(INDIRECT("'"&$B$4&"'!B23")="","",INDIRECT("'"&$B$4&"'!B23")),"")) -> 0
A39: SCORES PAR DOMAINE
A40: Domaine | B40: Score / 100 | C40: Poids (phase) | D40: Contribution
A41: =IF($B$4="","",IFERROR(IF(INDIRECT("'"&$B$4&"'!A208")="","",INDIRECT("'"&$B$4&"'!A208")),"")) -> 0 | B41: =IF($B$4="","",IFERROR(IF(INDIRECT("'"&$B$4&"'!B208")="","",INDIRECT("'"&$B$4&"'!B208")),"")) -> 0 | C41: =IF($B$4="","",IFERROR(IF(INDIRECT("'"&$B$4&"'!C208")="","",INDIRECT("'"&$B$4&"'!C208")),"")) -> 0 | D41: =IF($B$4="","",IFERROR(IF(INDIRECT("'"&$B$4&"'!D208")="","",INDIRECT("'"&$B$4&"'!D208")),"")) -> 0
A42: =IF($B$4="","",IFERROR(IF(INDIRECT("'"&$B$4&"'!A209")="","",INDIRECT("'"&$B$4&"'!A209")),"")) -> 0 | B42: =IF($B$4="","",IFERROR(IF(INDIRECT("'"&$B$4&"'!B209")="","",INDIRECT("'"&$B$4&"'!B209")),"")) -> 0 | C42: =IF($B$4="","",IFERROR(IF(INDIRECT("'"&$B$4&"'!C209")="","",INDIRECT("'"&$B$4&"'!C209")),"")) -> 0 | D42: =IF($B$4="","",IFERROR(IF(INDIRECT("'"&$B$4&"'!D209")="","",INDIRECT("'"&$B$4&"'!D209")),"")) -> 0
A43: =IF($B$4="","",IFERROR(IF(INDIRECT("'"&$B$4&"'!A210")="","",INDIRECT("'"&$B$4&"'!A210")),"")) -> 0 | B43: =IF($B$4="","",IFERROR(IF(INDIRECT("'"&$B$4&"'!B210")="","",INDIRECT("'"&$B$4&"'!B210")),"")) -> 0 | C43: =IF($B$4="","",IFERROR(IF(INDIRECT("'"&$B$4&"'!C210")="","",INDIRECT("'"&$B$4&"'!C210")),"")) -> 0 | D43: =IF($B$4="","",IFERROR(IF(INDIRECT("'"&$B$4&"'!D210")="","",INDIRECT("'"&$B$4&"'!D210")),"")) -> 0
A44: =IF($B$4="","",IFERROR(IF(INDIRECT("'"&$B$4&"'!A211")="","",INDIRECT("'"&$B$4&"'!A211")),"")) -> 0 | B44: =IF($B$4="","",IFERROR(IF(INDIRECT("'"&$B$4&"'!B211")="","",INDIRECT("'"&$B$4&"'!B211")),"")) -> 0 | C44: =IF($B$4="","",IFERROR(IF(INDIRECT("'"&$B$4&"'!C211")="","",INDIRECT("'"&$B$4&"'!C211")),"")) -> 0 | D44: =IF($B$4="","",IFERROR(IF(INDIRECT("'"&$B$4&"'!D211")="","",INDIRECT("'"&$B$4&"'!D211")),"")) -> 0
A45: =IF($B$4="","",IFERROR(IF(INDIRECT("'"&$B$4&"'!A212")="","",INDIRECT("'"&$B$4&"'!A212")),"")) -> 0 | B45: =IF($B$4="","",IFERROR(IF(INDIRECT("'"&$B$4&"'!B212")="","",INDIRECT("'"&$B$4&"'!B212")),"")) -> 0 | C45: =IF($B$4="","",IFERROR(IF(INDIRECT("'"&$B$4&"'!C212")="","",INDIRECT("'"&$B$4&"'!C212")),"")) -> 0 | D45: =IF($B$4="","",IFERROR(IF(INDIRECT("'"&$B$4&"'!D212")="","",INDIRECT("'"&$B$4&"'!D212")),"")) -> 0
A46: =IF($B$4="","",IFERROR(IF(INDIRECT("'"&$B$4&"'!A213")="","",INDIRECT("'"&$B$4&"'!A213")),"")) -> 0 | B46: =IF($B$4="","",IFERROR(IF(INDIRECT("'"&$B$4&"'!B213")="","",INDIRECT("'"&$B$4&"'!B213")),"")) -> 0 | C46: =IF($B$4="","",IFERROR(IF(INDIRECT("'"&$B$4&"'!C213")="","",INDIRECT("'"&$B$4&"'!C213")),"")) -> 0 | D46: =IF($B$4="","",IFERROR(IF(INDIRECT("'"&$B$4&"'!D213")="","",INDIRECT("'"&$B$4&"'!D213")),"")) -> 0
A47: =IF($B$4="","",IFERROR(IF(INDIRECT("'"&$B$4&"'!A214")="","",INDIRECT("'"&$B$4&"'!A214")),"")) -> 0 | B47: =IF($B$4="","",IFERROR(IF(INDIRECT("'"&$B$4&"'!B214")="","",INDIRECT("'"&$B$4&"'!B214")),"")) -> 0 | C47: =IF($B$4="","",IFERROR(IF(INDIRECT("'"&$B$4&"'!C214")="","",INDIRECT("'"&$B$4&"'!C214")),"")) -> 0 | D47: =IF($B$4="","",IFERROR(IF(INDIRECT("'"&$B$4&"'!D214")="","",INDIRECT("'"&$B$4&"'!D214")),"")) -> 0
A48: =IF($B$4="","",IFERROR(IF(INDIRECT("'"&$B$4&"'!A215")="","",INDIRECT("'"&$B$4&"'!A215")),"")) -> 0 | B48: =IF($B$4="","",IFERROR(IF(INDIRECT("'"&$B$4&"'!B215")="","",INDIRECT("'"&$B$4&"'!B215")),"")) -> 0 | C48: =IF($B$4="","",IFERROR(IF(INDIRECT("'"&$B$4&"'!C215")="","",INDIRECT("'"&$B$4&"'!C215")),"")) -> 0 | D48: =IF($B$4="","",IFERROR(IF(INDIRECT("'"&$B$4&"'!D215")="","",INDIRECT("'"&$B$4&"'!D215")),"")) -> 0
A49: =IF($B$4="","",IFERROR(IF(INDIRECT("'"&$B$4&"'!A216")="","",INDIRECT("'"&$B$4&"'!A216")),"")) -> 0 | B49: =IF($B$4="","",IFERROR(IF(INDIRECT("'"&$B$4&"'!B216")="","",INDIRECT("'"&$B$4&"'!B216")),"")) -> 0 | C49: =IF($B$4="","",IFERROR(IF(INDIRECT("'"&$B$4&"'!C216")="","",INDIRECT("'"&$B$4&"'!C216")),"")) -> 0 | D49: =IF($B$4="","",IFERROR(IF(INDIRECT("'"&$B$4&"'!D216")="","",INDIRECT("'"&$B$4&"'!D216")),"")) -> 0
A50: SCORE GLOBAL | D50: =IF($B$4="","",IFERROR(IF(INDIRECT("'"&$B$4&"'!B217")="","",INDIRECT("'"&$B$4&"'!B217")),"")) -> 0
A52: CE QUE LE DOSSIER ENSEIGNE / CONCLUSION DE L'ANALYSTE
A53: =IF($B$4="","",IFERROR(IF(INDIRECT("'"&$B$4&"'!A259")="","",INDIRECT("'"&$B$4&"'!A259")),"")) -> 0
A55: AVIS ET DÉCISION DU COMITÉ (à compléter à la main)
A56: Décision
A57: Conditions et réserves
A58: Date du comité
A59: Signatures

Sheet C1
A1: CAS 1 · Centrale solaire photovoltaïque 80 MWc | J1: DOSSIER_V8
A2: SPV « Solaris Drâa » SA (fictive) — Région de Drâa-Tafilalet
A3: Centrale PV vendant sa production à l'acheteur public national sous contrat d'achat de 25 ans à quantité garantie et tarif indexé. Financement en dirhams, EPC clé-en-main forfaitaire.
A4: À SAISIR (cellules orange) | B4: =COUNTIF($R$14:$R$56,0) -> 0 | C4: =IF(B4=0,"Saisie complète : lisez la note ci-dessous, puis « Fiche comité ».","Prochaine saisie : "&INDEX($P$14:$P$56,MATCH(0,$R$14:$R$56,0))) -> 0 | G4: =IF(B4=0,"",HYPERLINK("#"&INDEX($Q$14:$Q$56,MATCH(0,$R$14:$R$56,0)),"→ Aller à la cellule "&INDEX($Q$14:$Q$56,MATCH(0,$R$14:$R$56,0)))) -> 0
A5: TABLEAU DE BORD — se met à jour à chaque saisie
A6: NOTE APPROUVÉE (1 à 10) | B6: =B255 -> 0 | C6: Libellé | D6: =IFERROR(INDEX(P_ConvLib,MATCH(B255,P_ConvNote,0)),"") -> 0 | E6: Statut | F6: =B256 -> 0
A7: Score global (sur 100) | B7: =B217 -> 0 | C7: Note calculée | D7: =B218 -> 0 | E7: Plafond applicable | F7: =IF(B252>=10,"Aucun (10)",B252) -> 0
A8: Plafonds actifs | B8: =IF(TRIM(IF(E237="Oui","C1 ("&F237&") ","")&IF(E238="Oui","C2 ("&F238&") ","")&IF(E239="Oui","C3 ("&F239&") ","")&IF(E240="Oui","C4 ("&F240&") ","")&IF(E241="Oui","C5 ("&F241&") ","")&IF(E242="Oui","C6 ("&F242&") ","")&IF(E243="Oui","C7 ("&F243&") ","")&IF(E244="Oui","C8 ("&F244&") ","")&IF(E245="Oui","C9 ("&F245&") ","")&IF(E246="Oui","C10 ("&F246&") ","")&IF(E247="Oui","C11 ("&F247&") ","")&IF(E248="Oui","C12 ("&F248&") ","")&IF(E249="Oui","C13 ("&F249&") ","")&IF(E250="Oui","C14 ("&F250&") ","")&IF(E251="Oui","C15 ("&F251&") ",""))="","Aucun",TRIM(IF(E237="Oui","C1 ("&F237&") ","")&IF(E238="Oui","C2 ("&F238&") ","")&IF(E239="Oui","C3 ("&F239&") ","")&IF(E240="Oui","C4 ("&F240&") ","")&IF(E241="Oui","C5 ("&F241&") ","")&IF(E242="Oui","C6 ("&F242&") ","")&IF(E243="Oui","C7 ("&F243&") ","")&IF(E244="Oui","C8 ("&F244&") ","")&IF(E245="Oui","C9 ("&F245&") ","")&IF(E246="Oui","C10 ("&F246&") ","")&IF(E247="Oui","C11 ("&F247&") ","")&IF(E248="Oui","C12 ("&F248&") ","")&IF(E249="Oui","C13 ("&F249&") ","")&IF(E250="Oui","C14 ("&F250&") ","")&IF(E251="Oui","C15 ("&F251&") ","")))&IF(COUNTIF(E237:E251,"n.r.")>0," — "&COUNTIF(E237:E251,"n.r.")&" plafond(s) non évalué(s) faute de donnée","") -> 0
A9: Verrous actifs (exclusions X, blocages B) | B9: =IF(TRIM(IF(F222="Oui","X1 ","")&IF(F223="Oui","X2 ","")&IF(F224="Oui","X3 ","")&IF(F225="Oui","X4 ","")&IF(F226="Oui","B1 ","")&IF(F227="Oui","B2 ","")&IF(F228="Oui","B3 ","")&IF(F229="Oui","B4 ","")&IF(F230="Oui","B5 ","")&IF(F231="Oui","B6 ","")&IF(F232="Oui","B7 ","")&IF(F233="Oui","B8 ",""))="","Aucun",TRIM(IF(F222="Oui","X1 ","")&IF(F223="Oui","X2 ","")&IF(F224="Oui","X3 ","")&IF(F225="Oui","X4 ","")&IF(F226="Oui","B1 ","")&IF(F227="Oui","B2 ","")&IF(F228="Oui","B3 ","")&IF(F229="Oui","B4 ","")&IF(F230="Oui","B5 ","")&IF(F231="Oui","B6 ","")&IF(F232="Oui","B7 ","")&IF(F233="Oui","B8 ",""))) -> 0
A10: Régime de proportionnalité retenu | B10: =B35 -> 0 | C10: DSCR minimum | D10: =D133 -> 0 | E10: DSCR stressé min. | F10: =D134 -> 0
A11: Complétude (noyau N1-N6 et grille) | B11: =B204 -> 0 | C11: Noyau financier D7 | D11: =D148 -> 0 | E11: Orientation | F11: =IFERROR(INDEX(P_ConvOrient,MATCH(B255,P_ConvNote,0)),"") -> 0
A12: Aller à la section : | B12: =HYPERLINK("#A13","1 · Routage") -> 0 | C12: =HYPERLINK("#A37","3 · Sources") -> 0 | D12: =HYPERLINK("#A69","6 · Échéancier") -> 0 | E12: =HYPERLINK("#A140","7 · Noyau") -> 0 | F12: =HYPERLINK("#A167","8 · Grille") -> 0 | G12: =HYPERLINK("#A220","10 · Verrous") -> 0 | H12: =HYPERLINK("#A235","11 · Plafonds") -> 0
A13: 1 · ROUTAGE — pilote les seuils DSCR et les poids de domaine
A14: Axe | B14: Valeur | C14: Libellé | P14: 1 · Régime de revenus | Q14: B15 | R14: =IF($B$15<>"",1,0) -> 0
A15: C — Régime de revenus | B15: R1 | C15: =IFERROR(INDEX(P_RegLib,MATCH(B15,P_Regimes,0)),"") -> 0 | P15: 1 · Secteur du projet | Q15: B16 | R15: =IF($B$16<>"",1,0) -> 0
A16: D — Secteur du projet | B16: ENR | C16: =IFERROR(INDEX(P_SecLib,MATCH(B16,P_SecCodes,0)),"") -> 0 | P16: 1 · Phase du projet | Q16: B17 | R16: =IF($B$17<>"",1,0) -> 0
A17: B — Phase | B17: P1 | C17: =IFERROR(INDEX(P_PhaseLib,MATCH(B17,P_PhaseCodes,0)),"") -> 0 | P17: 1 · Périodicité des échéances | Q17: B18 | R17: =IF($B$18<>"",1,0) -> 0
A18: Périodicité du service de la dette | B18: Semestrielle | C18: Jamais annuelle : le DSCR se mesure échéance par échéance. | P18: 2 · Exposition de la banque (MMAD) | Q18: B23 | R18: =IF(ISNUMBER($B$23),1,0) -> 0
A19: A — Famille de financement | B19: PF-FLUX | C19: SPV dédiée, remboursement par les flux du projet (R5 vente d'actifs : hors outil). | P19: 2 · Recettes, coûts et dette en dirhams ? | Q19: B24 | R19: =IF($B$24<>"",1,0) -> 0
P20: 2 · Durée du financement (ans) | Q20: B25 | R20: =IF(ISNUMBER($B$25),1,0) -> 0
A21: 2 · RÉGIME DE PROPORTIONNALITÉ — calculé, jamais choisi | P21: 2 · Technologie éprouvée ? | Q21: B26 | R21: =IF($B$26<>"",1,0) -> 0
A22: CAPEX du projet économique complet (MMAD) | B22: =B47 -> 0 | C22: Repris du total des emplois (section 3). | P22: 2 · EPC clé-en-main de moins de 18 mois ? (phase P1) | Q22: B27 | R22: =IF(OR(NOT($B$17="P1"),$B$27<>""),1,0) -> 0
A23: Exposition de la banque (MMAD) | B23: 465 | P23: 2 · Acheteur principal unique ? | Q23: B28 | R23: =IF($B$28<>"",1,0) -> 0
A24: Recettes, coûts et dette intégralement en dirhams | B24: Oui | P24: 2 · Première référence technologique ? | Q24: B29 | R24: =IF($B$29<>"",1,0) -> 0
A25: Durée du financement (ans) | B25: 20 | P25: 2 · Opération consortiale ? | Q25: B30 | R25: =IF($B$30<>"",1,0) -> 0
A26: Technologie : ≥ 3 références industrielles de plus de 3 ans | B26: Oui | P26: 2 · Contrat de revenus de plus de 20 ans ? | Q26: B31 | R26: =IF($B$31<>"",1,0) -> 0
A27: En P1 : EPC clé-en-main forfaitaire, prix et délai garantis, < 18 mois | B27: Non | P27: 2 · Site à risque climatique élevé ? | Q27: B32 | R27: =IF($B$32<>"",1,0) -> 0
A28: Acheteur principal unique et identifié | B28: Oui | P28: 2 · Nombre de contreparties clés | Q28: B33 | R28: =IF(ISNUMBER($B$33),1,0) -> 0
A29: Technologie constituant une première référence dans la juridiction | B29: Non | P29: 3 · Emplois : montants du besoin à terminaison | Q29: B39 | R29: =IF(N($B$47)>0,1,0) -> 0
A30: Opération consortiale relevant de la directive 3/W/2025 | B30: Non | P30: 3 · Ressources engagées : montants | Q30: E39 | R30: =IF(N($E$47)>0,1,0) -> 0
A31: Concession ou contrat de revenus de plus de 20 ans | B31: Oui | P31: 3 · Nature de chaque ressource | Q31: F39 | R31: =IF(SUMPRODUCT(ISNUMBER($E$39:$E$46)*($F$39:$F$46=""))=0,1,0) -> 0
A32: Site classé à risque climatique physique élevé | B32: Non | P32: 3 · Plan de remédiation (couverture entre 95 et 100 %) | Q32: B50 | R32: =IF(OR(NOT(AND($B$17="P1",ISNUMBER($B$48),N($B$48)>=P_N3_V,N($B$48)<P_N3_F)),$B$50<>""),1,0) -> 0
A33: Nombre de contreparties clés | P33: 6 · Choc du scénario défavorable (%) | Q33: B70 | R33: =IF(ISNUMBER($B$70),1,0) -> 0
A34: Régime calculé (avant escalade) | B34: =IF(OR(B22="",B22=0,B15=""),"",IF(OR(B22>P_L_CAPEX,N(B23)>P_L_EXPO,B15="R4",B29="Oui",N(B153)>0,B30="Oui",B31="Oui",B32="Oui",N(B33)>P_L_NBCP),"L",IF(AND(B22<=P_S_CAPEX,B23<>"",N(B23)<=P_S_EXPO,OR(B15="R1",B15="R2"),B26="Oui",B24="Oui",B25<>"",N(B25)<=P_S_DUREE,OR(B17<>"P1",B27="Oui"),B28="Oui",COUNTIF($F$222:$F$233,"Oui")=0),"S","M"))) -> 0 | C34: =IF(B34="","",IF(B34="L","Escalade : "&IF(B22>P_L_CAPEX,"CAPEX > "&P_L_CAPEX&" MMAD ; ","")&IF(N(B23)>P_L_EXPO,"exposition > "&P_L_EXPO&" MMAD ; ","")&IF(B15="R4","régime de revenus R4 ; ","")&IF(B29="Oui","première référence technologique ; ","")&IF(N(B153)>0,"devises non intégralement couvertes ; ","")&IF(B30="Oui","opération consortiale ; ","")&IF(B31="Oui","contrat de revenus > 20 ans ; ","")&IF(B32="Oui","risque climatique élevé ; ","")&IF(N(B33)>P_L_NBCP,"plus de "&P_L_NBCP&" contreparties clés ; ",""),IF(B34="S","Toutes les conditions du régime simplifié sont réunies.","Régime standard par défaut : une condition du régime S manque, aucune condition d'escalade."))) -> 0 | P34: 6 · Échéancier : CFADS d'au moins deux périodes | Q34: B72 | R34: =IF(COUNT($B$72:$B$131)>=2,1,0) -> 0
A35: RÉGIME RETENU (après escalade automatique) | B35: =IF(B34="","",IF(AND(IF(AND(B34="S",COUNTIF($F$222:$F$233,"Oui")>0),"M",B34)="M",COUNTIF($E$237:$E$251,"Oui")>0),"L",IF(AND(B34="S",COUNTIF($F$222:$F$233,"Oui")>0),"M",B34))) -> 0 | C35: =IF(B35=B34,"Aucune escalade.",IF(B35="L","Escalade : un plafond de note est actif (M passe en L).","Escalade : un verrou est actif (S passe en M).")) -> 0 | P35: 6 · Service de la dette de chaque période | Q35: C72 | R35: =IF(SUMPRODUCT(ISNUMBER($B$72:$B$131)*(1-ISNUMBER($C$72:$C$131)))=0,1,0) -> 0
P36: 7 · N4 — Liquidité (DSRA, lignes, cascade) | Q36: B145 | R36: =IF($B$145<>"",1,0) -> 0
A37: 3 · SOURCES ET EMPLOIS (MMAD) — test de financement à terminaison | P37: 7 · N5 — Levier et fonds propres à risque | Q37: B146 | R37: =IF($B$146<>"",1,0) -> 0
A38: Emplois | B38: Montant | D38: Ressources | E38: Montant | F38: Nature | P38: 7 · N6 — Exposition résiduelle taux, change, refinancement | Q38: B147 | R38: =IF($B$147<>"",1,0) -> 0
A39: Contrat EPC (modules, structures, postes) | B39: 590 | D39: Dette senior (20 ans, 5,5 %) | E39: 465 | F39: Dette senior | P39: 7 · N3 hors phase P1 : note LLCR | Q39: B150 | R39: =IF(OR($B$17="P1",$B$150<>""),1,0) -> 0
A40: Raccordement au réseau | B40: 25 | D40: Fonds propres et quasi-fonds propres | E40: 242 | F40: Quasi-fonds propres | P40: 7 · LLCR (plafond C4) | Q40: B151 | R40: =IF(ISNUMBER($B$151),1,0) -> 0
A41: Développement, frais et assurances | B41: 20 | D41: Engagement sponsor de dépassement (engagé, non tiré) | E41: 40 | F41: Engagement sponsor | P41: 7 · DSRA en mois (plafond C7) | Q41: B152 | R41: =IF(ISNUMBER($B$152),1,0) -> 0
A42: Contingence | B42: 30 | P42: 7 · Exposition nette en devises (plafond C6) | Q42: B153 | R42: =IF(ISNUMBER($B$153),1,0) -> 0
A43: Intérêts intercalaires | B43: 18 | P43: 7 · Dette à refinancer à maturité (plafond C8) | Q43: B154 | R43: =IF(ISNUMBER($B$154),1,0) -> 0
A44: Dotation initiale DSRA | B44: 20 | P44: 7 · Stratégie de refinancement approuvée ? | Q44: B155 | R44: =IF(OR(N($B$154)<=P_C8,$B$155<>""),1,0) -> 0
A45: BFR de démarrage | B45: 4 | P45: 7 · Part des recettes de l'acheteur principal (C10) | Q45: B156 | R45: =IF(ISNUMBER($B$156),1,0) -> 0
P46: 7 · Qualité de crédit de l'acheteur principal | Q46: B157 | R46: =IF($B$157<>"",1,0) -> 0
A47: Total emplois (besoin à terminaison) | B47: =SUM(B39:B46) -> 0 | D47: Total ressources engagées | E47: =SUM(E39:E46) -> 0 | P47: 7 · Durée résiduelle du contrat de revenus (C5) | Q47: B158 | R47: =IF(OR($B$15="R4",ISNUMBER($B$158)),1,0) -> 0
A48: Couverture du besoin à terminaison (ressources / emplois) | B48: =IF(N(B47)=0,"",E47/B47) -> 0 | P48: 7 · Durée résiduelle de la dette | Q48: B159 | R48: =IF(ISNUMBER($B$159),1,0) -> 0
A49: Quote-part de dette (dette / besoin à terminaison) | B49: =IF(N(B47)=0,"",(SUMIF(F39:F46,"Dette senior",E39:E46)+SUMIF(F39:F46,"Dette subordonnée",E39:E46))/B47) -> 0 | P49: 7 · Solution documentée (contrat plus court que la dette) ? | Q49: B160 | R49: =IF(OR(NOT(AND(ISNUMBER($B$158),ISNUMBER($B$159))),N($B$158)>=N($B$159),$B$160<>""),1,0) -> 0
A50: Plan de remédiation approuvé (couverture entre 95 % et 100 %) | B50: Non | P50: 7 · Plan d'adaptation climatique financé ? (C11) | Q50: B161 | R50: =IF(OR($B$32<>"Oui",$B$161<>""),1,0) -> 0
P51: 7 · Capacité résiduelle du sponsor (C12) | Q51: B162 | R51: =IF($B$162<>"",1,0) -> 0
A52: 4 · HYPOTHÈSES D'EXPLOITATION (information, non calculées) | P52: 7 · Opérateur remplaçable ? (C13) | Q52: B163 | R52: =IF($B$163<>"",1,0) -> 0
A53: Production nette P50 | B53: 152 GWh/an | P53: 7 · Écart fin O&M / fin de dette (opérateur non remplaçable) | Q53: B164 | R53: =IF(OR($B$163<>"Non",ISNUMBER($B$164)),1,0) -> 0
A54: Tarif du contrat d'achat | B54: 0,48 MAD/kWh, indexé | P54: 7 · Facteur commun au-delà de la limite interne (C14) | Q54: B165 | R54: =IF($B$165<>"",1,0) -> 0
A55: Chiffre d'affaires | B55: 73 MMAD/an | P55: 8 · Grille : sous-critère requis non noté | Q55: ="B"&IF(COUNT($P$169:$P$201)=0,169,MIN($P$169:$P$201)) -> 0 | R55: =IF(COUNT($P$169:$P$201)=0,1,0) -> 0
A56: Charges d'exploitation | B56: 11 MMAD/an | P56: 10 · Verrous X1 à B8 : répondre Oui ou Non | Q56: E222 | R56: =IF(COUNTBLANK($E$222:$E$233)=0,1,0) -> 0
A57: EBITDA | B57: 62 MMAD/an
A58: CFADS de référence | B58: 54 MMAD/an
A59: Service de la dette | B59: 38,9 MMAD/an, semestriel
A62: 5 · SEUILS DSCR APPLICABLES = base du régime + Δ secteur + majoration de phase
A63: Seuil critique de base du régime | B63: =IFERROR(INDEX(P_Crit,MATCH($B$15,P_Regimes,0)),"") -> 0
A64: Écart sectoriel Δ | B64: =IFERROR(INDEX(P_SecDelta,MATCH($B$16,P_SecCodes,0)),"") -> 0
A65: Majoration de phase | B65: =IFERROR(INDEX(P_PhaseMaj,MATCH($B$17,P_PhaseCodes,0)),"") -> 0
A66: Seuils applicables | B66: Critique < | C66: Vigilance < | D66: Favorable < | E66: Très favorable ≥
A67: Seuil = base + Δ + majoration | B67: =IFERROR(INDEX(P_Crit,MATCH($B$15,P_Regimes,0))+$B$64+$B$65,"") -> 0 | C67: =IFERROR(INDEX(P_Vig,MATCH($B$15,P_Regimes,0))+$B$64+$B$65,"") -> 0 | D67: =IFERROR(INDEX(P_Fav,MATCH($B$15,P_Regimes,0))+$B$64+$B$65,"") -> 0 | E67: =D67 -> 0
A69: 6 · ÉCHÉANCIER DATÉ ET DSCR PAR ÉCHÉANCE (jusqu'à 60 périodes)
A70: Scénario défavorable : baisse du CFADS appliquée à chaque période | B70: 0.137871 | C70: Production P90 (− 8 %) et charges d’exploitation + 10 %
A71: Période | B71: CFADS central | C71: Service de la dette | D71: DSCR | E71: Classement | F71: CFADS stressé (saisie facultative) | G71: DSCR stressé | H71: DSCR annuel (paire de semestres)
A72: An 1 · S1 | B72: 25.9 | C72: 19.45 | D72: =IF(OR(B72="",C72=""),"",IF(C72=0,"",B72/C72)) -> 0 | E72: =IF(B72="","",IF(C72=0,"Différé",IF(B72<0,"Critique",IF(D72<$B$67,"Critique",IF(D72<$C$67,"Vigilance",IF(D72<$D$67,"Favorable","Très favorable")))))) -> 0 | G72: =IF(OR(B72="",C72="",C72=0),"",IF(F72<>"",F72,B72*(1-$B$70))/C72) -> 0
A73: An 1 · S2 | B73: 28.1 | C73: 19.45 | D73: =IF(OR(B73="",C73=""),"",IF(C73=0,"",B73/C73)) -> 0 | E73: =IF(B73="","",IF(C73=0,"Différé",IF(B73<0,"Critique",IF(D73<$B$67,"Critique",IF(D73<$C$67,"Vigilance",IF(D73<$D$67,"Favorable","Très favorable")))))) -> 0 | G73: =IF(OR(B73="",C73="",C73=0),"",IF(F73<>"",F73,B73*(1-$B$70))/C73) -> 0 | H73: =IF(AND($B$18="Semestrielle",B73<>"",B72<>"",N(C73)+N(C72)>0),(B73+B72)/(C73+C72),"") -> 0
A74: An 10 · S1 | B74: 25.5 | C74: 19.45 | D74: =IF(OR(B74="",C74=""),"",IF(C74=0,"",B74/C74)) -> 0 | E74: =IF(B74="","",IF(C74=0,"Différé",IF(B74<0,"Critique",IF(D74<$B$67,"Critique",IF(D74<$C$67,"Vigilance",IF(D74<$D$67,"Favorable","Très favorable")))))) -> 0 | G74: =IF(OR(B74="",C74="",C74=0),"",IF(F74<>"",F74,B74*(1-$B$70))/C74) -> 0
A75: An 10 · S2 | B75: 27.7 | C75: 19.45 | D75: =IF(OR(B75="",C75=""),"",IF(C75=0,"",B75/C75)) -> 0 | E75: =IF(B75="","",IF(C75=0,"Différé",IF(B75<0,"Critique",IF(D75<$B$67,"Critique",IF(D75<$C$67,"Vigilance",IF(D75<$D$67,"Favorable","Très favorable")))))) -> 0 | G75: =IF(OR(B75="",C75="",C75=0),"",IF(F75<>"",F75,B75*(1-$B$70))/C75) -> 0 | H75: =IF(AND($B$18="Semestrielle",B75<>"",B74<>"",N(C75)+N(C74)>0),(B75+B74)/(C75+C74),"") -> 0
A76: An 20 · S1 | B76: 25.2 | C76: 19.45 | D76: =IF(OR(B76="",C76=""),"",IF(C76=0,"",B76/C76)) -> 0 | E76: =IF(B76="","",IF(C76=0,"Différé",IF(B76<0,"Critique",IF(D76<$B$67,"Critique",IF(D76<$C$67,"Vigilance",IF(D76<$D$67,"Favorable","Très favorable")))))) -> 0 | G76: =IF(OR(B76="",C76="",C76=0),"",IF(F76<>"",F76,B76*(1-$B$70))/C76) -> 0
A77: An 20 · S2 | B77: 27.2 | C77: 19.45 | D77: =IF(OR(B77="",C77=""),"",IF(C77=0,"",B77/C77)) -> 0 | E77: =IF(B77="","",IF(C77=0,"Différé",IF(B77<0,"Critique",IF(D77<$B$67,"Critique",IF(D77<$C$67,"Vigilance",IF(D77<$D$67,"Favorable","Très favorable")))))) -> 0 | G77: =IF(OR(B77="",C77="",C77=0),"",IF(F77<>"",F77,B77*(1-$B$70))/C77) -> 0 | H77: =IF(AND($B$18="Semestrielle",B77<>"",B76<>"",N(C77)+N(C76)>0),(B77+B76)/(C77+C76),"") -> 0
D78: =IF(OR(B78="",C78=""),"",IF(C78=0,"",B78/C78)) -> 0 | E78: =IF(B78="","",IF(C78=0,"Différé",IF(B78<0,"Critique",IF(D78<$B$67,"Critique",IF(D78<$C$67,"Vigilance",IF(D78<$D$67,"Favorable","Très favorable")))))) -> 0 | G78: =IF(OR(B78="",C78="",C78=0),"",IF(F78<>"",F78,B78*(1-$B$70))/C78) -> 0
D79: =IF(OR(B79="",C79=""),"",IF(C79=0,"",B79/C79)) -> 0 | E79: =IF(B79="","",IF(C79=0,"Différé",IF(B79<0,"Critique",IF(D79<$B$67,"Critique",IF(D79<$C$67,"Vigilance",IF(D79<$D$67,"Favorable","Très favorable")))))) -> 0 | G79: =IF(OR(B79="",C79="",C79=0),"",IF(F79<>"",F79,B79*(1-$B$70))/C79) -> 0 | H79: =IF(AND($B$18="Semestrielle",B79<>"",B78<>"",N(C79)+N(C78)>0),(B79+B78)/(C79+C78),"") -> 0
D80: =IF(OR(B80="",C80=""),"",IF(C80=0,"",B80/C80)) -> 0 | E80: =IF(B80="","",IF(C80=0,"Différé",IF(B80<0,"Critique",IF(D80<$B$67,"Critique",IF(D80<$C$67,"Vigilance",IF(D80<$D$67,"Favorable","Très favorable")))))) -> 0 | G80: =IF(OR(B80="",C80="",C80=0),"",IF(F80<>"",F80,B80*(1-$B$70))/C80) -> 0
D81: =IF(OR(B81="",C81=""),"",IF(C81=0,"",B81/C81)) -> 0 | E81: =IF(B81="","",IF(C81=0,"Différé",IF(B81<0,"Critique",IF(D81<$B$67,"Critique",IF(D81<$C$67,"Vigilance",IF(D81<$D$67,"Favorable","Très favorable")))))) -> 0 | G81: =IF(OR(B81="",C81="",C81=0),"",IF(F81<>"",F81,B81*(1-$B$70))/C81) -> 0 | H81: =IF(AND($B$18="Semestrielle",B81<>"",B80<>"",N(C81)+N(C80)>0),(B81+B80)/(C81+C80),"") -> 0
D82: =IF(OR(B82="",C82=""),"",IF(C82=0,"",B82/C82)) -> 0 | E82: =IF(B82="","",IF(C82=0,"Différé",IF(B82<0,"Critique",IF(D82<$B$67,"Critique",IF(D82<$C$67,"Vigilance",IF(D82<$D$67,"Favorable","Très favorable")))))) -> 0 | G82: =IF(OR(B82="",C82="",C82=0),"",IF(F82<>"",F82,B82*(1-$B$70))/C82) -> 0
D83: =IF(OR(B83="",C83=""),"",IF(C83=0,"",B83/C83)) -> 0 | E83: =IF(B83="","",IF(C83=0,"Différé",IF(B83<0,"Critique",IF(D83<$B$67,"Critique",IF(D83<$C$67,"Vigilance",IF(D83<$D$67,"Favorable","Très favorable")))))) -> 0 | G83: =IF(OR(B83="",C83="",C83=0),"",IF(F83<>"",F83,B83*(1-$B$70))/C83) -> 0 | H83: =IF(AND($B$18="Semestrielle",B83<>"",B82<>"",N(C83)+N(C82)>0),(B83+B82)/(C83+C82),"") -> 0
D84: =IF(OR(B84="",C84=""),"",IF(C84=0,"",B84/C84)) -> 0 | E84: =IF(B84="","",IF(C84=0,"Différé",IF(B84<0,"Critique",IF(D84<$B$67,"Critique",IF(D84<$C$67,"Vigilance",IF(D84<$D$67,"Favorable","Très favorable")))))) -> 0 | G84: =IF(OR(B84="",C84="",C84=0),"",IF(F84<>"",F84,B84*(1-$B$70))/C84) -> 0
D85: =IF(OR(B85="",C85=""),"",IF(C85=0,"",B85/C85)) -> 0 | E85: =IF(B85="","",IF(C85=0,"Différé",IF(B85<0,"Critique",IF(D85<$B$67,"Critique",IF(D85<$C$67,"Vigilance",IF(D85<$D$67,"Favorable","Très favorable")))))) -> 0 | G85: =IF(OR(B85="",C85="",C85=0),"",IF(F85<>"",F85,B85*(1-$B$70))/C85) -> 0 | H85: =IF(AND($B$18="Semestrielle",B85<>"",B84<>"",N(C85)+N(C84)>0),(B85+B84)/(C85+C84),"") -> 0
D86: =IF(OR(B86="",C86=""),"",IF(C86=0,"",B86/C86)) -> 0 | E86: =IF(B86="","",IF(C86=0,"Différé",IF(B86<0,"Critique",IF(D86<$B$67,"Critique",IF(D86<$C$67,"Vigilance",IF(D86<$D$67,"Favorable","Très favorable")))))) -> 0 | G86: =IF(OR(B86="",C86="",C86=0),"",IF(F86<>"",F86,B86*(1-$B$70))/C86) -> 0
D87: =IF(OR(B87="",C87=""),"",IF(C87=0,"",B87/C87)) -> 0 | E87: =IF(B87="","",IF(C87=0,"Différé",IF(B87<0,"Critique",IF(D87<$B$67,"Critique",IF(D87<$C$67,"Vigilance",IF(D87<$D$67,"Favorable","Très favorable")))))) -> 0 | G87: =IF(OR(B87="",C87="",C87=0),"",IF(F87<>"",F87,B87*(1-$B$70))/C87) -> 0 | H87: =IF(AND($B$18="Semestrielle",B87<>"",B86<>"",N(C87)+N(C86)>0),(B87+B86)/(C87+C86),"") -> 0
D88: =IF(OR(B88="",C88=""),"",IF(C88=0,"",B88/C88)) -> 0 | E88: =IF(B88="","",IF(C88=0,"Différé",IF(B88<0,"Critique",IF(D88<$B$67,"Critique",IF(D88<$C$67,"Vigilance",IF(D88<$D$67,"Favorable","Très favorable")))))) -> 0 | G88: =IF(OR(B88="",C88="",C88=0),"",IF(F88<>"",F88,B88*(1-$B$70))/C88) -> 0
D89: =IF(OR(B89="",C89=""),"",IF(C89=0,"",B89/C89)) -> 0 | E89: =IF(B89="","",IF(C89=0,"Différé",IF(B89<0,"Critique",IF(D89<$B$67,"Critique",IF(D89<$C$67,"Vigilance",IF(D89<$D$67,"Favorable","Très favorable")))))) -> 0 | G89: =IF(OR(B89="",C89="",C89=0),"",IF(F89<>"",F89,B89*(1-$B$70))/C89) -> 0 | H89: =IF(AND($B$18="Semestrielle",B89<>"",B88<>"",N(C89)+N(C88)>0),(B89+B88)/(C89+C88),"") -> 0
D90: =IF(OR(B90="",C90=""),"",IF(C90=0,"",B90/C90)) -> 0 | E90: =IF(B90="","",IF(C90=0,"Différé",IF(B90<0,"Critique",IF(D90<$B$67,"Critique",IF(D90<$C$67,"Vigilance",IF(D90<$D$67,"Favorable","Très favorable")))))) -> 0 | G90: =IF(OR(B90="",C90="",C90=0),"",IF(F90<>"",F90,B90*(1-$B$70))/C90) -> 0
D91: =IF(OR(B91="",C91=""),"",IF(C91=0,"",B91/C91)) -> 0 | E91: =IF(B91="","",IF(C91=0,"Différé",IF(B91<0,"Critique",IF(D91<$B$67,"Critique",IF(D91<$C$67,"Vigilance",IF(D91<$D$67,"Favorable","Très favorable")))))) -> 0 | G91: =IF(OR(B91="",C91="",C91=0),"",IF(F91<>"",F91,B91*(1-$B$70))/C91) -> 0 | H91: =IF(AND($B$18="Semestrielle",B91<>"",B90<>"",N(C91)+N(C90)>0),(B91+B90)/(C91+C90),"") -> 0
D92: =IF(OR(B92="",C92=""),"",IF(C92=0,"",B92/C92)) -> 0 | E92: =IF(B92="","",IF(C92=0,"Différé",IF(B92<0,"Critique",IF(D92<$B$67,"Critique",IF(D92<$C$67,"Vigilance",IF(D92<$D$67,"Favorable","Très favorable")))))) -> 0 | G92: =IF(OR(B92="",C92="",C92=0),"",IF(F92<>"",F92,B92*(1-$B$70))/C92) -> 0
D93: =IF(OR(B93="",C93=""),"",IF(C93=0,"",B93/C93)) -> 0 | E93: =IF(B93="","",IF(C93=0,"Différé",IF(B93<0,"Critique",IF(D93<$B$67,"Critique",IF(D93<$C$67,"Vigilance",IF(D93<$D$67,"Favorable","Très favorable")))))) -> 0 | G93: =IF(OR(B93="",C93="",C93=0),"",IF(F93<>"",F93,B93*(1-$B$70))/C93) -> 0 | H93: =IF(AND($B$18="Semestrielle",B93<>"",B92<>"",N(C93)+N(C92)>0),(B93+B92)/(C93+C92),"") -> 0
D94: =IF(OR(B94="",C94=""),"",IF(C94=0,"",B94/C94)) -> 0 | E94: =IF(B94="","",IF(C94=0,"Différé",IF(B94<0,"Critique",IF(D94<$B$67,"Critique",IF(D94<$C$67,"Vigilance",IF(D94<$D$67,"Favorable","Très favorable")))))) -> 0 | G94: =IF(OR(B94="",C94="",C94=0),"",IF(F94<>"",F94,B94*(1-$B$70))/C94) -> 0
D95: =IF(OR(B95="",C95=""),"",IF(C95=0,"",B95/C95)) -> 0 | E95: =IF(B95="","",IF(C95=0,"Différé",IF(B95<0,"Critique",IF(D95<$B$67,"Critique",IF(D95<$C$67,"Vigilance",IF(D95<$D$67,"Favorable","Très favorable")))))) -> 0 | G95: =IF(OR(B95="",C95="",C95=0),"",IF(F95<>"",F95,B95*(1-$B$70))/C95) -> 0 | H95: =IF(AND($B$18="Semestrielle",B95<>"",B94<>"",N(C95)+N(C94)>0),(B95+B94)/(C95+C94),"") -> 0
D96: =IF(OR(B96="",C96=""),"",IF(C96=0,"",B96/C96)) -> 0 | E96: =IF(B96="","",IF(C96=0,"Différé",IF(B96<0,"Critique",IF(D96<$B$67,"Critique",IF(D96<$C$67,"Vigilance",IF(D96<$D$67,"Favorable","Très favorable")))))) -> 0 | G96: =IF(OR(B96="",C96="",C96=0),"",IF(F96<>"",F96,B96*(1-$B$70))/C96) -> 0
D97: =IF(OR(B97="",C97=""),"",IF(C97=0,"",B97/C97)) -> 0 | E97: =IF(B97="","",IF(C97=0,"Différé",IF(B97<0,"Critique",IF(D97<$B$67,"Critique",IF(D97<$C$67,"Vigilance",IF(D97<$D$67,"Favorable","Très favorable")))))) -> 0 | G97: =IF(OR(B97="",C97="",C97=0),"",IF(F97<>"",F97,B97*(1-$B$70))/C97) -> 0 | H97: =IF(AND($B$18="Semestrielle",B97<>"",B96<>"",N(C97)+N(C96)>0),(B97+B96)/(C97+C96),"") -> 0
D98: =IF(OR(B98="",C98=""),"",IF(C98=0,"",B98/C98)) -> 0 | E98: =IF(B98="","",IF(C98=0,"Différé",IF(B98<0,"Critique",IF(D98<$B$67,"Critique",IF(D98<$C$67,"Vigilance",IF(D98<$D$67,"Favorable","Très favorable")))))) -> 0 | G98: =IF(OR(B98="",C98="",C98=0),"",IF(F98<>"",F98,B98*(1-$B$70))/C98) -> 0
D99: =IF(OR(B99="",C99=""),"",IF(C99=0,"",B99/C99)) -> 0 | E99: =IF(B99="","",IF(C99=0,"Différé",IF(B99<0,"Critique",IF(D99<$B$67,"Critique",IF(D99<$C$67,"Vigilance",IF(D99<$D$67,"Favorable","Très favorable")))))) -> 0 | G99: =IF(OR(B99="",C99="",C99=0),"",IF(F99<>"",F99,B99*(1-$B$70))/C99) -> 0 | H99: =IF(AND($B$18="Semestrielle",B99<>"",B98<>"",N(C99)+N(C98)>0),(B99+B98)/(C99+C98),"") -> 0
D100: =IF(OR(B100="",C100=""),"",IF(C100=0,"",B100/C100)) -> 0 | E100: =IF(B100="","",IF(C100=0,"Différé",IF(B100<0,"Critique",IF(D100<$B$67,"Critique",IF(D100<$C$67,"Vigilance",IF(D100<$D$67,"Favorable","Très favorable")))))) -> 0 | G100: =IF(OR(B100="",C100="",C100=0),"",IF(F100<>"",F100,B100*(1-$B$70))/C100) -> 0
D101: =IF(OR(B101="",C101=""),"",IF(C101=0,"",B101/C101)) -> 0 | E101: =IF(B101="","",IF(C101=0,"Différé",IF(B101<0,"Critique",IF(D101<$B$67,"Critique",IF(D101<$C$67,"Vigilance",IF(D101<$D$67,"Favorable","Très favorable")))))) -> 0 | G101: =IF(OR(B101="",C101="",C101=0),"",IF(F101<>"",F101,B101*(1-$B$70))/C101) -> 0 | H101: =IF(AND($B$18="Semestrielle",B101<>"",B100<>"",N(C101)+N(C100)>0),(B101+B100)/(C101+C100),"") -> 0
D102: =IF(OR(B102="",C102=""),"",IF(C102=0,"",B102/C102)) -> 0 | E102: =IF(B102="","",IF(C102=0,"Différé",IF(B102<0,"Critique",IF(D102<$B$67,"Critique",IF(D102<$C$67,"Vigilance",IF(D102<$D$67,"Favorable","Très favorable")))))) -> 0 | G102: =IF(OR(B102="",C102="",C102=0),"",IF(F102<>"",F102,B102*(1-$B$70))/C102) -> 0
D103: =IF(OR(B103="",C103=""),"",IF(C103=0,"",B103/C103)) -> 0 | E103: =IF(B103="","",IF(C103=0,"Différé",IF(B103<0,"Critique",IF(D103<$B$67,"Critique",IF(D103<$C$67,"Vigilance",IF(D103<$D$67,"Favorable","Très favorable")))))) -> 0 | G103: =IF(OR(B103="",C103="",C103=0),"",IF(F103<>"",F103,B103*(1-$B$70))/C103) -> 0 | H103: =IF(AND($B$18="Semestrielle",B103<>"",B102<>"",N(C103)+N(C102)>0),(B103+B102)/(C103+C102),"") -> 0
...

Sheet C2
A1: CAS 2 · Usine de dessalement 100 000 m³/jour | J1: DOSSIER_V8
A2: SPV « Aqua Souss » SA (fictive) — Littoral de Souss-Massa
A3: Usine d'osmose inverse rémunérée par une redevance de capacité versée par l'acheteur public, assortie d'une redevance variable répercutant le coût de l'énergie dans une limite plafonnée.
A4: À SAISIR (cellules orange) | B4: =COUNTIF($R$14:$R$56,0) -> 0 | C4: =IF(B4=0,"Saisie complète : lisez la note ci-dessous, puis « Fiche comité ».","Prochaine saisie : "&INDEX($P$14:$P$56,MATCH(0,$R$14:$R$56,0))) -> 0 | G4: =IF(B4=0,"",HYPERLINK("#"&INDEX($Q$14:$Q$56,MATCH(0,$R$14:$R$56,0)),"→ Aller à la cellule "&INDEX($Q$14:$Q$56,MATCH(0,$R$14:$R$56,0)))) -> 0
A5: TABLEAU DE BORD — se met à jour à chaque saisie
A6: NOTE APPROUVÉE (1 à 10) | B6: =B255 -> 0 | C6: Libellé | D6: =IFERROR(INDEX(P_ConvLib,MATCH(B255,P_ConvNote,0)),"") -> 0 | E6: Statut | F6: =B256 -> 0
A7: Score global (sur 100) | B7: =B217 -> 0 | C7: Note calculée | D7: =B218 -> 0 | E7: Plafond applicable | F7: =IF(B252>=10,"Aucun (10)",B252) -> 0
A8: Plafonds actifs | B8: =IF(TRIM(IF(E237="Oui","C1 ("&F237&") ","")&IF(E238="Oui","C2 ("&F238&") ","")&IF(E239="Oui","C3 ("&F239&") ","")&IF(E240="Oui","C4 ("&F240&") ","")&IF(E241="Oui","C5 ("&F241&") ","")&IF(E242="Oui","C6 ("&F242&") ","")&IF(E243="Oui","C7 ("&F243&") ","")&IF(E244="Oui","C8 ("&F244&") ","")&IF(E245="Oui","C9 ("&F245&") ","")&IF(E246="Oui","C10 ("&F246&") ","")&IF(E247="Oui","C11 ("&F247&") ","")&IF(E248="Oui","C12 ("&F248&") ","")&IF(E249="Oui","C13 ("&F249&") ","")&IF(E250="Oui","C14 ("&F250&") ","")&IF(E251="Oui","C15 ("&F251&") ",""))="","Aucun",TRIM(IF(E237="Oui","C1 ("&F237&") ","")&IF(E238="Oui","C2 ("&F238&") ","")&IF(E239="Oui","C3 ("&F239&") ","")&IF(E240="Oui","C4 ("&F240&") ","")&IF(E241="Oui","C5 ("&F241&") ","")&IF(E242="Oui","C6 ("&F242&") ","")&IF(E243="Oui","C7 ("&F243&") ","")&IF(E244="Oui","C8 ("&F244&") ","")&IF(E245="Oui","C9 ("&F245&") ","")&IF(E246="Oui","C10 ("&F246&") ","")&IF(E247="Oui","C11 ("&F247&") ","")&IF(E248="Oui","C12 ("&F248&") ","")&IF(E249="Oui","C13 ("&F249&") ","")&IF(E250="Oui","C14 ("&F250&") ","")&IF(E251="Oui","C15 ("&F251&") ","")))&IF(COUNTIF(E237:E251,"n.r.")>0," — "&COUNTIF(E237:E251,"n.r.")&" plafond(s) non évalué(s) faute de donnée","") -> 0
A9: Verrous actifs (exclusions X, blocages B) | B9: =IF(TRIM(IF(F222="Oui","X1 ","")&IF(F223="Oui","X2 ","")&IF(F224="Oui","X3 ","")&IF(F225="Oui","X4 ","")&IF(F226="Oui","B1 ","")&IF(F227="Oui","B2 ","")&IF(F228="Oui","B3 ","")&IF(F229="Oui","B4 ","")&IF(F230="Oui","B5 ","")&IF(F231="Oui","B6 ","")&IF(F232="Oui","B7 ","")&IF(F233="Oui","B8 ",""))="","Aucun",TRIM(IF(F222="Oui","X1 ","")&IF(F223="Oui","X2 ","")&IF(F224="Oui","X3 ","")&IF(F225="Oui","X4 ","")&IF(F226="Oui","B1 ","")&IF(F227="Oui","B2 ","")&IF(F228="Oui","B3 ","")&IF(F229="Oui","B4 ","")&IF(F230="Oui","B5 ","")&IF(F231="Oui","B6 ","")&IF(F232="Oui","B7 ","")&IF(F233="Oui","B8 ",""))) -> 0
A10: Régime de proportionnalité retenu | B10: =B35 -> 0 | C10: DSCR minimum | D10: =D133 -> 0 | E10: DSCR stressé min. | F10: =D134 -> 0
A11: Complétude (noyau N1-N6 et grille) | B11: =B204 -> 0 | C11: Noyau financier D7 | D11: =D148 -> 0 | E11: Orientation | F11: =IFERROR(INDEX(P_ConvOrient,MATCH(B255,P_ConvNote,0)),"") -> 0
A12: Aller à la section : | B12: =HYPERLINK("#A13","1 · Routage") -> 0 | C12: =HYPERLINK("#A37","3 · Sources") -> 0 | D12: =HYPERLINK("#A69","6 · Échéancier") -> 0 | E12: =HYPERLINK("#A140","7 · Noyau") -> 0 | F12: =HYPERLINK("#A167","8 · Grille") -> 0 | G12: =HYPERLINK("#A220","10 · Verrous") -> 0 | H12: =HYPERLINK("#A235","11 · Plafonds") -> 0
A13: 1 · ROUTAGE — pilote les seuils DSCR et les poids de domaine
A14: Axe | B14: Valeur | C14: Libellé | P14: 1 · Régime de revenus | Q14: B15 | R14: =IF($B$15<>"",1,0) -> 0
A15: C — Régime de revenus | B15: R2 | C15: =IFERROR(INDEX(P_RegLib,MATCH(B15,P_Regimes,0)),"") -> 0 | P15: 1 · Secteur du projet | Q15: B16 | R15: =IF($B$16<>"",1,0) -> 0
A16: D — Secteur du projet | B16: EAU | C16: =IFERROR(INDEX(P_SecLib,MATCH(B16,P_SecCodes,0)),"") -> 0 | P16: 1 · Phase du projet | Q16: B17 | R16: =IF($B$17<>"",1,0) -> 0
A17: B — Phase | B17: P2 | C17: =IFERROR(INDEX(P_PhaseLib,MATCH(B17,P_PhaseCodes,0)),"") -> 0 | P17: 1 · Périodicité des échéances | Q17: B18 | R17: =IF($B$18<>"",1,0) -> 0
A18: Périodicité du service de la dette | B18: Semestrielle | C18: Jamais annuelle : le DSCR se mesure échéance par échéance. | P18: 2 · Exposition de la banque (MMAD) | Q18: B23 | R18: =IF(ISNUMBER($B$23),1,0) -> 0
A19: A — Famille de financement | B19: PF-FLUX | C19: SPV dédiée, remboursement par les flux du projet (R5 vente d'actifs : hors outil). | P19: 2 · Recettes, coûts et dette en dirhams ? | Q19: B24 | R19: =IF($B$24<>"",1,0) -> 0
P20: 2 · Durée du financement (ans) | Q20: B25 | R20: =IF(ISNUMBER($B$25),1,0) -> 0
A21: 2 · RÉGIME DE PROPORTIONNALITÉ — calculé, jamais choisi | P21: 2 · Technologie éprouvée ? | Q21: B26 | R21: =IF($B$26<>"",1,0) -> 0
A22: CAPEX du projet économique complet (MMAD) | B22: =B47 -> 0 | C22: Repris du total des emplois (section 3). | P22: 2 · EPC clé-en-main de moins de 18 mois ? (phase P1) | Q22: B27 | R22: =IF(OR(NOT($B$17="P1"),$B$27<>""),1,0) -> 0
A23: Exposition de la banque (MMAD) | P23: 2 · Acheteur principal unique ? | Q23: B28 | R23: =IF($B$28<>"",1,0) -> 0
A24: Recettes, coûts et dette intégralement en dirhams | B24: Non | P24: 2 · Première référence technologique ? | Q24: B29 | R24: =IF($B$29<>"",1,0) -> 0
A25: Durée du financement (ans) | B25: 20 | P25: 2 · Opération consortiale ? | Q25: B30 | R25: =IF($B$30<>"",1,0) -> 0
A26: Technologie : ≥ 3 références industrielles de plus de 3 ans | B26: Oui | P26: 2 · Contrat de revenus de plus de 20 ans ? | Q26: B31 | R26: =IF($B$31<>"",1,0) -> 0
A27: En P1 : EPC clé-en-main forfaitaire, prix et délai garantis, < 18 mois | B27: Non | P27: 2 · Site à risque climatique élevé ? | Q27: B32 | R27: =IF($B$32<>"",1,0) -> 0
A28: Acheteur principal unique et identifié | B28: Oui | P28: 2 · Nombre de contreparties clés | Q28: B33 | R28: =IF(ISNUMBER($B$33),1,0) -> 0
A29: Technologie constituant une première référence dans la juridiction | B29: Non | P29: 3 · Emplois : montants du besoin à terminaison | Q29: B39 | R29: =IF(N($B$47)>0,1,0) -> 0
A30: Opération consortiale relevant de la directive 3/W/2025 | B30: Oui | P30: 3 · Ressources engagées : montants | Q30: E39 | R30: =IF(N($E$47)>0,1,0) -> 0
A31: Concession ou contrat de revenus de plus de 20 ans | B31: Non | P31: 3 · Nature de chaque ressource | Q31: F39 | R31: =IF(SUMPRODUCT(ISNUMBER($E$39:$E$46)*($F$39:$F$46=""))=0,1,0) -> 0
A32: Site classé à risque climatique physique élevé | B32: Non | P32: 3 · Plan de remédiation (couverture entre 95 et 100 %) | Q32: B50 | R32: =IF(OR(NOT(AND($B$17="P1",ISNUMBER($B$48),N($B$48)>=P_N3_V,N($B$48)<P_N3_F)),$B$50<>""),1,0) -> 0
A33: Nombre de contreparties clés | P33: 6 · Choc du scénario défavorable (%) | Q33: B70 | R33: =IF(ISNUMBER($B$70),1,0) -> 0
A34: Régime calculé (avant escalade) | B34: =IF(OR(B22="",B22=0,B15=""),"",IF(OR(B22>P_L_CAPEX,N(B23)>P_L_EXPO,B15="R4",B29="Oui",N(B153)>0,B30="Oui",B31="Oui",B32="Oui",N(B33)>P_L_NBCP),"L",IF(AND(B22<=P_S_CAPEX,B23<>"",N(B23)<=P_S_EXPO,OR(B15="R1",B15="R2"),B26="Oui",B24="Oui",B25<>"",N(B25)<=P_S_DUREE,OR(B17<>"P1",B27="Oui"),B28="Oui",COUNTIF($F$222:$F$233,"Oui")=0),"S","M"))) -> 0 | C34: =IF(B34="","",IF(B34="L","Escalade : "&IF(B22>P_L_CAPEX,"CAPEX > "&P_L_CAPEX&" MMAD ; ","")&IF(N(B23)>P_L_EXPO,"exposition > "&P_L_EXPO&" MMAD ; ","")&IF(B15="R4","régime de revenus R4 ; ","")&IF(B29="Oui","première référence technologique ; ","")&IF(N(B153)>0,"devises non intégralement couvertes ; ","")&IF(B30="Oui","opération consortiale ; ","")&IF(B31="Oui","contrat de revenus > 20 ans ; ","")&IF(B32="Oui","risque climatique élevé ; ","")&IF(N(B33)>P_L_NBCP,"plus de "&P_L_NBCP&" contreparties clés ; ",""),IF(B34="S","Toutes les conditions du régime simplifié sont réunies.","Régime standard par défaut : une condition du régime S manque, aucune condition d'escalade."))) -> 0 | P34: 6 · Échéancier : CFADS d'au moins deux périodes | Q34: B72 | R34: =IF(COUNT($B$72:$B$131)>=2,1,0) -> 0
A35: RÉGIME RETENU (après escalade automatique) | B35: =IF(B34="","",IF(AND(IF(AND(B34="S",COUNTIF($F$222:$F$233,"Oui")>0),"M",B34)="M",COUNTIF($E$237:$E$251,"Oui")>0),"L",IF(AND(B34="S",COUNTIF($F$222:$F$233,"Oui")>0),"M",B34))) -> 0 | C35: =IF(B35=B34,"Aucune escalade.",IF(B35="L","Escalade : un plafond de note est actif (M passe en L).","Escalade : un verrou est actif (S passe en M).")) -> 0 | P35: 6 · Service de la dette de chaque période | Q35: C72 | R35: =IF(SUMPRODUCT(ISNUMBER($B$72:$B$131)*(1-ISNUMBER($C$72:$C$131)))=0,1,0) -> 0
P36: 7 · N4 — Liquidité (DSRA, lignes, cascade) | Q36: B145 | R36: =IF($B$145<>"",1,0) -> 0
A37: 3 · SOURCES ET EMPLOIS (MMAD) — test de financement à terminaison | P37: 7 · N5 — Levier et fonds propres à risque | Q37: B146 | R37: =IF($B$146<>"",1,0) -> 0
A38: Emplois | B38: Montant | D38: Ressources | E38: Montant | F38: Nature | P38: 7 · N6 — Exposition résiduelle taux, change, refinancement | Q38: B147 | R38: =IF($B$147<>"",1,0) -> 0
A39: Contrat EPC (prise d’eau, osmose inverse, rejet) | B39: 1780 | D39: Dette senior (20 ans, 6,0 %), dont 35 % en euros | E39: 1680 | F39: Dette senior | P39: 7 · N3 hors phase P1 : note LLCR | Q39: B150 | R39: =IF(OR($B$17="P1",$B$150<>""),1,0) -> 0
A40: Canalisations et raccordement électrique | B40: 240 | D40: Fonds propres | E40: 720 | F40: Fonds propres | P40: 7 · LLCR (plafond C4) | Q40: B151 | R40: =IF(ISNUMBER($B$151),1,0) -> 0
A41: Développement, frais et assurances | B41: 95 | P41: 7 · DSRA en mois (plafond C7) | Q41: B152 | R41: =IF(ISNUMBER($B$152),1,0) -> 0
A42: Contingence | B42: 110 | P42: 7 · Exposition nette en devises (plafond C6) | Q42: B153 | R42: =IF(ISNUMBER($B$153),1,0) -> 0
A43: Intérêts intercalaires | B43: 100 | P43: 7 · Dette à refinancer à maturité (plafond C8) | Q43: B154 | R43: =IF(ISNUMBER($B$154),1,0) -> 0
A44: Dotation initiale DSRA | B44: 50 | P44: 7 · Stratégie de refinancement approuvée ? | Q44: B155 | R44: =IF(OR(N($B$154)<=P_C8,$B$155<>""),1,0) -> 0
A45: BFR de démarrage | B45: 25 | P45: 7 · Part des recettes de l'acheteur principal (C10) | Q45: B156 | R45: =IF(ISNUMBER($B$156),1,0) -> 0
P46: 7 · Qualité de crédit de l'acheteur principal | Q46: B157 | R46: =IF($B$157<>"",1,0) -> 0
A47: Total emplois (besoin à terminaison) | B47: =SUM(B39:B46) -> 0 | D47: Total ressources engagées | E47: =SUM(E39:E46) -> 0 | P47: 7 · Durée résiduelle du contrat de revenus (C5) | Q47: B158 | R47: =IF(OR($B$15="R4",ISNUMBER($B$158)),1,0) -> 0
A48: Couverture du besoin à terminaison (ressources / emplois) | B48: =IF(N(B47)=0,"",E47/B47) -> 0 | P48: 7 · Durée résiduelle de la dette | Q48: B159 | R48: =IF(ISNUMBER($B$159),1,0) -> 0
A49: Quote-part de dette (dette / besoin à terminaison) | B49: =IF(N(B47)=0,"",(SUMIF(F39:F46,"Dette senior",E39:E46)+SUMIF(F39:F46,"Dette subordonnée",E39:E46))/B47) -> 0 | P49: 7 · Solution documentée (contrat plus court que la dette) ? | Q49: B160 | R49: =IF(OR(NOT(AND(ISNUMBER($B$158),ISNUMBER($B$159))),N($B$158)>=N($B$159),$B$160<>""),1,0) -> 0
A50: Plan de remédiation approuvé (couverture entre 95 % et 100 %) | B50: Non | P50: 7 · Plan d'adaptation climatique financé ? (C11) | Q50: B161 | R50: =IF(OR($B$32<>"Oui",$B$161<>""),1,0) -> 0
P51: 7 · Capacité résiduelle du sponsor (C12) | Q51: B162 | R51: =IF($B$162<>"",1,0) -> 0
A52: 4 · HYPOTHÈSES D'EXPLOITATION (information, non calculées) | P52: 7 · Opérateur remplaçable ? (C13) | Q52: B163 | R52: =IF($B$163<>"",1,0) -> 0
A53: Capacité contractuelle | B53: 100 000 m³/jour | P53: 7 · Écart fin O&M / fin de dette (opérateur non remplaçable) | Q53: B164 | R53: =IF(OR($B$163<>"Non",ISNUMBER($B$164)),1,0) -> 0
A54: Redevance de capacité | B54: 290 MMAD/an | P54: 7 · Facteur commun au-delà de la limite interne (C14) | Q54: B165 | R54: =IF($B$165<>"",1,0) -> 0
A55: Redevance variable énergie | B55: Répercutée à 60 % seulement au-delà d’un plafond | P55: 8 · Grille : sous-critère requis non noté | Q55: ="B"&IF(COUNT($P$169:$P$201)=0,169,MIN($P$169:$P$201)) -> 0 | R55: =IF(COUNT($P$169:$P$201)=0,1,0) -> 0
A56: Charges hors énergie | B56: 60 MMAD/an | P56: 10 · Verrous X1 à B8 : répondre Oui ou Non | Q56: E222 | R56: =IF(COUNTBLANK($E$222:$E$233)=0,1,0) -> 0
A57: EBITDA | B57: 230 MMAD/an
A58: CFADS à régime établi | B58: 196 MMAD/an
A59: Service de la dette | B59: 146,5 MMAD/an, semestriel
A62: 5 · SEUILS DSCR APPLICABLES = base du régime + Δ secteur + majoration de phase
A63: Seuil critique de base du régime | B63: =IFERROR(INDEX(P_Crit,MATCH($B$15,P_Regimes,0)),"") -> 0
A64: Écart sectoriel Δ | B64: =IFERROR(INDEX(P_SecDelta,MATCH($B$16,P_SecCodes,0)),"") -> 0
A65: Majoration de phase | B65: =IFERROR(INDEX(P_PhaseMaj,MATCH($B$17,P_PhaseCodes,0)),"") -> 0
A66: Seuils applicables | B66: Critique < | C66: Vigilance < | D66: Favorable < | E66: Très favorable ≥
A67: Seuil = base + Δ + majoration | B67: =IFERROR(INDEX(P_Crit,MATCH($B$15,P_Regimes,0))+$B$64+$B$65,"") -> 0 | C67: =IFERROR(INDEX(P_Vig,MATCH($B$15,P_Regimes,0))+$B$64+$B$65,"") -> 0 | D67: =IFERROR(INDEX(P_Fav,MATCH($B$15,P_Regimes,0))+$B$64+$B$65,"") -> 0 | E67: =D67 -> 0
A69: 6 · ÉCHÉANCIER DATÉ ET DSCR PAR ÉCHÉANCE (jusqu'à 60 périodes)
A70: Scénario défavorable : baisse du CFADS appliquée à chaque période | B70: 0.109606 | C70: Coût de l’énergie + 15 % répercuté à 60 % seulement, disponibilité ramenée à 92 %
A71: Période | B71: CFADS central | C71: Service de la dette | D71: DSCR | E71: Classement | F71: CFADS stressé (saisie facultative) | G71: DSCR stressé | H71: DSCR annuel (paire de semestres)
A72: An 1 · S1 (disponibilité 94 %) | B72: 90 | C72: 73.25 | D72: =IF(OR(B72="",C72=""),"",IF(C72=0,"",B72/C72)) -> 0 | E72: =IF(B72="","",IF(C72=0,"Différé",IF(B72<0,"Critique",IF(D72<$B$67,"Critique",IF(D72<$C$67,"Vigilance",IF(D72<$D$67,"Favorable","Très favorable")))))) -> 0 | G72: =IF(OR(B72="",C72="",C72=0),"",IF(F72<>"",F72,B72*(1-$B$70))/C72) -> 0
A73: An 1 · S2 (disponibilité 95 %) | B73: 93 | C73: 73.25 | D73: =IF(OR(B73="",C73=""),"",IF(C73=0,"",B73/C73)) -> 0 | E73: =IF(B73="","",IF(C73=0,"Différé",IF(B73<0,"Critique",IF(D73<$B$67,"Critique",IF(D73<$C$67,"Vigilance",IF(D73<$D$67,"Favorable","Très favorable")))))) -> 0 | G73: =IF(OR(B73="",C73="",C73=0),"",IF(F73<>"",F73,B73*(1-$B$70))/C73) -> 0 | H73: =IF(AND($B$18="Semestrielle",B73<>"",B72<>"",N(C73)+N(C72)>0),(B73+B72)/(C73+C72),"") -> 0
A74: An 3 · S1 (régime établi) | B74: 97 | C74: 73.25 | D74: =IF(OR(B74="",C74=""),"",IF(C74=0,"",B74/C74)) -> 0 | E74: =IF(B74="","",IF(C74=0,"Différé",IF(B74<0,"Critique",IF(D74<$B$67,"Critique",IF(D74<$C$67,"Vigilance",IF(D74<$D$67,"Favorable","Très favorable")))))) -> 0 | G74: =IF(OR(B74="",C74="",C74=0),"",IF(F74<>"",F74,B74*(1-$B$70))/C74) -> 0
A75: An 3 · S2 (régime établi) | B75: 99 | C75: 73.25 | D75: =IF(OR(B75="",C75=""),"",IF(C75=0,"",B75/C75)) -> 0 | E75: =IF(B75="","",IF(C75=0,"Différé",IF(B75<0,"Critique",IF(D75<$B$67,"Critique",IF(D75<$C$67,"Vigilance",IF(D75<$D$67,"Favorable","Très favorable")))))) -> 0 | G75: =IF(OR(B75="",C75="",C75=0),"",IF(F75<>"",F75,B75*(1-$B$70))/C75) -> 0 | H75: =IF(AND($B$18="Semestrielle",B75<>"",B74<>"",N(C75)+N(C74)>0),(B75+B74)/(C75+C74),"") -> 0
D76: =IF(OR(B76="",C76=""),"",IF(C76=0,"",B76/C76)) -> 0 | E76: =IF(B76="","",IF(C76=0,"Différé",IF(B76<0,"Critique",IF(D76<$B$67,"Critique",IF(D76<$C$67,"Vigilance",IF(D76<$D$67,"Favorable","Très favorable")))))) -> 0 | G76: =IF(OR(B76="",C76="",C76=0),"",IF(F76<>"",F76,B76*(1-$B$70))/C76) -> 0
D77: =IF(OR(B77="",C77=""),"",IF(C77=0,"",B77/C77)) -> 0 | E77: =IF(B77="","",IF(C77=0,"Différé",IF(B77<0,"Critique",IF(D77<$B$67,"Critique",IF(D77<$C$67,"Vigilance",IF(D77<$D$67,"Favorable","Très favorable")))))) -> 0 | G77: =IF(OR(B77="",C77="",C77=0),"",IF(F77<>"",F77,B77*(1-$B$70))/C77) -> 0 | H77: =IF(AND($B$18="Semestrielle",B77<>"",B76<>"",N(C77)+N(C76)>0),(B77+B76)/(C77+C76),"") -> 0
D78: =IF(OR(B78="",C78=""),"",IF(C78=0,"",B78/C78)) -> 0 | E78: =IF(B78="","",IF(C78=0,"Différé",IF(B78<0,"Critique",IF(D78<$B$67,"Critique",IF(D78<$C$67,"Vigilance",IF(D78<$D$67,"Favorable","Très favorable")))))) -> 0 | G78: =IF(OR(B78="",C78="",C78=0),"",IF(F78<>"",F78,B78*(1-$B$70))/C78) -> 0
D79: =IF(OR(B79="",C79=""),"",IF(C79=0,"",B79/C79)) -> 0 | E79: =IF(B79="","",IF(C79=0,"Différé",IF(B79<0,"Critique",IF(D79<$B$67,"Critique",IF(D79<$C$67,"Vigilance",IF(D79<$D$67,"Favorable","Très favorable")))))) -> 0 | G79: =IF(OR(B79="",C79="",C79=0),"",IF(F79<>"",F79,B79*(1-$B$70))/C79) -> 0 | H79: =IF(AND($B$18="Semestrielle",B79<>"",B78<>"",N(C79)+N(C78)>0),(B79+B78)/(C79+C78),"") -> 0
D80: =IF(OR(B80="",C80=""),"",IF(C80=0,"",B80/C80)) -> 0 | E80: =IF(B80="","",IF(C80=0,"Différé",IF(B80<0,"Critique",IF(D80<$B$67,"Critique",IF(D80<$C$67,"Vigilance",IF(D80<$D$67,"Favorable","Très favorable")))))) -> 0 | G80: =IF(OR(B80="",C80="",C80=0),"",IF(F80<>"",F80,B80*(1-$B$70))/C80) -> 0
D81: =IF(OR(B81="",C81=""),"",IF(C81=0,"",B81/C81)) -> 0 | E81: =IF(B81="","",IF(C81=0,"Différé",IF(B81<0,"Critique",IF(D81<$B$67,"Critique",IF(D81<$C$67,"Vigilance",IF(D81<$D$67,"Favorable","Très favorable")))))) -> 0 | G81: =IF(OR(B81="",C81="",C81=0),"",IF(F81<>"",F81,B81*(1-$B$70))/C81) -> 0 | H81: =IF(AND($B$18="Semestrielle",B81<>"",B80<>"",N(C81)+N(C80)>0),(B81+B80)/(C81+C80),"") -> 0
D82: =IF(OR(B82="",C82=""),"",IF(C82=0,"",B82/C82)) -> 0 | E82: =IF(B82="","",IF(C82=0,"Différé",IF(B82<0,"Critique",IF(D82<$B$67,"Critique",IF(D82<$C$67,"Vigilance",IF(D82<$D$67,"Favorable","Très favorable")))))) -> 0 | G82: =IF(OR(B82="",C82="",C82=0),"",IF(F82<>"",F82,B82*(1-$B$70))/C82) -> 0
D83: =IF(OR(B83="",C83=""),"",IF(C83=0,"",B83/C83)) -> 0 | E83: =IF(B83="","",IF(C83=0,"Différé",IF(B83<0,"Critique",IF(D83<$B$67,"Critique",IF(D83<$C$67,"Vigilance",IF(D83<$D$67,"Favorable","Très favorable")))))) -> 0 | G83: =IF(OR(B83="",C83="",C83=0),"",IF(F83<>"",F83,B83*(1-$B$70))/C83) -> 0 | H83: =IF(AND($B$18="Semestrielle",B83<>"",B82<>"",N(C83)+N(C82)>0),(B83+B82)/(C83+C82),"") -> 0
D84: =IF(OR(B84="",C84=""),"",IF(C84=0,"",B84/C84)) -> 0 | E84: =IF(B84="","",IF(C84=0,"Différé",IF(B84<0,"Critique",IF(D84<$B$67,"Critique",IF(D84<$C$67,"Vigilance",IF(D84<$D$67,"Favorable","Très favorable")))))) -> 0 | G84: =IF(OR(B84="",C84="",C84=0),"",IF(F84<>"",F84,B84*(1-$B$70))/C84) -> 0
D85: =IF(OR(B85="",C85=""),"",IF(C85=0,"",B85/C85)) -> 0 | E85: =IF(B85="","",IF(C85=0,"Différé",IF(B85<0,"Critique",IF(D85<$B$67,"Critique",IF(D85<$C$67,"Vigilance",IF(D85<$D$67,"Favorable","Très favorable")))))) -> 0 | G85: =IF(OR(B85="",C85="",C85=0),"",IF(F85<>"",F85,B85*(1-$B$70))/C85) -> 0 | H85: =IF(AND($B$18="Semestrielle",B85<>"",B84<>"",N(C85)+N(C84)>0),(B85+B84)/(C85+C84),"") -> 0
D86: =IF(OR(B86="",C86=""),"",IF(C86=0,"",B86/C86)) -> 0 | E86: =IF(B86="","",IF(C86=0,"Différé",IF(B86<0,"Critique",IF(D86<$B$67,"Critique",IF(D86<$C$67,"Vigilance",IF(D86<$D$67,"Favorable","Très favorable")))))) -> 0 | G86: =IF(OR(B86="",C86="",C86=0),"",IF(F86<>"",F86,B86*(1-$B$70))/C86) -> 0
D87: =IF(OR(B87="",C87=""),"",IF(C87=0,"",B87/C87)) -> 0 | E87: =IF(B87="","",IF(C87=0,"Différé",IF(B87<0,"Critique",IF(D87<$B$67,"Critique",IF(D87<$C$67,"Vigilance",IF(D87<$D$67,"Favorable","Très favorable")))))) -> 0 | G87: =IF(OR(B87="",C87="",C87=0),"",IF(F87<>"",F87,B87*(1-$B$70))/C87) -> 0 | H87: =IF(AND($B$18="Semestrielle",B87<>"",B86<>"",N(C87)+N(C86)>0),(B87+B86)/(C87+C86),"") -> 0
D88: =IF(OR(B88="",C88=""),"",IF(C88=0,"",B88/C88)) -> 0 | E88: =IF(B88="","",IF(C88=0,"Différé",IF(B88<0,"Critique",IF(D88<$B$67,"Critique",IF(D88<$C$67,"Vigilance",IF(D88<$D$67,"Favorable","Très favorable")))))) -> 0 | G88: =IF(OR(B88="",C88="",C88=0),"",IF(F88<>"",F88,B88*(1-$B$70))/C88) -> 0
D89: =IF(OR(B89="",C89=""),"",IF(C89=0,"",B89/C89)) -> 0 | E89: =IF(B89="","",IF(C89=0,"Différé",IF(B89<0,"Critique",IF(D89<$B$67,"Critique",IF(D89<$C$67,"Vigilance",IF(D89<$D$67,"Favorable","Très favorable")))))) -> 0 | G89: =IF(OR(B89="",C89="",C89=0),"",IF(F89<>"",F89,B89*(1-$B$70))/C89) -> 0 | H89: =IF(AND($B$18="Semestrielle",B89<>"",B88<>"",N(C89)+N(C88)>0),(B89+B88)/(C89+C88),"") -> 0
D90: =IF(OR(B90="",C90=""),"",IF(C90=0,"",B90/C90)) -> 0 | E90: =IF(B90="","",IF(C90=0,"Différé",IF(B90<0,"Critique",IF(D90<$B$67,"Critique",IF(D90<$C$67,"Vigilance",IF(D90<$D$67,"Favorable","Très favorable")))))) -> 0 | G90: =IF(OR(B90="",C90="",C90=0),"",IF(F90<>"",F90,B90*(1-$B$70))/C90) -> 0
D91: =IF(OR(B91="",C91=""),"",IF(C91=0,"",B91/C91)) -> 0 | E91: =IF(B91="","",IF(C91=0,"Différé",IF(B91<0,"Critique",IF(D91<$B$67,"Critique",IF(D91<$C$67,"Vigilance",IF(D91<$D$67,"Favorable","Très favorable")))))) -> 0 | G91: =IF(OR(B91="",C91="",C91=0),"",IF(F91<>"",F91,B91*(1-$B$70))/C91) -> 0 | H91: =IF(AND($B$18="Semestrielle",B91<>"",B90<>"",N(C91)+N(C90)>0),(B91+B90)/(C91+C90),"") -> 0
D92: =IF(OR(B92="",C92=""),"",IF(C92=0,"",B92/C92)) -> 0 | E92: =IF(B92="","",IF(C92=0,"Différé",IF(B92<0,"Critique",IF(D92<$B$67,"Critique",IF(D92<$C$67,"Vigilance",IF(D92<$D$67,"Favorable","Très favorable")))))) -> 0 | G92: =IF(OR(B92="",C92="",C92=0),"",IF(F92<>"",F92,B92*(1-$B$70))/C92) -> 0
D93: =IF(OR(B93="",C93=""),"",IF(C93=0,"",B93/C93)) -> 0 | E93: =IF(B93="","",IF(C93=0,"Différé",IF(B93<0,"Critique",IF(D93<$B$67,"Critique",IF(D93<$C$67,"Vigilance",IF(D93<$D$67,"Favorable","Très favorable")))))) -> 0 | G93: =IF(OR(B93="",C93="",C93=0),"",IF(F93<>"",F93,B93*(1-$B$70))/C93) -> 0 | H93: =IF(AND($B$18="Semestrielle",B93<>"",B92<>"",N(C93)+N(C92)>0),(B93+B92)/(C93+C92),"") -> 0
D94: =IF(OR(B94="",C94=""),"",IF(C94=0,"",B94/C94)) -> 0 | E94: =IF(B94="","",IF(C94=0,"Différé",IF(B94<0,"Critique",IF(D94<$B$67,"Critique",IF(D94<$C$67,"Vigilance",IF(D94<$D$67,"Favorable","Très favorable")))))) -> 0 | G94: =IF(OR(B94="",C94="",C94=0),"",IF(F94<>"",F94,B94*(1-$B$70))/C94) -> 0
D95: =IF(OR(B95="",C95=""),"",IF(C95=0,"",B95/C95)) -> 0 | E95: =IF(B95="","",IF(C95=0,"Différé",IF(B95<0,"Critique",IF(D95<$B$67,"Critique",IF(D95<$C$67,"Vigilance",IF(D95<$D$67,"Favorable","Très favorable")))))) -> 0 | G95: =IF(OR(B95="",C95="",C95=0),"",IF(F95<>"",F95,B95*(1-$B$70))/C95) -> 0 | H95: =IF(AND($B$18="Semestrielle",B95<>"",B94<>"",N(C95)+N(C94)>0),(B95+B94)/(C95+C94),"") -> 0
D96: =IF(OR(B96="",C96=""),"",IF(C96=0,"",B96/C96)) -> 0 | E96: =IF(B96="","",IF(C96=0,"Différé",IF(B96<0,"Critique",IF(D96<$B$67,"Critique",IF(D96<$C$67,"Vigilance",IF(D96<$D$67,"Favorable","Très favorable")))))) -> 0 | G96: =IF(OR(B96="",C96="",C96=0),"",IF(F96<>"",F96,B96*(1-$B$70))/C96) -> 0
D97: =IF(OR(B97="",C97=""),"",IF(C97=0,"",B97/C97)) -> 0 | E97: =IF(B97="","",IF(C97=0,"Différé",IF(B97<0,"Critique",IF(D97<$B$67,"Critique",IF(D97<$C$67,"Vigilance",IF(D97<$D$67,"Favorable","Très favorable")))))) -> 0 | G97: =IF(OR(B97="",C97="",C97=0),"",IF(F97<>"",F97,B97*(1-$B$70))/C97) -> 0 | H97: =IF(AND($B$18="Semestrielle",B97<>"",B96<>"",N(C97)+N(C96)>0),(B97+B96)/(C97+C96),"") -> 0
D98: =IF(OR(B98="",C98=""),"",IF(C98=0,"",B98/C98)) -> 0 | E98: =IF(B98="","",IF(C98=0,"Différé",IF(B98<0,"Critique",IF(D98<$B$67,"Critique",IF(D98<$C$67,"Vigilance",IF(D98<$D$67,"Favorable","Très favorable")))))) -> 0 | G98: =IF(OR(B98="",C98="",C98=0),"",IF(F98<>"",F98,B98*(1-$B$70))/C98) -> 0
D99: =IF(OR(B99="",C99=""),"",IF(C99=0,"",B99/C99)) -> 0 | E99: =IF(B99="","",IF(C99=0,"Différé",IF(B99<0,"Critique",IF(D99<$B$67,"Critique",IF(D99<$C$67,"Vigilance",IF(D99<$D$67,"Favorable","Très favorable")))))) -> 0 | G99: =IF(OR(B99="",C99="",C99=0),"",IF(F99<>"",F99,B99*(1-$B$70))/C99) -> 0 | H99: =IF(AND($B$18="Semestrielle",B99<>"",B98<>"",N(C99)+N(C98)>0),(B99+B98)/(C99+C98),"") -> 0
D100: =IF(OR(B100="",C100=""),"",IF(C100=0,"",B100/C100)) -> 0 | E100: =IF(B100="","",IF(C100=0,"Différé",IF(B100<0,"Critique",IF(D100<$B$67,"Critique",IF(D100<$C$67,"Vigilance",IF(D100<$D$67,"Favorable","Très favorable")))))) -> 0 | G100: =IF(OR(B100="",C100="",C100=0),"",IF(F100<>"",F100,B100*(1-$B$70))/C100) -> 0
D101: =IF(OR(B101="",C101=""),"",IF(C101=0,"",B101/C101)) -> 0 | E101: =IF(B101="","",IF(C101=0,"Différé",IF(B101<0,"Critique",IF(D101<$B$67,"Critique",IF(D101<$C$67,"Vigilance",IF(D101<$D$67,"Favorable","Très favorable")))))) -> 0 | G101: =IF(OR(B101="",C101="",C101=0),"",IF(F101<>"",F101,B101*(1-$B$70))/C101) -> 0 | H101: =IF(AND($B$18="Semestrielle",B101<>"",B100<>"",N(C101)+N(C100)>0),(B101+B100)/(C101+C100),"") -> 0
D102: =IF(OR(B102="",C102=""),"",IF(C102=0,"",B102/C102)) -> 0 | E102: =IF(B102="","",IF(C102=0,"Différé",IF(B102<0,"Critique",IF(D102<$B$67,"Critique",IF(D102<$C$67,"Vigilance",IF(D102<$D$67,"Favorable","Très favorable")))))) -> 0 | G102: =IF(OR(B102="",C102="",C102=0),"",IF(F102<>"",F102,B102*(1-$B$70))/C102) -> 0
D103: =IF(OR(B103="",C103=""),"",IF(C103=0,"",B103/C103)) -> 0 | E103: =IF(B103="","",IF(C103=0,"Différé",IF(B103<0,"Critique",IF(D103<$B$67,"Critique",IF(D103<$C$67,"Vigilance",IF(D103<$D$67,"Favorable","Très favorable")))))) -> 0 | G103: =IF(OR(B103="",C103="",C103=0),"",IF(F103<>"",F103,B103*(1-$B$70))/C103) -> 0 | H103: =IF(AND($B$18="Semestrielle",B103<>"",B102<>"",N(C103)+N(C102)>0),(B103+B102)/(C103+C102),"") -> 0
...

Sheet C3
A1: CAS 3 · Hôtel 4 étoiles, 220 clés | J1: DOSSIER_V8
A2: SPV « Atlas Hospitality » SA (fictive) — Marrakech
A3: Hôtel exploité sous contrat de gestion par un groupe international. Aucun contrat de revenus : prix et volume sont intégralement portés par le projet.
A4: À SAISIR (cellules orange) | B4: =COUNTIF($R$14:$R$56,0) -> 0 | C4: =IF(B4=0,"Saisie complète : lisez la note ci-dessous, puis « Fiche comité ».","Prochaine saisie : "&INDEX($P$14:$P$56,MATCH(0,$R$14:$R$56,0))) -> 0 | G4: =IF(B4=0,"",HYPERLINK("#"&INDEX($Q$14:$Q$56,MATCH(0,$R$14:$R$56,0)),"→ Aller à la cellule "&INDEX($Q$14:$Q$56,MATCH(0,$R$14:$R$56,0)))) -> 0
A5: TABLEAU DE BORD — se met à jour à chaque saisie
A6: NOTE APPROUVÉE (1 à 10) | B6: =B255 -> 0 | C6: Libellé | D6: =IFERROR(INDEX(P_ConvLib,MATCH(B255,P_ConvNote,0)),"") -> 0 | E6: Statut | F6: =B256 -> 0
A7: Score global (sur 100) | B7: =B217 -> 0 | C7: Note calculée | D7: =B218 -> 0 | E7: Plafond applicable | F7: =IF(B252>=10,"Aucun (10)",B252) -> 0
A8: Plafonds actifs | B8: =IF(TRIM(IF(E237="Oui","C1 ("&F237&") ","")&IF(E238="Oui","C2 ("&F238&") ","")&IF(E239="Oui","C3 ("&F239&") ","")&IF(E240="Oui","C4 ("&F240&") ","")&IF(E241="Oui","C5 ("&F241&") ","")&IF(E242="Oui","C6 ("&F242&") ","")&IF(E243="Oui","C7 ("&F243&") ","")&IF(E244="Oui","C8 ("&F244&") ","")&IF(E245="Oui","C9 ("&F245&") ","")&IF(E246="Oui","C10 ("&F246&") ","")&IF(E247="Oui","C11 ("&F247&") ","")&IF(E248="Oui","C12 ("&F248&") ","")&IF(E249="Oui","C13 ("&F249&") ","")&IF(E250="Oui","C14 ("&F250&") ","")&IF(E251="Oui","C15 ("&F251&") ",""))="","Aucun",TRIM(IF(E237="Oui","C1 ("&F237&") ","")&IF(E238="Oui","C2 ("&F238&") ","")&IF(E239="Oui","C3 ("&F239&") ","")&IF(E240="Oui","C4 ("&F240&") ","")&IF(E241="Oui","C5 ("&F241&") ","")&IF(E242="Oui","C6 ("&F242&") ","")&IF(E243="Oui","C7 ("&F243&") ","")&IF(E244="Oui","C8 ("&F244&") ","")&IF(E245="Oui","C9 ("&F245&") ","")&IF(E246="Oui","C10 ("&F246&") ","")&IF(E247="Oui","C11 ("&F247&") ","")&IF(E248="Oui","C12 ("&F248&") ","")&IF(E249="Oui","C13 ("&F249&") ","")&IF(E250="Oui","C14 ("&F250&") ","")&IF(E251="Oui","C15 ("&F251&") ","")))&IF(COUNTIF(E237:E251,"n.r.")>0," — "&COUNTIF(E237:E251,"n.r.")&" plafond(s) non évalué(s) faute de donnée","") -> 0
A9: Verrous actifs (exclusions X, blocages B) | B9: =IF(TRIM(IF(F222="Oui","X1 ","")&IF(F223="Oui","X2 ","")&IF(F224="Oui","X3 ","")&IF(F225="Oui","X4 ","")&IF(F226="Oui","B1 ","")&IF(F227="Oui","B2 ","")&IF(F228="Oui","B3 ","")&IF(F229="Oui","B4 ","")&IF(F230="Oui","B5 ","")&IF(F231="Oui","B6 ","")&IF(F232="Oui","B7 ","")&IF(F233="Oui","B8 ",""))="","Aucun",TRIM(IF(F222="Oui","X1 ","")&IF(F223="Oui","X2 ","")&IF(F224="Oui","X3 ","")&IF(F225="Oui","X4 ","")&IF(F226="Oui","B1 ","")&IF(F227="Oui","B2 ","")&IF(F228="Oui","B3 ","")&IF(F229="Oui","B4 ","")&IF(F230="Oui","B5 ","")&IF(F231="Oui","B6 ","")&IF(F232="Oui","B7 ","")&IF(F233="Oui","B8 ",""))) -> 0
A10: Régime de proportionnalité retenu | B10: =B35 -> 0 | C10: DSCR minimum | D10: =D133 -> 0 | E10: DSCR stressé min. | F10: =D134 -> 0
A11: Complétude (noyau N1-N6 et grille) | B11: =B204 -> 0 | C11: Noyau financier D7 | D11: =D148 -> 0 | E11: Orientation | F11: =IFERROR(INDEX(P_ConvOrient,MATCH(B255,P_ConvNote,0)),"") -> 0
A12: Aller à la section : | B12: =HYPERLINK("#A13","1 · Routage") -> 0 | C12: =HYPERLINK("#A37","3 · Sources") -> 0 | D12: =HYPERLINK("#A69","6 · Échéancier") -> 0 | E12: =HYPERLINK("#A140","7 · Noyau") -> 0 | F12: =HYPERLINK("#A167","8 · Grille") -> 0 | G12: =HYPERLINK("#A220","10 · Verrous") -> 0 | H12: =HYPERLINK("#A235","11 · Plafonds") -> 0
A13: 1 · ROUTAGE — pilote les seuils DSCR et les poids de domaine
A14: Axe | B14: Valeur | C14: Libellé | P14: 1 · Régime de revenus | Q14: B15 | R14: =IF($B$15<>"",1,0) -> 0
A15: C — Régime de revenus | B15: R4 | C15: =IFERROR(INDEX(P_RegLib,MATCH(B15,P_Regimes,0)),"") -> 0 | P15: 1 · Secteur du projet | Q15: B16 | R15: =IF($B$16<>"",1,0) -> 0
A16: D — Secteur du projet | B16: TOU | C16: =IFERROR(INDEX(P_SecLib,MATCH(B16,P_SecCodes,0)),"") -> 0 | P16: 1 · Phase du projet | Q16: B17 | R16: =IF($B$17<>"",1,0) -> 0
A17: B — Phase | B17: P2 | C17: =IFERROR(INDEX(P_PhaseLib,MATCH(B17,P_PhaseCodes,0)),"") -> 0 | P17: 1 · Périodicité des échéances | Q17: B18 | R17: =IF($B$18<>"",1,0) -> 0
A18: Périodicité du service de la dette | B18: Semestrielle | C18: Jamais annuelle : le DSCR se mesure échéance par échéance. | P18: 2 · Exposition de la banque (MMAD) | Q18: B23 | R18: =IF(ISNUMBER($B$23),1,0) -> 0
A19: A — Famille de financement | B19: PF-FLUX | C19: SPV dédiée, remboursement par les flux du projet (R5 vente d'actifs : hors outil). | P19: 2 · Recettes, coûts et dette en dirhams ? | Q19: B24 | R19: =IF($B$24<>"",1,0) -> 0
P20: 2 · Durée du financement (ans) | Q20: B25 | R20: =IF(ISNUMBER($B$25),1,0) -> 0
A21: 2 · RÉGIME DE PROPORTIONNALITÉ — calculé, jamais choisi | P21: 2 · Technologie éprouvée ? | Q21: B26 | R21: =IF($B$26<>"",1,0) -> 0
A22: CAPEX du projet économique complet (MMAD) | B22: =B47 -> 0 | C22: Repris du total des emplois (section 3). | P22: 2 · EPC clé-en-main de moins de 18 mois ? (phase P1) | Q22: B27 | R22: =IF(OR(NOT($B$17="P1"),$B$27<>""),1,0) -> 0
A23: Exposition de la banque (MMAD) | B23: 240 | P23: 2 · Acheteur principal unique ? | Q23: B28 | R23: =IF($B$28<>"",1,0) -> 0
A24: Recettes, coûts et dette intégralement en dirhams | B24: Oui | P24: 2 · Première référence technologique ? | Q24: B29 | R24: =IF($B$29<>"",1,0) -> 0
A25: Durée du financement (ans) | B25: 15 | P25: 2 · Opération consortiale ? | Q25: B30 | R25: =IF($B$30<>"",1,0) -> 0
A26: Technologie : ≥ 3 références industrielles de plus de 3 ans | B26: Oui | P26: 2 · Contrat de revenus de plus de 20 ans ? | Q26: B31 | R26: =IF($B$31<>"",1,0) -> 0
A27: En P1 : EPC clé-en-main forfaitaire, prix et délai garantis, < 18 mois | B27: Non | P27: 2 · Site à risque climatique élevé ? | Q27: B32 | R27: =IF($B$32<>"",1,0) -> 0
A28: Acheteur principal unique et identifié | B28: Non | P28: 2 · Nombre de contreparties clés | Q28: B33 | R28: =IF(ISNUMBER($B$33),1,0) -> 0
A29: Technologie constituant une première référence dans la juridiction | B29: Non | P29: 3 · Emplois : montants du besoin à terminaison | Q29: B39 | R29: =IF(N($B$47)>0,1,0) -> 0
A30: Opération consortiale relevant de la directive 3/W/2025 | B30: Non | P30: 3 · Ressources engagées : montants | Q30: E39 | R30: =IF(N($E$47)>0,1,0) -> 0
A31: Concession ou contrat de revenus de plus de 20 ans | B31: Non | P31: 3 · Nature de chaque ressource | Q31: F39 | R31: =IF(SUMPRODUCT(ISNUMBER($E$39:$E$46)*($F$39:$F$46=""))=0,1,0) -> 0
A32: Site classé à risque climatique physique élevé | B32: Non | P32: 3 · Plan de remédiation (couverture entre 95 et 100 %) | Q32: B50 | R32: =IF(OR(NOT(AND($B$17="P1",ISNUMBER($B$48),N($B$48)>=P_N3_V,N($B$48)<P_N3_F)),$B$50<>""),1,0) -> 0
A33: Nombre de contreparties clés | P33: 6 · Choc du scénario défavorable (%) | Q33: B70 | R33: =IF(ISNUMBER($B$70),1,0) -> 0
A34: Régime calculé (avant escalade) | B34: =IF(OR(B22="",B22=0,B15=""),"",IF(OR(B22>P_L_CAPEX,N(B23)>P_L_EXPO,B15="R4",B29="Oui",N(B153)>0,B30="Oui",B31="Oui",B32="Oui",N(B33)>P_L_NBCP),"L",IF(AND(B22<=P_S_CAPEX,B23<>"",N(B23)<=P_S_EXPO,OR(B15="R1",B15="R2"),B26="Oui",B24="Oui",B25<>"",N(B25)<=P_S_DUREE,OR(B17<>"P1",B27="Oui"),B28="Oui",COUNTIF($F$222:$F$233,"Oui")=0),"S","M"))) -> 0 | C34: =IF(B34="","",IF(B34="L","Escalade : "&IF(B22>P_L_CAPEX,"CAPEX > "&P_L_CAPEX&" MMAD ; ","")&IF(N(B23)>P_L_EXPO,"exposition > "&P_L_EXPO&" MMAD ; ","")&IF(B15="R4","régime de revenus R4 ; ","")&IF(B29="Oui","première référence technologique ; ","")&IF(N(B153)>0,"devises non intégralement couvertes ; ","")&IF(B30="Oui","opération consortiale ; ","")&IF(B31="Oui","contrat de revenus > 20 ans ; ","")&IF(B32="Oui","risque climatique élevé ; ","")&IF(N(B33)>P_L_NBCP,"plus de "&P_L_NBCP&" contreparties clés ; ",""),IF(B34="S","Toutes les conditions du régime simplifié sont réunies.","Régime standard par défaut : une condition du régime S manque, aucune condition d'escalade."))) -> 0 | P34: 6 · Échéancier : CFADS d'au moins deux périodes | Q34: B72 | R34: =IF(COUNT($B$72:$B$131)>=2,1,0) -> 0
A35: RÉGIME RETENU (après escalade automatique) | B35: =IF(B34="","",IF(AND(IF(AND(B34="S",COUNTIF($F$222:$F$233,"Oui")>0),"M",B34)="M",COUNTIF($E$237:$E$251,"Oui")>0),"L",IF(AND(B34="S",COUNTIF($F$222:$F$233,"Oui")>0),"M",B34))) -> 0 | C35: =IF(B35=B34,"Aucune escalade.",IF(B35="L","Escalade : un plafond de note est actif (M passe en L).","Escalade : un verrou est actif (S passe en M).")) -> 0 | P35: 6 · Service de la dette de chaque période | Q35: C72 | R35: =IF(SUMPRODUCT(ISNUMBER($B$72:$B$131)*(1-ISNUMBER($C$72:$C$131)))=0,1,0) -> 0
P36: 7 · N4 — Liquidité (DSRA, lignes, cascade) | Q36: B145 | R36: =IF($B$145<>"",1,0) -> 0
A37: 3 · SOURCES ET EMPLOIS (MMAD) — test de financement à terminaison | P37: 7 · N5 — Levier et fonds propres à risque | Q37: B146 | R37: =IF($B$146<>"",1,0) -> 0
A38: Emplois | B38: Montant | D38: Ressources | E38: Montant | F38: Nature | P38: 7 · N6 — Exposition résiduelle taux, change, refinancement | Q38: B147 | R38: =IF($B$147<>"",1,0) -> 0
A39: Construction et second œuvre | B39: 330 | D39: Dette senior (15 ans, 6,5 %) | E39: 240 | F39: Dette senior | P39: 7 · N3 hors phase P1 : note LLCR | Q39: B150 | R39: =IF(OR($B$17="P1",$B$150<>""),1,0) -> 0
A40: Terrain | B40: 60 | D40: Fonds propres | E40: 240 | F40: Fonds propres | P40: 7 · LLCR (plafond C4) | Q40: B151 | R40: =IF(ISNUMBER($B$151),1,0) -> 0
A41: Mobilier et équipements | B41: 45 | P41: 7 · DSRA en mois (plafond C7) | Q41: B152 | R41: =IF(ISNUMBER($B$152),1,0) -> 0
A42: Frais, intérêts intercalaires et pré-ouverture | B42: 30 | P42: 7 · Exposition nette en devises (plafond C6) | Q42: B153 | R42: =IF(ISNUMBER($B$153),1,0) -> 0
A43: Dotation initiale DSRA | B43: 15 | P43: 7 · Dette à refinancer à maturité (plafond C8) | Q43: B154 | R43: =IF(ISNUMBER($B$154),1,0) -> 0
P44: 7 · Stratégie de refinancement approuvée ? | Q44: B155 | R44: =IF(OR(N($B$154)<=P_C8,$B$155<>""),1,0) -> 0
P45: 7 · Part des recettes de l'acheteur principal (C10) | Q45: B156 | R45: =IF(ISNUMBER($B$156),1,0) -> 0
P46: 7 · Qualité de crédit de l'acheteur principal | Q46: B157 | R46: =IF($B$157<>"",1,0) -> 0
A47: Total emplois (besoin à terminaison) | B47: =SUM(B39:B46) -> 0 | D47: Total ressources engagées | E47: =SUM(E39:E46) -> 0 | P47: 7 · Durée résiduelle du contrat de revenus (C5) | Q47: B158 | R47: =IF(OR($B$15="R4",ISNUMBER($B$158)),1,0) -> 0
A48: Couverture du besoin à terminaison (ressources / emplois) | B48: =IF(N(B47)=0,"",E47/B47) -> 0 | P48: 7 · Durée résiduelle de la dette | Q48: B159 | R48: =IF(ISNUMBER($B$159),1,0) -> 0
A49: Quote-part de dette (dette / besoin à terminaison) | B49: =IF(N(B47)=0,"",(SUMIF(F39:F46,"Dette senior",E39:E46)+SUMIF(F39:F46,"Dette subordonnée",E39:E46))/B47) -> 0 | P49: 7 · Solution documentée (contrat plus court que la dette) ? | Q49: B160 | R49: =IF(OR(NOT(AND(ISNUMBER($B$158),ISNUMBER($B$159))),N($B$158)>=N($B$159),$B$160<>""),1,0) -> 0
A50: Plan de remédiation approuvé (couverture entre 95 % et 100 %) | B50: Non | P50: 7 · Plan d'adaptation climatique financé ? (C11) | Q50: B161 | R50: =IF(OR($B$32<>"Oui",$B$161<>""),1,0) -> 0
P51: 7 · Capacité résiduelle du sponsor (C12) | Q51: B162 | R51: =IF($B$162<>"",1,0) -> 0
A52: 4 · HYPOTHÈSES D'EXPLOITATION (information, non calculées) | P52: 7 · Opérateur remplaçable ? (C13) | Q52: B163 | R52: =IF($B$163<>"",1,0) -> 0
A53: Taux d’occupation retenu | B53: 65 % | P53: 7 · Écart fin O&M / fin de dette (opérateur non remplaçable) | Q53: B164 | R53: =IF(OR($B$163<>"Non",ISNUMBER($B$164)),1,0) -> 0
A54: Prix moyen (ADR) | B54: 1 350 MAD | P54: 7 · Facteur commun au-delà de la limite interne (C14) | Q54: B165 | R54: =IF($B$165<>"",1,0) -> 0
A55: Chiffre d’affaires | B55: 98 MMAD/an | P55: 8 · Grille : sous-critère requis non noté | Q55: ="B"&IF(COUNT($P$169:$P$201)=0,169,MIN($P$169:$P$201)) -> 0 | R55: =IF(COUNT($P$169:$P$201)=0,1,0) -> 0
A56: Charges d’exploitation | B56: 62 MMAD/an | P56: 10 · Verrous X1 à B8 : répondre Oui ou Non | Q56: E222 | R56: =IF(COUNTBLANK($E$222:$E$233)=0,1,0) -> 0
A57: EBITDA (GOP après loyer de gestion) | B57: 36 MMAD/an
A58: CFADS | B58: 30 MMAD/an
A59: Service de la dette | B59: 25,5 MMAD/an, semestriel
A60: Saisonnalité | B60: S1 55 % du CFADS annuel, S2 45 %
A62: 5 · SEUILS DSCR APPLICABLES = base du régime + Δ secteur + majoration de phase
A63: Seuil critique de base du régime | B63: =IFERROR(INDEX(P_Crit,MATCH($B$15,P_Regimes,0)),"") -> 0
A64: Écart sectoriel Δ | B64: =IFERROR(INDEX(P_SecDelta,MATCH($B$16,P_SecCodes,0)),"") -> 0
A65: Majoration de phase | B65: =IFERROR(INDEX(P_PhaseMaj,MATCH($B$17,P_PhaseCodes,0)),"") -> 0
A66: Seuils applicables | B66: Critique < | C66: Vigilance < | D66: Favorable < | E66: Très favorable ≥
A67: Seuil = base + Δ + majoration | B67: =IFERROR(INDEX(P_Crit,MATCH($B$15,P_Regimes,0))+$B$64+$B$65,"") -> 0 | C67: =IFERROR(INDEX(P_Vig,MATCH($B$15,P_Regimes,0))+$B$64+$B$65,"") -> 0 | D67: =IFERROR(INDEX(P_Fav,MATCH($B$15,P_Regimes,0))+$B$64+$B$65,"") -> 0 | E67: =D67 -> 0
A69: 6 · ÉCHÉANCIER DATÉ ET DSCR PAR ÉCHÉANCE (jusqu'à 60 périodes)
A70: Scénario défavorable : baisse du CFADS appliquée à chaque période | B70: 0.289778 | C70: Occupation ramenée de 65 % à 55 %, soit un chiffre d’affaires en recul de 15 %
A71: Période | B71: CFADS central | C71: Service de la dette | D71: DSCR | E71: Classement | F71: CFADS stressé (saisie facultative) | G71: DSCR stressé | H71: DSCR annuel (paire de semestres)
A72: An 2 · S1 (haute saison) | B72: 16.5 | C72: 12.75 | D72: =IF(OR(B72="",C72=""),"",IF(C72=0,"",B72/C72)) -> 0 | E72: =IF(B72="","",IF(C72=0,"Différé",IF(B72<0,"Critique",IF(D72<$B$67,"Critique",IF(D72<$C$67,"Vigilance",IF(D72<$D$67,"Favorable","Très favorable")))))) -> 0 | G72: =IF(OR(B72="",C72="",C72=0),"",IF(F72<>"",F72,B72*(1-$B$70))/C72) -> 0
A73: An 2 · S2 (creux estival) | B73: 13.5 | C73: 12.75 | D73: =IF(OR(B73="",C73=""),"",IF(C73=0,"",B73/C73)) -> 0 | E73: =IF(B73="","",IF(C73=0,"Différé",IF(B73<0,"Critique",IF(D73<$B$67,"Critique",IF(D73<$C$67,"Vigilance",IF(D73<$D$67,"Favorable","Très favorable")))))) -> 0 | G73: =IF(OR(B73="",C73="",C73=0),"",IF(F73<>"",F73,B73*(1-$B$70))/C73) -> 0 | H73: =IF(AND($B$18="Semestrielle",B73<>"",B72<>"",N(C73)+N(C72)>0),(B73+B72)/(C73+C72),"") -> 0
A74: An 5 · S1 | B74: 17.2 | C74: 12.75 | D74: =IF(OR(B74="",C74=""),"",IF(C74=0,"",B74/C74)) -> 0 | E74: =IF(B74="","",IF(C74=0,"Différé",IF(B74<0,"Critique",IF(D74<$B$67,"Critique",IF(D74<$C$67,"Vigilance",IF(D74<$D$67,"Favorable","Très favorable")))))) -> 0 | G74: =IF(OR(B74="",C74="",C74=0),"",IF(F74<>"",F74,B74*(1-$B$70))/C74) -> 0
A75: An 5 · S2 | B75: 14.1 | C75: 12.75 | D75: =IF(OR(B75="",C75=""),"",IF(C75=0,"",B75/C75)) -> 0 | E75: =IF(B75="","",IF(C75=0,"Différé",IF(B75<0,"Critique",IF(D75<$B$67,"Critique",IF(D75<$C$67,"Vigilance",IF(D75<$D$67,"Favorable","Très favorable")))))) -> 0 | G75: =IF(OR(B75="",C75="",C75=0),"",IF(F75<>"",F75,B75*(1-$B$70))/C75) -> 0 | H75: =IF(AND($B$18="Semestrielle",B75<>"",B74<>"",N(C75)+N(C74)>0),(B75+B74)/(C75+C74),"") -> 0
D76: =IF(OR(B76="",C76=""),"",IF(C76=0,"",B76/C76)) -> 0 | E76: =IF(B76="","",IF(C76=0,"Différé",IF(B76<0,"Critique",IF(D76<$B$67,"Critique",IF(D76<$C$67,"Vigilance",IF(D76<$D$67,"Favorable","Très favorable")))))) -> 0 | G76: =IF(OR(B76="",C76="",C76=0),"",IF(F76<>"",F76,B76*(1-$B$70))/C76) -> 0
D77: =IF(OR(B77="",C77=""),"",IF(C77=0,"",B77/C77)) -> 0 | E77: =IF(B77="","",IF(C77=0,"Différé",IF(B77<0,"Critique",IF(D77<$B$67,"Critique",IF(D77<$C$67,"Vigilance",IF(D77<$D$67,"Favorable","Très favorable")))))) -> 0 | G77: =IF(OR(B77="",C77="",C77=0),"",IF(F77<>"",F77,B77*(1-$B$70))/C77) -> 0 | H77: =IF(AND($B$18="Semestrielle",B77<>"",B76<>"",N(C77)+N(C76)>0),(B77+B76)/(C77+C76),"") -> 0
D78: =IF(OR(B78="",C78=""),"",IF(C78=0,"",B78/C78)) -> 0 | E78: =IF(B78="","",IF(C78=0,"Différé",IF(B78<0,"Critique",IF(D78<$B$67,"Critique",IF(D78<$C$67,"Vigilance",IF(D78<$D$67,"Favorable","Très favorable")))))) -> 0 | G78: =IF(OR(B78="",C78="",C78=0),"",IF(F78<>"",F78,B78*(1-$B$70))/C78) -> 0
D79: =IF(OR(B79="",C79=""),"",IF(C79=0,"",B79/C79)) -> 0 | E79: =IF(B79="","",IF(C79=0,"Différé",IF(B79<0,"Critique",IF(D79<$B$67,"Critique",IF(D79<$C$67,"Vigilance",IF(D79<$D$67,"Favorable","Très favorable")))))) -> 0 | G79: =IF(OR(B79="",C79="",C79=0),"",IF(F79<>"",F79,B79*(1-$B$70))/C79) -> 0 | H79: =IF(AND($B$18="Semestrielle",B79<>"",B78<>"",N(C79)+N(C78)>0),(B79+B78)/(C79+C78),"") -> 0
D80: =IF(OR(B80="",C80=""),"",IF(C80=0,"",B80/C80)) -> 0 | E80: =IF(B80="","",IF(C80=0,"Différé",IF(B80<0,"Critique",IF(D80<$B$67,"Critique",IF(D80<$C$67,"Vigilance",IF(D80<$D$67,"Favorable","Très favorable")))))) -> 0 | G80: =IF(OR(B80="",C80="",C80=0),"",IF(F80<>"",F80,B80*(1-$B$70))/C80) -> 0
D81: =IF(OR(B81="",C81=""),"",IF(C81=0,"",B81/C81)) -> 0 | E81: =IF(B81="","",IF(C81=0,"Différé",IF(B81<0,"Critique",IF(D81<$B$67,"Critique",IF(D81<$C$67,"Vigilance",IF(D81<$D$67,"Favorable","Très favorable")))))) -> 0 | G81: =IF(OR(B81="",C81="",C81=0),"",IF(F81<>"",F81,B81*(1-$B$70))/C81) -> 0 | H81: =IF(AND($B$18="Semestrielle",B81<>"",B80<>"",N(C81)+N(C80)>0),(B81+B80)/(C81+C80),"") -> 0
D82: =IF(OR(B82="",C82=""),"",IF(C82=0,"",B82/C82)) -> 0 | E82: =IF(B82="","",IF(C82=0,"Différé",IF(B82<0,"Critique",IF(D82<$B$67,"Critique",IF(D82<$C$67,"Vigilance",IF(D82<$D$67,"Favorable","Très favorable")))))) -> 0 | G82: =IF(OR(B82="",C82="",C82=0),"",IF(F82<>"",F82,B82*(1-$B$70))/C82) -> 0
D83: =IF(OR(B83="",C83=""),"",IF(C83=0,"",B83/C83)) -> 0 | E83: =IF(B83="","",IF(C83=0,"Différé",IF(B83<0,"Critique",IF(D83<$B$67,"Critique",IF(D83<$C$67,"Vigilance",IF(D83<$D$67,"Favorable","Très favorable")))))) -> 0 | G83: =IF(OR(B83="",C83="",C83=0),"",IF(F83<>"",F83,B83*(1-$B$70))/C83) -> 0 | H83: =IF(AND($B$18="Semestrielle",B83<>"",B82<>"",N(C83)+N(C82)>0),(B83+B82)/(C83+C82),"") -> 0
D84: =IF(OR(B84="",C84=""),"",IF(C84=0,"",B84/C84)) -> 0 | E84: =IF(B84="","",IF(C84=0,"Différé",IF(B84<0,"Critique",IF(D84<$B$67,"Critique",IF(D84<$C$67,"Vigilance",IF(D84<$D$67,"Favorable","Très favorable")))))) -> 0 | G84: =IF(OR(B84="",C84="",C84=0),"",IF(F84<>"",F84,B84*(1-$B$70))/C84) -> 0
D85: =IF(OR(B85="",C85=""),"",IF(C85=0,"",B85/C85)) -> 0 | E85: =IF(B85="","",IF(C85=0,"Différé",IF(B85<0,"Critique",IF(D85<$B$67,"Critique",IF(D85<$C$67,"Vigilance",IF(D85<$D$67,"Favorable","Très favorable")))))) -> 0 | G85: =IF(OR(B85="",C85="",C85=0),"",IF(F85<>"",F85,B85*(1-$B$70))/C85) -> 0 | H85: =IF(AND($B$18="Semestrielle",B85<>"",B84<>"",N(C85)+N(C84)>0),(B85+B84)/(C85+C84),"") -> 0
D86: =IF(OR(B86="",C86=""),"",IF(C86=0,"",B86/C86)) -> 0 | E86: =IF(B86="","",IF(C86=0,"Différé",IF(B86<0,"Critique",IF(D86<$B$67,"Critique",IF(D86<$C$67,"Vigilance",IF(D86<$D$67,"Favorable","Très favorable")))))) -> 0 | G86: =IF(OR(B86="",C86="",C86=0),"",IF(F86<>"",F86,B86*(1-$B$70))/C86) -> 0
D87: =IF(OR(B87="",C87=""),"",IF(C87=0,"",B87/C87)) -> 0 | E87: =IF(B87="","",IF(C87=0,"Différé",IF(B87<0,"Critique",IF(D87<$B$67,"Critique",IF(D87<$C$67,"Vigilance",IF(D87<$D$67,"Favorable","Très favorable")))))) -> 0 | G87: =IF(OR(B87="",C87="",C87=0),"",IF(F87<>"",F87,B87*(1-$B$70))/C87) -> 0 | H87: =IF(AND($B$18="Semestrielle",B87<>"",B86<>"",N(C87)+N(C86)>0),(B87+B86)/(C87+C86),"") -> 0
D88: =IF(OR(B88="",C88=""),"",IF(C88=0,"",B88/C88)) -> 0 | E88: =IF(B88="","",IF(C88=0,"Différé",IF(B88<0,"Critique",IF(D88<$B$67,"Critique",IF(D88<$C$67,"Vigilance",IF(D88<$D$67,"Favorable","Très favorable")))))) -> 0 | G88: =IF(OR(B88="",C88="",C88=0),"",IF(F88<>"",F88,B88*(1-$B$70))/C88) -> 0
D89: =IF(OR(B89="",C89=""),"",IF(C89=0,"",B89/C89)) -> 0 | E89: =IF(B89="","",IF(C89=0,"Différé",IF(B89<0,"Critique",IF(D89<$B$67,"Critique",IF(D89<$C$67,"Vigilance",IF(D89<$D$67,"Favorable","Très favorable")))))) -> 0 | G89: =IF(OR(B89="",C89="",C89=0),"",IF(F89<>"",F89,B89*(1-$B$70))/C89) -> 0 | H89: =IF(AND($B$18="Semestrielle",B89<>"",B88<>"",N(C89)+N(C88)>0),(B89+B88)/(C89+C88),"") -> 0
D90: =IF(OR(B90="",C90=""),"",IF(C90=0,"",B90/C90)) -> 0 | E90: =IF(B90="","",IF(C90=0,"Différé",IF(B90<0,"Critique",IF(D90<$B$67,"Critique",IF(D90<$C$67,"Vigilance",IF(D90<$D$67,"Favorable","Très favorable")))))) -> 0 | G90: =IF(OR(B90="",C90="",C90=0),"",IF(F90<>"",F90,B90*(1-$B$70))/C90) -> 0
D91: =IF(OR(B91="",C91=""),"",IF(C91=0,"",B91/C91)) -> 0 | E91: =IF(B91="","",IF(C91=0,"Différé",IF(B91<0,"Critique",IF(D91<$B$67,"Critique",IF(D91<$C$67,"Vigilance",IF(D91<$D$67,"Favorable","Très favorable")))))) -> 0 | G91: =IF(OR(B91="",C91="",C91=0),"",IF(F91<>"",F91,B91*(1-$B$70))/C91) -> 0 | H91: =IF(AND($B$18="Semestrielle",B91<>"",B90<>"",N(C91)+N(C90)>0),(B91+B90)/(C91+C90),"") -> 0
D92: =IF(OR(B92="",C92=""),"",IF(C92=0,"",B92/C92)) -> 0 | E92: =IF(B92="","",IF(C92=0,"Différé",IF(B92<0,"Critique",IF(D92<$B$67,"Critique",IF(D92<$C$67,"Vigilance",IF(D92<$D$67,"Favorable","Très favorable")))))) -> 0 | G92: =IF(OR(B92="",C92="",C92=0),"",IF(F92<>"",F92,B92*(1-$B$70))/C92) -> 0
D93: =IF(OR(B93="",C93=""),"",IF(C93=0,"",B93/C93)) -> 0 | E93: =IF(B93="","",IF(C93=0,"Différé",IF(B93<0,"Critique",IF(D93<$B$67,"Critique",IF(D93<$C$67,"Vigilance",IF(D93<$D$67,"Favorable","Très favorable")))))) -> 0 | G93: =IF(OR(B93="",C93="",C93=0),"",IF(F93<>"",F93,B93*(1-$B$70))/C93) -> 0 | H93: =IF(AND($B$18="Semestrielle",B93<>"",B92<>"",N(C93)+N(C92)>0),(B93+B92)/(C93+C92),"") -> 0
D94: =IF(OR(B94="",C94=""),"",IF(C94=0,"",B94/C94)) -> 0 | E94: =IF(B94="","",IF(C94=0,"Différé",IF(B94<0,"Critique",IF(D94<$B$67,"Critique",IF(D94<$C$67,"Vigilance",IF(D94<$D$67,"Favorable","Très favorable")))))) -> 0 | G94: =IF(OR(B94="",C94="",C94=0),"",IF(F94<>"",F94,B94*(1-$B$70))/C94) -> 0
D95: =IF(OR(B95="",C95=""),"",IF(C95=0,"",B95/C95)) -> 0 | E95: =IF(B95="","",IF(C95=0,"Différé",IF(B95<0,"Critique",IF(D95<$B$67,"Critique",IF(D95<$C$67,"Vigilance",IF(D95<$D$67,"Favorable","Très favorable")))))) -> 0 | G95: =IF(OR(B95="",C95="",C95=0),"",IF(F95<>"",F95,B95*(1-$B$70))/C95) -> 0 | H95: =IF(AND($B$18="Semestrielle",B95<>"",B94<>"",N(C95)+N(C94)>0),(B95+B94)/(C95+C94),"") -> 0
D96: =IF(OR(B96="",C96=""),"",IF(C96=0,"",B96/C96)) -> 0 | E96: =IF(B96="","",IF(C96=0,"Différé",IF(B96<0,"Critique",IF(D96<$B$67,"Critique",IF(D96<$C$67,"Vigilance",IF(D96<$D$67,"Favorable","Très favorable")))))) -> 0 | G96: =IF(OR(B96="",C96="",C96=0),"",IF(F96<>"",F96,B96*(1-$B$70))/C96) -> 0
D97: =IF(OR(B97="",C97=""),"",IF(C97=0,"",B97/C97)) -> 0 | E97: =IF(B97="","",IF(C97=0,"Différé",IF(B97<0,"Critique",IF(D97<$B$67,"Critique",IF(D97<$C$67,"Vigilance",IF(D97<$D$67,"Favorable","Très favorable")))))) -> 0 | G97: =IF(OR(B97="",C97="",C97=0),"",IF(F97<>"",F97,B97*(1-$B$70))/C97) -> 0 | H97: =IF(AND($B$18="Semestrielle",B97<>"",B96<>"",N(C97)+N(C96)>0),(B97+B96)/(C97+C96),"") -> 0
D98: =IF(OR(B98="",C98=""),"",IF(C98=0,"",B98/C98)) -> 0 | E98: =IF(B98="","",IF(C98=0,"Différé",IF(B98<0,"Critique",IF(D98<$B$67,"Critique",IF(D98<$C$67,"Vigilance",IF(D98<$D$67,"Favorable","Très favorable")))))) -> 0 | G98: =IF(OR(B98="",C98="",C98=0),"",IF(F98<>"",F98,B98*(1-$B$70))/C98) -> 0
D99: =IF(OR(B99="",C99=""),"",IF(C99=0,"",B99/C99)) -> 0 | E99: =IF(B99="","",IF(C99=0,"Différé",IF(B99<0,"Critique",IF(D99<$B$67,"Critique",IF(D99<$C$67,"Vigilance",IF(D99<$D$67,"Favorable","Très favorable")))))) -> 0 | G99: =IF(OR(B99="",C99="",C99=0),"",IF(F99<>"",F99,B99*(1-$B$70))/C99) -> 0 | H99: =IF(AND($B$18="Semestrielle",B99<>"",B98<>"",N(C99)+N(C98)>0),(B99+B98)/(C99+C98),"") -> 0
D100: =IF(OR(B100="",C100=""),"",IF(C100=0,"",B100/C100)) -> 0 | E100: =IF(B100="","",IF(C100=0,"Différé",IF(B100<0,"Critique",IF(D100<$B$67,"Critique",IF(D100<$C$67,"Vigilance",IF(D100<$D$67,"Favorable","Très favorable")))))) -> 0 | G100: =IF(OR(B100="",C100="",C100=0),"",IF(F100<>"",F100,B100*(1-$B$70))/C100) -> 0
D101: =IF(OR(B101="",C101=""),"",IF(C101=0,"",B101/C101)) -> 0 | E101: =IF(B101="","",IF(C101=0,"Différé",IF(B101<0,"Critique",IF(D101<$B$67,"Critique",IF(D101<$C$67,"Vigilance",IF(D101<$D$67,"Favorable","Très favorable")))))) -> 0 | G101: =IF(OR(B101="",C101="",C101=0),"",IF(F101<>"",F101,B101*(1-$B$70))/C101) -> 0 | H101: =IF(AND($B$18="Semestrielle",B101<>"",B100<>"",N(C101)+N(C100)>0),(B101+B100)/(C101+C100),"") -> 0
D102: =IF(OR(B102="",C102=""),"",IF(C102=0,"",B102/C102)) -> 0 | E102: =IF(B102="","",IF(C102=0,"Différé",IF(B102<0,"Critique",IF(D102<$B$67,"Critique",IF(D102<$C$67,"Vigilance",IF(D102<$D$67,"Favorable","Très favorable")))))) -> 0 | G102: =IF(OR(B102="",C102="",C102=0),"",IF(F102<>"",F102,B102*(1-$B$70))/C102) -> 0
...

Sheet C4A
A1: CAS 4 — variante A · Unité agro-industrielle de trituration et conditionnement | J1: DOSSIER_V8
A2: SPV « Doukkala Agro » SA (fictive) — Région de Doukkala-Abda
A3: Unité transformant une production agricole locale sous contrats d'enlèvement à prix convenu mais volume exposé. Structure initiale : amortissement semestriel linéaire, change non couvert.
A4: À SAISIR (cellules orange) | B4: =COUNTIF($R$14:$R$56,0) -> 0 | C4: =IF(B4=0,"Saisie complète : lisez la note ci-dessous, puis « Fiche comité ».","Prochaine saisie : "&INDEX($P$14:$P$56,MATCH(0,$R$14:$R$56,0))) -> 0 | G4: =IF(B4=0,"",HYPERLINK("#"&INDEX($Q$14:$Q$56,MATCH(0,$R$14:$R$56,0)),"→ Aller à la cellule "&INDEX($Q$14:$Q$56,MATCH(0,$R$14:$R$56,0)))) -> 0
A5: TABLEAU DE BORD — se met à jour à chaque saisie
A6: NOTE APPROUVÉE (1 à 10) | B6: =B255 -> 0 | C6: Libellé | D6: =IFERROR(INDEX(P_ConvLib,MATCH(B255,P_ConvNote,0)),"") -> 0 | E6: Statut | F6: =B256 -> 0
A7: Score global (sur 100) | B7: =B217 -> 0 | C7: Note calculée | D7: =B218 -> 0 | E7: Plafond applicable | F7: =IF(B252>=10,"Aucun (10)",B252) -> 0
A8: Plafonds actifs | B8: =IF(TRIM(IF(E237="Oui","C1 ("&F237&") ","")&IF(E238="Oui","C2 ("&F238&") ","")&IF(E239="Oui","C3 ("&F239&") ","")&IF(E240="Oui","C4 ("&F240&") ","")&IF(E241="Oui","C5 ("&F241&") ","")&IF(E242="Oui","C6 ("&F242&") ","")&IF(E243="Oui","C7 ("&F243&") ","")&IF(E244="Oui","C8 ("&F244&") ","")&IF(E245="Oui","C9 ("&F245&") ","")&IF(E246="Oui","C10 ("&F246&") ","")&IF(E247="Oui","C11 ("&F247&") ","")&IF(E248="Oui","C12 ("&F248&") ","")&IF(E249="Oui","C13 ("&F249&") ","")&IF(E250="Oui","C14 ("&F250&") ","")&IF(E251="Oui","C15 ("&F251&") ",""))="","Aucun",TRIM(IF(E237="Oui","C1 ("&F237&") ","")&IF(E238="Oui","C2 ("&F238&") ","")&IF(E239="Oui","C3 ("&F239&") ","")&IF(E240="Oui","C4 ("&F240&") ","")&IF(E241="Oui","C5 ("&F241&") ","")&IF(E242="Oui","C6 ("&F242&") ","")&IF(E243="Oui","C7 ("&F243&") ","")&IF(E244="Oui","C8 ("&F244&") ","")&IF(E245="Oui","C9 ("&F245&") ","")&IF(E246="Oui","C10 ("&F246&") ","")&IF(E247="Oui","C11 ("&F247&") ","")&IF(E248="Oui","C12 ("&F248&") ","")&IF(E249="Oui","C13 ("&F249&") ","")&IF(E250="Oui","C14 ("&F250&") ","")&IF(E251="Oui","C15 ("&F251&") ","")))&IF(COUNTIF(E237:E251,"n.r.")>0," — "&COUNTIF(E237:E251,"n.r.")&" plafond(s) non évalué(s) faute de donnée","") -> 0
A9: Verrous actifs (exclusions X, blocages B) | B9: =IF(TRIM(IF(F222="Oui","X1 ","")&IF(F223="Oui","X2 ","")&IF(F224="Oui","X3 ","")&IF(F225="Oui","X4 ","")&IF(F226="Oui","B1 ","")&IF(F227="Oui","B2 ","")&IF(F228="Oui","B3 ","")&IF(F229="Oui","B4 ","")&IF(F230="Oui","B5 ","")&IF(F231="Oui","B6 ","")&IF(F232="Oui","B7 ","")&IF(F233="Oui","B8 ",""))="","Aucun",TRIM(IF(F222="Oui","X1 ","")&IF(F223="Oui","X2 ","")&IF(F224="Oui","X3 ","")&IF(F225="Oui","X4 ","")&IF(F226="Oui","B1 ","")&IF(F227="Oui","B2 ","")&IF(F228="Oui","B3 ","")&IF(F229="Oui","B4 ","")&IF(F230="Oui","B5 ","")&IF(F231="Oui","B6 ","")&IF(F232="Oui","B7 ","")&IF(F233="Oui","B8 ",""))) -> 0
A10: Régime de proportionnalité retenu | B10: =B35 -> 0 | C10: DSCR minimum | D10: =D133 -> 0 | E10: DSCR stressé min. | F10: =D134 -> 0
A11: Complétude (noyau N1-N6 et grille) | B11: =B204 -> 0 | C11: Noyau financier D7 | D11: =D148 -> 0 | E11: Orientation | F11: =IFERROR(INDEX(P_ConvOrient,MATCH(B255,P_ConvNote,0)),"") -> 0
A12: Aller à la section : | B12: =HYPERLINK("#A13","1 · Routage") -> 0 | C12: =HYPERLINK("#A37","3 · Sources") -> 0 | D12: =HYPERLINK("#A69","6 · Échéancier") -> 0 | E12: =HYPERLINK("#A140","7 · Noyau") -> 0 | F12: =HYPERLINK("#A167","8 · Grille") -> 0 | G12: =HYPERLINK("#A220","10 · Verrous") -> 0 | H12: =HYPERLINK("#A235","11 · Plafonds") -> 0
A13: 1 · ROUTAGE — pilote les seuils DSCR et les poids de domaine
A14: Axe | B14: Valeur | C14: Libellé | P14: 1 · Régime de revenus | Q14: B15 | R14: =IF($B$15<>"",1,0) -> 0
A15: C — Régime de revenus | B15: R3 | C15: =IFERROR(INDEX(P_RegLib,MATCH(B15,P_Regimes,0)),"") -> 0 | P15: 1 · Secteur du projet | Q15: B16 | R15: =IF($B$16<>"",1,0) -> 0
A16: D — Secteur du projet | B16: AGR | C16: =IFERROR(INDEX(P_SecLib,MATCH(B16,P_SecCodes,0)),"") -> 0 | P16: 1 · Phase du projet | Q16: B17 | R16: =IF($B$17<>"",1,0) -> 0
A17: B — Phase | B17: P3 | C17: =IFERROR(INDEX(P_PhaseLib,MATCH(B17,P_PhaseCodes,0)),"") -> 0 | P17: 1 · Périodicité des échéances | Q17: B18 | R17: =IF($B$18<>"",1,0) -> 0
A18: Périodicité du service de la dette | B18: Semestrielle | C18: Jamais annuelle : le DSCR se mesure échéance par échéance. | P18: 2 · Exposition de la banque (MMAD) | Q18: B23 | R18: =IF(ISNUMBER($B$23),1,0) -> 0
A19: A — Famille de financement | B19: PF-FLUX | C19: SPV dédiée, remboursement par les flux du projet (R5 vente d'actifs : hors outil). | P19: 2 · Recettes, coûts et dette en dirhams ? | Q19: B24 | R19: =IF($B$24<>"",1,0) -> 0
P20: 2 · Durée du financement (ans) | Q20: B25 | R20: =IF(ISNUMBER($B$25),1,0) -> 0
A21: 2 · RÉGIME DE PROPORTIONNALITÉ — calculé, jamais choisi | P21: 2 · Technologie éprouvée ? | Q21: B26 | R21: =IF($B$26<>"",1,0) -> 0
A22: CAPEX du projet économique complet (MMAD) | B22: =B47 -> 0 | C22: Repris du total des emplois (section 3). | P22: 2 · EPC clé-en-main de moins de 18 mois ? (phase P1) | Q22: B27 | R22: =IF(OR(NOT($B$17="P1"),$B$27<>""),1,0) -> 0
A23: Exposition de la banque (MMAD) | B23: 250 | P23: 2 · Acheteur principal unique ? | Q23: B28 | R23: =IF($B$28<>"",1,0) -> 0
A24: Recettes, coûts et dette intégralement en dirhams | B24: Non | P24: 2 · Première référence technologique ? | Q24: B29 | R24: =IF($B$29<>"",1,0) -> 0
A25: Durée du financement (ans) | B25: 10 | P25: 2 · Opération consortiale ? | Q25: B30 | R25: =IF($B$30<>"",1,0) -> 0
A26: Technologie : ≥ 3 références industrielles de plus de 3 ans | B26: Oui | P26: 2 · Contrat de revenus de plus de 20 ans ? | Q26: B31 | R26: =IF($B$31<>"",1,0) -> 0
A27: En P1 : EPC clé-en-main forfaitaire, prix et délai garantis, < 18 mois | B27: Non | P27: 2 · Site à risque climatique élevé ? | Q27: B32 | R27: =IF($B$32<>"",1,0) -> 0
A28: Acheteur principal unique et identifié | B28: Non | P28: 2 · Nombre de contreparties clés | Q28: B33 | R28: =IF(ISNUMBER($B$33),1,0) -> 0
A29: Technologie constituant une première référence dans la juridiction | B29: Non | P29: 3 · Emplois : montants du besoin à terminaison | Q29: B39 | R29: =IF(N($B$47)>0,1,0) -> 0
A30: Opération consortiale relevant de la directive 3/W/2025 | B30: Non | P30: 3 · Ressources engagées : montants | Q30: E39 | R30: =IF(N($E$47)>0,1,0) -> 0
A31: Concession ou contrat de revenus de plus de 20 ans | B31: Non | P31: 3 · Nature de chaque ressource | Q31: F39 | R31: =IF(SUMPRODUCT(ISNUMBER($E$39:$E$46)*($F$39:$F$46=""))=0,1,0) -> 0
A32: Site classé à risque climatique physique élevé | B32: Non | P32: 3 · Plan de remédiation (couverture entre 95 et 100 %) | Q32: B50 | R32: =IF(OR(NOT(AND($B$17="P1",ISNUMBER($B$48),N($B$48)>=P_N3_V,N($B$48)<P_N3_F)),$B$50<>""),1,0) -> 0
A33: Nombre de contreparties clés | P33: 6 · Choc du scénario défavorable (%) | Q33: B70 | R33: =IF(ISNUMBER($B$70),1,0) -> 0
A34: Régime calculé (avant escalade) | B34: =IF(OR(B22="",B22=0,B15=""),"",IF(OR(B22>P_L_CAPEX,N(B23)>P_L_EXPO,B15="R4",B29="Oui",N(B153)>0,B30="Oui",B31="Oui",B32="Oui",N(B33)>P_L_NBCP),"L",IF(AND(B22<=P_S_CAPEX,B23<>"",N(B23)<=P_S_EXPO,OR(B15="R1",B15="R2"),B26="Oui",B24="Oui",B25<>"",N(B25)<=P_S_DUREE,OR(B17<>"P1",B27="Oui"),B28="Oui",COUNTIF($F$222:$F$233,"Oui")=0),"S","M"))) -> 0 | C34: =IF(B34="","",IF(B34="L","Escalade : "&IF(B22>P_L_CAPEX,"CAPEX > "&P_L_CAPEX&" MMAD ; ","")&IF(N(B23)>P_L_EXPO,"exposition > "&P_L_EXPO&" MMAD ; ","")&IF(B15="R4","régime de revenus R4 ; ","")&IF(B29="Oui","première référence technologique ; ","")&IF(N(B153)>0,"devises non intégralement couvertes ; ","")&IF(B30="Oui","opération consortiale ; ","")&IF(B31="Oui","contrat de revenus > 20 ans ; ","")&IF(B32="Oui","risque climatique élevé ; ","")&IF(N(B33)>P_L_NBCP,"plus de "&P_L_NBCP&" contreparties clés ; ",""),IF(B34="S","Toutes les conditions du régime simplifié sont réunies.","Régime standard par défaut : une condition du régime S manque, aucune condition d'escalade."))) -> 0 | P34: 6 · Échéancier : CFADS d'au moins deux périodes | Q34: B72 | R34: =IF(COUNT($B$72:$B$131)>=2,1,0) -> 0
A35: RÉGIME RETENU (après escalade automatique) | B35: =IF(B34="","",IF(AND(IF(AND(B34="S",COUNTIF($F$222:$F$233,"Oui")>0),"M",B34)="M",COUNTIF($E$237:$E$251,"Oui")>0),"L",IF(AND(B34="S",COUNTIF($F$222:$F$233,"Oui")>0),"M",B34))) -> 0 | C35: =IF(B35=B34,"Aucune escalade.",IF(B35="L","Escalade : un plafond de note est actif (M passe en L).","Escalade : un verrou est actif (S passe en M).")) -> 0 | P35: 6 · Service de la dette de chaque période | Q35: C72 | R35: =IF(SUMPRODUCT(ISNUMBER($B$72:$B$131)*(1-ISNUMBER($C$72:$C$131)))=0,1,0) -> 0
P36: 7 · N4 — Liquidité (DSRA, lignes, cascade) | Q36: B145 | R36: =IF($B$145<>"",1,0) -> 0
A37: 3 · SOURCES ET EMPLOIS (MMAD) — test de financement à terminaison | P37: 7 · N5 — Levier et fonds propres à risque | Q37: B146 | R37: =IF($B$146<>"",1,0) -> 0
A38: Emplois | B38: Montant | D38: Ressources | E38: Montant | F38: Nature | P38: 7 · N6 — Exposition résiduelle taux, change, refinancement | Q38: B147 | R38: =IF($B$147<>"",1,0) -> 0
A39: Ligne de production et bâtiments | B39: 300 | D39: Dette senior (10 ans, 6,0 %), amortissement linéaire | E39: 250 | F39: Dette senior | P39: 7 · N3 hors phase P1 : note LLCR | Q39: B150 | R39: =IF(OR($B$17="P1",$B$150<>""),1,0) -> 0
A40: Stockage et froid | B40: 70 | D40: Fonds propres | E40: 170 | F40: Fonds propres | P40: 7 · LLCR (plafond C4) | Q40: B151 | R40: =IF(ISNUMBER($B$151),1,0) -> 0
A41: Terrain et aménagements | B41: 25 | P41: 7 · DSRA en mois (plafond C7) | Q41: B152 | R41: =IF(ISNUMBER($B$152),1,0) -> 0
A42: Frais et intérêts intercalaires | B42: 17 | P42: 7 · Exposition nette en devises (plafond C6) | Q42: B153 | R42: =IF(ISNUMBER($B$153),1,0) -> 0
A43: Dotation DSRA | B43: 8 | P43: 7 · Dette à refinancer à maturité (plafond C8) | Q43: B154 | R43: =IF(ISNUMBER($B$154),1,0) -> 0
P44: 7 · Stratégie de refinancement approuvée ? | Q44: B155 | R44: =IF(OR(N($B$154)<=P_C8,$B$155<>""),1,0) -> 0
P45: 7 · Part des recettes de l'acheteur principal (C10) | Q45: B156 | R45: =IF(ISNUMBER($B$156),1,0) -> 0
P46: 7 · Qualité de crédit de l'acheteur principal | Q46: B157 | R46: =IF($B$157<>"",1,0) -> 0
A47: Total emplois (besoin à terminaison) | B47: =SUM(B39:B46) -> 0 | D47: Total ressources engagées | E47: =SUM(E39:E46) -> 0 | P47: 7 · Durée résiduelle du contrat de revenus (C5) | Q47: B158 | R47: =IF(OR($B$15="R4",ISNUMBER($B$158)),1,0) -> 0
A48: Couverture du besoin à terminaison (ressources / emplois) | B48: =IF(N(B47)=0,"",E47/B47) -> 0 | P48: 7 · Durée résiduelle de la dette | Q48: B159 | R48: =IF(ISNUMBER($B$159),1,0) -> 0
A49: Quote-part de dette (dette / besoin à terminaison) | B49: =IF(N(B47)=0,"",(SUMIF(F39:F46,"Dette senior",E39:E46)+SUMIF(F39:F46,"Dette subordonnée",E39:E46))/B47) -> 0 | P49: 7 · Solution documentée (contrat plus court que la dette) ? | Q49: B160 | R49: =IF(OR(NOT(AND(ISNUMBER($B$158),ISNUMBER($B$159))),N($B$158)>=N($B$159),$B$160<>""),1,0) -> 0
A50: Plan de remédiation approuvé (couverture entre 95 % et 100 %) | B50: Non | P50: 7 · Plan d'adaptation climatique financé ? (C11) | Q50: B161 | R50: =IF(OR($B$32<>"Oui",$B$161<>""),1,0) -> 0
P51: 7 · Capacité résiduelle du sponsor (C12) | Q51: B162 | R51: =IF($B$162<>"",1,0) -> 0
A52: 4 · HYPOTHÈSES D'EXPLOITATION (information, non calculées) | P52: 7 · Opérateur remplaçable ? (C13) | Q52: B163 | R52: =IF($B$163<>"",1,0) -> 0
A53: Chiffre d’affaires | B53: 380 MMAD/an | P53: 7 · Écart fin O&M / fin de dette (opérateur non remplaçable) | Q53: B164 | R53: =IF(OR($B$163<>"Non",ISNUMBER($B$164)),1,0) -> 0
A54: Charges d’exploitation | B54: 320 MMAD/an | P54: 7 · Facteur commun au-delà de la limite interne (C14) | Q54: B165 | R54: =IF($B$165<>"",1,0) -> 0
A55: EBITDA | B55: 60 MMAD/an | P55: 8 · Grille : sous-critère requis non noté | Q55: ="B"&IF(COUNT($P$169:$P$201)=0,169,MIN($P$169:$P$201)) -> 0 | R55: =IF(COUNT($P$169:$P$201)=0,1,0) -> 0
A56: CFADS | B56: 52 MMAD/an | P56: 10 · Verrous X1 à B8 : répondre Oui ou Non | Q56: E222 | R56: =IF(COUNTBLANK($E$222:$E$233)=0,1,0) -> 0
A57: Saisonnalité | B57: Campagne concentrée sur le premier semestre : 42 MMAD contre 10 MMAD
A58: Service de la dette | B58: 34 MMAD/an, soit 17 MMAD par semestre
A59: Achats importés non couverts | B59: 45 MMAD/an nets des recettes à l’export
A62: 5 · SEUILS DSCR APPLICABLES = base du régime + Δ secteur + majoration de phase
A63: Seuil critique de base du régime | B63: =IFERROR(INDEX(P_Crit,MATCH($B$15,P_Regimes,0)),"") -> 0
A64: Écart sectoriel Δ | B64: =IFERROR(INDEX(P_SecDelta,MATCH($B$16,P_SecCodes,0)),"") -> 0
A65: Majoration de phase | B65: =IFERROR(INDEX(P_PhaseMaj,MATCH($B$17,P_PhaseCodes,0)),"") -> 0
A66: Seuils applicables | B66: Critique < | C66: Vigilance < | D66: Favorable < | E66: Très favorable ≥
A67: Seuil = base + Δ + majoration | B67: =IFERROR(INDEX(P_Crit,MATCH($B$15,P_Regimes,0))+$B$64+$B$65,"") -> 0 | C67: =IFERROR(INDEX(P_Vig,MATCH($B$15,P_Regimes,0))+$B$64+$B$65,"") -> 0 | D67: =IFERROR(INDEX(P_Fav,MATCH($B$15,P_Regimes,0))+$B$64+$B$65,"") -> 0 | E67: =D67 -> 0
A69: 6 · ÉCHÉANCIER DATÉ ET DSCR PAR ÉCHÉANCE (jusqu'à 60 périodes)
A70: Scénario défavorable : baisse du CFADS appliquée à chaque période | B70: 0.3285 | C70: Récolte en recul de 20 % sous stress hydrique, soit un chiffre d’affaires en baisse de 15 %
A71: Période | B71: CFADS central | C71: Service de la dette | D71: DSCR | E71: Classement | F71: CFADS stressé (saisie facultative) | G71: DSCR stressé | H71: DSCR annuel (paire de semestres)
A72: An 3 · S1 (campagne) | B72: 42 | C72: 17 | D72: =IF(OR(B72="",C72=""),"",IF(C72=0,"",B72/C72)) -> 0 | E72: =IF(B72="","",IF(C72=0,"Différé",IF(B72<0,"Critique",IF(D72<$B$67,"Critique",IF(D72<$C$67,"Vigilance",IF(D72<$D$67,"Favorable","Très favorable")))))) -> 0 | G72: =IF(OR(B72="",C72="",C72=0),"",IF(F72<>"",F72,B72*(1-$B$70))/C72) -> 0
A73: An 3 · S2 (intercampagne) | B73: 10 | C73: 17 | D73: =IF(OR(B73="",C73=""),"",IF(C73=0,"",B73/C73)) -> 0 | E73: =IF(B73="","",IF(C73=0,"Différé",IF(B73<0,"Critique",IF(D73<$B$67,"Critique",IF(D73<$C$67,"Vigilance",IF(D73<$D$67,"Favorable","Très favorable")))))) -> 0 | G73: =IF(OR(B73="",C73="",C73=0),"",IF(F73<>"",F73,B73*(1-$B$70))/C73) -> 0 | H73: =IF(AND($B$18="Semestrielle",B73<>"",B72<>"",N(C73)+N(C72)>0),(B73+B72)/(C73+C72),"") -> 0
A74: An 6 · S1 (campagne) | B74: 43 | C74: 17 | D74: =IF(OR(B74="",C74=""),"",IF(C74=0,"",B74/C74)) -> 0 | E74: =IF(B74="","",IF(C74=0,"Différé",IF(B74<0,"Critique",IF(D74<$B$67,"Critique",IF(D74<$C$67,"Vigilance",IF(D74<$D$67,"Favorable","Très favorable")))))) -> 0 | G74: =IF(OR(B74="",C74="",C74=0),"",IF(F74<>"",F74,B74*(1-$B$70))/C74) -> 0
A75: An 6 · S2 (intercampagne) | B75: 10.5 | C75: 17 | D75: =IF(OR(B75="",C75=""),"",IF(C75=0,"",B75/C75)) -> 0 | E75: =IF(B75="","",IF(C75=0,"Différé",IF(B75<0,"Critique",IF(D75<$B$67,"Critique",IF(D75<$C$67,"Vigilance",IF(D75<$D$67,"Favorable","Très favorable")))))) -> 0 | G75: =IF(OR(B75="",C75="",C75=0),"",IF(F75<>"",F75,B75*(1-$B$70))/C75) -> 0 | H75: =IF(AND($B$18="Semestrielle",B75<>"",B74<>"",N(C75)+N(C74)>0),(B75+B74)/(C75+C74),"") -> 0
D76: =IF(OR(B76="",C76=""),"",IF(C76=0,"",B76/C76)) -> 0 | E76: =IF(B76="","",IF(C76=0,"Différé",IF(B76<0,"Critique",IF(D76<$B$67,"Critique",IF(D76<$C$67,"Vigilance",IF(D76<$D$67,"Favorable","Très favorable")))))) -> 0 | G76: =IF(OR(B76="",C76="",C76=0),"",IF(F76<>"",F76,B76*(1-$B$70))/C76) -> 0
D77: =IF(OR(B77="",C77=""),"",IF(C77=0,"",B77/C77)) -> 0 | E77: =IF(B77="","",IF(C77=0,"Différé",IF(B77<0,"Critique",IF(D77<$B$67,"Critique",IF(D77<$C$67,"Vigilance",IF(D77<$D$67,"Favorable","Très favorable")))))) -> 0 | G77: =IF(OR(B77="",C77="",C77=0),"",IF(F77<>"",F77,B77*(1-$B$70))/C77) -> 0 | H77: =IF(AND($B$18="Semestrielle",B77<>"",B76<>"",N(C77)+N(C76)>0),(B77+B76)/(C77+C76),"") -> 0
D78: =IF(OR(B78="",C78=""),"",IF(C78=0,"",B78/C78)) -> 0 | E78: =IF(B78="","",IF(C78=0,"Différé",IF(B78<0,"Critique",IF(D78<$B$67,"Critique",IF(D78<$C$67,"Vigilance",IF(D78<$D$67,"Favorable","Très favorable")))))) -> 0 | G78: =IF(OR(B78="",C78="",C78=0),"",IF(F78<>"",F78,B78*(1-$B$70))/C78) -> 0
D79: =IF(OR(B79="",C79=""),"",IF(C79=0,"",B79/C79)) -> 0 | E79: =IF(B79="","",IF(C79=0,"Différé",IF(B79<0,"Critique",IF(D79<$B$67,"Critique",IF(D79<$C$67,"Vigilance",IF(D79<$D$67,"Favorable","Très favorable")))))) -> 0 | G79: =IF(OR(B79="",C79="",C79=0),"",IF(F79<>"",F79,B79*(1-$B$70))/C79) -> 0 | H79: =IF(AND($B$18="Semestrielle",B79<>"",B78<>"",N(C79)+N(C78)>0),(B79+B78)/(C79+C78),"") -> 0
D80: =IF(OR(B80="",C80=""),"",IF(C80=0,"",B80/C80)) -> 0 | E80: =IF(B80="","",IF(C80=0,"Différé",IF(B80<0,"Critique",IF(D80<$B$67,"Critique",IF(D80<$C$67,"Vigilance",IF(D80<$D$67,"Favorable","Très favorable")))))) -> 0 | G80: =IF(OR(B80="",C80="",C80=0),"",IF(F80<>"",F80,B80*(1-$B$70))/C80) -> 0
D81: =IF(OR(B81="",C81=""),"",IF(C81=0,"",B81/C81)) -> 0 | E81: =IF(B81="","",IF(C81=0,"Différé",IF(B81<0,"Critique",IF(D81<$B$67,"Critique",IF(D81<$C$67,"Vigilance",IF(D81<$D$67,"Favorable","Très favorable")))))) -> 0 | G81: =IF(OR(B81="",C81="",C81=0),"",IF(F81<>"",F81,B81*(1-$B$70))/C81) -> 0 | H81: =IF(AND($B$18="Semestrielle",B81<>"",B80<>"",N(C81)+N(C80)>0),(B81+B80)/(C81+C80),"") -> 0
D82: =IF(OR(B82="",C82=""),"",IF(C82=0,"",B82/C82)) -> 0 | E82: =IF(B82="","",IF(C82=0,"Différé",IF(B82<0,"Critique",IF(D82<$B$67,"Critique",IF(D82<$C$67,"Vigilance",IF(D82<$D$67,"Favorable","Très favorable")))))) -> 0 | G82: =IF(OR(B82="",C82="",C82=0),"",IF(F82<>"",F82,B82*(1-$B$70))/C82) -> 0
D83: =IF(OR(B83="",C83=""),"",IF(C83=0,"",B83/C83)) -> 0 | E83: =IF(B83="","",IF(C83=0,"Différé",IF(B83<0,"Critique",IF(D83<$B$67,"Critique",IF(D83<$C$67,"Vigilance",IF(D83<$D$67,"Favorable","Très favorable")))))) -> 0 | G83: =IF(OR(B83="",C83="",C83=0),"",IF(F83<>"",F83,B83*(1-$B$70))/C83) -> 0 | H83: =IF(AND($B$18="Semestrielle",B83<>"",B82<>"",N(C83)+N(C82)>0),(B83+B82)/(C83+C82),"") -> 0
D84: =IF(OR(B84="",C84=""),"",IF(C84=0,"",B84/C84)) -> 0 | E84: =IF(B84="","",IF(C84=0,"Différé",IF(B84<0,"Critique",IF(D84<$B$67,"Critique",IF(D84<$C$67,"Vigilance",IF(D84<$D$67,"Favorable","Très favorable")))))) -> 0 | G84: =IF(OR(B84="",C84="",C84=0),"",IF(F84<>"",F84,B84*(1-$B$70))/C84) -> 0
D85: =IF(OR(B85="",C85=""),"",IF(C85=0,"",B85/C85)) -> 0 | E85: =IF(B85="","",IF(C85=0,"Différé",IF(B85<0,"Critique",IF(D85<$B$67,"Critique",IF(D85<$C$67,"Vigilance",IF(D85<$D$67,"Favorable","Très favorable")))))) -> 0 | G85: =IF(OR(B85="",C85="",C85=0),"",IF(F85<>"",F85,B85*(1-$B$70))/C85) -> 0 | H85: =IF(AND($B$18="Semestrielle",B85<>"",B84<>"",N(C85)+N(C84)>0),(B85+B84)/(C85+C84),"") -> 0
D86: =IF(OR(B86="",C86=""),"",IF(C86=0,"",B86/C86)) -> 0 | E86: =IF(B86="","",IF(C86=0,"Différé",IF(B86<0,"Critique",IF(D86<$B$67,"Critique",IF(D86<$C$67,"Vigilance",IF(D86<$D$67,"Favorable","Très favorable")))))) -> 0 | G86: =IF(OR(B86="",C86="",C86=0),"",IF(F86<>"",F86,B86*(1-$B$70))/C86) -> 0
D87: =IF(OR(B87="",C87=""),"",IF(C87=0,"",B87/C87)) -> 0 | E87: =IF(B87="","",IF(C87=0,"Différé",IF(B87<0,"Critique",IF(D87<$B$67,"Critique",IF(D87<$C$67,"Vigilance",IF(D87<$D$67,"Favorable","Très favorable")))))) -> 0 | G87: =IF(OR(B87="",C87="",C87=0),"",IF(F87<>"",F87,B87*(1-$B$70))/C87) -> 0 | H87: =IF(AND($B$18="Semestrielle",B87<>"",B86<>"",N(C87)+N(C86)>0),(B87+B86)/(C87+C86),"") -> 0
D88: =IF(OR(B88="",C88=""),"",IF(C88=0,"",B88/C88)) -> 0 | E88: =IF(B88="","",IF(C88=0,"Différé",IF(B88<0,"Critique",IF(D88<$B$67,"Critique",IF(D88<$C$67,"Vigilance",IF(D88<$D$67,"Favorable","Très favorable")))))) -> 0 | G88: =IF(OR(B88="",C88="",C88=0),"",IF(F88<>"",F88,B88*(1-$B$70))/C88) -> 0
D89: =IF(OR(B89="",C89=""),"",IF(C89=0,"",B89/C89)) -> 0 | E89: =IF(B89="","",IF(C89=0,"Différé",IF(B89<0,"Critique",IF(D89<$B$67,"Critique",IF(D89<$C$67,"Vigilance",IF(D89<$D$67,"Favorable","Très favorable")))))) -> 0 | G89: =IF(OR(B89="",C89="",C89=0),"",IF(F89<>"",F89,B89*(1-$B$70))/C89) -> 0 | H89: =IF(AND($B$18="Semestrielle",B89<>"",B88<>"",N(C89)+N(C88)>0),(B89+B88)/(C89+C88),"") -> 0
D90: =IF(OR(B90="",C90=""),"",IF(C90=0,"",B90/C90)) -> 0 | E90: =IF(B90="","",IF(C90=0,"Différé",IF(B90<0,"Critique",IF(D90<$B$67,"Critique",IF(D90<$C$67,"Vigilance",IF(D90<$D$67,"Favorable","Très favorable")))))) -> 0 | G90: =IF(OR(B90="",C90="",C90=0),"",IF(F90<>"",F90,B90*(1-$B$70))/C90) -> 0
D91: =IF(OR(B91="",C91=""),"",IF(C91=0,"",B91/C91)) -> 0 | E91: =IF(B91="","",IF(C91=0,"Différé",IF(B91<0,"Critique",IF(D91<$B$67,"Critique",IF(D91<$C$67,"Vigilance",IF(D91<$D$67,"Favorable","Très favorable")))))) -> 0 | G91: =IF(OR(B91="",C91="",C91=0),"",IF(F91<>"",F91,B91*(1-$B$70))/C91) -> 0 | H91: =IF(AND($B$18="Semestrielle",B91<>"",B90<>"",N(C91)+N(C90)>0),(B91+B90)/(C91+C90),"") -> 0
D92: =IF(OR(B92="",C92=""),"",IF(C92=0,"",B92/C92)) -> 0 | E92: =IF(B92="","",IF(C92=0,"Différé",IF(B92<0,"Critique",IF(D92<$B$67,"Critique",IF(D92<$C$67,"Vigilance",IF(D92<$D$67,"Favorable","Très favorable")))))) -> 0 | G92: =IF(OR(B92="",C92="",C92=0),"",IF(F92<>"",F92,B92*(1-$B$70))/C92) -> 0
D93: =IF(OR(B93="",C93=""),"",IF(C93=0,"",B93/C93)) -> 0 | E93: =IF(B93="","",IF(C93=0,"Différé",IF(B93<0,"Critique",IF(D93<$B$67,"Critique",IF(D93<$C$67,"Vigilance",IF(D93<$D$67,"Favorable","Très favorable")))))) -> 0 | G93: =IF(OR(B93="",C93="",C93=0),"",IF(F93<>"",F93,B93*(1-$B$70))/C93) -> 0 | H93: =IF(AND($B$18="Semestrielle",B93<>"",B92<>"",N(C93)+N(C92)>0),(B93+B92)/(C93+C92),"") -> 0
D94: =IF(OR(B94="",C94=""),"",IF(C94=0,"",B94/C94)) -> 0 | E94: =IF(B94="","",IF(C94=0,"Différé",IF(B94<0,"Critique",IF(D94<$B$67,"Critique",IF(D94<$C$67,"Vigilance",IF(D94<$D$67,"Favorable","Très favorable")))))) -> 0 | G94: =IF(OR(B94="",C94="",C94=0),"",IF(F94<>"",F94,B94*(1-$B$70))/C94) -> 0
D95: =IF(OR(B95="",C95=""),"",IF(C95=0,"",B95/C95)) -> 0 | E95: =IF(B95="","",IF(C95=0,"Différé",IF(B95<0,"Critique",IF(D95<$B$67,"Critique",IF(D95<$C$67,"Vigilance",IF(D95<$D$67,"Favorable","Très favorable")))))) -> 0 | G95: =IF(OR(B95="",C95="",C95=0),"",IF(F95<>"",F95,B95*(1-$B$70))/C95) -> 0 | H95: =IF(AND($B$18="Semestrielle",B95<>"",B94<>"",N(C95)+N(C94)>0),(B95+B94)/(C95+C94),"") -> 0
D96: =IF(OR(B96="",C96=""),"",IF(C96=0,"",B96/C96)) -> 0 | E96: =IF(B96="","",IF(C96=0,"Différé",IF(B96<0,"Critique",IF(D96<$B$67,"Critique",IF(D96<$C$67,"Vigilance",IF(D96<$D$67,"Favorable","Très favorable")))))) -> 0 | G96: =IF(OR(B96="",C96="",C96=0),"",IF(F96<>"",F96,B96*(1-$B$70))/C96) -> 0
D97: =IF(OR(B97="",C97=""),"",IF(C97=0,"",B97/C97)) -> 0 | E97: =IF(B97="","",IF(C97=0,"Différé",IF(B97<0,"Critique",IF(D97<$B$67,"Critique",IF(D97<$C$67,"Vigilance",IF(D97<$D$67,"Favorable","Très favorable")))))) -> 0 | G97: =IF(OR(B97="",C97="",C97=0),"",IF(F97<>"",F97,B97*(1-$B$70))/C97) -> 0 | H97: =IF(AND($B$18="Semestrielle",B97<>"",B96<>"",N(C97)+N(C96)>0),(B97+B96)/(C97+C96),"") -> 0
D98: =IF(OR(B98="",C98=""),"",IF(C98=0,"",B98/C98)) -> 0 | E98: =IF(B98="","",IF(C98=0,"Différé",IF(B98<0,"Critique",IF(D98<$B$67,"Critique",IF(D98<$C$67,"Vigilance",IF(D98<$D$67,"Favorable","Très favorable")))))) -> 0 | G98: =IF(OR(B98="",C98="",C98=0),"",IF(F98<>"",F98,B98*(1-$B$70))/C98) -> 0
D99: =IF(OR(B99="",C99=""),"",IF(C99=0,"",B99/C99)) -> 0 | E99: =IF(B99="","",IF(C99=0,"Différé",IF(B99<0,"Critique",IF(D99<$B$67,"Critique",IF(D99<$C$67,"Vigilance",IF(D99<$D$67,"Favorable","Très favorable")))))) -> 0 | G99: =IF(OR(B99="",C99="",C99=0),"",IF(F99<>"",F99,B99*(1-$B$70))/C99) -> 0 | H99: =IF(AND($B$18="Semestrielle",B99<>"",B98<>"",N(C99)+N(C98)>0),(B99+B98)/(C99+C98),"") -> 0
D100: =IF(OR(B100="",C100=""),"",IF(C100=0,"",B100/C100)) -> 0 | E100: =IF(B100="","",IF(C100=0,"Différé",IF(B100<0,"Critique",IF(D100<$B$67,"Critique",IF(D100<$C$67,"Vigilance",IF(D100<$D$67,"Favorable","Très favorable")))))) -> 0 | G100: =IF(OR(B100="",C100="",C100=0),"",IF(F100<>"",F100,B100*(1-$B$70))/C100) -> 0
D101: =IF(OR(B101="",C101=""),"",IF(C101=0,"",B101/C101)) -> 0 | E101: =IF(B101="","",IF(C101=0,"Différé",IF(B101<0,"Critique",IF(D101<$B$67,"Critique",IF(D101<$C$67,"Vigilance",IF(D101<$D$67,"Favorable","Très favorable")))))) -> 0 | G101: =IF(OR(B101="",C101="",C101=0),"",IF(F101<>"",F101,B101*(1-$B$70))/C101) -> 0 | H101: =IF(AND($B$18="Semestrielle",B101<>"",B100<>"",N(C101)+N(C100)>0),(B101+B100)/(C101+C100),"") -> 0
D102: =IF(OR(B102="",C102=""),"",IF(C102=0,"",B102/C102)) -> 0 | E102: =IF(B102="","",IF(C102=0,"Différé",IF(B102<0,"Critique",IF(D102<$B$67,"Critique",IF(D102<$C$67,"Vigilance",IF(D102<$D$67,"Favorable","Très favorable")))))) -> 0 | G102: =IF(OR(B102="",C102="",C102=0),"",IF(F102<>"",F102,B102*(1-$B$70))/C102) -> 0
D103: =IF(OR(B103="",C103=""),"",IF(C103=0,"",B103/C103)) -> 0 | E103: =IF(B103="","",IF(C103=0,"Différé",IF(B103<0,"Critique",IF(D103<$B$67,"Critique",IF(D103<$C$67,"Vigilance",IF(D103<$D$67,"Favorable","Très favorable")))))) -> 0 | G103: =IF(OR(B103="",C103="",C103=0),"",IF(F103<>"",F103,B103*(1-$B$70))/C103) -> 0 | H103: =IF(AND($B$18="Semestrielle",B103<>"",B102<>"",N(C103)+N(C102)>0),(B103+B102)/(C103+C102),"") -> 0
...

Sheet C4B
A1: CAS 4 — variante B · Unité agro-industrielle — structure restructurée | J1: DOSSIER_V8
A2: SPV « Doukkala Agro » SA (fictive) — Région de Doukkala-Abda
A3: Même actif, même marché, même grille qualitative. Trois corrections de montage : amortissement sculpté sur la campagne, apport complémentaire de 40 MMAD, couverture de change portée à 90 %.
A4: À SAISIR (cellules orange) | B4: =COUNTIF($R$14:$R$56,0) -> 0 | C4: =IF(B4=0,"Saisie complète : lisez la note ci-dessous, puis « Fiche comité ».","Prochaine saisie : "&INDEX($P$14:$P$56,MATCH(0,$R$14:$R$56,0))) -> 0 | G4: =IF(B4=0,"",HYPERLINK("#"&INDEX($Q$14:$Q$56,MATCH(0,$R$14:$R$56,0)),"→ Aller à la cellule "&INDEX($Q$14:$Q$56,MATCH(0,$R$14:$R$56,0)))) -> 0
A5: TABLEAU DE BORD — se met à jour à chaque saisie
A6: NOTE APPROUVÉE (1 à 10) | B6: =B255 -> 0 | C6: Libellé | D6: =IFERROR(INDEX(P_ConvLib,MATCH(B255,P_ConvNote,0)),"") -> 0 | E6: Statut | F6: =B256 -> 0
A7: Score global (sur 100) | B7: =B217 -> 0 | C7: Note calculée | D7: =B218 -> 0 | E7: Plafond applicable | F7: =IF(B252>=10,"Aucun (10)",B252) -> 0
A8: Plafonds actifs | B8: =IF(TRIM(IF(E237="Oui","C1 ("&F237&") ","")&IF(E238="Oui","C2 ("&F238&") ","")&IF(E239="Oui","C3 ("&F239&") ","")&IF(E240="Oui","C4 ("&F240&") ","")&IF(E241="Oui","C5 ("&F241&") ","")&IF(E242="Oui","C6 ("&F242&") ","")&IF(E243="Oui","C7 ("&F243&") ","")&IF(E244="Oui","C8 ("&F244&") ","")&IF(E245="Oui","C9 ("&F245&") ","")&IF(E246="Oui","C10 ("&F246&") ","")&IF(E247="Oui","C11 ("&F247&") ","")&IF(E248="Oui","C12 ("&F248&") ","")&IF(E249="Oui","C13 ("&F249&") ","")&IF(E250="Oui","C14 ("&F250&") ","")&IF(E251="Oui","C15 ("&F251&") ",""))="","Aucun",TRIM(IF(E237="Oui","C1 ("&F237&") ","")&IF(E238="Oui","C2 ("&F238&") ","")&IF(E239="Oui","C3 ("&F239&") ","")&IF(E240="Oui","C4 ("&F240&") ","")&IF(E241="Oui","C5 ("&F241&") ","")&IF(E242="Oui","C6 ("&F242&") ","")&IF(E243="Oui","C7 ("&F243&") ","")&IF(E244="Oui","C8 ("&F244&") ","")&IF(E245="Oui","C9 ("&F245&") ","")&IF(E246="Oui","C10 ("&F246&") ","")&IF(E247="Oui","C11 ("&F247&") ","")&IF(E248="Oui","C12 ("&F248&") ","")&IF(E249="Oui","C13 ("&F249&") ","")&IF(E250="Oui","C14 ("&F250&") ","")&IF(E251="Oui","C15 ("&F251&") ","")))&IF(COUNTIF(E237:E251,"n.r.")>0," — "&COUNTIF(E237:E251,"n.r.")&" plafond(s) non évalué(s) faute de donnée","") -> 0
A9: Verrous actifs (exclusions X, blocages B) | B9: =IF(TRIM(IF(F222="Oui","X1 ","")&IF(F223="Oui","X2 ","")&IF(F224="Oui","X3 ","")&IF(F225="Oui","X4 ","")&IF(F226="Oui","B1 ","")&IF(F227="Oui","B2 ","")&IF(F228="Oui","B3 ","")&IF(F229="Oui","B4 ","")&IF(F230="Oui","B5 ","")&IF(F231="Oui","B6 ","")&IF(F232="Oui","B7 ","")&IF(F233="Oui","B8 ",""))="","Aucun",TRIM(IF(F222="Oui","X1 ","")&IF(F223="Oui","X2 ","")&IF(F224="Oui","X3 ","")&IF(F225="Oui","X4 ","")&IF(F226="Oui","B1 ","")&IF(F227="Oui","B2 ","")&IF(F228="Oui","B3 ","")&IF(F229="Oui","B4 ","")&IF(F230="Oui","B5 ","")&IF(F231="Oui","B6 ","")&IF(F232="Oui","B7 ","")&IF(F233="Oui","B8 ",""))) -> 0
A10: Régime de proportionnalité retenu | B10: =B35 -> 0 | C10: DSCR minimum | D10: =D133 -> 0 | E10: DSCR stressé min. | F10: =D134 -> 0
A11: Complétude (noyau N1-N6 et grille) | B11: =B204 -> 0 | C11: Noyau financier D7 | D11: =D148 -> 0 | E11: Orientation | F11: =IFERROR(INDEX(P_ConvOrient,MATCH(B255,P_ConvNote,0)),"") -> 0
A12: Aller à la section : | B12: =HYPERLINK("#A13","1 · Routage") -> 0 | C12: =HYPERLINK("#A37","3 · Sources") -> 0 | D12: =HYPERLINK("#A69","6 · Échéancier") -> 0 | E12: =HYPERLINK("#A140","7 · Noyau") -> 0 | F12: =HYPERLINK("#A167","8 · Grille") -> 0 | G12: =HYPERLINK("#A220","10 · Verrous") -> 0 | H12: =HYPERLINK("#A235","11 · Plafonds") -> 0
A13: 1 · ROUTAGE — pilote les seuils DSCR et les poids de domaine
A14: Axe | B14: Valeur | C14: Libellé | P14: 1 · Régime de revenus | Q14: B15 | R14: =IF($B$15<>"",1,0) -> 0
A15: C — Régime de revenus | B15: R3 | C15: =IFERROR(INDEX(P_RegLib,MATCH(B15,P_Regimes,0)),"") -> 0 | P15: 1 · Secteur du projet | Q15: B16 | R15: =IF($B$16<>"",1,0) -> 0
A16: D — Secteur du projet | B16: AGR | C16: =IFERROR(INDEX(P_SecLib,MATCH(B16,P_SecCodes,0)),"") -> 0 | P16: 1 · Phase du projet | Q16: B17 | R16: =IF($B$17<>"",1,0) -> 0
A17: B — Phase | B17: P3 | C17: =IFERROR(INDEX(P_PhaseLib,MATCH(B17,P_PhaseCodes,0)),"") -> 0 | P17: 1 · Périodicité des échéances | Q17: B18 | R17: =IF($B$18<>"",1,0) -> 0
A18: Périodicité du service de la dette | B18: Semestrielle | C18: Jamais annuelle : le DSCR se mesure échéance par échéance. | P18: 2 · Exposition de la banque (MMAD) | Q18: B23 | R18: =IF(ISNUMBER($B$23),1,0) -> 0
A19: A — Famille de financement | B19: PF-FLUX | C19: SPV dédiée, remboursement par les flux du projet (R5 vente d'actifs : hors outil). | P19: 2 · Recettes, coûts et dette en dirhams ? | Q19: B24 | R19: =IF($B$24<>"",1,0) -> 0
P20: 2 · Durée du financement (ans) | Q20: B25 | R20: =IF(ISNUMBER($B$25),1,0) -> 0
A21: 2 · RÉGIME DE PROPORTIONNALITÉ — calculé, jamais choisi | P21: 2 · Technologie éprouvée ? | Q21: B26 | R21: =IF($B$26<>"",1,0) -> 0
A22: CAPEX du projet économique complet (MMAD) | B22: =B47 -> 0 | C22: Repris du total des emplois (section 3). | P22: 2 · EPC clé-en-main de moins de 18 mois ? (phase P1) | Q22: B27 | R22: =IF(OR(NOT($B$17="P1"),$B$27<>""),1,0) -> 0
A23: Exposition de la banque (MMAD) | B23: 210 | P23: 2 · Acheteur principal unique ? | Q23: B28 | R23: =IF($B$28<>"",1,0) -> 0
A24: Recettes, coûts et dette intégralement en dirhams | B24: Non | P24: 2 · Première référence technologique ? | Q24: B29 | R24: =IF($B$29<>"",1,0) -> 0
A25: Durée du financement (ans) | B25: 10 | P25: 2 · Opération consortiale ? | Q25: B30 | R25: =IF($B$30<>"",1,0) -> 0
A26: Technologie : ≥ 3 références industrielles de plus de 3 ans | B26: Oui | P26: 2 · Contrat de revenus de plus de 20 ans ? | Q26: B31 | R26: =IF($B$31<>"",1,0) -> 0
A27: En P1 : EPC clé-en-main forfaitaire, prix et délai garantis, < 18 mois | B27: Non | P27: 2 · Site à risque climatique élevé ? | Q27: B32 | R27: =IF($B$32<>"",1,0) -> 0
A28: Acheteur principal unique et identifié | B28: Non | P28: 2 · Nombre de contreparties clés | Q28: B33 | R28: =IF(ISNUMBER($B$33),1,0) -> 0
A29: Technologie constituant une première référence dans la juridiction | B29: Non | P29: 3 · Emplois : montants du besoin à terminaison | Q29: B39 | R29: =IF(N($B$47)>0,1,0) -> 0
A30: Opération consortiale relevant de la directive 3/W/2025 | B30: Non | P30: 3 · Ressources engagées : montants | Q30: E39 | R30: =IF(N($E$47)>0,1,0) -> 0
A31: Concession ou contrat de revenus de plus de 20 ans | B31: Non | P31: 3 · Nature de chaque ressource | Q31: F39 | R31: =IF(SUMPRODUCT(ISNUMBER($E$39:$E$46)*($F$39:$F$46=""))=0,1,0) -> 0
A32: Site classé à risque climatique physique élevé | B32: Non | P32: 3 · Plan de remédiation (couverture entre 95 et 100 %) | Q32: B50 | R32: =IF(OR(NOT(AND($B$17="P1",ISNUMBER($B$48),N($B$48)>=P_N3_V,N($B$48)<P_N3_F)),$B$50<>""),1,0) -> 0
A33: Nombre de contreparties clés | P33: 6 · Choc du scénario défavorable (%) | Q33: B70 | R33: =IF(ISNUMBER($B$70),1,0) -> 0
A34: Régime calculé (avant escalade) | B34: =IF(OR(B22="",B22=0,B15=""),"",IF(OR(B22>P_L_CAPEX,N(B23)>P_L_EXPO,B15="R4",B29="Oui",N(B153)>0,B30="Oui",B31="Oui",B32="Oui",N(B33)>P_L_NBCP),"L",IF(AND(B22<=P_S_CAPEX,B23<>"",N(B23)<=P_S_EXPO,OR(B15="R1",B15="R2"),B26="Oui",B24="Oui",B25<>"",N(B25)<=P_S_DUREE,OR(B17<>"P1",B27="Oui"),B28="Oui",COUNTIF($F$222:$F$233,"Oui")=0),"S","M"))) -> 0 | C34: =IF(B34="","",IF(B34="L","Escalade : "&IF(B22>P_L_CAPEX,"CAPEX > "&P_L_CAPEX&" MMAD ; ","")&IF(N(B23)>P_L_EXPO,"exposition > "&P_L_EXPO&" MMAD ; ","")&IF(B15="R4","régime de revenus R4 ; ","")&IF(B29="Oui","première référence technologique ; ","")&IF(N(B153)>0,"devises non intégralement couvertes ; ","")&IF(B30="Oui","opération consortiale ; ","")&IF(B31="Oui","contrat de revenus > 20 ans ; ","")&IF(B32="Oui","risque climatique élevé ; ","")&IF(N(B33)>P_L_NBCP,"plus de "&P_L_NBCP&" contreparties clés ; ",""),IF(B34="S","Toutes les conditions du régime simplifié sont réunies.","Régime standard par défaut : une condition du régime S manque, aucune condition d'escalade."))) -> 0 | P34: 6 · Échéancier : CFADS d'au moins deux périodes | Q34: B72 | R34: =IF(COUNT($B$72:$B$131)>=2,1,0) -> 0
A35: RÉGIME RETENU (après escalade automatique) | B35: =IF(B34="","",IF(AND(IF(AND(B34="S",COUNTIF($F$222:$F$233,"Oui")>0),"M",B34)="M",COUNTIF($E$237:$E$251,"Oui")>0),"L",IF(AND(B34="S",COUNTIF($F$222:$F$233,"Oui")>0),"M",B34))) -> 0 | C35: =IF(B35=B34,"Aucune escalade.",IF(B35="L","Escalade : un plafond de note est actif (M passe en L).","Escalade : un verrou est actif (S passe en M).")) -> 0 | P35: 6 · Service de la dette de chaque période | Q35: C72 | R35: =IF(SUMPRODUCT(ISNUMBER($B$72:$B$131)*(1-ISNUMBER($C$72:$C$131)))=0,1,0) -> 0
P36: 7 · N4 — Liquidité (DSRA, lignes, cascade) | Q36: B145 | R36: =IF($B$145<>"",1,0) -> 0
A37: 3 · SOURCES ET EMPLOIS (MMAD) — test de financement à terminaison | P37: 7 · N5 — Levier et fonds propres à risque | Q37: B146 | R37: =IF($B$146<>"",1,0) -> 0
A38: Emplois | B38: Montant | D38: Ressources | E38: Montant | F38: Nature | P38: 7 · N6 — Exposition résiduelle taux, change, refinancement | Q38: B147 | R38: =IF($B$147<>"",1,0) -> 0
A39: Ligne de production et bâtiments | B39: 300 | D39: Dette senior (10 ans, 6,0 %), amortissement sculpté | E39: 210 | F39: Dette senior | P39: 7 · N3 hors phase P1 : note LLCR | Q39: B150 | R39: =IF(OR($B$17="P1",$B$150<>""),1,0) -> 0
A40: Stockage et froid | B40: 70 | D40: Fonds propres | E40: 210 | F40: Fonds propres | P40: 7 · LLCR (plafond C4) | Q40: B151 | R40: =IF(ISNUMBER($B$151),1,0) -> 0
A41: Terrain et aménagements | B41: 25 | D41: Ligne de campagne dédiée (engagée) | E41: 25 | F41: Ligne dédiée engagée | P41: 7 · DSRA en mois (plafond C7) | Q41: B152 | R41: =IF(ISNUMBER($B$152),1,0) -> 0
A42: Frais et intérêts intercalaires | B42: 17 | P42: 7 · Exposition nette en devises (plafond C6) | Q42: B153 | R42: =IF(ISNUMBER($B$153),1,0) -> 0
A43: Dotation DSRA | B43: 8 | P43: 7 · Dette à refinancer à maturité (plafond C8) | Q43: B154 | R43: =IF(ISNUMBER($B$154),1,0) -> 0
P44: 7 · Stratégie de refinancement approuvée ? | Q44: B155 | R44: =IF(OR(N($B$154)<=P_C8,$B$155<>""),1,0) -> 0
P45: 7 · Part des recettes de l'acheteur principal (C10) | Q45: B156 | R45: =IF(ISNUMBER($B$156),1,0) -> 0
P46: 7 · Qualité de crédit de l'acheteur principal | Q46: B157 | R46: =IF($B$157<>"",1,0) -> 0
A47: Total emplois (besoin à terminaison) | B47: =SUM(B39:B46) -> 0 | D47: Total ressources engagées | E47: =SUM(E39:E46) -> 0 | P47: 7 · Durée résiduelle du contrat de revenus (C5) | Q47: B158 | R47: =IF(OR($B$15="R4",ISNUMBER($B$158)),1,0) -> 0
A48: Couverture du besoin à terminaison (ressources / emplois) | B48: =IF(N(B47)=0,"",E47/B47) -> 0 | P48: 7 · Durée résiduelle de la dette | Q48: B159 | R48: =IF(ISNUMBER($B$159),1,0) -> 0
A49: Quote-part de dette (dette / besoin à terminaison) | B49: =IF(N(B47)=0,"",(SUMIF(F39:F46,"Dette senior",E39:E46)+SUMIF(F39:F46,"Dette subordonnée",E39:E46))/B47) -> 0 | P49: 7 · Solution documentée (contrat plus court que la dette) ? | Q49: B160 | R49: =IF(OR(NOT(AND(ISNUMBER($B$158),ISNUMBER($B$159))),N($B$158)>=N($B$159),$B$160<>""),1,0) -> 0
A50: Plan de remédiation approuvé (couverture entre 95 % et 100 %) | B50: Non | P50: 7 · Plan d'adaptation climatique financé ? (C11) | Q50: B161 | R50: =IF(OR($B$32<>"Oui",$B$161<>""),1,0) -> 0
P51: 7 · Capacité résiduelle du sponsor (C12) | Q51: B162 | R51: =IF($B$162<>"",1,0) -> 0
A52: 4 · HYPOTHÈSES D'EXPLOITATION (information, non calculées) | P52: 7 · Opérateur remplaçable ? (C13) | Q52: B163 | R52: =IF($B$163<>"",1,0) -> 0
A53: Chiffre d’affaires | B53: 380 MMAD/an — inchangé | P53: 7 · Écart fin O&M / fin de dette (opérateur non remplaçable) | Q53: B164 | R53: =IF(OR($B$163<>"Non",ISNUMBER($B$164)),1,0) -> 0
A54: CFADS | B54: 52 MMAD/an — inchangé | P54: 7 · Facteur commun au-delà de la limite interne (C14) | Q54: B165 | R54: =IF($B$165<>"",1,0) -> 0
A55: Service sculpté | B55: 25 MMAD en campagne, 3,5 MMAD en intercampagne | P55: 8 · Grille : sous-critère requis non noté | Q55: ="B"&IF(COUNT($P$169:$P$201)=0,169,MIN($P$169:$P$201)) -> 0 | R55: =IF(COUNT($P$169:$P$201)=0,1,0) -> 0
A56: Couverture de change | B56: 90 % des achats importés | P56: 10 · Verrous X1 à B8 : répondre Oui ou Non | Q56: E222 | R56: =IF(COUNTBLANK($E$222:$E$233)=0,1,0) -> 0
A57: Exposition nette résiduelle | B57: 4,5 MMAD, soit 16 % du service annuel
A62: 5 · SEUILS DSCR APPLICABLES = base du régime + Δ secteur + majoration de phase
A63: Seuil critique de base du régime | B63: =IFERROR(INDEX(P_Crit,MATCH($B$15,P_Regimes,0)),"") -> 0
A64: Écart sectoriel Δ | B64: =IFERROR(INDEX(P_SecDelta,MATCH($B$16,P_SecCodes,0)),"") -> 0
A65: Majoration de phase | B65: =IFERROR(INDEX(P_PhaseMaj,MATCH($B$17,P_PhaseCodes,0)),"") -> 0
A66: Seuils applicables | B66: Critique < | C66: Vigilance < | D66: Favorable < | E66: Très favorable ≥
A67: Seuil = base + Δ + majoration | B67: =IFERROR(INDEX(P_Crit,MATCH($B$15,P_Regimes,0))+$B$64+$B$65,"") -> 0 | C67: =IFERROR(INDEX(P_Vig,MATCH($B$15,P_Regimes,0))+$B$64+$B$65,"") -> 0 | D67: =IFERROR(INDEX(P_Fav,MATCH($B$15,P_Regimes,0))+$B$64+$B$65,"") -> 0 | E67: =D67 -> 0
A69: 6 · ÉCHÉANCIER DATÉ ET DSCR PAR ÉCHÉANCE (jusqu'à 60 périodes)
A70: Scénario défavorable : baisse du CFADS appliquée à chaque période | B70: 0.32619 | C70: Même choc : récolte en recul de 20 % sous stress hydrique
A71: Période | B71: CFADS central | C71: Service de la dette | D71: DSCR | E71: Classement | F71: CFADS stressé (saisie facultative) | G71: DSCR stressé | H71: DSCR annuel (paire de semestres)
A72: An 3 · S1 (campagne) | B72: 42 | C72: 25 | D72: =IF(OR(B72="",C72=""),"",IF(C72=0,"",B72/C72)) -> 0 | E72: =IF(B72="","",IF(C72=0,"Différé",IF(B72<0,"Critique",IF(D72<$B$67,"Critique",IF(D72<$C$67,"Vigilance",IF(D72<$D$67,"Favorable","Très favorable")))))) -> 0 | G72: =IF(OR(B72="",C72="",C72=0),"",IF(F72<>"",F72,B72*(1-$B$70))/C72) -> 0
A73: An 3 · S2 (intercampagne) | B73: 10 | C73: 3.5 | D73: =IF(OR(B73="",C73=""),"",IF(C73=0,"",B73/C73)) -> 0 | E73: =IF(B73="","",IF(C73=0,"Différé",IF(B73<0,"Critique",IF(D73<$B$67,"Critique",IF(D73<$C$67,"Vigilance",IF(D73<$D$67,"Favorable","Très favorable")))))) -> 0 | G73: =IF(OR(B73="",C73="",C73=0),"",IF(F73<>"",F73,B73*(1-$B$70))/C73) -> 0 | H73: =IF(AND($B$18="Semestrielle",B73<>"",B72<>"",N(C73)+N(C72)>0),(B73+B72)/(C73+C72),"") -> 0
A74: An 6 · S1 (campagne) | B74: 43 | C74: 25 | D74: =IF(OR(B74="",C74=""),"",IF(C74=0,"",B74/C74)) -> 0 | E74: =IF(B74="","",IF(C74=0,"Différé",IF(B74<0,"Critique",IF(D74<$B$67,"Critique",IF(D74<$C$67,"Vigilance",IF(D74<$D$67,"Favorable","Très favorable")))))) -> 0 | G74: =IF(OR(B74="",C74="",C74=0),"",IF(F74<>"",F74,B74*(1-$B$70))/C74) -> 0
A75: An 6 · S2 (intercampagne) | B75: 10.5 | C75: 3.5 | D75: =IF(OR(B75="",C75=""),"",IF(C75=0,"",B75/C75)) -> 0 | E75: =IF(B75="","",IF(C75=0,"Différé",IF(B75<0,"Critique",IF(D75<$B$67,"Critique",IF(D75<$C$67,"Vigilance",IF(D75<$D$67,"Favorable","Très favorable")))))) -> 0 | G75: =IF(OR(B75="",C75="",C75=0),"",IF(F75<>"",F75,B75*(1-$B$70))/C75) -> 0 | H75: =IF(AND($B$18="Semestrielle",B75<>"",B74<>"",N(C75)+N(C74)>0),(B75+B74)/(C75+C74),"") -> 0
D76: =IF(OR(B76="",C76=""),"",IF(C76=0,"",B76/C76)) -> 0 | E76: =IF(B76="","",IF(C76=0,"Différé",IF(B76<0,"Critique",IF(D76<$B$67,"Critique",IF(D76<$C$67,"Vigilance",IF(D76<$D$67,"Favorable","Très favorable")))))) -> 0 | G76: =IF(OR(B76="",C76="",C76=0),"",IF(F76<>"",F76,B76*(1-$B$70))/C76) -> 0
D77: =IF(OR(B77="",C77=""),"",IF(C77=0,"",B77/C77)) -> 0 | E77: =IF(B77="","",IF(C77=0,"Différé",IF(B77<0,"Critique",IF(D77<$B$67,"Critique",IF(D77<$C$67,"Vigilance",IF(D77<$D$67,"Favorable","Très favorable")))))) -> 0 | G77: =IF(OR(B77="",C77="",C77=0),"",IF(F77<>"",F77,B77*(1-$B$70))/C77) -> 0 | H77: =IF(AND($B$18="Semestrielle",B77<>"",B76<>"",N(C77)+N(C76)>0),(B77+B76)/(C77+C76),"") -> 0
D78: =IF(OR(B78="",C78=""),"",IF(C78=0,"",B78/C78)) -> 0 | E78: =IF(B78="","",IF(C78=0,"Différé",IF(B78<0,"Critique",IF(D78<$B$67,"Critique",IF(D78<$C$67,"Vigilance",IF(D78<$D$67,"Favorable","Très favorable")))))) -> 0 | G78: =IF(OR(B78="",C78="",C78=0),"",IF(F78<>"",F78,B78*(1-$B$70))/C78) -> 0
D79: =IF(OR(B79="",C79=""),"",IF(C79=0,"",B79/C79)) -> 0 | E79: =IF(B79="","",IF(C79=0,"Différé",IF(B79<0,"Critique",IF(D79<$B$67,"Critique",IF(D79<$C$67,"Vigilance",IF(D79<$D$67,"Favorable","Très favorable")))))) -> 0 | G79: =IF(OR(B79="",C79="",C79=0),"",IF(F79<>"",F79,B79*(1-$B$70))/C79) -> 0 | H79: =IF(AND($B$18="Semestrielle",B79<>"",B78<>"",N(C79)+N(C78)>0),(B79+B78)/(C79+C78),"") -> 0
D80: =IF(OR(B80="",C80=""),"",IF(C80=0,"",B80/C80)) -> 0 | E80: =IF(B80="","",IF(C80=0,"Différé",IF(B80<0,"Critique",IF(D80<$B$67,"Critique",IF(D80<$C$67,"Vigilance",IF(D80<$D$67,"Favorable","Très favorable")))))) -> 0 | G80: =IF(OR(B80="",C80="",C80=0),"",IF(F80<>"",F80,B80*(1-$B$70))/C80) -> 0
D81: =IF(OR(B81="",C81=""),"",IF(C81=0,"",B81/C81)) -> 0 | E81: =IF(B81="","",IF(C81=0,"Différé",IF(B81<0,"Critique",IF(D81<$B$67,"Critique",IF(D81<$C$67,"Vigilance",IF(D81<$D$67,"Favorable","Très favorable")))))) -> 0 | G81: =IF(OR(B81="",C81="",C81=0),"",IF(F81<>"",F81,B81*(1-$B$70))/C81) -> 0 | H81: =IF(AND($B$18="Semestrielle",B81<>"",B80<>"",N(C81)+N(C80)>0),(B81+B80)/(C81+C80),"") -> 0
D82: =IF(OR(B82="",C82=""),"",IF(C82=0,"",B82/C82)) -> 0 | E82: =IF(B82="","",IF(C82=0,"Différé",IF(B82<0,"Critique",IF(D82<$B$67,"Critique",IF(D82<$C$67,"Vigilance",IF(D82<$D$67,"Favorable","Très favorable")))))) -> 0 | G82: =IF(OR(B82="",C82="",C82=0),"",IF(F82<>"",F82,B82*(1-$B$70))/C82) -> 0
D83: =IF(OR(B83="",C83=""),"",IF(C83=0,"",B83/C83)) -> 0 | E83: =IF(B83="","",IF(C83=0,"Différé",IF(B83<0,"Critique",IF(D83<$B$67,"Critique",IF(D83<$C$67,"Vigilance",IF(D83<$D$67,"Favorable","Très favorable")))))) -> 0 | G83: =IF(OR(B83="",C83="",C83=0),"",IF(F83<>"",F83,B83*(1-$B$70))/C83) -> 0 | H83: =IF(AND($B$18="Semestrielle",B83<>"",B82<>"",N(C83)+N(C82)>0),(B83+B82)/(C83+C82),"") -> 0
D84: =IF(OR(B84="",C84=""),"",IF(C84=0,"",B84/C84)) -> 0 | E84: =IF(B84="","",IF(C84=0,"Différé",IF(B84<0,"Critique",IF(D84<$B$67,"Critique",IF(D84<$C$67,"Vigilance",IF(D84<$D$67,"Favorable","Très favorable")))))) -> 0 | G84: =IF(OR(B84="",C84="",C84=0),"",IF(F84<>"",F84,B84*(1-$B$70))/C84) -> 0
D85: =IF(OR(B85="",C85=""),"",IF(C85=0,"",B85/C85)) -> 0 | E85: =IF(B85="","",IF(C85=0,"Différé",IF(B85<0,"Critique",IF(D85<$B$67,"Critique",IF(D85<$C$67,"Vigilance",IF(D85<$D$67,"Favorable","Très favorable")))))) -> 0 | G85: =IF(OR(B85="",C85="",C85=0),"",IF(F85<>"",F85,B85*(1-$B$70))/C85) -> 0 | H85: =IF(AND($B$18="Semestrielle",B85<>"",B84<>"",N(C85)+N(C84)>0),(B85+B84)/(C85+C84),"") -> 0
D86: =IF(OR(B86="",C86=""),"",IF(C86=0,"",B86/C86)) -> 0 | E86: =IF(B86="","",IF(C86=0,"Différé",IF(B86<0,"Critique",IF(D86<$B$67,"Critique",IF(D86<$C$67,"Vigilance",IF(D86<$D$67,"Favorable","Très favorable")))))) -> 0 | G86: =IF(OR(B86="",C86="",C86=0),"",IF(F86<>"",F86,B86*(1-$B$70))/C86) -> 0
D87: =IF(OR(B87="",C87=""),"",IF(C87=0,"",B87/C87)) -> 0 | E87: =IF(B87="","",IF(C87=0,"Différé",IF(B87<0,"Critique",IF(D87<$B$67,"Critique",IF(D87<$C$67,"Vigilance",IF(D87<$D$67,"Favorable","Très favorable")))))) -> 0 | G87: =IF(OR(B87="",C87="",C87=0),"",IF(F87<>"",F87,B87*(1-$B$70))/C87) -> 0 | H87: =IF(AND($B$18="Semestrielle",B87<>"",B86<>"",N(C87)+N(C86)>0),(B87+B86)/(C87+C86),"") -> 0
D88: =IF(OR(B88="",C88=""),"",IF(C88=0,"",B88/C88)) -> 0 | E88: =IF(B88="","",IF(C88=0,"Différé",IF(B88<0,"Critique",IF(D88<$B$67,"Critique",IF(D88<$C$67,"Vigilance",IF(D88<$D$67,"Favorable","Très favorable")))))) -> 0 | G88: =IF(OR(B88="",C88="",C88=0),"",IF(F88<>"",F88,B88*(1-$B$70))/C88) -> 0
D89: =IF(OR(B89="",C89=""),"",IF(C89=0,"",B89/C89)) -> 0 | E89: =IF(B89="","",IF(C89=0,"Différé",IF(B89<0,"Critique",IF(D89<$B$67,"Critique",IF(D89<$C$67,"Vigilance",IF(D89<$D$67,"Favorable","Très favorable")))))) -> 0 | G89: =IF(OR(B89="",C89="",C89=0),"",IF(F89<>"",F89,B89*(1-$B$70))/C89) -> 0 | H89: =IF(AND($B$18="Semestrielle",B89<>"",B88<>"",N(C89)+N(C88)>0),(B89+B88)/(C89+C88),"") -> 0
D90: =IF(OR(B90="",C90=""),"",IF(C90=0,"",B90/C90)) -> 0 | E90: =IF(B90="","",IF(C90=0,"Différé",IF(B90<0,"Critique",IF(D90<$B$67,"Critique",IF(D90<$C$67,"Vigilance",IF(D90<$D$67,"Favorable","Très favorable")))))) -> 0 | G90: =IF(OR(B90="",C90="",C90=0),"",IF(F90<>"",F90,B90*(1-$B$70))/C90) -> 0
D91: =IF(OR(B91="",C91=""),"",IF(C91=0,"",B91/C91)) -> 0 | E91: =IF(B91="","",IF(C91=0,"Différé",IF(B91<0,"Critique",IF(D91<$B$67,"Critique",IF(D91<$C$67,"Vigilance",IF(D91<$D$67,"Favorable","Très favorable")))))) -> 0 | G91: =IF(OR(B91="",C91="",C91=0),"",IF(F91<>"",F91,B91*(1-$B$70))/C91) -> 0 | H91: =IF(AND($B$18="Semestrielle",B91<>"",B90<>"",N(C91)+N(C90)>0),(B91+B90)/(C91+C90),"") -> 0
D92: =IF(OR(B92="",C92=""),"",IF(C92=0,"",B92/C92)) -> 0 | E92: =IF(B92="","",IF(C92=0,"Différé",IF(B92<0,"Critique",IF(D92<$B$67,"Critique",IF(D92<$C$67,"Vigilance",IF(D92<$D$67,"Favorable","Très favorable")))))) -> 0 | G92: =IF(OR(B92="",C92="",C92=0),"",IF(F92<>"",F92,B92*(1-$B$70))/C92) -> 0
D93: =IF(OR(B93="",C93=""),"",IF(C93=0,"",B93/C93)) -> 0 | E93: =IF(B93="","",IF(C93=0,"Différé",IF(B93<0,"Critique",IF(D93<$B$67,"Critique",IF(D93<$C$67,"Vigilance",IF(D93<$D$67,"Favorable","Très favorable")))))) -> 0 | G93: =IF(OR(B93="",C93="",C93=0),"",IF(F93<>"",F93,B93*(1-$B$70))/C93) -> 0 | H93: =IF(AND($B$18="Semestrielle",B93<>"",B92<>"",N(C93)+N(C92)>0),(B93+B92)/(C93+C92),"") -> 0
D94: =IF(OR(B94="",C94=""),"",IF(C94=0,"",B94/C94)) -> 0 | E94: =IF(B94="","",IF(C94=0,"Différé",IF(B94<0,"Critique",IF(D94<$B$67,"Critique",IF(D94<$C$67,"Vigilance",IF(D94<$D$67,"Favorable","Très favorable")))))) -> 0 | G94: =IF(OR(B94="",C94="",C94=0),"",IF(F94<>"",F94,B94*(1-$B$70))/C94) -> 0
D95: =IF(OR(B95="",C95=""),"",IF(C95=0,"",B95/C95)) -> 0 | E95: =IF(B95="","",IF(C95=0,"Différé",IF(B95<0,"Critique",IF(D95<$B$67,"Critique",IF(D95<$C$67,"Vigilance",IF(D95<$D$67,"Favorable","Très favorable")))))) -> 0 | G95: =IF(OR(B95="",C95="",C95=0),"",IF(F95<>"",F95,B95*(1-$B$70))/C95) -> 0 | H95: =IF(AND($B$18="Semestrielle",B95<>"",B94<>"",N(C95)+N(C94)>0),(B95+B94)/(C95+C94),"") -> 0
D96: =IF(OR(B96="",C96=""),"",IF(C96=0,"",B96/C96)) -> 0 | E96: =IF(B96="","",IF(C96=0,"Différé",IF(B96<0,"Critique",IF(D96<$B$67,"Critique",IF(D96<$C$67,"Vigilance",IF(D96<$D$67,"Favorable","Très favorable")))))) -> 0 | G96: =IF(OR(B96="",C96="",C96=0),"",IF(F96<>"",F96,B96*(1-$B$70))/C96) -> 0
D97: =IF(OR(B97="",C97=""),"",IF(C97=0,"",B97/C97)) -> 0 | E97: =IF(B97="","",IF(C97=0,"Différé",IF(B97<0,"Critique",IF(D97<$B$67,"Critique",IF(D97<$C$67,"Vigilance",IF(D97<$D$67,"Favorable","Très favorable")))))) -> 0 | G97: =IF(OR(B97="",C97="",C97=0),"",IF(F97<>"",F97,B97*(1-$B$70))/C97) -> 0 | H97: =IF(AND($B$18="Semestrielle",B97<>"",B96<>"",N(C97)+N(C96)>0),(B97+B96)/(C97+C96),"") -> 0
D98: =IF(OR(B98="",C98=""),"",IF(C98=0,"",B98/C98)) -> 0 | E98: =IF(B98="","",IF(C98=0,"Différé",IF(B98<0,"Critique",IF(D98<$B$67,"Critique",IF(D98<$C$67,"Vigilance",IF(D98<$D$67,"Favorable","Très favorable")))))) -> 0 | G98: =IF(OR(B98="",C98="",C98=0),"",IF(F98<>"",F98,B98*(1-$B$70))/C98) -> 0
D99: =IF(OR(B99="",C99=""),"",IF(C99=0,"",B99/C99)) -> 0 | E99: =IF(B99="","",IF(C99=0,"Différé",IF(B99<0,"Critique",IF(D99<$B$67,"Critique",IF(D99<$C$67,"Vigilance",IF(D99<$D$67,"Favorable","Très favorable")))))) -> 0 | G99: =IF(OR(B99="",C99="",C99=0),"",IF(F99<>"",F99,B99*(1-$B$70))/C99) -> 0 | H99: =IF(AND($B$18="Semestrielle",B99<>"",B98<>"",N(C99)+N(C98)>0),(B99+B98)/(C99+C98),"") -> 0
D100: =IF(OR(B100="",C100=""),"",IF(C100=0,"",B100/C100)) -> 0 | E100: =IF(B100="","",IF(C100=0,"Différé",IF(B100<0,"Critique",IF(D100<$B$67,"Critique",IF(D100<$C$67,"Vigilance",IF(D100<$D$67,"Favorable","Très favorable")))))) -> 0 | G100: =IF(OR(B100="",C100="",C100=0),"",IF(F100<>"",F100,B100*(1-$B$70))/C100) -> 0
D101: =IF(OR(B101="",C101=""),"",IF(C101=0,"",B101/C101)) -> 0 | E101: =IF(B101="","",IF(C101=0,"Différé",IF(B101<0,"Critique",IF(D101<$B$67,"Critique",IF(D101<$C$67,"Vigilance",IF(D101<$D$67,"Favorable","Très favorable")))))) -> 0 | G101: =IF(OR(B101="",C101="",C101=0),"",IF(F101<>"",F101,B101*(1-$B$70))/C101) -> 0 | H101: =IF(AND($B$18="Semestrielle",B101<>"",B100<>"",N(C101)+N(C100)>0),(B101+B100)/(C101+C100),"") -> 0
D102: =IF(OR(B102="",C102=""),"",IF(C102=0,"",B102/C102)) -> 0 | E102: =IF(B102="","",IF(C102=0,"Différé",IF(B102<0,"Critique",IF(D102<$B$67,"Critique",IF(D102<$C$67,"Vigilance",IF(D102<$D$67,"Favorable","Très favorable")))))) -> 0 | G102: =IF(OR(B102="",C102="",C102=0),"",IF(F102<>"",F102,B102*(1-$B$70))/C102) -> 0
D103: =IF(OR(B103="",C103=""),"",IF(C103=0,"",B103/C103)) -> 0 | E103: =IF(B103="","",IF(C103=0,"Différé",IF(B103<0,"Critique",IF(D103<$B$67,"Critique",IF(D103<$C$67,"Vigilance",IF(D103<$D$67,"Favorable","Très favorable")))))) -> 0 | G103: =IF(OR(B103="",C103="",C103=0),"",IF(F103<>"",F103,B103*(1-$B$70))/C103) -> 0 | H103: =IF(AND($B$18="Semestrielle",B103<>"",B102<>"",N(C103)+N(C102)>0),(B103+B102)/(C103+C102),"") -> 0
D104: =IF(OR(B104="",C104=""),"",IF(C104=0,"",B104/C104)) -> 0 | E104: =IF(B104="","",IF(C104=0,"Différé",IF(B104<0,"Critique",IF(D104<$B$67,"Critique",IF(D104<$C$67,"Vigilance",IF(D104<$D$67,"Favorable","Très favorable")))))) -> 0 | G104: =IF(OR(B104="",C104="",C104=0),"",IF(F104<>"",F104,B104*(1-$B$70))/C104) -> 0
D105: =IF(OR(B105="",C105=""),"",IF(C105=0,"",B105/C105)) -> 0 | E105: =IF(B105="","",IF(C105=0,"Différé",IF(B105<0,"Critique",IF(D105<$B$67,"Critique",IF(D105<$C$67,"Vigilance",IF(D105<$D$67,"Favorable","Très favorable")))))) -> 0 | G105: =IF(OR(B105="",C105="",C105=0),"",IF(F105<>"",F105,B105*(1-$B$70))/C105) -> 0 | H105: =IF(AND($B$18="Semestrielle",B105<>"",B104<>"",N(C105)+N(C104)>0),(B105+B104)/(C105+C104),"") -> 0
...

Sheet C5
A1: CAS 5 · Centrale PV d’autoproduction 12 MWc | J1: DOSSIER_V8
A2: SPV « Gharb Énergie » SARL (fictive) — Zone industrielle de Kénitra
A3: Centrale vendant sa production à un industriel privé voisin sous contrat ferme de 15 ans. Petit ticket éligible au régime d'instruction simplifié.
A4: À SAISIR (cellules orange) | B4: =COUNTIF($R$14:$R$56,0) -> 0 | C4: =IF(B4=0,"Saisie complète : lisez la note ci-dessous, puis « Fiche comité ».","Prochaine saisie : "&INDEX($P$14:$P$56,MATCH(0,$R$14:$R$56,0))) -> 0 | G4: =IF(B4=0,"",HYPERLINK("#"&INDEX($Q$14:$Q$56,MATCH(0,$R$14:$R$56,0)),"→ Aller à la cellule "&INDEX($Q$14:$Q$56,MATCH(0,$R$14:$R$56,0)))) -> 0
A5: TABLEAU DE BORD — se met à jour à chaque saisie
A6: NOTE APPROUVÉE (1 à 10) | B6: =B255 -> 0 | C6: Libellé | D6: =IFERROR(INDEX(P_ConvLib,MATCH(B255,P_ConvNote,0)),"") -> 0 | E6: Statut | F6: =B256 -> 0
A7: Score global (sur 100) | B7: =B217 -> 0 | C7: Note calculée | D7: =B218 -> 0 | E7: Plafond applicable | F7: =IF(B252>=10,"Aucun (10)",B252) -> 0
A8: Plafonds actifs | B8: =IF(TRIM(IF(E237="Oui","C1 ("&F237&") ","")&IF(E238="Oui","C2 ("&F238&") ","")&IF(E239="Oui","C3 ("&F239&") ","")&IF(E240="Oui","C4 ("&F240&") ","")&IF(E241="Oui","C5 ("&F241&") ","")&IF(E242="Oui","C6 ("&F242&") ","")&IF(E243="Oui","C7 ("&F243&") ","")&IF(E244="Oui","C8 ("&F244&") ","")&IF(E245="Oui","C9 ("&F245&") ","")&IF(E246="Oui","C10 ("&F246&") ","")&IF(E247="Oui","C11 ("&F247&") ","")&IF(E248="Oui","C12 ("&F248&") ","")&IF(E249="Oui","C13 ("&F249&") ","")&IF(E250="Oui","C14 ("&F250&") ","")&IF(E251="Oui","C15 ("&F251&") ",""))="","Aucun",TRIM(IF(E237="Oui","C1 ("&F237&") ","")&IF(E238="Oui","C2 ("&F238&") ","")&IF(E239="Oui","C3 ("&F239&") ","")&IF(E240="Oui","C4 ("&F240&") ","")&IF(E241="Oui","C5 ("&F241&") ","")&IF(E242="Oui","C6 ("&F242&") ","")&IF(E243="Oui","C7 ("&F243&") ","")&IF(E244="Oui","C8 ("&F244&") ","")&IF(E245="Oui","C9 ("&F245&") ","")&IF(E246="Oui","C10 ("&F246&") ","")&IF(E247="Oui","C11 ("&F247&") ","")&IF(E248="Oui","C12 ("&F248&") ","")&IF(E249="Oui","C13 ("&F249&") ","")&IF(E250="Oui","C14 ("&F250&") ","")&IF(E251="Oui","C15 ("&F251&") ","")))&IF(COUNTIF(E237:E251,"n.r.")>0," — "&COUNTIF(E237:E251,"n.r.")&" plafond(s) non évalué(s) faute de donnée","") -> 0
A9: Verrous actifs (exclusions X, blocages B) | B9: =IF(TRIM(IF(F222="Oui","X1 ","")&IF(F223="Oui","X2 ","")&IF(F224="Oui","X3 ","")&IF(F225="Oui","X4 ","")&IF(F226="Oui","B1 ","")&IF(F227="Oui","B2 ","")&IF(F228="Oui","B3 ","")&IF(F229="Oui","B4 ","")&IF(F230="Oui","B5 ","")&IF(F231="Oui","B6 ","")&IF(F232="Oui","B7 ","")&IF(F233="Oui","B8 ",""))="","Aucun",TRIM(IF(F222="Oui","X1 ","")&IF(F223="Oui","X2 ","")&IF(F224="Oui","X3 ","")&IF(F225="Oui","X4 ","")&IF(F226="Oui","B1 ","")&IF(F227="Oui","B2 ","")&IF(F228="Oui","B3 ","")&IF(F229="Oui","B4 ","")&IF(F230="Oui","B5 ","")&IF(F231="Oui","B6 ","")&IF(F232="Oui","B7 ","")&IF(F233="Oui","B8 ",""))) -> 0
A10: Régime de proportionnalité retenu | B10: =B35 -> 0 | C10: DSCR minimum | D10: =D133 -> 0 | E10: DSCR stressé min. | F10: =D134 -> 0
A11: Complétude (noyau N1-N6 et grille) | B11: =B204 -> 0 | C11: Noyau financier D7 | D11: =D148 -> 0 | E11: Orientation | F11: =IFERROR(INDEX(P_ConvOrient,MATCH(B255,P_ConvNote,0)),"") -> 0
A12: Aller à la section : | B12: =HYPERLINK("#A13","1 · Routage") -> 0 | C12: =HYPERLINK("#A37","3 · Sources") -> 0 | D12: =HYPERLINK("#A69","6 · Échéancier") -> 0 | E12: =HYPERLINK("#A140","7 · Noyau") -> 0 | F12: =HYPERLINK("#A167","8 · Grille") -> 0 | G12: =HYPERLINK("#A220","10 · Verrous") -> 0 | H12: =HYPERLINK("#A235","11 · Plafonds") -> 0
A13: 1 · ROUTAGE — pilote les seuils DSCR et les poids de domaine
A14: Axe | B14: Valeur | C14: Libellé | P14: 1 · Régime de revenus | Q14: B15 | R14: =IF($B$15<>"",1,0) -> 0
A15: C — Régime de revenus | B15: R1 | C15: =IFERROR(INDEX(P_RegLib,MATCH(B15,P_Regimes,0)),"") -> 0 | P15: 1 · Secteur du projet | Q15: B16 | R15: =IF($B$16<>"",1,0) -> 0
A16: D — Secteur du projet | B16: ENR | C16: =IFERROR(INDEX(P_SecLib,MATCH(B16,P_SecCodes,0)),"") -> 0 | P16: 1 · Phase du projet | Q16: B17 | R16: =IF($B$17<>"",1,0) -> 0
A17: B — Phase | B17: P1 | C17: =IFERROR(INDEX(P_PhaseLib,MATCH(B17,P_PhaseCodes,0)),"") -> 0 | P17: 1 · Périodicité des échéances | Q17: B18 | R17: =IF($B$18<>"",1,0) -> 0
A18: Périodicité du service de la dette | B18: Semestrielle | C18: Jamais annuelle : le DSCR se mesure échéance par échéance. | P18: 2 · Exposition de la banque (MMAD) | Q18: B23 | R18: =IF(ISNUMBER($B$23),1,0) -> 0
A19: A — Famille de financement | B19: PF-FLUX | C19: SPV dédiée, remboursement par les flux du projet (R5 vente d'actifs : hors outil). | P19: 2 · Recettes, coûts et dette en dirhams ? | Q19: B24 | R19: =IF($B$24<>"",1,0) -> 0
P20: 2 · Durée du financement (ans) | Q20: B25 | R20: =IF(ISNUMBER($B$25),1,0) -> 0
A21: 2 · RÉGIME DE PROPORTIONNALITÉ — calculé, jamais choisi | P21: 2 · Technologie éprouvée ? | Q21: B26 | R21: =IF($B$26<>"",1,0) -> 0
A22: CAPEX du projet économique complet (MMAD) | B22: =B47 -> 0 | C22: Repris du total des emplois (section 3). | P22: 2 · EPC clé-en-main de moins de 18 mois ? (phase P1) | Q22: B27 | R22: =IF(OR(NOT($B$17="P1"),$B$27<>""),1,0) -> 0
A23: Exposition de la banque (MMAD) | B23: 60 | P23: 2 · Acheteur principal unique ? | Q23: B28 | R23: =IF($B$28<>"",1,0) -> 0
A24: Recettes, coûts et dette intégralement en dirhams | B24: Oui | P24: 2 · Première référence technologique ? | Q24: B29 | R24: =IF($B$29<>"",1,0) -> 0
A25: Durée du financement (ans) | B25: 12 | P25: 2 · Opération consortiale ? | Q25: B30 | R25: =IF($B$30<>"",1,0) -> 0
A26: Technologie : ≥ 3 références industrielles de plus de 3 ans | B26: Oui | P26: 2 · Contrat de revenus de plus de 20 ans ? | Q26: B31 | R26: =IF($B$31<>"",1,0) -> 0
A27: En P1 : EPC clé-en-main forfaitaire, prix et délai garantis, < 18 mois | B27: Oui | P27: 2 · Site à risque climatique élevé ? | Q27: B32 | R27: =IF($B$32<>"",1,0) -> 0
A28: Acheteur principal unique et identifié | B28: Oui | P28: 2 · Nombre de contreparties clés | Q28: B33 | R28: =IF(ISNUMBER($B$33),1,0) -> 0
A29: Technologie constituant une première référence dans la juridiction | B29: Non | P29: 3 · Emplois : montants du besoin à terminaison | Q29: B39 | R29: =IF(N($B$47)>0,1,0) -> 0
A30: Opération consortiale relevant de la directive 3/W/2025 | B30: Non | P30: 3 · Ressources engagées : montants | Q30: E39 | R30: =IF(N($E$47)>0,1,0) -> 0
A31: Concession ou contrat de revenus de plus de 20 ans | B31: Non | P31: 3 · Nature de chaque ressource | Q31: F39 | R31: =IF(SUMPRODUCT(ISNUMBER($E$39:$E$46)*($F$39:$F$46=""))=0,1,0) -> 0
A32: Site classé à risque climatique physique élevé | B32: Non | P32: 3 · Plan de remédiation (couverture entre 95 et 100 %) | Q32: B50 | R32: =IF(OR(NOT(AND($B$17="P1",ISNUMBER($B$48),N($B$48)>=P_N3_V,N($B$48)<P_N3_F)),$B$50<>""),1,0) -> 0
A33: Nombre de contreparties clés | P33: 6 · Choc du scénario défavorable (%) | Q33: B70 | R33: =IF(ISNUMBER($B$70),1,0) -> 0
A34: Régime calculé (avant escalade) | B34: =IF(OR(B22="",B22=0,B15=""),"",IF(OR(B22>P_L_CAPEX,N(B23)>P_L_EXPO,B15="R4",B29="Oui",N(B153)>0,B30="Oui",B31="Oui",B32="Oui",N(B33)>P_L_NBCP),"L",IF(AND(B22<=P_S_CAPEX,B23<>"",N(B23)<=P_S_EXPO,OR(B15="R1",B15="R2"),B26="Oui",B24="Oui",B25<>"",N(B25)<=P_S_DUREE,OR(B17<>"P1",B27="Oui"),B28="Oui",COUNTIF($F$222:$F$233,"Oui")=0),"S","M"))) -> 0 | C34: =IF(B34="","",IF(B34="L","Escalade : "&IF(B22>P_L_CAPEX,"CAPEX > "&P_L_CAPEX&" MMAD ; ","")&IF(N(B23)>P_L_EXPO,"exposition > "&P_L_EXPO&" MMAD ; ","")&IF(B15="R4","régime de revenus R4 ; ","")&IF(B29="Oui","première référence technologique ; ","")&IF(N(B153)>0,"devises non intégralement couvertes ; ","")&IF(B30="Oui","opération consortiale ; ","")&IF(B31="Oui","contrat de revenus > 20 ans ; ","")&IF(B32="Oui","risque climatique élevé ; ","")&IF(N(B33)>P_L_NBCP,"plus de "&P_L_NBCP&" contreparties clés ; ",""),IF(B34="S","Toutes les conditions du régime simplifié sont réunies.","Régime standard par défaut : une condition du régime S manque, aucune condition d'escalade."))) -> 0 | P34: 6 · Échéancier : CFADS d'au moins deux périodes | Q34: B72 | R34: =IF(COUNT($B$72:$B$131)>=2,1,0) -> 0
A35: RÉGIME RETENU (après escalade automatique) | B35: =IF(B34="","",IF(AND(IF(AND(B34="S",COUNTIF($F$222:$F$233,"Oui")>0),"M",B34)="M",COUNTIF($E$237:$E$251,"Oui")>0),"L",IF(AND(B34="S",COUNTIF($F$222:$F$233,"Oui")>0),"M",B34))) -> 0 | C35: =IF(B35=B34,"Aucune escalade.",IF(B35="L","Escalade : un plafond de note est actif (M passe en L).","Escalade : un verrou est actif (S passe en M).")) -> 0 | P35: 6 · Service de la dette de chaque période | Q35: C72 | R35: =IF(SUMPRODUCT(ISNUMBER($B$72:$B$131)*(1-ISNUMBER($C$72:$C$131)))=0,1,0) -> 0
P36: 7 · N4 — Liquidité (DSRA, lignes, cascade) | Q36: B145 | R36: =IF($B$145<>"",1,0) -> 0
A37: 3 · SOURCES ET EMPLOIS (MMAD) — test de financement à terminaison | P37: 7 · N5 — Levier et fonds propres à risque | Q37: B146 | R37: =IF($B$146<>"",1,0) -> 0
A38: Emplois | B38: Montant | D38: Ressources | E38: Montant | F38: Nature | P38: 7 · N6 — Exposition résiduelle taux, change, refinancement | Q38: B147 | R38: =IF($B$147<>"",1,0) -> 0
A39: Contrat EPC clé-en-main | B39: 88 | D39: Dette senior (12 ans, 6,0 %) | E39: 60 | F39: Dette senior | P39: 7 · N3 hors phase P1 : note LLCR | Q39: B150 | R39: =IF(OR($B$17="P1",$B$150<>""),1,0) -> 0
A40: Raccordement et poste de livraison | B40: 7 | D40: Fonds propres | E40: 48 | F40: Fonds propres | P40: 7 · LLCR (plafond C4) | Q40: B151 | R40: =IF(ISNUMBER($B$151),1,0) -> 0
A41: Frais et contingence | B41: 5 | P41: 7 · DSRA en mois (plafond C7) | Q41: B152 | R41: =IF(ISNUMBER($B$152),1,0) -> 0
A42: Intérêts intercalaires | B42: 2 | P42: 7 · Exposition nette en devises (plafond C6) | Q42: B153 | R42: =IF(ISNUMBER($B$153),1,0) -> 0
A43: Dotation DSRA | B43: 3.6 | P43: 7 · Dette à refinancer à maturité (plafond C8) | Q43: B154 | R43: =IF(ISNUMBER($B$154),1,0) -> 0
P44: 7 · Stratégie de refinancement approuvée ? | Q44: B155 | R44: =IF(OR(N($B$154)<=P_C8,$B$155<>""),1,0) -> 0
P45: 7 · Part des recettes de l'acheteur principal (C10) | Q45: B156 | R45: =IF(ISNUMBER($B$156),1,0) -> 0
P46: 7 · Qualité de crédit de l'acheteur principal | Q46: B157 | R46: =IF($B$157<>"",1,0) -> 0
A47: Total emplois (besoin à terminaison) | B47: =SUM(B39:B46) -> 0 | D47: Total ressources engagées | E47: =SUM(E39:E46) -> 0 | P47: 7 · Durée résiduelle du contrat de revenus (C5) | Q47: B158 | R47: =IF(OR($B$15="R4",ISNUMBER($B$158)),1,0) -> 0
A48: Couverture du besoin à terminaison (ressources / emplois) | B48: =IF(N(B47)=0,"",E47/B47) -> 0 | P48: 7 · Durée résiduelle de la dette | Q48: B159 | R48: =IF(ISNUMBER($B$159),1,0) -> 0
A49: Quote-part de dette (dette / besoin à terminaison) | B49: =IF(N(B47)=0,"",(SUMIF(F39:F46,"Dette senior",E39:E46)+SUMIF(F39:F46,"Dette subordonnée",E39:E46))/B47) -> 0 | P49: 7 · Solution documentée (contrat plus court que la dette) ? | Q49: B160 | R49: =IF(OR(NOT(AND(ISNUMBER($B$158),ISNUMBER($B$159))),N($B$158)>=N($B$159),$B$160<>""),1,0) -> 0
A50: Plan de remédiation approuvé (couverture entre 95 % et 100 %) | B50: Non | P50: 7 · Plan d'adaptation climatique financé ? (C11) | Q50: B161 | R50: =IF(OR($B$32<>"Oui",$B$161<>""),1,0) -> 0
P51: 7 · Capacité résiduelle du sponsor (C12) | Q51: B162 | R51: =IF($B$162<>"",1,0) -> 0
A52: 4 · HYPOTHÈSES D'EXPLOITATION (information, non calculées) | P52: 7 · Opérateur remplaçable ? (C13) | Q52: B163 | R52: =IF($B$163<>"",1,0) -> 0
A53: Production nette | B53: 21,6 GWh/an | P53: 7 · Écart fin O&M / fin de dette (opérateur non remplaçable) | Q53: B164 | R53: =IF(OR($B$163<>"Non",ISNUMBER($B$164)),1,0) -> 0
A54: Tarif contractuel | B54: 0,80 MAD/kWh | P54: 7 · Facteur commun au-delà de la limite interne (C14) | Q54: B165 | R54: =IF($B$165<>"",1,0) -> 0
A55: Chiffre d’affaires | B55: 17,3 MMAD/an | P55: 8 · Grille : sous-critère requis non noté | Q55: ="B"&IF(COUNT($P$169:$P$201)=0,169,MIN($P$169:$P$201)) -> 0 | R55: =IF(COUNT($P$169:$P$201)=0,1,0) -> 0
A56: Charges d’exploitation | B56: 2,3 MMAD/an | P56: 10 · Verrous X1 à B8 : répondre Oui ou Non | Q56: E222 | R56: =IF(COUNTBLANK($E$222:$E$233)=0,1,0) -> 0
A57: CFADS | B57: 13,2 MMAD/an
A58: Service de la dette | B58: 7,16 MMAD/an, semestriel
A62: 5 · SEUILS DSCR APPLICABLES = base du régime + Δ secteur + majoration de phase
A63: Seuil critique de base du régime | B63: =IFERROR(INDEX(P_Crit,MATCH($B$15,P_Regimes,0)),"") -> 0
A64: Écart sectoriel Δ | B64: =IFERROR(INDEX(P_SecDelta,MATCH($B$16,P_SecCodes,0)),"") -> 0
A65: Majoration de phase | B65: =IFERROR(INDEX(P_PhaseMaj,MATCH($B$17,P_PhaseCodes,0)),"") -> 0
A66: Seuils applicables | B66: Critique < | C66: Vigilance < | D66: Favorable < | E66: Très favorable ≥
A67: Seuil = base + Δ + majoration | B67: =IFERROR(INDEX(P_Crit,MATCH($B$15,P_Regimes,0))+$B$64+$B$65,"") -> 0 | C67: =IFERROR(INDEX(P_Vig,MATCH($B$15,P_Regimes,0))+$B$64+$B$65,"") -> 0 | D67: =IFERROR(INDEX(P_Fav,MATCH($B$15,P_Regimes,0))+$B$64+$B$65,"") -> 0 | E67: =D67 -> 0
A69: 6 · ÉCHÉANCIER DATÉ ET DSCR PAR ÉCHÉANCE (jusqu'à 60 périodes)
A70: Scénario défavorable : baisse du CFADS appliquée à chaque période | B70: 0.066813 | C70: Production P90 (− 8 %) et retard de paiement de l’acheteur de 90 jours
A71: Période | B71: CFADS central | C71: Service de la dette | D71: DSCR | E71: Classement | F71: CFADS stressé (saisie facultative) | G71: DSCR stressé | H71: DSCR annuel (paire de semestres)
A72: An 1 · S1 | B72: 6.3 | C72: 3.58 | D72: =IF(OR(B72="",C72=""),"",IF(C72=0,"",B72/C72)) -> 0 | E72: =IF(B72="","",IF(C72=0,"Différé",IF(B72<0,"Critique",IF(D72<$B$67,"Critique",IF(D72<$C$67,"Vigilance",IF(D72<$D$67,"Favorable","Très favorable")))))) -> 0 | G72: =IF(OR(B72="",C72="",C72=0),"",IF(F72<>"",F72,B72*(1-$B$70))/C72) -> 0
A73: An 1 · S2 | B73: 6.9 | C73: 3.58 | D73: =IF(OR(B73="",C73=""),"",IF(C73=0,"",B73/C73)) -> 0 | E73: =IF(B73="","",IF(C73=0,"Différé",IF(B73<0,"Critique",IF(D73<$B$67,"Critique",IF(D73<$C$67,"Vigilance",IF(D73<$D$67,"Favorable","Très favorable")))))) -> 0 | G73: =IF(OR(B73="",C73="",C73=0),"",IF(F73<>"",F73,B73*(1-$B$70))/C73) -> 0 | H73: =IF(AND($B$18="Semestrielle",B73<>"",B72<>"",N(C73)+N(C72)>0),(B73+B72)/(C73+C72),"") -> 0
A74: An 12 · S1 | B74: 6 | C74: 3.58 | D74: =IF(OR(B74="",C74=""),"",IF(C74=0,"",B74/C74)) -> 0 | E74: =IF(B74="","",IF(C74=0,"Différé",IF(B74<0,"Critique",IF(D74<$B$67,"Critique",IF(D74<$C$67,"Vigilance",IF(D74<$D$67,"Favorable","Très favorable")))))) -> 0 | G74: =IF(OR(B74="",C74="",C74=0),"",IF(F74<>"",F74,B74*(1-$B$70))/C74) -> 0
A75: An 12 · S2 | B75: 6.6 | C75: 3.58 | D75: =IF(OR(B75="",C75=""),"",IF(C75=0,"",B75/C75)) -> 0 | E75: =IF(B75="","",IF(C75=0,"Différé",IF(B75<0,"Critique",IF(D75<$B$67,"Critique",IF(D75<$C$67,"Vigilance",IF(D75<$D$67,"Favorable","Très favorable")))))) -> 0 | G75: =IF(OR(B75="",C75="",C75=0),"",IF(F75<>"",F75,B75*(1-$B$70))/C75) -> 0 | H75: =IF(AND($B$18="Semestrielle",B75<>"",B74<>"",N(C75)+N(C74)>0),(B75+B74)/(C75+C74),"") -> 0
D76: =IF(OR(B76="",C76=""),"",IF(C76=0,"",B76/C76)) -> 0 | E76: =IF(B76="","",IF(C76=0,"Différé",IF(B76<0,"Critique",IF(D76<$B$67,"Critique",IF(D76<$C$67,"Vigilance",IF(D76<$D$67,"Favorable","Très favorable")))))) -> 0 | G76: =IF(OR(B76="",C76="",C76=0),"",IF(F76<>"",F76,B76*(1-$B$70))/C76) -> 0
D77: =IF(OR(B77="",C77=""),"",IF(C77=0,"",B77/C77)) -> 0 | E77: =IF(B77="","",IF(C77=0,"Différé",IF(B77<0,"Critique",IF(D77<$B$67,"Critique",IF(D77<$C$67,"Vigilance",IF(D77<$D$67,"Favorable","Très favorable")))))) -> 0 | G77: =IF(OR(B77="",C77="",C77=0),"",IF(F77<>"",F77,B77*(1-$B$70))/C77) -> 0 | H77: =IF(AND($B$18="Semestrielle",B77<>"",B76<>"",N(C77)+N(C76)>0),(B77+B76)/(C77+C76),"") -> 0
D78: =IF(OR(B78="",C78=""),"",IF(C78=0,"",B78/C78)) -> 0 | E78: =IF(B78="","",IF(C78=0,"Différé",IF(B78<0,"Critique",IF(D78<$B$67,"Critique",IF(D78<$C$67,"Vigilance",IF(D78<$D$67,"Favorable","Très favorable")))))) -> 0 | G78: =IF(OR(B78="",C78="",C78=0),"",IF(F78<>"",F78,B78*(1-$B$70))/C78) -> 0
D79: =IF(OR(B79="",C79=""),"",IF(C79=0,"",B79/C79)) -> 0 | E79: =IF(B79="","",IF(C79=0,"Différé",IF(B79<0,"Critique",IF(D79<$B$67,"Critique",IF(D79<$C$67,"Vigilance",IF(D79<$D$67,"Favorable","Très favorable")))))) -> 0 | G79: =IF(OR(B79="",C79="",C79=0),"",IF(F79<>"",F79,B79*(1-$B$70))/C79) -> 0 | H79: =IF(AND($B$18="Semestrielle",B79<>"",B78<>"",N(C79)+N(C78)>0),(B79+B78)/(C79+C78),"") -> 0
D80: =IF(OR(B80="",C80=""),"",IF(C80=0,"",B80/C80)) -> 0 | E80: =IF(B80="","",IF(C80=0,"Différé",IF(B80<0,"Critique",IF(D80<$B$67,"Critique",IF(D80<$C$67,"Vigilance",IF(D80<$D$67,"Favorable","Très favorable")))))) -> 0 | G80: =IF(OR(B80="",C80="",C80=0),"",IF(F80<>"",F80,B80*(1-$B$70))/C80) -> 0
D81: =IF(OR(B81="",C81=""),"",IF(C81=0,"",B81/C81)) -> 0 | E81: =IF(B81="","",IF(C81=0,"Différé",IF(B81<0,"Critique",IF(D81<$B$67,"Critique",IF(D81<$C$67,"Vigilance",IF(D81<$D$67,"Favorable","Très favorable")))))) -> 0 | G81: =IF(OR(B81="",C81="",C81=0),"",IF(F81<>"",F81,B81*(1-$B$70))/C81) -> 0 | H81: =IF(AND($B$18="Semestrielle",B81<>"",B80<>"",N(C81)+N(C80)>0),(B81+B80)/(C81+C80),"") -> 0
D82: =IF(OR(B82="",C82=""),"",IF(C82=0,"",B82/C82)) -> 0 | E82: =IF(B82="","",IF(C82=0,"Différé",IF(B82<0,"Critique",IF(D82<$B$67,"Critique",IF(D82<$C$67,"Vigilance",IF(D82<$D$67,"Favorable","Très favorable")))))) -> 0 | G82: =IF(OR(B82="",C82="",C82=0),"",IF(F82<>"",F82,B82*(1-$B$70))/C82) -> 0
D83: =IF(OR(B83="",C83=""),"",IF(C83=0,"",B83/C83)) -> 0 | E83: =IF(B83="","",IF(C83=0,"Différé",IF(B83<0,"Critique",IF(D83<$B$67,"Critique",IF(D83<$C$67,"Vigilance",IF(D83<$D$67,"Favorable","Très favorable")))))) -> 0 | G83: =IF(OR(B83="",C83="",C83=0),"",IF(F83<>"",F83,B83*(1-$B$70))/C83) -> 0 | H83: =IF(AND($B$18="Semestrielle",B83<>"",B82<>"",N(C83)+N(C82)>0),(B83+B82)/(C83+C82),"") -> 0
D84: =IF(OR(B84="",C84=""),"",IF(C84=0,"",B84/C84)) -> 0 | E84: =IF(B84="","",IF(C84=0,"Différé",IF(B84<0,"Critique",IF(D84<$B$67,"Critique",IF(D84<$C$67,"Vigilance",IF(D84<$D$67,"Favorable","Très favorable")))))) -> 0 | G84: =IF(OR(B84="",C84="",C84=0),"",IF(F84<>"",F84,B84*(1-$B$70))/C84) -> 0
D85: =IF(OR(B85="",C85=""),"",IF(C85=0,"",B85/C85)) -> 0 | E85: =IF(B85="","",IF(C85=0,"Différé",IF(B85<0,"Critique",IF(D85<$B$67,"Critique",IF(D85<$C$67,"Vigilance",IF(D85<$D$67,"Favorable","Très favorable")))))) -> 0 | G85: =IF(OR(B85="",C85="",C85=0),"",IF(F85<>"",F85,B85*(1-$B$70))/C85) -> 0 | H85: =IF(AND($B$18="Semestrielle",B85<>"",B84<>"",N(C85)+N(C84)>0),(B85+B84)/(C85+C84),"") -> 0
D86: =IF(OR(B86="",C86=""),"",IF(C86=0,"",B86/C86)) -> 0 | E86: =IF(B86="","",IF(C86=0,"Différé",IF(B86<0,"Critique",IF(D86<$B$67,"Critique",IF(D86<$C$67,"Vigilance",IF(D86<$D$67,"Favorable","Très favorable")))))) -> 0 | G86: =IF(OR(B86="",C86="",C86=0),"",IF(F86<>"",F86,B86*(1-$B$70))/C86) -> 0
D87: =IF(OR(B87="",C87=""),"",IF(C87=0,"",B87/C87)) -> 0 | E87: =IF(B87="","",IF(C87=0,"Différé",IF(B87<0,"Critique",IF(D87<$B$67,"Critique",IF(D87<$C$67,"Vigilance",IF(D87<$D$67,"Favorable","Très favorable")))))) -> 0 | G87: =IF(OR(B87="",C87="",C87=0),"",IF(F87<>"",F87,B87*(1-$B$70))/C87) -> 0 | H87: =IF(AND($B$18="Semestrielle",B87<>"",B86<>"",N(C87)+N(C86)>0),(B87+B86)/(C87+C86),"") -> 0
D88: =IF(OR(B88="",C88=""),"",IF(C88=0,"",B88/C88)) -> 0 | E88: =IF(B88="","",IF(C88=0,"Différé",IF(B88<0,"Critique",IF(D88<$B$67,"Critique",IF(D88<$C$67,"Vigilance",IF(D88<$D$67,"Favorable","Très favorable")))))) -> 0 | G88: =IF(OR(B88="",C88="",C88=0),"",IF(F88<>"",F88,B88*(1-$B$70))/C88) -> 0
D89: =IF(OR(B89="",C89=""),"",IF(C89=0,"",B89/C89)) -> 0 | E89: =IF(B89="","",IF(C89=0,"Différé",IF(B89<0,"Critique",IF(D89<$B$67,"Critique",IF(D89<$C$67,"Vigilance",IF(D89<$D$67,"Favorable","Très favorable")))))) -> 0 | G89: =IF(OR(B89="",C89="",C89=0),"",IF(F89<>"",F89,B89*(1-$B$70))/C89) -> 0 | H89: =IF(AND($B$18="Semestrielle",B89<>"",B88<>"",N(C89)+N(C88)>0),(B89+B88)/(C89+C88),"") -> 0
D90: =IF(OR(B90="",C90=""),"",IF(C90=0,"",B90/C90)) -> 0 | E90: =IF(B90="","",IF(C90=0,"Différé",IF(B90<0,"Critique",IF(D90<$B$67,"Critique",IF(D90<$C$67,"Vigilance",IF(D90<$D$67,"Favorable","Très favorable")))))) -> 0 | G90: =IF(OR(B90="",C90="",C90=0),"",IF(F90<>"",F90,B90*(1-$B$70))/C90) -> 0
D91: =IF(OR(B91="",C91=""),"",IF(C91=0,"",B91/C91)) -> 0 | E91: =IF(B91="","",IF(C91=0,"Différé",IF(B91<0,"Critique",IF(D91<$B$67,"Critique",IF(D91<$C$67,"Vigilance",IF(D91<$D$67,"Favorable","Très favorable")))))) -> 0 | G91: =IF(OR(B91="",C91="",C91=0),"",IF(F91<>"",F91,B91*(1-$B$70))/C91) -> 0 | H91: =IF(AND($B$18="Semestrielle",B91<>"",B90<>"",N(C91)+N(C90)>0),(B91+B90)/(C91+C90),"") -> 0
D92: =IF(OR(B92="",C92=""),"",IF(C92=0,"",B92/C92)) -> 0 | E92: =IF(B92="","",IF(C92=0,"Différé",IF(B92<0,"Critique",IF(D92<$B$67,"Critique",IF(D92<$C$67,"Vigilance",IF(D92<$D$67,"Favorable","Très favorable")))))) -> 0 | G92: =IF(OR(B92="",C92="",C92=0),"",IF(F92<>"",F92,B92*(1-$B$70))/C92) -> 0
D93: =IF(OR(B93="",C93=""),"",IF(C93=0,"",B93/C93)) -> 0 | E93: =IF(B93="","",IF(C93=0,"Différé",IF(B93<0,"Critique",IF(D93<$B$67,"Critique",IF(D93<$C$67,"Vigilance",IF(D93<$D$67,"Favorable","Très favorable")))))) -> 0 | G93: =IF(OR(B93="",C93="",C93=0),"",IF(F93<>"",F93,B93*(1-$B$70))/C93) -> 0 | H93: =IF(AND($B$18="Semestrielle",B93<>"",B92<>"",N(C93)+N(C92)>0),(B93+B92)/(C93+C92),"") -> 0
D94: =IF(OR(B94="",C94=""),"",IF(C94=0,"",B94/C94)) -> 0 | E94: =IF(B94="","",IF(C94=0,"Différé",IF(B94<0,"Critique",IF(D94<$B$67,"Critique",IF(D94<$C$67,"Vigilance",IF(D94<$D$67,"Favorable","Très favorable")))))) -> 0 | G94: =IF(OR(B94="",C94="",C94=0),"",IF(F94<>"",F94,B94*(1-$B$70))/C94) -> 0
D95: =IF(OR(B95="",C95=""),"",IF(C95=0,"",B95/C95)) -> 0 | E95: =IF(B95="","",IF(C95=0,"Différé",IF(B95<0,"Critique",IF(D95<$B$67,"Critique",IF(D95<$C$67,"Vigilance",IF(D95<$D$67,"Favorable","Très favorable")))))) -> 0 | G95: =IF(OR(B95="",C95="",C95=0),"",IF(F95<>"",F95,B95*(1-$B$70))/C95) -> 0 | H95: =IF(AND($B$18="Semestrielle",B95<>"",B94<>"",N(C95)+N(C94)>0),(B95+B94)/(C95+C94),"") -> 0
D96: =IF(OR(B96="",C96=""),"",IF(C96=0,"",B96/C96)) -> 0 | E96: =IF(B96="","",IF(C96=0,"Différé",IF(B96<0,"Critique",IF(D96<$B$67,"Critique",IF(D96<$C$67,"Vigilance",IF(D96<$D$67,"Favorable","Très favorable")))))) -> 0 | G96: =IF(OR(B96="",C96="",C96=0),"",IF(F96<>"",F96,B96*(1-$B$70))/C96) -> 0
D97: =IF(OR(B97="",C97=""),"",IF(C97=0,"",B97/C97)) -> 0 | E97: =IF(B97="","",IF(C97=0,"Différé",IF(B97<0,"Critique",IF(D97<$B$67,"Critique",IF(D97<$C$67,"Vigilance",IF(D97<$D$67,"Favorable","Très favorable")))))) -> 0 | G97: =IF(OR(B97="",C97="",C97=0),"",IF(F97<>"",F97,B97*(1-$B$70))/C97) -> 0 | H97: =IF(AND($B$18="Semestrielle",B97<>"",B96<>"",N(C97)+N(C96)>0),(B97+B96)/(C97+C96),"") -> 0
D98: =IF(OR(B98="",C98=""),"",IF(C98=0,"",B98/C98)) -> 0 | E98: =IF(B98="","",IF(C98=0,"Différé",IF(B98<0,"Critique",IF(D98<$B$67,"Critique",IF(D98<$C$67,"Vigilance",IF(D98<$D$67,"Favorable","Très favorable")))))) -> 0 | G98: =IF(OR(B98="",C98="",C98=0),"",IF(F98<>"",F98,B98*(1-$B$70))/C98) -> 0
D99: =IF(OR(B99="",C99=""),"",IF(C99=0,"",B99/C99)) -> 0 | E99: =IF(B99="","",IF(C99=0,"Différé",IF(B99<0,"Critique",IF(D99<$B$67,"Critique",IF(D99<$C$67,"Vigilance",IF(D99<$D$67,"Favorable","Très favorable")))))) -> 0 | G99: =IF(OR(B99="",C99="",C99=0),"",IF(F99<>"",F99,B99*(1-$B$70))/C99) -> 0 | H99: =IF(AND($B$18="Semestrielle",B99<>"",B98<>"",N(C99)+N(C98)>0),(B99+B98)/(C99+C98),"") -> 0
D100: =IF(OR(B100="",C100=""),"",IF(C100=0,"",B100/C100)) -> 0 | E100: =IF(B100="","",IF(C100=0,"Différé",IF(B100<0,"Critique",IF(D100<$B$67,"Critique",IF(D100<$C$67,"Vigilance",IF(D100<$D$67,"Favorable","Très favorable")))))) -> 0 | G100: =IF(OR(B100="",C100="",C100=0),"",IF(F100<>"",F100,B100*(1-$B$70))/C100) -> 0
D101: =IF(OR(B101="",C101=""),"",IF(C101=0,"",B101/C101)) -> 0 | E101: =IF(B101="","",IF(C101=0,"Différé",IF(B101<0,"Critique",IF(D101<$B$67,"Critique",IF(D101<$C$67,"Vigilance",IF(D101<$D$67,"Favorable","Très favorable")))))) -> 0 | G101: =IF(OR(B101="",C101="",C101=0),"",IF(F101<>"",F101,B101*(1-$B$70))/C101) -> 0 | H101: =IF(AND($B$18="Semestrielle",B101<>"",B100<>"",N(C101)+N(C100)>0),(B101+B100)/(C101+C100),"") -> 0
D102: =IF(OR(B102="",C102=""),"",IF(C102=0,"",B102/C102)) -> 0 | E102: =IF(B102="","",IF(C102=0,"Différé",IF(B102<0,"Critique",IF(D102<$B$67,"Critique",IF(D102<$C$67,"Vigilance",IF(D102<$D$67,"Favorable","Très favorable")))))) -> 0 | G102: =IF(OR(B102="",C102="",C102=0),"",IF(F102<>"",F102,B102*(1-$B$70))/C102) -> 0
D103: =IF(OR(B103="",C103=""),"",IF(C103=0,"",B103/C103)) -> 0 | E103: =IF(B103="","",IF(C103=0,"Différé",IF(B103<0,"Critique",IF(D103<$B$67,"Critique",IF(D103<$C$67,"Vigilance",IF(D103<$D$67,"Favorable","Très favorable")))))) -> 0 | G103: =IF(OR(B103="",C103="",C103=0),"",IF(F103<>"",F103,B103*(1-$B$70))/C103) -> 0 | H103: =IF(AND($B$18="Semestrielle",B103<>"",B102<>"",N(C103)+N(C102)>0),(B103+B102)/(C103+C102),"") -> 0
D104: =IF(OR(B104="",C104=""),"",IF(C104=0,"",B104/C104)) -> 0 | E104: =IF(B104="","",IF(C104=0,"Différé",IF(B104<0,"Critique",IF(D104<$B$67,"Critique",IF(D104<$C$67,"Vigilance",IF(D104<$D$67,"Favorable","Très favorable")))))) -> 0 | G104: =IF(OR(B104="",C104="",C104=0),"",IF(F104<>"",F104,B104*(1-$B$70))/C104) -> 0
...

Sheet Modèle
A1: Nouveau dossier — intitulé du projet | J1: MODELE
A2: SPV — localisation
A3: Résumé du projet : objet, contrat de recettes, financement.
A4: À SAISIR (cellules orange) | B4: =COUNTIF($R$14:$R$56,0) -> 0 | C4: =IF(B4=0,"Saisie complète : lisez la note ci-dessous, puis « Fiche comité ».","Prochaine saisie : "&INDEX($P$14:$P$56,MATCH(0,$R$14:$R$56,0))) -> 0 | G4: =IF(B4=0,"",HYPERLINK("#"&INDEX($Q$14:$Q$56,MATCH(0,$R$14:$R$56,0)),"→ Aller à la cellule "&INDEX($Q$14:$Q$56,MATCH(0,$R$14:$R$56,0)))) -> 0
A5: TABLEAU DE BORD — se met à jour à chaque saisie
A6: NOTE APPROUVÉE (1 à 10) | B6: =B255 -> 0 | C6: Libellé | D6: =IFERROR(INDEX(P_ConvLib,MATCH(B255,P_ConvNote,0)),"") -> 0 | E6: Statut | F6: =B256 -> 0
A7: Score global (sur 100) | B7: =B217 -> 0 | C7: Note calculée | D7: =B218 -> 0 | E7: Plafond applicable | F7: =IF(B252>=10,"Aucun (10)",B252) -> 0
A8: Plafonds actifs | B8: =IF(TRIM(IF(E237="Oui","C1 ("&F237&") ","")&IF(E238="Oui","C2 ("&F238&") ","")&IF(E239="Oui","C3 ("&F239&") ","")&IF(E240="Oui","C4 ("&F240&") ","")&IF(E241="Oui","C5 ("&F241&") ","")&IF(E242="Oui","C6 ("&F242&") ","")&IF(E243="Oui","C7 ("&F243&") ","")&IF(E244="Oui","C8 ("&F244&") ","")&IF(E245="Oui","C9 ("&F245&") ","")&IF(E246="Oui","C10 ("&F246&") ","")&IF(E247="Oui","C11 ("&F247&") ","")&IF(E248="Oui","C12 ("&F248&") ","")&IF(E249="Oui","C13 ("&F249&") ","")&IF(E250="Oui","C14 ("&F250&") ","")&IF(E251="Oui","C15 ("&F251&") ",""))="","Aucun",TRIM(IF(E237="Oui","C1 ("&F237&") ","")&IF(E238="Oui","C2 ("&F238&") ","")&IF(E239="Oui","C3 ("&F239&") ","")&IF(E240="Oui","C4 ("&F240&") ","")&IF(E241="Oui","C5 ("&F241&") ","")&IF(E242="Oui","C6 ("&F242&") ","")&IF(E243="Oui","C7 ("&F243&") ","")&IF(E244="Oui","C8 ("&F244&") ","")&IF(E245="Oui","C9 ("&F245&") ","")&IF(E246="Oui","C10 ("&F246&") ","")&IF(E247="Oui","C11 ("&F247&") ","")&IF(E248="Oui","C12 ("&F248&") ","")&IF(E249="Oui","C13 ("&F249&") ","")&IF(E250="Oui","C14 ("&F250&") ","")&IF(E251="Oui","C15 ("&F251&") ","")))&IF(COUNTIF(E237:E251,"n.r.")>0," — "&COUNTIF(E237:E251,"n.r.")&" plafond(s) non évalué(s) faute de donnée","") -> 0
A9: Verrous actifs (exclusions X, blocages B) | B9: =IF(TRIM(IF(F222="Oui","X1 ","")&IF(F223="Oui","X2 ","")&IF(F224="Oui","X3 ","")&IF(F225="Oui","X4 ","")&IF(F226="Oui","B1 ","")&IF(F227="Oui","B2 ","")&IF(F228="Oui","B3 ","")&IF(F229="Oui","B4 ","")&IF(F230="Oui","B5 ","")&IF(F231="Oui","B6 ","")&IF(F232="Oui","B7 ","")&IF(F233="Oui","B8 ",""))="","Aucun",TRIM(IF(F222="Oui","X1 ","")&IF(F223="Oui","X2 ","")&IF(F224="Oui","X3 ","")&IF(F225="Oui","X4 ","")&IF(F226="Oui","B1 ","")&IF(F227="Oui","B2 ","")&IF(F228="Oui","B3 ","")&IF(F229="Oui","B4 ","")&IF(F230="Oui","B5 ","")&IF(F231="Oui","B6 ","")&IF(F232="Oui","B7 ","")&IF(F233="Oui","B8 ",""))) -> 0
A10: Régime de proportionnalité retenu | B10: =B35 -> 0 | C10: DSCR minimum | D10: =D133 -> 0 | E10: DSCR stressé min. | F10: =D134 -> 0
A11: Complétude (noyau N1-N6 et grille) | B11: =B204 -> 0 | C11: Noyau financier D7 | D11: =D148 -> 0 | E11: Orientation | F11: =IFERROR(INDEX(P_ConvOrient,MATCH(B255,P_ConvNote,0)),"") -> 0
A12: Aller à la section : | B12: =HYPERLINK("#A13","1 · Routage") -> 0 | C12: =HYPERLINK("#A37","3 · Sources") -> 0 | D12: =HYPERLINK("#A69","6 · Échéancier") -> 0 | E12: =HYPERLINK("#A140","7 · Noyau") -> 0 | F12: =HYPERLINK("#A167","8 · Grille") -> 0 | G12: =HYPERLINK("#A220","10 · Verrous") -> 0 | H12: =HYPERLINK("#A235","11 · Plafonds") -> 0
A13: 1 · ROUTAGE — pilote les seuils DSCR et les poids de domaine
A14: Axe | B14: Valeur | C14: Libellé | P14: 1 · Régime de revenus | Q14: B15 | R14: =IF($B$15<>"",1,0) -> 0
A15: C — Régime de revenus | C15: =IFERROR(INDEX(P_RegLib,MATCH(B15,P_Regimes,0)),"") -> 0 | P15: 1 · Secteur du projet | Q15: B16 | R15: =IF($B$16<>"",1,0) -> 0
A16: D — Secteur du projet | C16: =IFERROR(INDEX(P_SecLib,MATCH(B16,P_SecCodes,0)),"") -> 0 | P16: 1 · Phase du projet | Q16: B17 | R16: =IF($B$17<>"",1,0) -> 0
A17: B — Phase | C17: =IFERROR(INDEX(P_PhaseLib,MATCH(B17,P_PhaseCodes,0)),"") -> 0 | P17: 1 · Périodicité des échéances | Q17: B18 | R17: =IF($B$18<>"",1,0) -> 0
A18: Périodicité du service de la dette | C18: Jamais annuelle : le DSCR se mesure échéance par échéance. | P18: 2 · Exposition de la banque (MMAD) | Q18: B23 | R18: =IF(ISNUMBER($B$23),1,0) -> 0
A19: A — Famille de financement | B19: PF-FLUX | C19: SPV dédiée, remboursement par les flux du projet (R5 vente d'actifs : hors outil). | P19: 2 · Recettes, coûts et dette en dirhams ? | Q19: B24 | R19: =IF($B$24<>"",1,0) -> 0
P20: 2 · Durée du financement (ans) | Q20: B25 | R20: =IF(ISNUMBER($B$25),1,0) -> 0
A21: 2 · RÉGIME DE PROPORTIONNALITÉ — calculé, jamais choisi | P21: 2 · Technologie éprouvée ? | Q21: B26 | R21: =IF($B$26<>"",1,0) -> 0
A22: CAPEX du projet économique complet (MMAD) | B22: =B47 -> 0 | C22: Repris du total des emplois (section 3). | P22: 2 · EPC clé-en-main de moins de 18 mois ? (phase P1) | Q22: B27 | R22: =IF(OR(NOT($B$17="P1"),$B$27<>""),1,0) -> 0
A23: Exposition de la banque (MMAD) | P23: 2 · Acheteur principal unique ? | Q23: B28 | R23: =IF($B$28<>"",1,0) -> 0
A24: Recettes, coûts et dette intégralement en dirhams | P24: 2 · Première référence technologique ? | Q24: B29 | R24: =IF($B$29<>"",1,0) -> 0
A25: Durée du financement (ans) | P25: 2 · Opération consortiale ? | Q25: B30 | R25: =IF($B$30<>"",1,0) -> 0
A26: Technologie : ≥ 3 références industrielles de plus de 3 ans | P26: 2 · Contrat de revenus de plus de 20 ans ? | Q26: B31 | R26: =IF($B$31<>"",1,0) -> 0
A27: En P1 : EPC clé-en-main forfaitaire, prix et délai garantis, < 18 mois | P27: 2 · Site à risque climatique élevé ? | Q27: B32 | R27: =IF($B$32<>"",1,0) -> 0
A28: Acheteur principal unique et identifié | P28: 2 · Nombre de contreparties clés | Q28: B33 | R28: =IF(ISNUMBER($B$33),1,0) -> 0
A29: Technologie constituant une première référence dans la juridiction | P29: 3 · Emplois : montants du besoin à terminaison | Q29: B39 | R29: =IF(N($B$47)>0,1,0) -> 0
A30: Opération consortiale relevant de la directive 3/W/2025 | P30: 3 · Ressources engagées : montants | Q30: E39 | R30: =IF(N($E$47)>0,1,0) -> 0
A31: Concession ou contrat de revenus de plus de 20 ans | P31: 3 · Nature de chaque ressource | Q31: F39 | R31: =IF(SUMPRODUCT(ISNUMBER($E$39:$E$46)*($F$39:$F$46=""))=0,1,0) -> 0
A32: Site classé à risque climatique physique élevé | P32: 3 · Plan de remédiation (couverture entre 95 et 100 %) | Q32: B50 | R32: =IF(OR(NOT(AND($B$17="P1",ISNUMBER($B$48),N($B$48)>=P_N3_V,N($B$48)<P_N3_F)),$B$50<>""),1,0) -> 0
A33: Nombre de contreparties clés | P33: 6 · Choc du scénario défavorable (%) | Q33: B70 | R33: =IF(ISNUMBER($B$70),1,0) -> 0
A34: Régime calculé (avant escalade) | B34: =IF(OR(B22="",B22=0,B15=""),"",IF(OR(B22>P_L_CAPEX,N(B23)>P_L_EXPO,B15="R4",B29="Oui",N(B153)>0,B30="Oui",B31="Oui",B32="Oui",N(B33)>P_L_NBCP),"L",IF(AND(B22<=P_S_CAPEX,B23<>"",N(B23)<=P_S_EXPO,OR(B15="R1",B15="R2"),B26="Oui",B24="Oui",B25<>"",N(B25)<=P_S_DUREE,OR(B17<>"P1",B27="Oui"),B28="Oui",COUNTIF($F$222:$F$233,"Oui")=0),"S","M"))) -> 0 | C34: =IF(B34="","",IF(B34="L","Escalade : "&IF(B22>P_L_CAPEX,"CAPEX > "&P_L_CAPEX&" MMAD ; ","")&IF(N(B23)>P_L_EXPO,"exposition > "&P_L_EXPO&" MMAD ; ","")&IF(B15="R4","régime de revenus R4 ; ","")&IF(B29="Oui","première référence technologique ; ","")&IF(N(B153)>0,"devises non intégralement couvertes ; ","")&IF(B30="Oui","opération consortiale ; ","")&IF(B31="Oui","contrat de revenus > 20 ans ; ","")&IF(B32="Oui","risque climatique élevé ; ","")&IF(N(B33)>P_L_NBCP,"plus de "&P_L_NBCP&" contreparties clés ; ",""),IF(B34="S","Toutes les conditions du régime simplifié sont réunies.","Régime standard par défaut : une condition du régime S manque, aucune condition d'escalade."))) -> 0 | P34: 6 · Échéancier : CFADS d'au moins deux périodes | Q34: B72 | R34: =IF(COUNT($B$72:$B$131)>=2,1,0) -> 0
A35: RÉGIME RETENU (après escalade automatique) | B35: =IF(B34="","",IF(AND(IF(AND(B34="S",COUNTIF($F$222:$F$233,"Oui")>0),"M",B34)="M",COUNTIF($E$237:$E$251,"Oui")>0),"L",IF(AND(B34="S",COUNTIF($F$222:$F$233,"Oui")>0),"M",B34))) -> 0 | C35: =IF(B35=B34,"Aucune escalade.",IF(B35="L","Escalade : un plafond de note est actif (M passe en L).","Escalade : un verrou est actif (S passe en M).")) -> 0 | P35: 6 · Service de la dette de chaque période | Q35: C72 | R35: =IF(SUMPRODUCT(ISNUMBER($B$72:$B$131)*(1-ISNUMBER($C$72:$C$131)))=0,1,0) -> 0
P36: 7 · N4 — Liquidité (DSRA, lignes, cascade) | Q36: B145 | R36: =IF($B$145<>"",1,0) -> 0
A37: 3 · SOURCES ET EMPLOIS (MMAD) — test de financement à terminaison | P37: 7 · N5 — Levier et fonds propres à risque | Q37: B146 | R37: =IF($B$146<>"",1,0) -> 0
A38: Emplois | B38: Montant | D38: Ressources | E38: Montant | F38: Nature | P38: 7 · N6 — Exposition résiduelle taux, change, refinancement | Q38: B147 | R38: =IF($B$147<>"",1,0) -> 0
P39: 7 · N3 hors phase P1 : note LLCR | Q39: B150 | R39: =IF(OR($B$17="P1",$B$150<>""),1,0) -> 0
P40: 7 · LLCR (plafond C4) | Q40: B151 | R40: =IF(ISNUMBER($B$151),1,0) -> 0
P41: 7 · DSRA en mois (plafond C7) | Q41: B152 | R41: =IF(ISNUMBER($B$152),1,0) -> 0
P42: 7 · Exposition nette en devises (plafond C6) | Q42: B153 | R42: =IF(ISNUMBER($B$153),1,0) -> 0
P43: 7 · Dette à refinancer à maturité (plafond C8) | Q43: B154 | R43: =IF(ISNUMBER($B$154),1,0) -> 0
P44: 7 · Stratégie de refinancement approuvée ? | Q44: B155 | R44: =IF(OR(N($B$154)<=P_C8,$B$155<>""),1,0) -> 0
P45: 7 · Part des recettes de l'acheteur principal (C10) | Q45: B156 | R45: =IF(ISNUMBER($B$156),1,0) -> 0
P46: 7 · Qualité de crédit de l'acheteur principal | Q46: B157 | R46: =IF($B$157<>"",1,0) -> 0
A47: Total emplois (besoin à terminaison) | B47: =SUM(B39:B46) -> 0 | D47: Total ressources engagées | E47: =SUM(E39:E46) -> 0 | P47: 7 · Durée résiduelle du contrat de revenus (C5) | Q47: B158 | R47: =IF(OR($B$15="R4",ISNUMBER($B$158)),1,0) -> 0
A48: Couverture du besoin à terminaison (ressources / emplois) | B48: =IF(N(B47)=0,"",E47/B47) -> 0 | P48: 7 · Durée résiduelle de la dette | Q48: B159 | R48: =IF(ISNUMBER($B$159),1,0) -> 0
A49: Quote-part de dette (dette / besoin à terminaison) | B49: =IF(N(B47)=0,"",(SUMIF(F39:F46,"Dette senior",E39:E46)+SUMIF(F39:F46,"Dette subordonnée",E39:E46))/B47) -> 0 | P49: 7 · Solution documentée (contrat plus court que la dette) ? | Q49: B160 | R49: =IF(OR(NOT(AND(ISNUMBER($B$158),ISNUMBER($B$159))),N($B$158)>=N($B$159),$B$160<>""),1,0) -> 0
A50: Plan de remédiation approuvé (couverture entre 95 % et 100 %) | P50: 7 · Plan d'adaptation climatique financé ? (C11) | Q50: B161 | R50: =IF(OR($B$32<>"Oui",$B$161<>""),1,0) -> 0
P51: 7 · Capacité résiduelle du sponsor (C12) | Q51: B162 | R51: =IF($B$162<>"",1,0) -> 0
A52: 4 · HYPOTHÈSES D'EXPLOITATION (information, non calculées) | P52: 7 · Opérateur remplaçable ? (C13) | Q52: B163 | R52: =IF($B$163<>"",1,0) -> 0
P53: 7 · Écart fin O&M / fin de dette (opérateur non remplaçable) | Q53: B164 | R53: =IF(OR($B$163<>"Non",ISNUMBER($B$164)),1,0) -> 0
P54: 7 · Facteur commun au-delà de la limite interne (C14) | Q54: B165 | R54: =IF($B$165<>"",1,0) -> 0
P55: 8 · Grille : sous-critère requis non noté | Q55: ="B"&IF(COUNT($P$169:$P$201)=0,169,MIN($P$169:$P$201)) -> 0 | R55: =IF(COUNT($P$169:$P$201)=0,1,0) -> 0
P56: 10 · Verrous X1 à B8 : répondre Oui ou Non | Q56: E222 | R56: =IF(COUNTBLANK($E$222:$E$233)=0,1,0) -> 0
A62: 5 · SEUILS DSCR APPLICABLES = base du régime + Δ secteur + majoration de phase
A63: Seuil critique de base du régime | B63: =IFERROR(INDEX(P_Crit,MATCH($B$15,P_Regimes,0)),"") -> 0
A64: Écart sectoriel Δ | B64: =IFERROR(INDEX(P_SecDelta,MATCH($B$16,P_SecCodes,0)),"") -> 0
A65: Majoration de phase | B65: =IFERROR(INDEX(P_PhaseMaj,MATCH($B$17,P_PhaseCodes,0)),"") -> 0
A66: Seuils applicables | B66: Critique < | C66: Vigilance < | D66: Favorable < | E66: Très favorable ≥
A67: Seuil = base + Δ + majoration | B67: =IFERROR(INDEX(P_Crit,MATCH($B$15,P_Regimes,0))+$B$64+$B$65,"") -> 0 | C67: =IFERROR(INDEX(P_Vig,MATCH($B$15,P_Regimes,0))+$B$64+$B$65,"") -> 0 | D67: =IFERROR(INDEX(P_Fav,MATCH($B$15,P_Regimes,0))+$B$64+$B$65,"") -> 0 | E67: =D67 -> 0
A69: 6 · ÉCHÉANCIER DATÉ ET DSCR PAR ÉCHÉANCE (jusqu'à 60 périodes)
A70: Scénario défavorable : baisse du CFADS appliquée à chaque période | C70: Description du scénario défavorable
A71: Période | B71: CFADS central | C71: Service de la dette | D71: DSCR | E71: Classement | F71: CFADS stressé (saisie facultative) | G71: DSCR stressé | H71: DSCR annuel (paire de semestres)
D72: =IF(OR(B72="",C72=""),"",IF(C72=0,"",B72/C72)) -> 0 | E72: =IF(B72="","",IF(C72=0,"Différé",IF(B72<0,"Critique",IF(D72<$B$67,"Critique",IF(D72<$C$67,"Vigilance",IF(D72<$D$67,"Favorable","Très favorable")))))) -> 0 | G72: =IF(OR(B72="",C72="",C72=0),"",IF(F72<>"",F72,B72*(1-$B$70))/C72) -> 0
D73: =IF(OR(B73="",C73=""),"",IF(C73=0,"",B73/C73)) -> 0 | E73: =IF(B73="","",IF(C73=0,"Différé",IF(B73<0,"Critique",IF(D73<$B$67,"Critique",IF(D73<$C$67,"Vigilance",IF(D73<$D$67,"Favorable","Très favorable")))))) -> 0 | G73: =IF(OR(B73="",C73="",C73=0),"",IF(F73<>"",F73,B73*(1-$B$70))/C73) -> 0 | H73: =IF(AND($B$18="Semestrielle",B73<>"",B72<>"",N(C73)+N(C72)>0),(B73+B72)/(C73+C72),"") -> 0
D74: =IF(OR(B74="",C74=""),"",IF(C74=0,"",B74/C74)) -> 0 | E74: =IF(B74="","",IF(C74=0,"Différé",IF(B74<0,"Critique",IF(D74<$B$67,"Critique",IF(D74<$C$67,"Vigilance",IF(D74<$D$67,"Favorable","Très favorable")))))) -> 0 | G74: =IF(OR(B74="",C74="",C74=0),"",IF(F74<>"",F74,B74*(1-$B$70))/C74) -> 0
D75: =IF(OR(B75="",C75=""),"",IF(C75=0,"",B75/C75)) -> 0 | E75: =IF(B75="","",IF(C75=0,"Différé",IF(B75<0,"Critique",IF(D75<$B$67,"Critique",IF(D75<$C$67,"Vigilance",IF(D75<$D$67,"Favorable","Très favorable")))))) -> 0 | G75: =IF(OR(B75="",C75="",C75=0),"",IF(F75<>"",F75,B75*(1-$B$70))/C75) -> 0 | H75: =IF(AND($B$18="Semestrielle",B75<>"",B74<>"",N(C75)+N(C74)>0),(B75+B74)/(C75+C74),"") -> 0
D76: =IF(OR(B76="",C76=""),"",IF(C76=0,"",B76/C76)) -> 0 | E76: =IF(B76="","",IF(C76=0,"Différé",IF(B76<0,"Critique",IF(D76<$B$67,"Critique",IF(D76<$C$67,"Vigilance",IF(D76<$D$67,"Favorable","Très favorable")))))) -> 0 | G76: =IF(OR(B76="",C76="",C76=0),"",IF(F76<>"",F76,B76*(1-$B$70))/C76) -> 0
D77: =IF(OR(B77="",C77=""),"",IF(C77=0,"",B77/C77)) -> 0 | E77: =IF(B77="","",IF(C77=0,"Différé",IF(B77<0,"Critique",IF(D77<$B$67,"Critique",IF(D77<$C$67,"Vigilance",IF(D77<$D$67,"Favorable","Très favorable")))))) -> 0 | G77: =IF(OR(B77="",C77="",C77=0),"",IF(F77<>"",F77,B77*(1-$B$70))/C77) -> 0 | H77: =IF(AND($B$18="Semestrielle",B77<>"",B76<>"",N(C77)+N(C76)>0),(B77+B76)/(C77+C76),"") -> 0
D78: =IF(OR(B78="",C78=""),"",IF(C78=0,"",B78/C78)) -> 0 | E78: =IF(B78="","",IF(C78=0,"Différé",IF(B78<0,"Critique",IF(D78<$B$67,"Critique",IF(D78<$C$67,"Vigilance",IF(D78<$D$67,"Favorable","Très favorable")))))) -> 0 | G78: =IF(OR(B78="",C78="",C78=0),"",IF(F78<>"",F78,B78*(1-$B$70))/C78) -> 0
D79: =IF(OR(B79="",C79=""),"",IF(C79=0,"",B79/C79)) -> 0 | E79: =IF(B79="","",IF(C79=0,"Différé",IF(B79<0,"Critique",IF(D79<$B$67,"Critique",IF(D79<$C$67,"Vigilance",IF(D79<$D$67,"Favorable","Très favorable")))))) -> 0 | G79: =IF(OR(B79="",C79="",C79=0),"",IF(F79<>"",F79,B79*(1-$B$70))/C79) -> 0 | H79: =IF(AND($B$18="Semestrielle",B79<>"",B78<>"",N(C79)+N(C78)>0),(B79+B78)/(C79+C78),"") -> 0
D80: =IF(OR(B80="",C80=""),"",IF(C80=0,"",B80/C80)) -> 0 | E80: =IF(B80="","",IF(C80=0,"Différé",IF(B80<0,"Critique",IF(D80<$B$67,"Critique",IF(D80<$C$67,"Vigilance",IF(D80<$D$67,"Favorable","Très favorable")))))) -> 0 | G80: =IF(OR(B80="",C80="",C80=0),"",IF(F80<>"",F80,B80*(1-$B$70))/C80) -> 0
D81: =IF(OR(B81="",C81=""),"",IF(C81=0,"",B81/C81)) -> 0 | E81: =IF(B81="","",IF(C81=0,"Différé",IF(B81<0,"Critique",IF(D81<$B$67,"Critique",IF(D81<$C$67,"Vigilance",IF(D81<$D$67,"Favorable","Très favorable")))))) -> 0 | G81: =IF(OR(B81="",C81="",C81=0),"",IF(F81<>"",F81,B81*(1-$B$70))/C81) -> 0 | H81: =IF(AND($B$18="Semestrielle",B81<>"",B80<>"",N(C81)+N(C80)>0),(B81+B80)/(C81+C80),"") -> 0
D82: =IF(OR(B82="",C82=""),"",IF(C82=0,"",B82/C82)) -> 0 | E82: =IF(B82="","",IF(C82=0,"Différé",IF(B82<0,"Critique",IF(D82<$B$67,"Critique",IF(D82<$C$67,"Vigilance",IF(D82<$D$67,"Favorable","Très favorable")))))) -> 0 | G82: =IF(OR(B82="",C82="",C82=0),"",IF(F82<>"",F82,B82*(1-$B$70))/C82) -> 0
D83: =IF(OR(B83="",C83=""),"",IF(C83=0,"",B83/C83)) -> 0 | E83: =IF(B83="","",IF(C83=0,"Différé",IF(B83<0,"Critique",IF(D83<$B$67,"Critique",IF(D83<$C$67,"Vigilance",IF(D83<$D$67,"Favorable","Très favorable")))))) -> 0 | G83: =IF(OR(B83="",C83="",C83=0),"",IF(F83<>"",F83,B83*(1-$B$70))/C83) -> 0 | H83: =IF(AND($B$18="Semestrielle",B83<>"",B82<>"",N(C83)+N(C82)>0),(B83+B82)/(C83+C82),"") -> 0
D84: =IF(OR(B84="",C84=""),"",IF(C84=0,"",B84/C84)) -> 0 | E84: =IF(B84="","",IF(C84=0,"Différé",IF(B84<0,"Critique",IF(D84<$B$67,"Critique",IF(D84<$C$67,"Vigilance",IF(D84<$D$67,"Favorable","Très favorable")))))) -> 0 | G84: =IF(OR(B84="",C84="",C84=0),"",IF(F84<>"",F84,B84*(1-$B$70))/C84) -> 0
D85: =IF(OR(B85="",C85=""),"",IF(C85=0,"",B85/C85)) -> 0 | E85: =IF(B85="","",IF(C85=0,"Différé",IF(B85<0,"Critique",IF(D85<$B$67,"Critique",IF(D85<$C$67,"Vigilance",IF(D85<$D$67,"Favorable","Très favorable")))))) -> 0 | G85: =IF(OR(B85="",C85="",C85=0),"",IF(F85<>"",F85,B85*(1-$B$70))/C85) -> 0 | H85: =IF(AND($B$18="Semestrielle",B85<>"",B84<>"",N(C85)+N(C84)>0),(B85+B84)/(C85+C84),"") -> 0
D86: =IF(OR(B86="",C86=""),"",IF(C86=0,"",B86/C86)) -> 0 | E86: =IF(B86="","",IF(C86=0,"Différé",IF(B86<0,"Critique",IF(D86<$B$67,"Critique",IF(D86<$C$67,"Vigilance",IF(D86<$D$67,"Favorable","Très favorable")))))) -> 0 | G86: =IF(OR(B86="",C86="",C86=0),"",IF(F86<>"",F86,B86*(1-$B$70))/C86) -> 0
D87: =IF(OR(B87="",C87=""),"",IF(C87=0,"",B87/C87)) -> 0 | E87: =IF(B87="","",IF(C87=0,"Différé",IF(B87<0,"Critique",IF(D87<$B$67,"Critique",IF(D87<$C$67,"Vigilance",IF(D87<$D$67,"Favorable","Très favorable")))))) -> 0 | G87: =IF(OR(B87="",C87="",C87=0),"",IF(F87<>"",F87,B87*(1-$B$70))/C87) -> 0 | H87: =IF(AND($B$18="Semestrielle",B87<>"",B86<>"",N(C87)+N(C86)>0),(B87+B86)/(C87+C86),"") -> 0
