Workbook
Name IA_Champs: 'Champs IA'!$A$12:$D$472
Name L_Avis: 'Paramètres'!$C$82:$C$85
Name L_Decision: 'Paramètres'!$D$82:$D$85
Name L_Devise: 'Paramètres'!$B$82:$B$85
Name L_Nature: 'Paramètres'!$D$70:$D$77
Name L_NatureCredit: 'Paramètres'!$A$82:$A$87
Name L_Notes: 'Paramètres'!$B$70:$B$74
Name L_OuiNon: 'Paramètres'!$A$70:$A$71
Name L_Periodicite: 'Paramètres'!$C$70:$C$72
Name L_QualAch: 'Paramètres'!$E$70:$E$72
Name P_Ancre_C: 'Paramètres'!$C$63
Name P_Ancre_F: 'Paramètres'!$C$61
Name P_Ancre_TF: 'Paramètres'!$C$60
Name P_Ancre_V: 'Paramètres'!$C$62
Name P_C10: 'Paramètres'!$J$55
Name P_C13: 'Paramètres'!$J$56
Name P_C1: 'Paramètres'!$J$48
Name P_C3: 'Paramètres'!$J$49
Name P_C4: 'Paramètres'!$J$50
Name P_C6: 'Paramètres'!$J$51
Name P_C7: 'Paramètres'!$J$52
Name P_C8: 'Paramètres'!$J$53
Name P_C9: 'Paramètres'!$J$54
Name P_ConvLib: 'Paramètres'!$J$6:$J$15
Name P_ConvNote: 'Paramètres'!$I$6:$I$15
Name P_ConvOrient: 'Paramètres'!$K$6:$K$15
Name P_ConvSeuil: 'Paramètres'!$H$6:$H$15
Name P_COUV: 'Paramètres'!$J$57
Name P_Crit: 'Paramètres'!$C$6:$C$9
Name P_DomCodes: 'Paramètres'!$A$37:$A$45
Name P_DomLib: 'Paramètres'!$B$37:$B$45
Name P_Fav: 'Paramètres'!$E$6:$E$9
Name P_InfoInsuff: 'Paramètres'!$C$64
Name P_L_CAPEX: 'Paramètres'!$J$42
Name P_L_EXPO: 'Paramètres'!$J$43
Name P_L_NBCP: 'Paramètres'!$J$44
Name P_N3_F: 'Paramètres'!$J$46
Name P_N3_TF: 'Paramètres'!$J$45
Name P_N3_V: 'Paramètres'!$J$47
Name P_PhaseCodes: 'Paramètres'!$A$30:$A$32
Name P_PhaseLib: 'Paramètres'!$B$30:$B$32
Name P_PhaseMaj: 'Paramètres'!$C$30:$C$32
Name P_PlafCode: 'Paramètres'!$H$20:$H$34
Name P_PlafFait: 'Paramètres'!$I$20:$I$34
Name P_PlafNiv: 'Paramètres'!$J$20:$J$34
Name P_PoidsDom: 'Paramètres'!$C$37:$E$45
Name P_PoidsHdr: 'Paramètres'!$C$36:$E$36
Name P_PoidsN: 'Paramètres'!$C$50:$C$55
Name P_Regimes: 'Paramètres'!$A$6:$A$9
Name P_RegLib: 'Paramètres'!$B$6:$B$9
Name P_S_CAPEX: 'Paramètres'!$J$39
Name P_S_DUREE: 'Paramètres'!$J$41
Name P_S_EXPO: 'Paramètres'!$J$40
Name P_SCCle: 'Paramètres'!$H$62:$H$86
Name P_SCPoids: 'Paramètres'!$J$62:$J$86
Name P_SecCodes: 'Paramètres'!$A$14:$A$25
Name P_SecDelta: 'Paramètres'!$C$14:$C$25
Name P_SecLib: 'Paramètres'!$B$14:$B$25
Name P_Vig: 'Paramètres'!$D$6:$D$9
Name R_Cles: 'Référentiel des niveaux'!$J$8:$J$83

Sheet Accueil
B2: Outil de scoring Project Finance — modèle V8
B3: Version 3 · dix-huit dossiers préchargés · situations descriptives · commentaires et conditions · comparaison · concordance · import des propositions de l'IA.
B5: SCORER UN PROJET EN 5 ÉTAPES
B6: 1. Cliquez « Nouveau dossier » (à droite) : dossier vide, ou copie d'un dossier existant avec « Dupliquer ». Avec un fichier de propositions de l'IA, cliquez « Nouveau dossier depuis l'IA ».
B7: 2. Saisissez d'abord les codes (client T24, radical à 7 chiffres, code projet PF-AAAA-NNNN), puis remplissez les cellules ORANGE : ce sont les saisies obligatoires encore vides. Sélectionnez une cellule pour lire son aide.
B8: 3. Grille et indicateurs N4 à N6 : choisissez dans la liste la situation qui décrit le dossier ; la note s'affiche à côté. Une situation Critique ou « Info. insuffisante » exige un commentaire.
B9: 4. Lisez le tableau de bord : note approuvée, plafonds et verrous actifs, statut. Rédigez le bloc 13 « Commentaires et conditions » : synthèse obligatoire, justification des écarts si un plafond ou un verrou est actif.
B10: 5. Cliquez « Contrôler la saisie », puis « Fiche comité » pour imprimer la page de présentation ou l'exporter en PDF.
B12: LÉGENDE
B13: Saisie | C13: Saisie obligatoire manquante | D13: Calcul | E13: Note ≥ 8 | F13: Note 6 ou 7 | G13: Note ≤ 5
B14: Les cellules de calcul sont protégées (sans mot de passe) pour éviter d'écraser une formule par erreur. Pour modifier la structure : onglet Révision › Ôter la protection de la feuille.
B16: CATALOGUE DES 18 CAS D'ÉTUDE — dossiers fictifs ; cliquez sur un onglet pour l'ouvrir
B17: Onglet | C17: Projet | D17: Code projet | E17: Secteur | F17: Régime · phase | G17: Note approuvée | H17: Situations illustrées | I17: Ce que ce cas enseigne
B18: C1 | C18: Centrale solaire photovoltaïque 80 MWc | D18: PF-2026-0001 | E18: ENR | F18: R1 · P1 | G18: =IFERROR(INDIRECT("'C1'!B276"),"—") -> 0 | H18: Référence P1, contrat ferme R1 ; marge de financement à terminaison étroite (N3 = 80). | I18: Cas de référence. Deux points méritent attention malgré la note élevée : le test de financement à terminaison ne donne que 5,7 % de marge, ce qui vaut 8 et non 10 sur N3 ; et le DSCR sous stress P90 tombe à 1,12, soit Vigilance. Un dossier solide n'obtient pas 10 partout.
B19: C2 | C19: Usine de dessalement 100 000 m³/jour | D19: PF-2026-0002 | E19: EAU | F19: R2 · P2 | G19: =IFERROR(INDIRECT("'C2'!B276"),"—") -> 0 | H19: Paiement à la disponibilité R2 en montée en charge P2 ; risque énergie partiellement retenu. | I19: Un paiement à la disponibilité n'est pas un take-or-pay. L'acheteur porte le risque de demande ; le projet porte le risque de performance et, ici, une part du risque énergie. La phase de montée en charge relève le seuil de 0,05, et le stress énergie fait tomber N2 à 20, ce qui suffit à ramener le noyau à 57,5.
B20: C3 | C20: Hôtel 4 étoiles, 220 clés | D20: PF-2026-0003 | E20: TOU | F20: R4 · P2 | G20: =IFERROR(INDIRECT("'C3'!B276"),"—") -> 0 | H20: Anti-compensation : score 73,7 ramené à 4 par C2 et C3 (creux saisonnier). | I20: C'est la démonstration centrale du modèle. Le dossier est excellent presque partout : D1 et D8 à 100, D3 à 95, D2 à 95. Le score calculé atteint 73,7, soit la note 7. Mais le DSCR minimum tombe à 1,06 sur le creux estival, très en dessous du seuil critique de 1,60 applicable à un hôtel exposé au marché, et le DSCR sous stress passe sous 1,00. Les plafonds C2 et C3 ramènent la note approuvée à 4. Aucune qualité de sponsor ne compense une trésorerie qui ne couvre pas une échéance.
B21: C4A | C21: Unité agro-industrielle de trituration et conditionnement | D21: PF-2026-0004 | E21: AGR | F21: R3 · P3 | G21: =IFERROR(INDIRECT("'C4A'!B276"),"—") -> 0 | H21: Piège du ratio annuel : 1,53 en annuel, 0,59 par échéance ; change non couvert. | I21: Le piège du ratio annuel. Le DSCR annuel ressort à 1,53, ce qui aurait été lu comme Favorable sur l'ancienne ligne sectorielle agro-industrie. Le DSCR minimum par échéance est de 0,59 sur le semestre d'intercampagne : l'échéance n'est pas payable sans trésorerie externe. Le plafond C1 s'applique, le stress hydrique fait passer le DSCR stressé sous 1,00 (C3) et l'exposition de change non couverte déclenche C6.
B22: C4B | C22: Unité agro-industrielle — structure restructurée | D22: PF-2026-0004 | E22: AGR | F22: R3 · P3 | G22: =IFERROR(INDIRECT("'C4B'!B276"),"—") -> 0 | H22: Même projet que C4A restructuré : la note passe de 3 à 6 sans changement de marché. | I22: Trois corrections de montage, aucun changement de marché ni de grille qualitative, et la note passe de 3 à 6. Le modèle n'a pas seulement sanctionné : il a désigné précisément quoi corriger — le profil d'amortissement, le niveau de dette et la couverture de change.
B23: C5 | C23: Centrale PV d’autoproduction 12 MWc | D23: PF-2026-0005 | E23: ENR | F23: R1 · P1 | G23: =IFERROR(INDIRECT("'C5'!B276"),"—") -> 0 | H23: Régime simplifié S : grille allégée, plafonds intacts (C10, acheteur unique non noté). | I23: Le régime simplifié en action : 25 notes de sous-critère au lieu de 75, aucune revue externe imposée. Le noyau financier reste complet et ressort à 97, ce qui est excellent. Mais la concentration sur un acheteur unique non noté déclenche le plafond C10, et la note approuvée tombe de 8 à 6. Alléger la grille de jugement n'allège jamais les plafonds.
B24: ENR | C24: Parc éolien terrestre 140 MW | D24: PF-2026-0006 | E24: ENR | F24: R1 · P1 | G24: =IFERROR(INDIRECT("'ENR'!B276"),"—") -> 0 | H24: Dossier de référence : régime M, aucun plafond, note 10. | I24: Le dossier de référence : régime M (aucune condition d'escalade), toutes les mesures du noyau favorables, aucun plafond. Il montre ce qu'il faut réunir pour atteindre la note 10.
B25: EAU | C25: Usine de dessalement couplée à l'irrigation, 120 000 m³/jour | D25: PF-2026-0007 | E25: EAU | F25: R2 · P2 | G25: =IFERROR(INDIRECT("'EAU'!B276"),"—") -> 0 | H25: Montée en charge P2 ; climat élevé neutralisé par un plan financé ; régime L. | I25: Montre la majoration de phase P2 (+ 0,05 sur les seuils), le noyau hors construction (N3 fondé sur le LLCR), un risque climatique élevé neutralisé par un plan d'adaptation financé, et l'escalade en régime L par la durée du contrat et la part en devises.
B26: TEL | C26: Centre de données Tier III, 24 MW informatiques | D26: PF-2026-0008 | E26: TEL | F26: R3 · P2 | G26: =IFERROR(INDIRECT("'TEL'!B276"),"—") -> 0 | H26: Plafond C3 : DSCR défavorable sous 1,00 ; escalade M → L par le plafond. | I26: Le scénario défavorable fait tomber le DSCR sous 1,00 : plafond C3 (note 4 au plus) malgré un score de 6. Le plafond fait aussi passer le régime calculé M en régime L.
B27: TRA | C27: Autoroute à péage de 95 km | D27: PF-2026-0009 | E27: TRA | F27: R4 · P3 | G27: =IFERROR(INDIRECT("'TRA'!B276"),"—") -> 0 | H27: Régime R4 : seuils les plus exigeants ; C2 actif à 1,37 ; C5 sans objet. | I27: Régime R4 : les seuils DSCR sont les plus exigeants (1,40 critique avec Δ transport). Un DSCR minimum de 1,37 déclenche C2. Le plafond C5 est sans objet en R4, faute de contrat de recettes. Le régime R4 impose le régime L.
B28: POR | C28: Terminal à conteneurs de 1,2 million d'EVP | D28: PF-2026-0010 | E28: POR | F28: R3 · P1 | G28: =IFERROR(INDIRECT("'POR'!B276"),"—") -> 0 | H28: Construction sans EPC signé (B2) ; C10 et C14 ; couverture 97 % avec plan de remédiation. | I28: Construction avec un financement à terminaison couvert à 97 % seulement : N3 Vigilance grâce au plan de remédiation approuvé (sans plan, Critique). EPC non signé : blocage B2, note provisoire. Concentration sur un armateur non noté (C10) et exposition du groupe sur le transport maritime (C14).
B29: SAN | C29: Centre hospitalier de 600 lits en partenariat public-privé | D29: PF-2026-0011 | E29: SAN | F29: R2 · P1 | G29: =IFERROR(INDIRECT("'SAN'!B276"),"—") -> 0 | H29: Informations insuffisantes (B7, C15) ; opérateur non remplaçable (C13). | I29: Deux sous-critères en « Info. insuffisante » : ils comptent pour 20, la complétude tombe sous 100 % (blocage B7) et le plafond C15 s'applique. Le contrat de maintenance biomédicale expire 7 ans avant la dette avec un prestataire non remplaçable (C13).
B30: ETH | C30: Centrale à cycle combiné au gaz de 450 MW | D30: PF-2026-0012 | E30: ETH | F30: R1 · P3 | G30: =IFERROR(INDIRECT("'ETH'!B276"),"—") -> 0 | H30: LLCR sous 1,10 (C4) et ballon de 35 % sans stratégie (C8). | I30: Un LLCR de 1,08 déclenche C4 (note 4 au plus) ; le ballon de 35 % sans stratégie de refinancement approuvée déclenche C8 (5). Le plafond le plus contraignant s'applique : 4.
B31: IMMO | C31: Ensemble de bureaux et commerces loués, 48 000 m² | D31: PF-2026-0013 | E31: IMMO-REND | F31: R3 · P3 | G31: =IFERROR(INDIRECT("'IMMO'!B276"),"—") -> 0 | H31: Levier 88 % (C9) et DSRA de 2 mois (C7) ; N4 et N5 Critiques. | I31: Deux plafonds se cumulent : DSRA de 2 mois (C7, note 6 au plus) et quote-part de dette de 88 % (C9, note 5 au plus). La note approuvée retient le plus contraignant, 5. Le plafond fait passer le régime M en L.
B32: IND | C32: Usine de verre plat de 600 tonnes/jour | D32: PF-2026-0014 | E32: IND | F32: R3 · P2 | G32: =IFERROR(INDIRECT("'IND'!B276"),"—") -> 0 | H32: Avis juridique avec réserve (B5) ; contrat plus court que la dette (C5) ; change (C6). | I32: Différé : les deux premières périodes (service nul) sont signalées et exclues du DSCR minimum. Exposition en euros non couverte (C6) et contrat d'enlèvement plus court que la dette sans solution (C5). L'avis juridique sur les sûretés n'est pas reçu : blocage B5 au stade du décaissement.
B33: AGR | C33: Unité de trituration d'olives et de conditionnement d'huile | D33: PF-2026-0015 | E33: AGR | F33: R1 · P1 | G33: =IFERROR(INDIRECT("'AGR'!B276"),"—") -> 0 | H33: Régime S en construction : petit projet, contrat d'achat ferme, aucun plafond. | I33: Toutes les conditions du régime simplifié S sont réunies : dossier allégé. L'écart sectoriel Δ de + 0,15 rend les seuils plus exigeants qu'en énergie : un DSCR minimum de 1,37 n'est que Favorable.
B34: TOU | C34: Complexe hôtelier balnéaire de 420 chambres | D34: PF-2026-0016 | E34: TOU | F34: R4 · P2 | G34: =IFERROR(INDIRECT("'TOU'!B276"),"—") -> 0 | H34: CFADS négatif en basse saison (C1) ; droit d'occupation non établi (B4) ; climat sans plan (C11). | I34: Le cas le plus dégradé : seuils les plus élevés (R4, Δ tourisme + 0,20, majoration P2), CFADS négatif (N1 Critique d'office), DSCR minimum sous 1,05 (C1, note 3 au plus), risque d'érosion côtière sans plan (C11), et titre d'occupation insuffisant (B4).
B35: MIN | C35: Mine de cuivre à ciel ouvert et usine de concentration | D35: PF-2026-0017 | E35: MIN | F35: R4 · P1 | G35: =IFERROR(INDIRECT("'MIN'!B276"),"—") -> 0 | H35: Exclusion X3 (contrepartie sous sanctions) : aucune note ; B3 et B8 en plus. | I35: Une exclusion X (contrepartie clé sous sanctions) : aucune note n'est produite, quel que soit le score. Le calcul est présenté pour l'apprentissage : il montre aussi un financement à terminaison couvert à 92 % (N3 Critique et blocage B3 détecté automatiquement), un sponsor sans capacité résiduelle (C12) et l'acceptabilité environnementale non obtenue (B8).
B37: VOS DOSSIERS — tous les onglets de dossier, lus dans la synthèse
B38: Onglet | C38: Intitulé | D38: Code projet | E38: Phase | F38: Note approuvée | G38: Manquantes | H38: Statut
B39: =IF('Synthèse'!$B$4="","",HYPERLINK("#'"&'Synthèse'!$B$4&"'!A1",'Synthèse'!$B$4)) -> 0 | C39: =IF('Synthèse'!$B$4="","",'Synthèse'!$B$5) -> 0 | D39: =IF('Synthèse'!$B$4="","",'Synthèse'!$B$8) -> 0 | E39: =IF('Synthèse'!$B$4="","",'Synthèse'!$B$11) -> 0 | F39: =IF('Synthèse'!$B$4="","",'Synthèse'!$B$24) -> 0 | G39: =IF('Synthèse'!$B$4="","",'Synthèse'!$B$27) -> 0 | H39: =IF('Synthèse'!$B$4="","",'Synthèse'!$B$25) -> 0
B40: =IF('Synthèse'!$C$4="","",HYPERLINK("#'"&'Synthèse'!$C$4&"'!A1",'Synthèse'!$C$4)) -> 0 | C40: =IF('Synthèse'!$C$4="","",'Synthèse'!$C$5) -> 0 | D40: =IF('Synthèse'!$C$4="","",'Synthèse'!$C$8) -> 0 | E40: =IF('Synthèse'!$C$4="","",'Synthèse'!$C$11) -> 0 | F40: =IF('Synthèse'!$C$4="","",'Synthèse'!$C$24) -> 0 | G40: =IF('Synthèse'!$C$4="","",'Synthèse'!$C$27) -> 0 | H40: =IF('Synthèse'!$C$4="","",'Synthèse'!$C$25) -> 0
B41: =IF('Synthèse'!$D$4="","",HYPERLINK("#'"&'Synthèse'!$D$4&"'!A1",'Synthèse'!$D$4)) -> 0 | C41: =IF('Synthèse'!$D$4="","",'Synthèse'!$D$5) -> 0 | D41: =IF('Synthèse'!$D$4="","",'Synthèse'!$D$8) -> 0 | E41: =IF('Synthèse'!$D$4="","",'Synthèse'!$D$11) -> 0 | F41: =IF('Synthèse'!$D$4="","",'Synthèse'!$D$24) -> 0 | G41: =IF('Synthèse'!$D$4="","",'Synthèse'!$D$27) -> 0 | H41: =IF('Synthèse'!$D$4="","",'Synthèse'!$D$25) -> 0
B42: =IF('Synthèse'!$E$4="","",HYPERLINK("#'"&'Synthèse'!$E$4&"'!A1",'Synthèse'!$E$4)) -> 0 | C42: =IF('Synthèse'!$E$4="","",'Synthèse'!$E$5) -> 0 | D42: =IF('Synthèse'!$E$4="","",'Synthèse'!$E$8) -> 0 | E42: =IF('Synthèse'!$E$4="","",'Synthèse'!$E$11) -> 0 | F42: =IF('Synthèse'!$E$4="","",'Synthèse'!$E$24) -> 0 | G42: =IF('Synthèse'!$E$4="","",'Synthèse'!$E$27) -> 0 | H42: =IF('Synthèse'!$E$4="","",'Synthèse'!$E$25) -> 0
B43: =IF('Synthèse'!$F$4="","",HYPERLINK("#'"&'Synthèse'!$F$4&"'!A1",'Synthèse'!$F$4)) -> 0 | C43: =IF('Synthèse'!$F$4="","",'Synthèse'!$F$5) -> 0 | D43: =IF('Synthèse'!$F$4="","",'Synthèse'!$F$8) -> 0 | E43: =IF('Synthèse'!$F$4="","",'Synthèse'!$F$11) -> 0 | F43: =IF('Synthèse'!$F$4="","",'Synthèse'!$F$24) -> 0 | G43: =IF('Synthèse'!$F$4="","",'Synthèse'!$F$27) -> 0 | H43: =IF('Synthèse'!$F$4="","",'Synthèse'!$F$25) -> 0
B44: =IF('Synthèse'!$G$4="","",HYPERLINK("#'"&'Synthèse'!$G$4&"'!A1",'Synthèse'!$G$4)) -> 0 | C44: =IF('Synthèse'!$G$4="","",'Synthèse'!$G$5) -> 0 | D44: =IF('Synthèse'!$G$4="","",'Synthèse'!$G$8) -> 0 | E44: =IF('Synthèse'!$G$4="","",'Synthèse'!$G$11) -> 0 | F44: =IF('Synthèse'!$G$4="","",'Synthèse'!$G$24) -> 0 | G44: =IF('Synthèse'!$G$4="","",'Synthèse'!$G$27) -> 0 | H44: =IF('Synthèse'!$G$4="","",'Synthèse'!$G$25) -> 0
B45: =IF('Synthèse'!$H$4="","",HYPERLINK("#'"&'Synthèse'!$H$4&"'!A1",'Synthèse'!$H$4)) -> 0 | C45: =IF('Synthèse'!$H$4="","",'Synthèse'!$H$5) -> 0 | D45: =IF('Synthèse'!$H$4="","",'Synthèse'!$H$8) -> 0 | E45: =IF('Synthèse'!$H$4="","",'Synthèse'!$H$11) -> 0 | F45: =IF('Synthèse'!$H$4="","",'Synthèse'!$H$24) -> 0 | G45: =IF('Synthèse'!$H$4="","",'Synthèse'!$H$27) -> 0 | H45: =IF('Synthèse'!$H$4="","",'Synthèse'!$H$25) -> 0
B46: =IF('Synthèse'!$I$4="","",HYPERLINK("#'"&'Synthèse'!$I$4&"'!A1",'Synthèse'!$I$4)) -> 0 | C46: =IF('Synthèse'!$I$4="","",'Synthèse'!$I$5) -> 0 | D46: =IF('Synthèse'!$I$4="","",'Synthèse'!$I$8) -> 0 | E46: =IF('Synthèse'!$I$4="","",'Synthèse'!$I$11) -> 0 | F46: =IF('Synthèse'!$I$4="","",'Synthèse'!$I$24) -> 0 | G46: =IF('Synthèse'!$I$4="","",'Synthèse'!$I$27) -> 0 | H46: =IF('Synthèse'!$I$4="","",'Synthèse'!$I$25) -> 0
B47: =IF('Synthèse'!$J$4="","",HYPERLINK("#'"&'Synthèse'!$J$4&"'!A1",'Synthèse'!$J$4)) -> 0 | C47: =IF('Synthèse'!$J$4="","",'Synthèse'!$J$5) -> 0 | D47: =IF('Synthèse'!$J$4="","",'Synthèse'!$J$8) -> 0 | E47: =IF('Synthèse'!$J$4="","",'Synthèse'!$J$11) -> 0 | F47: =IF('Synthèse'!$J$4="","",'Synthèse'!$J$24) -> 0 | G47: =IF('Synthèse'!$J$4="","",'Synthèse'!$J$27) -> 0 | H47: =IF('Synthèse'!$J$4="","",'Synthèse'!$J$25) -> 0
B48: =IF('Synthèse'!$K$4="","",HYPERLINK("#'"&'Synthèse'!$K$4&"'!A1",'Synthèse'!$K$4)) -> 0 | C48: =IF('Synthèse'!$K$4="","",'Synthèse'!$K$5) -> 0 | D48: =IF('Synthèse'!$K$4="","",'Synthèse'!$K$8) -> 0 | E48: =IF('Synthèse'!$K$4="","",'Synthèse'!$K$11) -> 0 | F48: =IF('Synthèse'!$K$4="","",'Synthèse'!$K$24) -> 0 | G48: =IF('Synthèse'!$K$4="","",'Synthèse'!$K$27) -> 0 | H48: =IF('Synthèse'!$K$4="","",'Synthèse'!$K$25) -> 0
B49: =IF('Synthèse'!$L$4="","",HYPERLINK("#'"&'Synthèse'!$L$4&"'!A1",'Synthèse'!$L$4)) -> 0 | C49: =IF('Synthèse'!$L$4="","",'Synthèse'!$L$5) -> 0 | D49: =IF('Synthèse'!$L$4="","",'Synthèse'!$L$8) -> 0 | E49: =IF('Synthèse'!$L$4="","",'Synthèse'!$L$11) -> 0 | F49: =IF('Synthèse'!$L$4="","",'Synthèse'!$L$24) -> 0 | G49: =IF('Synthèse'!$L$4="","",'Synthèse'!$L$27) -> 0 | H49: =IF('Synthèse'!$L$4="","",'Synthèse'!$L$25) -> 0
B50: =IF('Synthèse'!$M$4="","",HYPERLINK("#'"&'Synthèse'!$M$4&"'!A1",'Synthèse'!$M$4)) -> 0 | C50: =IF('Synthèse'!$M$4="","",'Synthèse'!$M$5) -> 0 | D50: =IF('Synthèse'!$M$4="","",'Synthèse'!$M$8) -> 0 | E50: =IF('Synthèse'!$M$4="","",'Synthèse'!$M$11) -> 0 | F50: =IF('Synthèse'!$M$4="","",'Synthèse'!$M$24) -> 0 | G50: =IF('Synthèse'!$M$4="","",'Synthèse'!$M$27) -> 0 | H50: =IF('Synthèse'!$M$4="","",'Synthèse'!$M$25) -> 0
B51: =IF('Synthèse'!$N$4="","",HYPERLINK("#'"&'Synthèse'!$N$4&"'!A1",'Synthèse'!$N$4)) -> 0 | C51: =IF('Synthèse'!$N$4="","",'Synthèse'!$N$5) -> 0 | D51: =IF('Synthèse'!$N$4="","",'Synthèse'!$N$8) -> 0 | E51: =IF('Synthèse'!$N$4="","",'Synthèse'!$N$11) -> 0 | F51: =IF('Synthèse'!$N$4="","",'Synthèse'!$N$24) -> 0 | G51: =IF('Synthèse'!$N$4="","",'Synthèse'!$N$27) -> 0 | H51: =IF('Synthèse'!$N$4="","",'Synthèse'!$N$25) -> 0
B52: =IF('Synthèse'!$O$4="","",HYPERLINK("#'"&'Synthèse'!$O$4&"'!A1",'Synthèse'!$O$4)) -> 0 | C52: =IF('Synthèse'!$O$4="","",'Synthèse'!$O$5) -> 0 | D52: =IF('Synthèse'!$O$4="","",'Synthèse'!$O$8) -> 0 | E52: =IF('Synthèse'!$O$4="","",'Synthèse'!$O$11) -> 0 | F52: =IF('Synthèse'!$O$4="","",'Synthèse'!$O$24) -> 0 | G52: =IF('Synthèse'!$O$4="","",'Synthèse'!$O$27) -> 0 | H52: =IF('Synthèse'!$O$4="","",'Synthèse'!$O$25) -> 0
B53: =IF('Synthèse'!$P$4="","",HYPERLINK("#'"&'Synthèse'!$P$4&"'!A1",'Synthèse'!$P$4)) -> 0 | C53: =IF('Synthèse'!$P$4="","",'Synthèse'!$P$5) -> 0 | D53: =IF('Synthèse'!$P$4="","",'Synthèse'!$P$8) -> 0 | E53: =IF('Synthèse'!$P$4="","",'Synthèse'!$P$11) -> 0 | F53: =IF('Synthèse'!$P$4="","",'Synthèse'!$P$24) -> 0 | G53: =IF('Synthèse'!$P$4="","",'Synthèse'!$P$27) -> 0 | H53: =IF('Synthèse'!$P$4="","",'Synthèse'!$P$25) -> 0
B54: =IF('Synthèse'!$Q$4="","",HYPERLINK("#'"&'Synthèse'!$Q$4&"'!A1",'Synthèse'!$Q$4)) -> 0 | C54: =IF('Synthèse'!$Q$4="","",'Synthèse'!$Q$5) -> 0 | D54: =IF('Synthèse'!$Q$4="","",'Synthèse'!$Q$8) -> 0 | E54: =IF('Synthèse'!$Q$4="","",'Synthèse'!$Q$11) -> 0 | F54: =IF('Synthèse'!$Q$4="","",'Synthèse'!$Q$24) -> 0 | G54: =IF('Synthèse'!$Q$4="","",'Synthèse'!$Q$27) -> 0 | H54: =IF('Synthèse'!$Q$4="","",'Synthèse'!$Q$25) -> 0
B55: =IF('Synthèse'!$R$4="","",HYPERLINK("#'"&'Synthèse'!$R$4&"'!A1",'Synthèse'!$R$4)) -> 0 | C55: =IF('Synthèse'!$R$4="","",'Synthèse'!$R$5) -> 0 | D55: =IF('Synthèse'!$R$4="","",'Synthèse'!$R$8) -> 0 | E55: =IF('Synthèse'!$R$4="","",'Synthèse'!$R$11) -> 0 | F55: =IF('Synthèse'!$R$4="","",'Synthèse'!$R$24) -> 0 | G55: =IF('Synthèse'!$R$4="","",'Synthèse'!$R$27) -> 0 | H55: =IF('Synthèse'!$R$4="","",'Synthèse'!$R$25) -> 0
B56: =IF('Synthèse'!$S$4="","",HYPERLINK("#'"&'Synthèse'!$S$4&"'!A1",'Synthèse'!$S$4)) -> 0 | C56: =IF('Synthèse'!$S$4="","",'Synthèse'!$S$5) -> 0 | D56: =IF('Synthèse'!$S$4="","",'Synthèse'!$S$8) -> 0 | E56: =IF('Synthèse'!$S$4="","",'Synthèse'!$S$11) -> 0 | F56: =IF('Synthèse'!$S$4="","",'Synthèse'!$S$24) -> 0 | G56: =IF('Synthèse'!$S$4="","",'Synthèse'!$S$27) -> 0 | H56: =IF('Synthèse'!$S$4="","",'Synthèse'!$S$25) -> 0
B57: =IF('Synthèse'!$T$4="","",HYPERLINK("#'"&'Synthèse'!$T$4&"'!A1",'Synthèse'!$T$4)) -> 0 | C57: =IF('Synthèse'!$T$4="","",'Synthèse'!$T$5) -> 0 | D57: =IF('Synthèse'!$T$4="","",'Synthèse'!$T$8) -> 0 | E57: =IF('Synthèse'!$T$4="","",'Synthèse'!$T$11) -> 0 | F57: =IF('Synthèse'!$T$4="","",'Synthèse'!$T$24) -> 0 | G57: =IF('Synthèse'!$T$4="","",'Synthèse'!$T$27) -> 0 | H57: =IF('Synthèse'!$T$4="","",'Synthèse'!$T$25) -> 0
B58: =IF('Synthèse'!$U$4="","",HYPERLINK("#'"&'Synthèse'!$U$4&"'!A1",'Synthèse'!$U$4)) -> 0 | C58: =IF('Synthèse'!$U$4="","",'Synthèse'!$U$5) -> 0 | D58: =IF('Synthèse'!$U$4="","",'Synthèse'!$U$8) -> 0 | E58: =IF('Synthèse'!$U$4="","",'Synthèse'!$U$11) -> 0 | F58: =IF('Synthèse'!$U$4="","",'Synthèse'!$U$24) -> 0 | G58: =IF('Synthèse'!$U$4="","",'Synthèse'!$U$27) -> 0 | H58: =IF('Synthèse'!$U$4="","",'Synthèse'!$U$25) -> 0
B59: =IF('Synthèse'!$V$4="","",HYPERLINK("#'"&'Synthèse'!$V$4&"'!A1",'Synthèse'!$V$4)) -> 0 | C59: =IF('Synthèse'!$V$4="","",'Synthèse'!$V$5) -> 0 | D59: =IF('Synthèse'!$V$4="","",'Synthèse'!$V$8) -> 0 | E59: =IF('Synthèse'!$V$4="","",'Synthèse'!$V$11) -> 0 | F59: =IF('Synthèse'!$V$4="","",'Synthèse'!$V$24) -> 0 | G59: =IF('Synthèse'!$V$4="","",'Synthèse'!$V$27) -> 0 | H59: =IF('Synthèse'!$V$4="","",'Synthèse'!$V$25) -> 0
B60: =IF('Synthèse'!$W$4="","",HYPERLINK("#'"&'Synthèse'!$W$4&"'!A1",'Synthèse'!$W$4)) -> 0 | C60: =IF('Synthèse'!$W$4="","",'Synthèse'!$W$5) -> 0 | D60: =IF('Synthèse'!$W$4="","",'Synthèse'!$W$8) -> 0 | E60: =IF('Synthèse'!$W$4="","",'Synthèse'!$W$11) -> 0 | F60: =IF('Synthèse'!$W$4="","",'Synthèse'!$W$24) -> 0 | G60: =IF('Synthèse'!$W$4="","",'Synthèse'!$W$27) -> 0 | H60: =IF('Synthèse'!$W$4="","",'Synthèse'!$W$25) -> 0
B61: =IF('Synthèse'!$X$4="","",HYPERLINK("#'"&'Synthèse'!$X$4&"'!A1",'Synthèse'!$X$4)) -> 0 | C61: =IF('Synthèse'!$X$4="","",'Synthèse'!$X$5) -> 0 | D61: =IF('Synthèse'!$X$4="","",'Synthèse'!$X$8) -> 0 | E61: =IF('Synthèse'!$X$4="","",'Synthèse'!$X$11) -> 0 | F61: =IF('Synthèse'!$X$4="","",'Synthèse'!$X$24) -> 0 | G61: =IF('Synthèse'!$X$4="","",'Synthèse'!$X$27) -> 0 | H61: =IF('Synthèse'!$X$4="","",'Synthèse'!$X$25) -> 0
B62: =IF('Synthèse'!$Y$4="","",HYPERLINK("#'"&'Synthèse'!$Y$4&"'!A1",'Synthèse'!$Y$4)) -> 0 | C62: =IF('Synthèse'!$Y$4="","",'Synthèse'!$Y$5) -> 0 | D62: =IF('Synthèse'!$Y$4="","",'Synthèse'!$Y$8) -> 0 | E62: =IF('Synthèse'!$Y$4="","",'Synthèse'!$Y$11) -> 0 | F62: =IF('Synthèse'!$Y$4="","",'Synthèse'!$Y$24) -> 0 | G62: =IF('Synthèse'!$Y$4="","",'Synthèse'!$Y$27) -> 0 | H62: =IF('Synthèse'!$Y$4="","",'Synthèse'!$Y$25) -> 0
B63: =IF('Synthèse'!$Z$4="","",HYPERLINK("#'"&'Synthèse'!$Z$4&"'!A1",'Synthèse'!$Z$4)) -> 0 | C63: =IF('Synthèse'!$Z$4="","",'Synthèse'!$Z$5) -> 0 | D63: =IF('Synthèse'!$Z$4="","",'Synthèse'!$Z$8) -> 0 | E63: =IF('Synthèse'!$Z$4="","",'Synthèse'!$Z$11) -> 0 | F63: =IF('Synthèse'!$Z$4="","",'Synthèse'!$Z$24) -> 0 | G63: =IF('Synthèse'!$Z$4="","",'Synthèse'!$Z$27) -> 0 | H63: =IF('Synthèse'!$Z$4="","",'Synthèse'!$Z$25) -> 0
B64: =IF('Synthèse'!$AA$4="","",HYPERLINK("#'"&'Synthèse'!$AA$4&"'!A1",'Synthèse'!$AA$4)) -> 0 | C64: =IF('Synthèse'!$AA$4="","",'Synthèse'!$AA$5) -> 0 | D64: =IF('Synthèse'!$AA$4="","",'Synthèse'!$AA$8) -> 0 | E64: =IF('Synthèse'!$AA$4="","",'Synthèse'!$AA$11) -> 0 | F64: =IF('Synthèse'!$AA$4="","",'Synthèse'!$AA$24) -> 0 | G64: =IF('Synthèse'!$AA$4="","",'Synthèse'!$AA$27) -> 0 | H64: =IF('Synthèse'!$AA$4="","",'Synthèse'!$AA$25) -> 0
B65: =IF('Synthèse'!$AB$4="","",HYPERLINK("#'"&'Synthèse'!$AB$4&"'!A1",'Synthèse'!$AB$4)) -> 0 | C65: =IF('Synthèse'!$AB$4="","",'Synthèse'!$AB$5) -> 0 | D65: =IF('Synthèse'!$AB$4="","",'Synthèse'!$AB$8) -> 0 | E65: =IF('Synthèse'!$AB$4="","",'Synthèse'!$AB$11) -> 0 | F65: =IF('Synthèse'!$AB$4="","",'Synthèse'!$AB$24) -> 0 | G65: =IF('Synthèse'!$AB$4="","",'Synthèse'!$AB$27) -> 0 | H65: =IF('Synthèse'!$AB$4="","",'Synthèse'!$AB$25) -> 0
B66: =IF('Synthèse'!$AC$4="","",HYPERLINK("#'"&'Synthèse'!$AC$4&"'!A1",'Synthèse'!$AC$4)) -> 0 | C66: =IF('Synthèse'!$AC$4="","",'Synthèse'!$AC$5) -> 0 | D66: =IF('Synthèse'!$AC$4="","",'Synthèse'!$AC$8) -> 0 | E66: =IF('Synthèse'!$AC$4="","",'Synthèse'!$AC$11) -> 0 | F66: =IF('Synthèse'!$AC$4="","",'Synthèse'!$AC$24) -> 0 | G66: =IF('Synthèse'!$AC$4="","",'Synthèse'!$AC$27) -> 0 | H66: =IF('Synthèse'!$AC$4="","",'Synthèse'!$AC$25) -> 0
B67: =IF('Synthèse'!$AD$4="","",HYPERLINK("#'"&'Synthèse'!$AD$4&"'!A1",'Synthèse'!$AD$4)) -> 0 | C67: =IF('Synthèse'!$AD$4="","",'Synthèse'!$AD$5) -> 0 | D67: =IF('Synthèse'!$AD$4="","",'Synthèse'!$AD$8) -> 0 | E67: =IF('Synthèse'!$AD$4="","",'Synthèse'!$AD$11) -> 0 | F67: =IF('Synthèse'!$AD$4="","",'Synthèse'!$AD$24) -> 0 | G67: =IF('Synthèse'!$AD$4="","",'Synthèse'!$AD$27) -> 0 | H67: =IF('Synthèse'!$AD$4="","",'Synthèse'!$AD$25) -> 0
B68: =IF('Synthèse'!$AE$4="","",HYPERLINK("#'"&'Synthèse'!$AE$4&"'!A1",'Synthèse'!$AE$4)) -> 0 | C68: =IF('Synthèse'!$AE$4="","",'Synthèse'!$AE$5) -> 0 | D68: =IF('Synthèse'!$AE$4="","",'Synthèse'!$AE$8) -> 0 | E68: =IF('Synthèse'!$AE$4="","",'Synthèse'!$AE$11) -> 0 | F68: =IF('Synthèse'!$AE$4="","",'Synthèse'!$AE$24) -> 0 | G68: =IF('Synthèse'!$AE$4="","",'Synthèse'!$AE$27) -> 0 | H68: =IF('Synthèse'!$AE$4="","",'Synthèse'!$AE$25) -> 0
B69: =IF('Synthèse'!$AF$4="","",HYPERLINK("#'"&'Synthèse'!$AF$4&"'!A1",'Synthèse'!$AF$4)) -> 0 | C69: =IF('Synthèse'!$AF$4="","",'Synthèse'!$AF$5) -> 0 | D69: =IF('Synthèse'!$AF$4="","",'Synthèse'!$AF$8) -> 0 | E69: =IF('Synthèse'!$AF$4="","",'Synthèse'!$AF$11) -> 0 | F69: =IF('Synthèse'!$AF$4="","",'Synthèse'!$AF$24) -> 0 | G69: =IF('Synthèse'!$AF$4="","",'Synthèse'!$AF$27) -> 0 | H69: =IF('Synthèse'!$AF$4="","",'Synthèse'!$AF$25) -> 0
B70: =IF('Synthèse'!$AG$4="","",HYPERLINK("#'"&'Synthèse'!$AG$4&"'!A1",'Synthèse'!$AG$4)) -> 0 | C70: =IF('Synthèse'!$AG$4="","",'Synthèse'!$AG$5) -> 0 | D70: =IF('Synthèse'!$AG$4="","",'Synthèse'!$AG$8) -> 0 | E70: =IF('Synthèse'!$AG$4="","",'Synthèse'!$AG$11) -> 0 | F70: =IF('Synthèse'!$AG$4="","",'Synthèse'!$AG$24) -> 0 | G70: =IF('Synthèse'!$AG$4="","",'Synthèse'!$AG$27) -> 0 | H70: =IF('Synthèse'!$AG$4="","",'Synthèse'!$AG$25) -> 0
B71: =IF('Synthèse'!$AH$4="","",HYPERLINK("#'"&'Synthèse'!$AH$4&"'!A1",'Synthèse'!$AH$4)) -> 0 | C71: =IF('Synthèse'!$AH$4="","",'Synthèse'!$AH$5) -> 0 | D71: =IF('Synthèse'!$AH$4="","",'Synthèse'!$AH$8) -> 0 | E71: =IF('Synthèse'!$AH$4="","",'Synthèse'!$AH$11) -> 0 | F71: =IF('Synthèse'!$AH$4="","",'Synthèse'!$AH$24) -> 0 | G71: =IF('Synthèse'!$AH$4="","",'Synthèse'!$AH$27) -> 0 | H71: =IF('Synthèse'!$AH$4="","",'Synthèse'!$AH$25) -> 0
B72: =IF('Synthèse'!$AI$4="","",HYPERLINK("#'"&'Synthèse'!$AI$4&"'!A1",'Synthèse'!$AI$4)) -> 0 | C72: =IF('Synthèse'!$AI$4="","",'Synthèse'!$AI$5) -> 0 | D72: =IF('Synthèse'!$AI$4="","",'Synthèse'!$AI$8) -> 0 | E72: =IF('Synthèse'!$AI$4="","",'Synthèse'!$AI$11) -> 0 | F72: =IF('Synthèse'!$AI$4="","",'Synthèse'!$AI$24) -> 0 | G72: =IF('Synthèse'!$AI$4="","",'Synthèse'!$AI$27) -> 0 | H72: =IF('Synthèse'!$AI$4="","",'Synthèse'!$AI$25) -> 0
B73: =IF('Synthèse'!$AJ$4="","",HYPERLINK("#'"&'Synthèse'!$AJ$4&"'!A1",'Synthèse'!$AJ$4)) -> 0 | C73: =IF('Synthèse'!$AJ$4="","",'Synthèse'!$AJ$5) -> 0 | D73: =IF('Synthèse'!$AJ$4="","",'Synthèse'!$AJ$8) -> 0 | E73: =IF('Synthèse'!$AJ$4="","",'Synthèse'!$AJ$11) -> 0 | F73: =IF('Synthèse'!$AJ$4="","",'Synthèse'!$AJ$24) -> 0 | G73: =IF('Synthèse'!$AJ$4="","",'Synthèse'!$AJ$27) -> 0 | H73: =IF('Synthèse'!$AJ$4="","",'Synthèse'!$AJ$25) -> 0
B74: =IF('Synthèse'!$AK$4="","",HYPERLINK("#'"&'Synthèse'!$AK$4&"'!A1",'Synthèse'!$AK$4)) -> 0 | C74: =IF('Synthèse'!$AK$4="","",'Synthèse'!$AK$5) -> 0 | D74: =IF('Synthèse'!$AK$4="","",'Synthèse'!$AK$8) -> 0 | E74: =IF('Synthèse'!$AK$4="","",'Synthèse'!$AK$11) -> 0 | F74: =IF('Synthèse'!$AK$4="","",'Synthèse'!$AK$24) -> 0 | G74: =IF('Synthèse'!$AK$4="","",'Synthèse'!$AK$27) -> 0 | H74: =IF('Synthèse'!$AK$4="","",'Synthèse'!$AK$25) -> 0
B75: =IF('Synthèse'!$AL$4="","",HYPERLINK("#'"&'Synthèse'!$AL$4&"'!A1",'Synthèse'!$AL$4)) -> 0 | C75: =IF('Synthèse'!$AL$4="","",'Synthèse'!$AL$5) -> 0 | D75: =IF('Synthèse'!$AL$4="","",'Synthèse'!$AL$8) -> 0 | E75: =IF('Synthèse'!$AL$4="","",'Synthèse'!$AL$11) -> 0 | F75: =IF('Synthèse'!$AL$4="","",'Synthèse'!$AL$24) -> 0 | G75: =IF('Synthèse'!$AL$4="","",'Synthèse'!$AL$27) -> 0 | H75: =IF('Synthèse'!$AL$4="","",'Synthèse'!$AL$25) -> 0
B76: =IF('Synthèse'!$AM$4="","",HYPERLINK("#'"&'Synthèse'!$AM$4&"'!A1",'Synthèse'!$AM$4)) -> 0 | C76: =IF('Synthèse'!$AM$4="","",'Synthèse'!$AM$5) -> 0 | D76: =IF('Synthèse'!$AM$4="","",'Synthèse'!$AM$8) -> 0 | E76: =IF('Synthèse'!$AM$4="","",'Synthèse'!$AM$11) -> 0 | F76: =IF('Synthèse'!$AM$4="","",'Synthèse'!$AM$24) -> 0 | G76: =IF('Synthèse'!$AM$4="","",'Synthèse'!$AM$27) -> 0 | H76: =IF('Synthèse'!$AM$4="","",'Synthèse'!$AM$25) -> 0
B77: =IF('Synthèse'!$AN$4="","",HYPERLINK("#'"&'Synthèse'!$AN$4&"'!A1",'Synthèse'!$AN$4)) -> 0 | C77: =IF('Synthèse'!$AN$4="","",'Synthèse'!$AN$5) -> 0 | D77: =IF('Synthèse'!$AN$4="","",'Synthèse'!$AN$8) -> 0 | E77: =IF('Synthèse'!$AN$4="","",'Synthèse'!$AN$11) -> 0 | F77: =IF('Synthèse'!$AN$4="","",'Synthèse'!$AN$24) -> 0 | G77: =IF('Synthèse'!$AN$4="","",'Synthèse'!$AN$27) -> 0 | H77: =IF('Synthèse'!$AN$4="","",'Synthèse'!$AN$25) -> 0
B78: =IF('Synthèse'!$AO$4="","",HYPERLINK("#'"&'Synthèse'!$AO$4&"'!A1",'Synthèse'!$AO$4)) -> 0 | C78: =IF('Synthèse'!$AO$4="","",'Synthèse'!$AO$5) -> 0 | D78: =IF('Synthèse'!$AO$4="","",'Synthèse'!$AO$8) -> 0 | E78: =IF('Synthèse'!$AO$4="","",'Synthèse'!$AO$11) -> 0 | F78: =IF('Synthèse'!$AO$4="","",'Synthèse'!$AO$24) -> 0 | G78: =IF('Synthèse'!$AO$4="","",'Synthèse'!$AO$27) -> 0 | H78: =IF('Synthèse'!$AO$4="","",'Synthèse'!$AO$25) -> 0
B80: BON À SAVOIR
B81: Les dix-huit dossiers fournis sont FICTIFS et pédagogiques ; leurs codes client, radicaux, codes projet et numéros de crédit sont fictifs. Les seuils, poids et plafonds de l'onglet Paramètres sont des paramètres CANDIDATS, non approuvés par le Comité de validation : ne pas les utiliser en production avant validation.
B82: Macros : activez-les à l'ouverture (bandeau « Activer le contenu »). Sans macros, tout se calcule quand même ; seuls les boutons sont inactifs. Pour créer un dossier sans macros : clic droit sur un onglet › Afficher › Modèle, puis clic droit sur Modèle › Déplacer ou copier › Créer une copie ; renommez la copie et tapez son nom en ligne 4 de la Synthèse.
B83: Automatique : seuils DSCR (régime + secteur + phase), DSCR par échéance et stressé, N1 à N3, notes de la grille et de N4 à N6 déduites des situations choisies, plafonds C1 à C15, verrous B3 et B7, régime S / M / L avec escalade.
B84: Onglets : Référentiel des niveaux (situations de chaque sous-critère, variantes sectorielles), Comparaison (deux dossiers côte à côte), Concordance (notes de référence des 18 cas), Champs IA (format du fichier de propositions), Revue IA, Diagnostic (corrections apportées) et Journal (trace des actions).
B85: Propositions de l'IA : l'outil web produit un fichier de propositions à partir des documents du projet. « Importer les propositions IA » vérifie les codes client et projet, affiche chaque proposition en bleu avec sa source à côté de la valeur actuelle ; rien n'est écrit dans le dossier sans votre acceptation, et chaque décision est tracée.

Sheet Synthèse
A1: Synthèse des dossiers
A2: Une colonne par onglet de dossier, lue en direct : c'est le tableau comparatif de tous les cas. Les dossiers créés par « Nouveau dossier » sont ajoutés automatiquement ; sans macros, tapez le nom de l'onglet en ligne 4.
A4: Onglet | B4: C1 | C4: C2 | D4: C3 | E4: C4A | F4: C4B | G4: C5 | H4: ENR | I4: EAU | J4: TEL | K4: TRA | L4: POR | M4: SAN | N4: ETH | O4: IMMO | P4: IND | Q4: AGR | R4: TOU | S4: MIN
A5: Intitulé du dossier | B5: =IF(B$4="","",IFERROR(INDIRECT("'"&B$4&"'!"&$AQ5),"")) -> 0 | C5: =IF(C$4="","",IFERROR(INDIRECT("'"&C$4&"'!"&$AQ5),"")) -> 0 | D5: =IF(D$4="","",IFERROR(INDIRECT("'"&D$4&"'!"&$AQ5),"")) -> 0 | E5: =IF(E$4="","",IFERROR(INDIRECT("'"&E$4&"'!"&$AQ5),"")) -> 0 | F5: =IF(F$4="","",IFERROR(INDIRECT("'"&F$4&"'!"&$AQ5),"")) -> 0 | G5: =IF(G$4="","",IFERROR(INDIRECT("'"&G$4&"'!"&$AQ5),"")) -> 0 | H5: =IF(H$4="","",IFERROR(INDIRECT("'"&H$4&"'!"&$AQ5),"")) -> 0 | I5: =IF(I$4="","",IFERROR(INDIRECT("'"&I$4&"'!"&$AQ5),"")) -> 0 | ... AO5: =IF(AO$4="","",IFERROR(INDIRECT("'"&AO$4&"'!"&$AQ5),"")) -> 0 | AQ5: A1
A6: Code client T24 | B6: =IF(B$4="","",IFERROR(INDIRECT("'"&B$4&"'!"&$AQ6),"")) -> 0 | C6: =IF(C$4="","",IFERROR(INDIRECT("'"&C$4&"'!"&$AQ6),"")) -> 0 | D6: =IF(D$4="","",IFERROR(INDIRECT("'"&D$4&"'!"&$AQ6),"")) -> 0 | E6: =IF(E$4="","",IFERROR(INDIRECT("'"&E$4&"'!"&$AQ6),"")) -> 0 | F6: =IF(F$4="","",IFERROR(INDIRECT("'"&F$4&"'!"&$AQ6),"")) -> 0 | G6: =IF(G$4="","",IFERROR(INDIRECT("'"&G$4&"'!"&$AQ6),"")) -> 0 | H6: =IF(H$4="","",IFERROR(INDIRECT("'"&H$4&"'!"&$AQ6),"")) -> 0 | I6: =IF(I$4="","",IFERROR(INDIRECT("'"&I$4&"'!"&$AQ6),"")) -> 0 | ... AO6: =IF(AO$4="","",IFERROR(INDIRECT("'"&AO$4&"'!"&$AQ6),"")) -> 0 | AQ6: B15
A7: Radical | B7: =IF(B$4="","",IFERROR(INDIRECT("'"&B$4&"'!"&$AQ7),"")) -> 0 | C7: =IF(C$4="","",IFERROR(INDIRECT("'"&C$4&"'!"&$AQ7),"")) -> 0 | D7: =IF(D$4="","",IFERROR(INDIRECT("'"&D$4&"'!"&$AQ7),"")) -> 0 | E7: =IF(E$4="","",IFERROR(INDIRECT("'"&E$4&"'!"&$AQ7),"")) -> 0 | F7: =IF(F$4="","",IFERROR(INDIRECT("'"&F$4&"'!"&$AQ7),"")) -> 0 | G7: =IF(G$4="","",IFERROR(INDIRECT("'"&G$4&"'!"&$AQ7),"")) -> 0 | H7: =IF(H$4="","",IFERROR(INDIRECT("'"&H$4&"'!"&$AQ7),"")) -> 0 | I7: =IF(I$4="","",IFERROR(INDIRECT("'"&I$4&"'!"&$AQ7),"")) -> 0 | ... AO7: =IF(AO$4="","",IFERROR(INDIRECT("'"&AO$4&"'!"&$AQ7),"")) -> 0 | AQ7: B16
A8: Code projet | B8: =IF(B$4="","",IFERROR(INDIRECT("'"&B$4&"'!"&$AQ8),"")) -> 0 | C8: =IF(C$4="","",IFERROR(INDIRECT("'"&C$4&"'!"&$AQ8),"")) -> 0 | D8: =IF(D$4="","",IFERROR(INDIRECT("'"&D$4&"'!"&$AQ8),"")) -> 0 | E8: =IF(E$4="","",IFERROR(INDIRECT("'"&E$4&"'!"&$AQ8),"")) -> 0 | F8: =IF(F$4="","",IFERROR(INDIRECT("'"&F$4&"'!"&$AQ8),"")) -> 0 | G8: =IF(G$4="","",IFERROR(INDIRECT("'"&G$4&"'!"&$AQ8),"")) -> 0 | H8: =IF(H$4="","",IFERROR(INDIRECT("'"&H$4&"'!"&$AQ8),"")) -> 0 | I8: =IF(I$4="","",IFERROR(INDIRECT("'"&I$4&"'!"&$AQ8),"")) -> 0 | ... AO8: =IF(AO$4="","",IFERROR(INDIRECT("'"&AO$4&"'!"&$AQ8),"")) -> 0 | AQ8: B17
A9: Régime de revenus | B9: =IF(B$4="","",IFERROR(INDIRECT("'"&B$4&"'!"&$AQ9),"")) -> 0 | C9: =IF(C$4="","",IFERROR(INDIRECT("'"&C$4&"'!"&$AQ9),"")) -> 0 | D9: =IF(D$4="","",IFERROR(INDIRECT("'"&D$4&"'!"&$AQ9),"")) -> 0 | E9: =IF(E$4="","",IFERROR(INDIRECT("'"&E$4&"'!"&$AQ9),"")) -> 0 | F9: =IF(F$4="","",IFERROR(INDIRECT("'"&F$4&"'!"&$AQ9),"")) -> 0 | G9: =IF(G$4="","",IFERROR(INDIRECT("'"&G$4&"'!"&$AQ9),"")) -> 0 | H9: =IF(H$4="","",IFERROR(INDIRECT("'"&H$4&"'!"&$AQ9),"")) -> 0 | I9: =IF(I$4="","",IFERROR(INDIRECT("'"&I$4&"'!"&$AQ9),"")) -> 0 | ... AO9: =IF(AO$4="","",IFERROR(INDIRECT("'"&AO$4&"'!"&$AQ9),"")) -> 0 | AQ9: B18
A10: Secteur | B10: =IF(B$4="","",IFERROR(INDIRECT("'"&B$4&"'!"&$AQ10),"")) -> 0 | C10: =IF(C$4="","",IFERROR(INDIRECT("'"&C$4&"'!"&$AQ10),"")) -> 0 | D10: =IF(D$4="","",IFERROR(INDIRECT("'"&D$4&"'!"&$AQ10),"")) -> 0 | E10: =IF(E$4="","",IFERROR(INDIRECT("'"&E$4&"'!"&$AQ10),"")) -> 0 | F10: =IF(F$4="","",IFERROR(INDIRECT("'"&F$4&"'!"&$AQ10),"")) -> 0 | G10: =IF(G$4="","",IFERROR(INDIRECT("'"&G$4&"'!"&$AQ10),"")) -> 0 | H10: =IF(H$4="","",IFERROR(INDIRECT("'"&H$4&"'!"&$AQ10),"")) -> 0 | I10: =IF(I$4="","",IFERROR(INDIRECT("'"&I$4&"'!"&$AQ10),"")) -> 0 | ... AO10: =IF(AO$4="","",IFERROR(INDIRECT("'"&AO$4&"'!"&$AQ10),"")) -> 0 | AQ10: B19
A11: Phase | B11: =IF(B$4="","",IFERROR(INDIRECT("'"&B$4&"'!"&$AQ11),"")) -> 0 | C11: =IF(C$4="","",IFERROR(INDIRECT("'"&C$4&"'!"&$AQ11),"")) -> 0 | D11: =IF(D$4="","",IFERROR(INDIRECT("'"&D$4&"'!"&$AQ11),"")) -> 0 | E11: =IF(E$4="","",IFERROR(INDIRECT("'"&E$4&"'!"&$AQ11),"")) -> 0 | F11: =IF(F$4="","",IFERROR(INDIRECT("'"&F$4&"'!"&$AQ11),"")) -> 0 | G11: =IF(G$4="","",IFERROR(INDIRECT("'"&G$4&"'!"&$AQ11),"")) -> 0 | H11: =IF(H$4="","",IFERROR(INDIRECT("'"&H$4&"'!"&$AQ11),"")) -> 0 | I11: =IF(I$4="","",IFERROR(INDIRECT("'"&I$4&"'!"&$AQ11),"")) -> 0 | ... AO11: =IF(AO$4="","",IFERROR(INDIRECT("'"&AO$4&"'!"&$AQ11),"")) -> 0 | AQ11: B20
A12: Régime de proportionnalité retenu | B12: =IF(B$4="","",IFERROR(INDIRECT("'"&B$4&"'!"&$AQ12),"")) -> 0 | C12: =IF(C$4="","",IFERROR(INDIRECT("'"&C$4&"'!"&$AQ12),"")) -> 0 | D12: =IF(D$4="","",IFERROR(INDIRECT("'"&D$4&"'!"&$AQ12),"")) -> 0 | E12: =IF(E$4="","",IFERROR(INDIRECT("'"&E$4&"'!"&$AQ12),"")) -> 0 | F12: =IF(F$4="","",IFERROR(INDIRECT("'"&F$4&"'!"&$AQ12),"")) -> 0 | G12: =IF(G$4="","",IFERROR(INDIRECT("'"&G$4&"'!"&$AQ12),"")) -> 0 | H12: =IF(H$4="","",IFERROR(INDIRECT("'"&H$4&"'!"&$AQ12),"")) -> 0 | I12: =IF(I$4="","",IFERROR(INDIRECT("'"&I$4&"'!"&$AQ12),"")) -> 0 | ... AO12: =IF(AO$4="","",IFERROR(INDIRECT("'"&AO$4&"'!"&$AQ12),"")) -> 0 | AQ12: B38
A13: Seuil DSCR critique applicable | B13: =IF(B$4="","",IFERROR(INDIRECT("'"&B$4&"'!"&$AQ13),"")) -> 0 | C13: =IF(C$4="","",IFERROR(INDIRECT("'"&C$4&"'!"&$AQ13),"")) -> 0 | D13: =IF(D$4="","",IFERROR(INDIRECT("'"&D$4&"'!"&$AQ13),"")) -> 0 | E13: =IF(E$4="","",IFERROR(INDIRECT("'"&E$4&"'!"&$AQ13),"")) -> 0 | F13: =IF(F$4="","",IFERROR(INDIRECT("'"&F$4&"'!"&$AQ13),"")) -> 0 | G13: =IF(G$4="","",IFERROR(INDIRECT("'"&G$4&"'!"&$AQ13),"")) -> 0 | H13: =IF(H$4="","",IFERROR(INDIRECT("'"&H$4&"'!"&$AQ13),"")) -> 0 | I13: =IF(I$4="","",IFERROR(INDIRECT("'"&I$4&"'!"&$AQ13),"")) -> 0 | ... AO13: =IF(AO$4="","",IFERROR(INDIRECT("'"&AO$4&"'!"&$AQ13),"")) -> 0 | AQ13: B88
A14: DSCR minimum par échéance | B14: =IF(B$4="","",IFERROR(INDIRECT("'"&B$4&"'!"&$AQ14),"")) -> 0 | C14: =IF(C$4="","",IFERROR(INDIRECT("'"&C$4&"'!"&$AQ14),"")) -> 0 | D14: =IF(D$4="","",IFERROR(INDIRECT("'"&D$4&"'!"&$AQ14),"")) -> 0 | E14: =IF(E$4="","",IFERROR(INDIRECT("'"&E$4&"'!"&$AQ14),"")) -> 0 | F14: =IF(F$4="","",IFERROR(INDIRECT("'"&F$4&"'!"&$AQ14),"")) -> 0 | G14: =IF(G$4="","",IFERROR(INDIRECT("'"&G$4&"'!"&$AQ14),"")) -> 0 | H14: =IF(H$4="","",IFERROR(INDIRECT("'"&H$4&"'!"&$AQ14),"")) -> 0 | I14: =IF(I$4="","",IFERROR(INDIRECT("'"&I$4&"'!"&$AQ14),"")) -> 0 | ... AO14: =IF(AO$4="","",IFERROR(INDIRECT("'"&AO$4&"'!"&$AQ14),"")) -> 0 | AQ14: D154
A15: DSCR minimum sous stress | B15: =IF(B$4="","",IFERROR(INDIRECT("'"&B$4&"'!"&$AQ15),"")) -> 0 | C15: =IF(C$4="","",IFERROR(INDIRECT("'"&C$4&"'!"&$AQ15),"")) -> 0 | D15: =IF(D$4="","",IFERROR(INDIRECT("'"&D$4&"'!"&$AQ15),"")) -> 0 | E15: =IF(E$4="","",IFERROR(INDIRECT("'"&E$4&"'!"&$AQ15),"")) -> 0 | F15: =IF(F$4="","",IFERROR(INDIRECT("'"&F$4&"'!"&$AQ15),"")) -> 0 | G15: =IF(G$4="","",IFERROR(INDIRECT("'"&G$4&"'!"&$AQ15),"")) -> 0 | H15: =IF(H$4="","",IFERROR(INDIRECT("'"&H$4&"'!"&$AQ15),"")) -> 0 | I15: =IF(I$4="","",IFERROR(INDIRECT("'"&I$4&"'!"&$AQ15),"")) -> 0 | ... AO15: =IF(AO$4="","",IFERROR(INDIRECT("'"&AO$4&"'!"&$AQ15),"")) -> 0 | AQ15: D155
A16: DSCR moyen (indicatif) | B16: =IF(B$4="","",IFERROR(INDIRECT("'"&B$4&"'!"&$AQ16),"")) -> 0 | C16: =IF(C$4="","",IFERROR(INDIRECT("'"&C$4&"'!"&$AQ16),"")) -> 0 | D16: =IF(D$4="","",IFERROR(INDIRECT("'"&D$4&"'!"&$AQ16),"")) -> 0 | E16: =IF(E$4="","",IFERROR(INDIRECT("'"&E$4&"'!"&$AQ16),"")) -> 0 | F16: =IF(F$4="","",IFERROR(INDIRECT("'"&F$4&"'!"&$AQ16),"")) -> 0 | G16: =IF(G$4="","",IFERROR(INDIRECT("'"&G$4&"'!"&$AQ16),"")) -> 0 | H16: =IF(H$4="","",IFERROR(INDIRECT("'"&H$4&"'!"&$AQ16),"")) -> 0 | I16: =IF(I$4="","",IFERROR(INDIRECT("'"&I$4&"'!"&$AQ16),"")) -> 0 | ... AO16: =IF(AO$4="","",IFERROR(INDIRECT("'"&AO$4&"'!"&$AQ16),"")) -> 0 | AQ16: D156
... A28: Prochaine saisie | B28: =IF(B$4="","",IFERROR(INDIRECT("'"&B$4&"'!"&$AQ28),"")) -> 0 | C28: =IF(C$4="","",IFERROR(INDIRECT("'"&C$4&"'!"&$AQ28),"")) -> 0 | D28: =IF(D$4="","",IFERROR(INDIRECT("'"&D$4&"'!"&$AQ28),"")) -> 0 | E28: =IF(E$4="","",IFERROR(INDIRECT("'"&E$4&"'!"&$AQ28),"")) -> 0 | F28: =IF(F$4="","",IFERROR(INDIRECT("'"&F$4&"'!"&$AQ28),"")) -> 0 | G28: =IF(G$4="","",IFERROR(INDIRECT("'"&G$4&"'!"&$AQ28),"")) -> 0 | H28: =IF(H$4="","",IFERROR(INDIRECT("'"&H$4&"'!"&$AQ28),"")) -> 0 | I28: =IF(I$4="","",IFERROR(INDIRECT("'"&I$4&"'!"&$AQ28),"")) -> 0 | ... AO28: =IF(AO$4="","",IFERROR(INDIRECT("'"&AO$4&"'!"&$AQ28),"")) -> 0 | AQ28: C4
A30: Les démonstrations à retenir
A31: C3 — Anti-compensation : un score de 73,7 (note 7) ramené à 4 par les plafonds C2 et C3. Un sponsor à 100 et une documentation à 100 ne compensent pas un DSCR de 1,06 sur le creux saisonnier.
A32: C4A et C4B — Le ratio annuel trompe : 1,53 en annuel, 0,59 par échéance. Après sculpture de l'amortissement, apport complémentaire et couverture de change, la note passe de 3 à 6 sans que le marché ait changé.
A33: C5 et AGR — Proportionnalité : le régime simplifié allège la grille de jugement, jamais les plafonds. Un noyau financier à 97 reste plafonné à 6 par la concentration sur un acheteur unique non noté.
A34: TEL, ETH, IMMO — Les plafonds C3, C4, C7, C8 et C9 se déclenchent sur des données, jamais sur une appréciation. MIN — une exclusion X3 empêche toute note, quel que soit le score.

Sheet Fiche comité
A1: Fiche comité — notation Project Finance (modèle V8)
A2: Choisissez le dossier dans la cellule jaune. Tout est lu dans l'onglet du dossier ; imprimez la page ou utilisez « Exporter en PDF ».
A4: Dossier (nom de l'onglet) | B4: C3 | D4: Édité le | E4: =TODAY() -> 0
A6: IDENTIFICATION
A7: Intitulé | B7: =IF($B$4="","",IFERROR(IF(INDIRECT("'"&$B$4&"'!A1")="","",INDIRECT("'"&$B$4&"'!A1")),"")) -> 0
A8: Société de projet — localisation | B8: =IF($B$4="","",IFERROR(IF(INDIRECT("'"&$B$4&"'!A2")="","",INDIRECT("'"&$B$4&"'!A2")),"")) -> 0
A9: Code client T24 | B9: =IF($B$4="","",IFERROR(IF(INDIRECT("'"&$B$4&"'!B15")="","",INDIRECT("'"&$B$4&"'!B15")),"")) -> 0 | C9: Radical | D9: =IF($B$4="","",IFERROR(IF(INDIRECT("'"&$B$4&"'!B16")="","",INDIRECT("'"&$B$4&"'!B16")),"")) -> 0 | E9: Code projet | F9: =IF($B$4="","",IFERROR(IF(INDIRECT("'"&$B$4&"'!B17")="","",INDIRECT("'"&$B$4&"'!B17")),"")) -> 0
A10: Résumé | B10: =IF($B$4="","",IFERROR(IF(INDIRECT("'"&$B$4&"'!A3")="","",INDIRECT("'"&$B$4&"'!A3")),"")) -> 0
A12: NOTATION
A13: NOTE APPROUVÉE (1 à 10) | B13: =IF($B$4="","",IFERROR(IF(INDIRECT("'"&$B$4&"'!B276")="","",INDIRECT("'"&$B$4&"'!B276")),"")) -> 0 | C13: =IF($B$4="","",IFERROR(IF(INDIRECT("'"&$B$4&"'!D6")="","",INDIRECT("'"&$B$4&"'!D6")),"")) -> 0
A14: Statut | B14: =IF($B$4="","",IFERROR(IF(INDIRECT("'"&$B$4&"'!B277")="","",INDIRECT("'"&$B$4&"'!B277")),"")) -> 0
A15: Orientation | B15: =IF($B$4="","",IFERROR(IF(INDIRECT("'"&$B$4&"'!F11")="","",INDIRECT("'"&$B$4&"'!F11")),"")) -> 0
A16: Score global (sur 100) | B16: =IF($B$4="","",IFERROR(IF(INDIRECT("'"&$B$4&"'!B238")="","",INDIRECT("'"&$B$4&"'!B238")),"")) -> 0 | C16: Note calculée | D16: =IF($B$4="","",IFERROR(IF(INDIRECT("'"&$B$4&"'!B239")="","",INDIRECT("'"&$B$4&"'!B239")),"")) -> 0 | E16: Plafond | F16: =IF($B$4="","",IFERROR(IF(INDIRECT("'"&$B$4&"'!F7")="","",INDIRECT("'"&$B$4&"'!F7")),"")) -> 0
A17: Plafonds actifs | B17: =IF($B$4="","",IFERROR(IF(INDIRECT("'"&$B$4&"'!B8")="","",INDIRECT("'"&$B$4&"'!B8")),"")) -> 0
A18: Verrous actifs (X, B) | B18: =IF($B$4="","",IFERROR(IF(INDIRECT("'"&$B$4&"'!B9")="","",INDIRECT("'"&$B$4&"'!B9")),"")) -> 0
A19: Saisies obligatoires manquantes | B19: =IF($B$4="","",IFERROR(IF(INDIRECT("'"&$B$4&"'!B4")="","",INDIRECT("'"&$B$4&"'!B4")),"")) -> 0 | C19: =IF($B$4="","",IFERROR(IF(INDIRECT("'"&$B$4&"'!C4")="","",INDIRECT("'"&$B$4&"'!C4")),"")) -> 0
A21: ROUTAGE ET PROPORTIONNALITÉ
A22: Régime de revenus | B22: =IF($B$4="","",IFERROR(IF(INDIRECT("'"&$B$4&"'!B18")="","",INDIRECT("'"&$B$4&"'!B18")),"")) -> 0 | C22: =IF($B$4="","",IFERROR(IF(INDIRECT("'"&$B$4&"'!C18")="","",INDIRECT("'"&$B$4&"'!C18")),"")) -> 0
A23: Secteur | B23: =IF($B$4="","",IFERROR(IF(INDIRECT("'"&$B$4&"'!B19")="","",INDIRECT("'"&$B$4&"'!B19")),"")) -> 0 | C23: =IF($B$4="","",IFERROR(IF(INDIRECT("'"&$B$4&"'!C19")="","",INDIRECT("'"&$B$4&"'!C19")),"")) -> 0
A24: Phase | B24: =IF($B$4="","",IFERROR(IF(INDIRECT("'"&$B$4&"'!B20")="","",INDIRECT("'"&$B$4&"'!B20")),"")) -> 0 | C24: =IF($B$4="","",IFERROR(IF(INDIRECT("'"&$B$4&"'!C20")="","",INDIRECT("'"&$B$4&"'!C20")),"")) -> 0
A25: Régime de proportionnalité (S / M / L) | B25: =IF($B$4="","",IFERROR(IF(INDIRECT("'"&$B$4&"'!B38")="","",INDIRECT("'"&$B$4&"'!B38")),"")) -> 0 | C25: =IF($B$4="","",IFERROR(IF(INDIRECT("'"&$B$4&"'!C38")="","",INDIRECT("'"&$B$4&"'!C38")),"")) -> 0
A27: INDICATEURS FINANCIERS
A28: Indicateur | B28: Valeur | C28: Repère | D28: Appréciation
A29: DSCR minimum par échéance (retenu) | B29: =IF($B$4="","",IFERROR(IF(INDIRECT("'"&$B$4&"'!D154")="","",INDIRECT("'"&$B$4&"'!D154")),"")) -> 0 | C29: =IF($B$4="","",IFERROR(IF(INDIRECT("'"&$B$4&"'!B88")="","",INDIRECT("'"&$B$4&"'!B88")),"")) -> 0 | D29: =IF($B$4="","",IFERROR(IF(INDIRECT("'"&$B$4&"'!E154")="","",INDIRECT("'"&$B$4&"'!E154")),"")) -> 0
A30: DSCR minimum sous scénario défavorable | B30: =IF($B$4="","",IFERROR(IF(INDIRECT("'"&$B$4&"'!D155")="","",INDIRECT("'"&$B$4&"'!D155")),"")) -> 0 | D30: =IF($B$4="","",IFERROR(IF(INDIRECT("'"&$B$4&"'!E155")="","",INDIRECT("'"&$B$4&"'!E155")),"")) -> 0
A31: DSCR moyen (indicatif) | B31: =IF($B$4="","",IFERROR(IF(INDIRECT("'"&$B$4&"'!D156")="","",INDIRECT("'"&$B$4&"'!D156")),"")) -> 0
A32: DSCR annuel minimum (indicatif) | B32: =IF($B$4="","",IFERROR(IF(INDIRECT("'"&$B$4&"'!D157")="","",INDIRECT("'"&$B$4&"'!D157")),"")) -> 0
A33: Couverture du besoin à terminaison | B33: =IF($B$4="","",IFERROR(IF(INDIRECT("'"&$B$4&"'!B51")="","",INDIRECT("'"&$B$4&"'!B51")),"")) -> 0
A34: Quote-part de dette | B34: =IF($B$4="","",IFERROR(IF(INDIRECT("'"&$B$4&"'!B52")="","",INDIRECT("'"&$B$4&"'!B52")),"")) -> 0 | C34: =P_C9 -> 0
A35: LLCR | B35: =IF($B$4="","",IFERROR(IF(INDIRECT("'"&$B$4&"'!B172")="","",INDIRECT("'"&$B$4&"'!B172")),"")) -> 0 | C35: =P_C4 -> 0
A36: DSRA (mois de service) | B36: =IF($B$4="","",IFERROR(IF(INDIRECT("'"&$B$4&"'!B173")="","",INDIRECT("'"&$B$4&"'!B173")),"")) -> 0 | C36: =P_C7 -> 0
A37: CAPEX du projet (MMAD) | B37: =IF($B$4="","",IFERROR(IF(INDIRECT("'"&$B$4&"'!B25")="","",INDIRECT("'"&$B$4&"'!B25")),"")) -> 0
A38: Exposition de la banque (MMAD) | B38: =IF($B$4="","",IFERROR(IF(INDIRECT("'"&$B$4&"'!B26")="","",INDIRECT("'"&$B$4&"'!B26")),"")) -> 0
A40: CRÉDITS DE LA BANQUE SUR LE PROJET
A41: Numéro du dossier de crédit | B41: Nature | D41: Montant (MMAD) | E41: Devise | F41: Durée (ans)
A42: =IF($B$4="","",IFERROR(IF(INDIRECT("'"&$B$4&"'!A57")="","",INDIRECT("'"&$B$4&"'!A57")),"")) -> 0 | B42: =IF($B$4="","",IFERROR(IF(INDIRECT("'"&$B$4&"'!B57")="","",INDIRECT("'"&$B$4&"'!B57")),"")) -> 0 | D42: =IF($B$4="","",IFERROR(IF(INDIRECT("'"&$B$4&"'!E57")="","",INDIRECT("'"&$B$4&"'!E57")),"")) -> 0 | E42: =IF($B$4="","",IFERROR(IF(INDIRECT("'"&$B$4&"'!F57")="","",INDIRECT("'"&$B$4&"'!F57")),"")) -> 0 | F42: =IF($B$4="","",IFERROR(IF(INDIRECT("'"&$B$4&"'!G57")="","",INDIRECT("'"&$B$4&"'!G57")),"")) -> 0
A43: =IF($B$4="","",IFERROR(IF(INDIRECT("'"&$B$4&"'!A58")="","",INDIRECT("'"&$B$4&"'!A58")),"")) -> 0 | B43: =IF($B$4="","",IFERROR(IF(INDIRECT("'"&$B$4&"'!B58")="","",INDIRECT("'"&$B$4&"'!B58")),"")) -> 0 | D43: =IF($B$4="","",IFERROR(IF(INDIRECT("'"&$B$4&"'!E58")="","",INDIRECT("'"&$B$4&"'!E58")),"")) -> 0 | E43: =IF($B$4="","",IFERROR(IF(INDIRECT("'"&$B$4&"'!F58")="","",INDIRECT("'"&$B$4&"'!F58")),"")) -> 0 | F43: =IF($B$4="","",IFERROR(IF(INDIRECT("'"&$B$4&"'!G58")="","",INDIRECT("'"&$B$4&"'!G58")),"")) -> 0
A44: =IF($B$4="","",IFERROR(IF(INDIRECT("'"&$B$4&"'!A59")="","",INDIRECT("'"&$B$4&"'!A59")),"")) -> 0 | B44: =IF($B$4="","",IFERROR(IF(INDIRECT("'"&$B$4&"'!B59")="","",INDIRECT("'"&$B$4&"'!B59")),"")) -> 0 | D44: =IF($B$4="","",IFERROR(IF(INDIRECT("'"&$B$4&"'!E59")="","",INDIRECT("'"&$B$4&"'!E59")),"")) -> 0 | E44: =IF($B$4="","",IFERROR(IF(INDIRECT("'"&$B$4&"'!F59")="","",INDIRECT("'"&$B$4&"'!F59")),"")) -> 0 | F44: =IF($B$4="","",IFERROR(IF(INDIRECT("'"&$B$4&"'!G59")="","",INDIRECT("'"&$B$4&"'!G59")),"")) -> 0
A45: =IF($B$4="","",IFERROR(IF(INDIRECT("'"&$B$4&"'!A60")="","",INDIRECT("'"&$B$4&"'!A60")),"")) -> 0 | B45: =IF($B$4="","",IFERROR(IF(INDIRECT("'"&$B$4&"'!B60")="","",INDIRECT("'"&$B$4&"'!B60")),"")) -> 0 | D45: =IF($B$4="","",IFERROR(IF(INDIRECT("'"&$B$4&"'!E60")="","",INDIRECT("'"&$B$4&"'!E60")),"")) -> 0 | E45: =IF($B$4="","",IFERROR(IF(INDIRECT("'"&$B$4&"'!F60")="","",INDIRECT("'"&$B$4&"'!F60")),"")) -> 0 | F45: =IF($B$4="","",IFERROR(IF(INDIRECT("'"&$B$4&"'!G60")="","",INDIRECT("'"&$B$4&"'!G60")),"")) -> 0
A46: =IF($B$4="","",IFERROR(IF(INDIRECT("'"&$B$4&"'!A61")="","",INDIRECT("'"&$B$4&"'!A61")),"")) -> 0 | B46: =IF($B$4="","",IFERROR(IF(INDIRECT("'"&$B$4&"'!B61")="","",INDIRECT("'"&$B$4&"'!B61")),"")) -> 0 | D46: =IF($B$4="","",IFERROR(IF(INDIRECT("'"&$B$4&"'!E61")="","",INDIRECT("'"&$B$4&"'!E61")),"")) -> 0 | E46: =IF($B$4="","",IFERROR(IF(INDIRECT("'"&$B$4&"'!F61")="","",INDIRECT("'"&$B$4&"'!F61")),"")) -> 0 | F46: =IF($B$4="","",IFERROR(IF(INDIRECT("'"&$B$4&"'!G61")="","",INDIRECT("'"&$B$4&"'!G61")),"")) -> 0
A47: =IF($B$4="","",IFERROR(IF(INDIRECT("'"&$B$4&"'!A62")="","",INDIRECT("'"&$B$4&"'!A62")),"")) -> 0 | B47: =IF($B$4="","",IFERROR(IF(INDIRECT("'"&$B$4&"'!B62")="","",INDIRECT("'"&$B$4&"'!B62")),"")) -> 0 | D47: =IF($B$4="","",IFERROR(IF(INDIRECT("'"&$B$4&"'!E62")="","",INDIRECT("'"&$B$4&"'!E62")),"")) -> 0 | E47: =IF($B$4="","",IFERROR(IF(INDIRECT("'"&$B$4&"'!F62")="","",INDIRECT("'"&$B$4&"'!F62")),"")) -> 0 | F47: =IF($B$4="","",IFERROR(IF(INDIRECT("'"&$B$4&"'!G62")="","",INDIRECT("'"&$B$4&"'!G62")),"")) -> 0
A48: Total (MMAD, contre-valeur) | D48: =IF($B$4="","",IFERROR(IF(INDIRECT("'"&$B$4&"'!E63")="","",INDIRECT("'"&$B$4&"'!E63")),"")) -> 0
A49: SCORES PAR DOMAINE
A50: Domaine | B50: Score / 100 | C50: Poids (phase) | D50: Contribution
A51: =IF($B$4="","",IFERROR(IF(INDIRECT("'"&$B$4&"'!A229")="","",INDIRECT("'"&$B$4&"'!A229")),"")) -> 0 | B51: =IF($B$4="","",IFERROR(IF(INDIRECT("'"&$B$4&"'!B229")="","",INDIRECT("'"&$B$4&"'!B229")),"")) -> 0 | C51: =IF($B$4="","",IFERROR(IF(INDIRECT("'"&$B$4&"'!C229")="","",INDIRECT("'"&$B$4&"'!C229")),"")) -> 0 | D51: =IF($B$4="","",IFERROR(IF(INDIRECT("'"&$B$4&"'!D229")="","",INDIRECT("'"&$B$4&"'!D229")),"")) -> 0
A52: =IF($B$4="","",IFERROR(IF(INDIRECT("'"&$B$4&"'!A230")="","",INDIRECT("'"&$B$4&"'!A230")),"")) -> 0 | B52: =IF($B$4="","",IFERROR(IF(INDIRECT("'"&$B$4&"'!B230")="","",INDIRECT("'"&$B$4&"'!B230")),"")) -> 0 | C52: =IF($B$4="","",IFERROR(IF(INDIRECT("'"&$B$4&"'!C230")="","",INDIRECT("'"&$B$4&"'!C230")),"")) -> 0 | D52: =IF($B$4="","",IFERROR(IF(INDIRECT("'"&$B$4&"'!D230")="","",INDIRECT("'"&$B$4&"'!D230")),"")) -> 0
A53: =IF($B$4="","",IFERROR(IF(INDIRECT("'"&$B$4&"'!A231")="","",INDIRECT("'"&$B$4&"'!A231")),"")) -> 0 | B53: =IF($B$4="","",IFERROR(IF(INDIRECT("'"&$B$4&"'!B231")="","",INDIRECT("'"&$B$4&"'!B231")),"")) -> 0 | C53: =IF($B$4="","",IFERROR(IF(INDIRECT("'"&$B$4&"'!C231")="","",INDIRECT("'"&$B$4&"'!C231")),"")) -> 0 | D53: =IF($B$4="","",IFERROR(IF(INDIRECT("'"&$B$4&"'!D231")="","",INDIRECT("'"&$B$4&"'!D231")),"")) -> 0
A54: =IF($B$4="","",IFERROR(IF(INDIRECT("'"&$B$4&"'!A232")="","",INDIRECT("'"&$B$4&"'!A232")),"")) -> 0 | B54: =IF($B$4="","",IFERROR(IF(INDIRECT("'"&$B$4&"'!B232")="","",INDIRECT("'"&$B$4&"'!B232")),"")) -> 0 | C54: =IF($B$4="","",IFERROR(IF(INDIRECT("'"&$B$4&"'!C232")="","",INDIRECT("'"&$B$4&"'!C232")),"")) -> 0 | D54: =IF($B$4="","",IFERROR(IF(INDIRECT("'"&$B$4&"'!D232")="","",INDIRECT("'"&$B$4&"'!D232")),"")) -> 0
A55: =IF($B$4="","",IFERROR(IF(INDIRECT("'"&$B$4&"'!A233")="","",INDIRECT("'"&$B$4&"'!A233")),"")) -> 0 | B55: =IF($B$4="","",IFERROR(IF(INDIRECT("'"&$B$4&"'!B233")="","",INDIRECT("'"&$B$4&"'!B233")),"")) -> 0 | C55: =IF($B$4="","",IFERROR(IF(INDIRECT("'"&$B$4&"'!C233")="","",INDIRECT("'"&$B$4&"'!C233")),"")) -> 0 | D55: =IF($B$4="","",IFERROR(IF(INDIRECT("'"&$B$4&"'!D233")="","",INDIRECT("'"&$B$4&"'!D233")),"")) -> 0
A56: =IF($B$4="","",IFERROR(IF(INDIRECT("'"&$B$4&"'!A234")="","",INDIRECT("'"&$B$4&"'!A234")),"")) -> 0 | B56: =IF($B$4="","",IFERROR(IF(INDIRECT("'"&$B$4&"'!B234")="","",INDIRECT("'"&$B$4&"'!B234")),"")) -> 0 | C56: =IF($B$4="","",IFERROR(IF(INDIRECT("'"&$B$4&"'!C234")="","",INDIRECT("'"&$B$4&"'!C234")),"")) -> 0 | D56: =IF($B$4="","",IFERROR(IF(INDIRECT("'"&$B$4&"'!D234")="","",INDIRECT("'"&$B$4&"'!D234")),"")) -> 0
A57: =IF($B$4="","",IFERROR(IF(INDIRECT("'"&$B$4&"'!A235")="","",INDIRECT("'"&$B$4&"'!A235")),"")) -> 0 | B57: =IF($B$4="","",IFERROR(IF(INDIRECT("'"&$B$4&"'!B235")="","",INDIRECT("'"&$B$4&"'!B235")),"")) -> 0 | C57: =IF($B$4="","",IFERROR(IF(INDIRECT("'"&$B$4&"'!C235")="","",INDIRECT("'"&$B$4&"'!C235")),"")) -> 0 | D57: =IF($B$4="","",IFERROR(IF(INDIRECT("'"&$B$4&"'!D235")="","",INDIRECT("'"&$B$4&"'!D235")),"")) -> 0
A58: =IF($B$4="","",IFERROR(IF(INDIRECT("'"&$B$4&"'!A236")="","",INDIRECT("'"&$B$4&"'!A236")),"")) -> 0 | B58: =IF($B$4="","",IFERROR(IF(INDIRECT("'"&$B$4&"'!B236")="","",INDIRECT("'"&$B$4&"'!B236")),"")) -> 0 | C58: =IF($B$4="","",IFERROR(IF(INDIRECT("'"&$B$4&"'!C236")="","",INDIRECT("'"&$B$4&"'!C236")),"")) -> 0 | D58: =IF($B$4="","",IFERROR(IF(INDIRECT("'"&$B$4&"'!D236")="","",INDIRECT("'"&$B$4&"'!D236")),"")) -> 0
A59: =IF($B$4="","",IFERROR(IF(INDIRECT("'"&$B$4&"'!A237")="","",INDIRECT("'"&$B$4&"'!A237")),"")) -> 0 | B59: =IF($B$4="","",IFERROR(IF(INDIRECT("'"&$B$4&"'!B237")="","",INDIRECT("'"&$B$4&"'!B237")),"")) -> 0 | C59: =IF($B$4="","",IFERROR(IF(INDIRECT("'"&$B$4&"'!C237")="","",INDIRECT("'"&$B$4&"'!C237")),"")) -> 0 | D59: =IF($B$4="","",IFERROR(IF(INDIRECT("'"&$B$4&"'!D237")="","",INDIRECT("'"&$B$4&"'!D237")),"")) -> 0
A60: SCORE GLOBAL | D60: =IF($B$4="","",IFERROR(IF(INDIRECT("'"&$B$4&"'!B238")="","",INDIRECT("'"&$B$4&"'!B238")),"")) -> 0
A62: COMMENTAIRES ET CONDITIONS (bloc 13 du dossier)
A63: Synthèse de l'analyste | B63: =IF($B$4="","",IFERROR(IF(INDIRECT("'"&$B$4&"'!B280")="","",INDIRECT("'"&$B$4&"'!B280")),"")) -> 0
A64: Forces | B64: =IF($B$4="","",IFERROR(IF(INDIRECT("'"&$B$4&"'!B281")="","",INDIRECT("'"&$B$4&"'!B281")),"")) -> 0
A65: Faiblesses et mitigants | B65: =IF($B$4="","",IFERROR(IF(INDIRECT("'"&$B$4&"'!B282")="","",INDIRECT("'"&$B$4&"'!B282")),"")) -> 0
A66: Conditions proposées | B66: =IF($B$4="","",IFERROR(IF(INDIRECT("'"&$B$4&"'!B283")="","",INDIRECT("'"&$B$4&"'!B283")),"")) -> 0
A67: Justification des écarts | B67: =IF($B$4="","",IFERROR(IF(INDIRECT("'"&$B$4&"'!B284")="","",INDIRECT("'"&$B$4&"'!B284")),"")) -> 0
A68: Avis risques | B68: =IF($B$4="","",IFERROR(IF(INDIRECT("'"&$B$4&"'!B285")="","",INDIRECT("'"&$B$4&"'!B285")),"")) -> 0 | C68: =IF($B$4="","",IFERROR(IF(INDIRECT("'"&$B$4&"'!D285")="","",INDIRECT("'"&$B$4&"'!D285")),"")) -> 0
A70: DÉCISION DU COMITÉ
A71: Décision (bloc 13 du dossier) | B71: =IF($B$4="","",IFERROR(IF(INDIRECT("'"&$B$4&"'!B286")="","",INDIRECT("'"&$B$4&"'!B286")),"")) -> 0 | C71: =IF($B$4="","",IFERROR(IF(INDIRECT("'"&$B$4&"'!D286")="","",INDIRECT("'"&$B$4&"'!D286")),"")) -> 0
A72: Conditions et réserves du comité
A73: Date du comité
A74: Signatures

Sheet Comparaison
A1: Comparaison de deux dossiers
A2: Choisissez deux dossiers dans les cellules jaunes : variante de montage, avant et après restructuration, ou deux projets du même secteur. Les écarts significatifs sont surlignés.
A4: Dossiers comparés (noms d'onglet) | B4: C4A | C4: C4B | D4: Écart (B − A)
A6: Indicateur | B6: Dossier A | C6: Dossier B | D6: Écart
A7: Intitulé | B7: =IF($B$4="","",IFERROR(IF(INDIRECT("'"&$B$4&"'!A1")="","",INDIRECT("'"&$B$4&"'!A1")),"")) -> 0 | C7: =IF($C$4="","",IFERROR(IF(INDIRECT("'"&$C$4&"'!A1")="","",INDIRECT("'"&$C$4&"'!A1")),"")) -> 0 | D7: =IF(B7=C7,"=","≠") -> 0
A8: Code projet | B8: =IF($B$4="","",IFERROR(IF(INDIRECT("'"&$B$4&"'!B17")="","",INDIRECT("'"&$B$4&"'!B17")),"")) -> 0 | C8: =IF($C$4="","",IFERROR(IF(INDIRECT("'"&$C$4&"'!B17")="","",INDIRECT("'"&$C$4&"'!B17")),"")) -> 0 | D8: =IF(B8=C8,"=","≠") -> 0
A9: Radical | B9: =IF($B$4="","",IFERROR(IF(INDIRECT("'"&$B$4&"'!B16")="","",INDIRECT("'"&$B$4&"'!B16")),"")) -> 0 | C9: =IF($C$4="","",IFERROR(IF(INDIRECT("'"&$C$4&"'!B16")="","",INDIRECT("'"&$C$4&"'!B16")),"")) -> 0 | D9: =IF(B9=C9,"=","≠") -> 0
A10: Régime de revenus | B10: =IF($B$4="","",IFERROR(IF(INDIRECT("'"&$B$4&"'!B18")="","",INDIRECT("'"&$B$4&"'!B18")),"")) -> 0 | C10: =IF($C$4="","",IFERROR(IF(INDIRECT("'"&$C$4&"'!B18")="","",INDIRECT("'"&$C$4&"'!B18")),"")) -> 0 | D10: =IF(B10=C10,"=","≠") -> 0
A11: Secteur | B11: =IF($B$4="","",IFERROR(IF(INDIRECT("'"&$B$4&"'!B19")="","",INDIRECT("'"&$B$4&"'!B19")),"")) -> 0 | C11: =IF($C$4="","",IFERROR(IF(INDIRECT("'"&$C$4&"'!B19")="","",INDIRECT("'"&$C$4&"'!B19")),"")) -> 0 | D11: =IF(B11=C11,"=","≠") -> 0
A12: Phase | B12: =IF($B$4="","",IFERROR(IF(INDIRECT("'"&$B$4&"'!B20")="","",INDIRECT("'"&$B$4&"'!B20")),"")) -> 0 | C12: =IF($C$4="","",IFERROR(IF(INDIRECT("'"&$C$4&"'!B20")="","",INDIRECT("'"&$C$4&"'!B20")),"")) -> 0 | D12: =IF(B12=C12,"=","≠") -> 0
A13: Régime de proportionnalité | B13: =IF($B$4="","",IFERROR(IF(INDIRECT("'"&$B$4&"'!B38")="","",INDIRECT("'"&$B$4&"'!B38")),"")) -> 0 | C13: =IF($C$4="","",IFERROR(IF(INDIRECT("'"&$C$4&"'!B38")="","",INDIRECT("'"&$C$4&"'!B38")),"")) -> 0 | D13: =IF(B13=C13,"=","≠") -> 0
A14: CAPEX (MMAD) | B14: =IF($B$4="","",IFERROR(IF(INDIRECT("'"&$B$4&"'!B25")="","",INDIRECT("'"&$B$4&"'!B25")),"")) -> 0 | C14: =IF($C$4="","",IFERROR(IF(INDIRECT("'"&$C$4&"'!B25")="","",INDIRECT("'"&$C$4&"'!B25")),"")) -> 0 | D14: =IF(AND(ISNUMBER(B14),ISNUMBER(C14)),C14-B14,IF(B14=C14,"=","≠")) -> 0
A15: Exposition de la banque (MMAD) | B15: =IF($B$4="","",IFERROR(IF(INDIRECT("'"&$B$4&"'!B26")="","",INDIRECT("'"&$B$4&"'!B26")),"")) -> 0 | C15: =IF($C$4="","",IFERROR(IF(INDIRECT("'"&$C$4&"'!B26")="","",INDIRECT("'"&$C$4&"'!B26")),"")) -> 0 | D15: =IF(AND(ISNUMBER(B15),ISNUMBER(C15)),C15-B15,IF(B15=C15,"=","≠")) -> 0
A16: Couverture à terminaison | B16: =IF($B$4="","",IFERROR(IF(INDIRECT("'"&$B$4&"'!B51")="","",INDIRECT("'"&$B$4&"'!B51")),"")) -> 0 | C16: =IF($C$4="","",IFERROR(IF(INDIRECT("'"&$C$4&"'!B51")="","",INDIRECT("'"&$C$4&"'!B51")),"")) -> 0 | D16: =IF(AND(ISNUMBER(B16),ISNUMBER(C16)),C16-B16,IF(B16=C16,"=","≠")) -> 0
A17: Quote-part de dette | B17: =IF($B$4="","",IFERROR(IF(INDIRECT("'"&$B$4&"'!B52")="","",INDIRECT("'"&$B$4&"'!B52")),"")) -> 0 | C17: =IF($C$4="","",IFERROR(IF(INDIRECT("'"&$C$4&"'!B52")="","",INDIRECT("'"&$C$4&"'!B52")),"")) -> 0 | D17: =IF(AND(ISNUMBER(B17),ISNUMBER(C17)),C17-B17,IF(B17=C17,"=","≠")) -> 0
A18: Seuil DSCR critique | B18: =IF($B$4="","",IFERROR(IF(INDIRECT("'"&$B$4&"'!B88")="","",INDIRECT("'"&$B$4&"'!B88")),"")) -> 0 | C18: =IF($C$4="","",IFERROR(IF(INDIRECT("'"&$C$4&"'!B88")="","",INDIRECT("'"&$C$4&"'!B88")),"")) -> 0 | D18: =IF(AND(ISNUMBER(B18),ISNUMBER(C18)),C18-B18,IF(B18=C18,"=","≠")) -> 0
A19: DSCR minimum par échéance | B19: =IF($B$4="","",IFERROR(IF(INDIRECT("'"&$B$4&"'!D154")="","",INDIRECT("'"&$B$4&"'!D154")),"")) -> 0 | C19: =IF($C$4="","",IFERROR(IF(INDIRECT("'"&$C$4&"'!D154")="","",INDIRECT("'"&$C$4&"'!D154")),"")) -> 0 | D19: =IF(AND(ISNUMBER(B19),ISNUMBER(C19)),C19-B19,IF(B19=C19,"=","≠")) -> 0
A20: DSCR minimum sous stress | B20: =IF($B$4="","",IFERROR(IF(INDIRECT("'"&$B$4&"'!D155")="","",INDIRECT("'"&$B$4&"'!D155")),"")) -> 0 | C20: =IF($C$4="","",IFERROR(IF(INDIRECT("'"&$C$4&"'!D155")="","",INDIRECT("'"&$C$4&"'!D155")),"")) -> 0 | D20: =IF(AND(ISNUMBER(B20),ISNUMBER(C20)),C20-B20,IF(B20=C20,"=","≠")) -> 0
A21: DSCR annuel minimum (indicatif) | B21: =IF($B$4="","",IFERROR(IF(INDIRECT("'"&$B$4&"'!D157")="","",INDIRECT("'"&$B$4&"'!D157")),"")) -> 0 | C21: =IF($C$4="","",IFERROR(IF(INDIRECT("'"&$C$4&"'!D157")="","",INDIRECT("'"&$C$4&"'!D157")),"")) -> 0 | D21: =IF(AND(ISNUMBER(B21),ISNUMBER(C21)),C21-B21,IF(B21=C21,"=","≠")) -> 0
A22: LLCR | B22: =IF($B$4="","",IFERROR(IF(INDIRECT("'"&$B$4&"'!B172")="","",INDIRECT("'"&$B$4&"'!B172")),"")) -> 0 | C22: =IF($C$4="","",IFERROR(IF(INDIRECT("'"&$C$4&"'!B172")="","",INDIRECT("'"&$C$4&"'!B172")),"")) -> 0 | D22: =IF(AND(ISNUMBER(B22),ISNUMBER(C22)),C22-B22,IF(B22=C22,"=","≠")) -> 0
A23: DSRA (mois) | B23: =IF($B$4="","",IFERROR(IF(INDIRECT("'"&$B$4&"'!B173")="","",INDIRECT("'"&$B$4&"'!B173")),"")) -> 0 | C23: =IF($C$4="","",IFERROR(IF(INDIRECT("'"&$C$4&"'!B173")="","",INDIRECT("'"&$C$4&"'!B173")),"")) -> 0 | D23: =IF(AND(ISNUMBER(B23),ISNUMBER(C23)),C23-B23,IF(B23=C23,"=","≠")) -> 0
A24: Exposition nette en devises | B24: =IF($B$4="","",IFERROR(IF(INDIRECT("'"&$B$4&"'!B174")="","",INDIRECT("'"&$B$4&"'!B174")),"")) -> 0 | C24: =IF($C$4="","",IFERROR(IF(INDIRECT("'"&$C$4&"'!B174")="","",INDIRECT("'"&$C$4&"'!B174")),"")) -> 0 | D24: =IF(AND(ISNUMBER(B24),ISNUMBER(C24)),C24-B24,IF(B24=C24,"=","≠")) -> 0
A25: Score D1 — Sponsors et actionnariat | B25: =IF($B$4="","",IFERROR(IF(INDIRECT("'"&$B$4&"'!B229")="","",INDIRECT("'"&$B$4&"'!B229")),"")) -> 0 | C25: =IF($C$4="","",IFERROR(IF(INDIRECT("'"&$C$4&"'!B229")="","",INDIRECT("'"&$C$4&"'!B229")),"")) -> 0 | D25: =IF(AND(ISNUMBER(B25),ISNUMBER(C25)),C25-B25,IF(B25=C25,"=","≠")) -> 0
A26: Score D2 — Projet, site, technologie | B26: =IF($B$4="","",IFERROR(IF(INDIRECT("'"&$B$4&"'!B230")="","",INDIRECT("'"&$B$4&"'!B230")),"")) -> 0 | C26: =IF($C$4="","",IFERROR(IF(INDIRECT("'"&$C$4&"'!B230")="","",INDIRECT("'"&$C$4&"'!B230")),"")) -> 0 | D26: =IF(AND(ISNUMBER(B26),ISNUMBER(C26)),C26-B26,IF(B26=C26,"=","≠")) -> 0
A27: Score D3 — Construction et achèvement | B27: =IF($B$4="","",IFERROR(IF(INDIRECT("'"&$B$4&"'!B231")="","",INDIRECT("'"&$B$4&"'!B231")),"")) -> 0 | C27: =IF($C$4="","",IFERROR(IF(INDIRECT("'"&$C$4&"'!B231")="","",INDIRECT("'"&$C$4&"'!B231")),"")) -> 0 | D27: =IF(AND(ISNUMBER(B27),ISNUMBER(C27)),C27-B27,IF(B27=C27,"=","≠")) -> 0
A28: Score D4 — Mécanisme des recettes | B28: =IF($B$4="","",IFERROR(IF(INDIRECT("'"&$B$4&"'!B232")="","",INDIRECT("'"&$B$4&"'!B232")),"")) -> 0 | C28: =IF($C$4="","",IFERROR(IF(INDIRECT("'"&$C$4&"'!B232")="","",INDIRECT("'"&$C$4&"'!B232")),"")) -> 0 | D28: =IF(AND(ISNUMBER(B28),ISNUMBER(C28)),C28-B28,IF(B28=C28,"=","≠")) -> 0
A29: Score D5 — Exploitation et maintenance | B29: =IF($B$4="","",IFERROR(IF(INDIRECT("'"&$B$4&"'!B233")="","",INDIRECT("'"&$B$4&"'!B233")),"")) -> 0 | C29: =IF($C$4="","",IFERROR(IF(INDIRECT("'"&$C$4&"'!B233")="","",INDIRECT("'"&$C$4&"'!B233")),"")) -> 0 | D29: =IF(AND(ISNUMBER(B29),ISNUMBER(C29)),C29-B29,IF(B29=C29,"=","≠")) -> 0
A30: Score D6 — Contreparties et consortium | B30: =IF($B$4="","",IFERROR(IF(INDIRECT("'"&$B$4&"'!B234")="","",INDIRECT("'"&$B$4&"'!B234")),"")) -> 0 | C30: =IF($C$4="","",IFERROR(IF(INDIRECT("'"&$C$4&"'!B234")="","",INDIRECT("'"&$C$4&"'!B234")),"")) -> 0 | D30: =IF(AND(ISNUMBER(B30),ISNUMBER(C30)),C30-B30,IF(B30=C30,"=","≠")) -> 0
A31: Score D7 — Finance et trésorerie (noyau) | B31: =IF($B$4="","",IFERROR(IF(INDIRECT("'"&$B$4&"'!B235")="","",INDIRECT("'"&$B$4&"'!B235")),"")) -> 0 | C31: =IF($C$4="","",IFERROR(IF(INDIRECT("'"&$C$4&"'!B235")="","",INDIRECT("'"&$C$4&"'!B235")),"")) -> 0 | D31: =IF(AND(ISNUMBER(B31),ISNUMBER(C31)),C31-B31,IF(B31=C31,"=","≠")) -> 0
A32: Score D8 — Juridique, sûretés, continuité | B32: =IF($B$4="","",IFERROR(IF(INDIRECT("'"&$B$4&"'!B236")="","",INDIRECT("'"&$B$4&"'!B236")),"")) -> 0 | C32: =IF($C$4="","",IFERROR(IF(INDIRECT("'"&$C$4&"'!B236")="","",INDIRECT("'"&$C$4&"'!B236")),"")) -> 0 | D32: =IF(AND(ISNUMBER(B32),ISNUMBER(C32)),C32-B32,IF(B32=C32,"=","≠")) -> 0
A33: Score D9 — ESG et climat résiduel | B33: =IF($B$4="","",IFERROR(IF(INDIRECT("'"&$B$4&"'!B237")="","",INDIRECT("'"&$B$4&"'!B237")),"")) -> 0 | C33: =IF($C$4="","",IFERROR(IF(INDIRECT("'"&$C$4&"'!B237")="","",INDIRECT("'"&$C$4&"'!B237")),"")) -> 0 | D33: =IF(AND(ISNUMBER(B33),ISNUMBER(C33)),C33-B33,IF(B33=C33,"=","≠")) -> 0
A34: Score global | B34: =IF($B$4="","",IFERROR(IF(INDIRECT("'"&$B$4&"'!B238")="","",INDIRECT("'"&$B$4&"'!B238")),"")) -> 0 | C34: =IF($C$4="","",IFERROR(IF(INDIRECT("'"&$C$4&"'!B238")="","",INDIRECT("'"&$C$4&"'!B238")),"")) -> 0 | D34: =IF(AND(ISNUMBER(B34),ISNUMBER(C34)),C34-B34,IF(B34=C34,"=","≠")) -> 0
A35: Note calculée | B35: =IF($B$4="","",IFERROR(IF(INDIRECT("'"&$B$4&"'!B239")="","",INDIRECT("'"&$B$4&"'!B239")),"")) -> 0 | C35: =IF($C$4="","",IFERROR(IF(INDIRECT("'"&$C$4&"'!B239")="","",INDIRECT("'"&$C$4&"'!B239")),"")) -> 0 | D35: =IF(AND(ISNUMBER(B35),ISNUMBER(C35)),C35-B35,IF(B35=C35,"=","≠")) -> 0
A36: Plafond le plus contraignant | B36: =IF($B$4="","",IFERROR(IF(INDIRECT("'"&$B$4&"'!B273")="","",INDIRECT("'"&$B$4&"'!B273")),"")) -> 0 | C36: =IF($C$4="","",IFERROR(IF(INDIRECT("'"&$C$4&"'!B273")="","",INDIRECT("'"&$C$4&"'!B273")),"")) -> 0 | D36: =IF(AND(ISNUMBER(B36),ISNUMBER(C36)),C36-B36,IF(B36=C36,"=","≠")) -> 0
A37: NOTE APPROUVÉE | B37: =IF($B$4="","",IFERROR(IF(INDIRECT("'"&$B$4&"'!B276")="","",INDIRECT("'"&$B$4&"'!B276")),"")) -> 0 | C37: =IF($C$4="","",IFERROR(IF(INDIRECT("'"&$C$4&"'!B276")="","",INDIRECT("'"&$C$4&"'!B276")),"")) -> 0 | D37: =IF(AND(ISNUMBER(B37),ISNUMBER(C37)),C37-B37,IF(B37=C37,"=","≠")) -> 0
A38: Statut | B38: =IF($B$4="","",IFERROR(IF(INDIRECT("'"&$B$4&"'!B277")="","",INDIRECT("'"&$B$4&"'!B277")),"")) -> 0 | C38: =IF($C$4="","",IFERROR(IF(INDIRECT("'"&$C$4&"'!B277")="","",INDIRECT("'"&$C$4&"'!B277")),"")) -> 0 | D38: =IF(B38=C38,"=","≠") -> 0
A39: Plafonds actifs | B39: =IF($B$4="","",IFERROR(IF(INDIRECT("'"&$B$4&"'!B8")="","",INDIRECT("'"&$B$4&"'!B8")),"")) -> 0 | C39: =IF($C$4="","",IFERROR(IF(INDIRECT("'"&$C$4&"'!B8")="","",INDIRECT("'"&$C$4&"'!B8")),"")) -> 0 | D39: =IF(B39=C39,"=","≠") -> 0
A40: Verrous actifs | B40: =IF($B$4="","",IFERROR(IF(INDIRECT("'"&$B$4&"'!B9")="","",INDIRECT("'"&$B$4&"'!B9")),"")) -> 0 | C40: =IF($C$4="","",IFERROR(IF(INDIRECT("'"&$C$4&"'!B9")="","",INDIRECT("'"&$C$4&"'!B9")),"")) -> 0 | D40: =IF(B40=C40,"=","≠") -> 0
A41: Avis risques | B41: =IF($B$4="","",IFERROR(IF(INDIRECT("'"&$B$4&"'!B285")="","",INDIRECT("'"&$B$4&"'!B285")),"")) -> 0 | C41: =IF($C$4="","",IFERROR(IF(INDIRECT("'"&$C$4&"'!B285")="","",INDIRECT("'"&$C$4&"'!B285")),"")) -> 0 | D41: =IF(B41=C41,"=","≠") -> 0
A42: Saisies obligatoires manquantes | B42: =IF($B$4="","",IFERROR(IF(INDIRECT("'"&$B$4&"'!B4")="","",INDIRECT("'"&$B$4&"'!B4")),"")) -> 0 | C42: =IF($C$4="","",IFERROR(IF(INDIRECT("'"&$C$4&"'!B4")="","",INDIRECT("'"&$C$4&"'!B4")),"")) -> 0 | D42: =IF(AND(ISNUMBER(B42),ISNUMBER(C42)),C42-B42,IF(B42=C42,"=","≠")) -> 0

Sheet C1
A1: CAS 1 · Centrale solaire photovoltaïque 80 MWc | J1: DOSSIER_V8 | K1: V3
A2: SPV « Solaris Drâa » SA (fictive) — Région de Drâa-Tafilalet
A3: Centrale PV vendant sa production à l'acheteur public national sous contrat d'achat de 25 ans à quantité garantie et tarif indexé. Financement en dirhams, EPC clé-en-main forfaitaire.
A4: À SAISIR (cellules orange) | B4: =COUNTIF($R$14:$R$63,0) -> 0 | C4: =IF(B4=0,"Saisie complète : lisez la note ci-dessous, puis « Fiche comité ».","Prochaine saisie : "&INDEX($P$14:$P$63,MATCH(0,$R$14:$R$63,0))) -> 0 | G4: =IF(B4=0,"",HYPERLINK("#"&INDEX($Q$14:$Q$63,MATCH(0,$R$14:$R$63,0)),"→ Aller à la cellule "&INDEX($Q$14:$Q$63,MATCH(0,$R$14:$R$63,0)))) -> 0
A5: ="TABLEAU DE BORD — "&IF($B$17="","code projet à saisir",$B$17)&" · client "&IF($B$15="","—",$B$15)&" · radical "&IF($B$16="","—",$B$16) -> 0
A6: NOTE APPROUVÉE (1 à 10) | B6: =B276 -> 0 | C6: Libellé | D6: =IFERROR(INDEX(P_ConvLib,MATCH(B276,P_ConvNote,0)),"") -> 0 | E6: Statut | F6: =B277 -> 0
A7: Score global (sur 100) | B7: =B238 -> 0 | C7: Note calculée | D7: =B239 -> 0 | E7: Plafond applicable | F7: =IF(B273>=10,"Aucun (10)",B273) -> 0
A8: Plafonds actifs | B8: =IF(TRIM(IF(E258="Oui","C1 ("&F258&") ","")&IF(E259="Oui","C2 ("&F259&") ","")&IF(E260="Oui","C3 ("&F260&") ","")&IF(E261="Oui","C4 ("&F261&") ","")&IF(E262="Oui","C5 ("&F262&") ","")&IF(E263="Oui","C6 ("&F263&") ","")&IF(E264="Oui","C7 ("&F264&") ","")&IF(E265="Oui","C8 ("&F265&") ","")&IF(E266="Oui","C9 ("&F266&") ","")&IF(E267="Oui","C10 ("&F267&") ","")&IF(E268="Oui","C11 ("&F268&") ","")&IF(E269="Oui","C12 ("&F269&") ","")&IF(E270="Oui","C13 ("&F270&") ","")&IF(E271="Oui","C14 ("&F271&") ","")&IF(E272="Oui","C15 ("&F272&") ",""))="","Aucun",TRIM(IF(E258="Oui","C1 ("&F258&") ","")&IF(E259="Oui","C2 ("&F259&") ","")&IF(E260="Oui","C3 ("&F260&") ","")&IF(E261="Oui","C4 ("&F261&") ","")&IF(E262="Oui","C5 ("&F262&") ","")&IF(E263="Oui","C6 ("&F263&") ","")&IF(E264="Oui","C7 ("&F264&") ","")&IF(E265="Oui","C8 ("&F265&") ","")&IF(E266="Oui","C9 ("&F266&") ","")&IF(E267="Oui","C10 ("&F267&") ","")&IF(E268="Oui","C11 ("&F268&") ","")&IF(E269="Oui","C12 ("&F269&") ","")&IF(E270="Oui","C13 ("&F270&") ","")&IF(E271="Oui","C14 ("&F271&") ","")&IF(E272="Oui","C15 ("&F272&") ","")))&IF(COUNTIF(E258:E272,"n.r.")>0," — "&COUNTIF(E258:E272,"n.r.")&" plafond(s) non évalué(s) faute de donnée","") -> 0
A9: Verrous actifs (exclusions X, blocages B) | B9: =IF(TRIM(IF(F243="Oui","X1 ","")&IF(F244="Oui","X2 ","")&IF(F245="Oui","X3 ","")&IF(F246="Oui","X4 ","")&IF(F247="Oui","B1 ","")&IF(F248="Oui","B2 ","")&IF(F249="Oui","B3 ","")&IF(F250="Oui","B4 ","")&IF(F251="Oui","B5 ","")&IF(F252="Oui","B6 ","")&IF(F253="Oui","B7 ","")&IF(F254="Oui","B8 ",""))="","Aucun",TRIM(IF(F243="Oui","X1 ","")&IF(F244="Oui","X2 ","")&IF(F245="Oui","X3 ","")&IF(F246="Oui","X4 ","")&IF(F247="Oui","B1 ","")&IF(F248="Oui","B2 ","")&IF(F249="Oui","B3 ","")&IF(F250="Oui","B4 ","")&IF(F251="Oui","B5 ","")&IF(F252="Oui","B6 ","")&IF(F253="Oui","B7 ","")&IF(F254="Oui","B8 ",""))) -> 0
A10: Régime de proportionnalité retenu | B10: =B38 -> 0 | C10: DSCR minimum | D10: =D154 -> 0 | E10: DSCR stressé min. | F10: =D155 -> 0
A11: Complétude (noyau N1-N6 et grille) | B11: =B225 -> 0 | C11: Noyau financier D7 | D11: =D169 -> 0 | E11: Orientation | F11: =IFERROR(INDEX(P_ConvOrient,MATCH(B276,P_ConvNote,0)),"") -> 0
A12: Aller à la section : | B12: =HYPERLINK("#A13","1 · Identification") -> 0 | C12: =HYPERLINK("#A40","3 · Sources") -> 0 | D12: =HYPERLINK("#A90","6 · Échéancier") -> 0 | E12: =HYPERLINK("#A161","7 · Noyau") -> 0 | F12: =HYPERLINK("#A188","8 · Grille") -> 0 | G12: =HYPERLINK("#A256","11 · Plafonds") -> 0 | H12: =HYPERLINK("#A279","13 · Commentaires") -> 0
A13: 1 · IDENTIFICATION ET ROUTAGE — codes du client et du projet ; le routage pilote seuils et poids
A14: Axe | B14: Valeur | C14: Libellé, contrôle | P14: 1 · Code client T24 | Q14: B15 | R14: =IF(AND(LEN(TRIM($B$15))>=1,LEN($B$15)<=20),1,0) -> 0
A15: Code client T24 (société de projet) | B15: 20041027 | C15: =IF(B15="","À saisir — Texte, zéros de tête conservés.",IF(AND(LEN(TRIM(B15))>=1,LEN(B15)<=20),"Format conforme.","Format non conforme : Texte, zéros de tête conservés.")) -> 0 | P15: 1 · Radical du client (7 chiffres) | Q15: B16 | R15: =IF(AND(LEN($B$16)=7,SUMPRODUCT(--ISNUMBER(FIND(MID($B$16,ROW(INDIRECT("1:7"))+0,1),"0123456789")))=7),1,0) -> 0
A16: Radical du client (7 chiffres) | B16: 0041027 | C16: =IF(B16="","À saisir — Exactement 7 chiffres, zéros de tête compris.",IF(AND(LEN(B16)=7,SUMPRODUCT(--ISNUMBER(FIND(MID(B16,ROW(INDIRECT("1:7"))+0,1),"0123456789")))=7),"Format conforme.","Format non conforme : Exactement 7 chiffres, zéros de tête compris.")) -> 0 | P16: 1 · Code projet (PF-AAAA-NNNN) | Q16: B17 | R16: =IF(AND(LEN($B$17)=12,EXACT(LEFT($B$17,3),"PF-"),MID($B$17,8,1)="-",SUMPRODUCT(--ISNUMBER(FIND(MID($B$17,ROW(INDIRECT("1:4"))+3,1),"0123456789")))=4,SUMPRODUCT(--ISNUMBER(FIND(MID($B$17,ROW(INDIRECT("1:4"))+8,1),"0123456789")))=4),1,0) -> 0
A17: Code projet | B17: PF-2026-0001 | C17: =IF(B17="","À saisir — Format PF-AAAA-NNNN.",IF(AND(LEN(B17)=12,EXACT(LEFT(B17,3),"PF-"),MID(B17,8,1)="-",SUMPRODUCT(--ISNUMBER(FIND(MID(B17,ROW(INDIRECT("1:4"))+3,1),"0123456789")))=4,SUMPRODUCT(--ISNUMBER(FIND(MID(B17,ROW(INDIRECT("1:4"))+8,1),"0123456789")))=4),"Format conforme.","Format non conforme : Format PF-AAAA-NNNN.")) -> 0 | P17: 1 · Régime de revenus | Q17: B18 | R17: =IF($B$18<>"",1,0) -> 0
A18: C — Régime de revenus | B18: R1 | C18: =IFERROR(INDEX(P_RegLib,MATCH(B18,P_Regimes,0)),"") -> 0 | P18: 1 · Secteur du projet | Q18: B19 | R18: =IF($B$19<>"",1,0) -> 0
A19: D — Secteur du projet | B19: ENR | C19: =IFERROR(INDEX(P_SecLib,MATCH(B19,P_SecCodes,0)),"") -> 0 | P19: 1 · Phase du projet | Q19: B20 | R19: =IF($B$20<>"",1,0) -> 0
A20: B — Phase | B20: P1 | C20: =IFERROR(INDEX(P_PhaseLib,MATCH(B20,P_PhaseCodes,0)),"") -> 0 | P20: 1 · Périodicité des échéances | Q20: B21 | R20: =IF($B$21<>"",1,0) -> 0
A21: Périodicité du service de la dette | B21: Semestrielle | C21: Jamais annuelle : le DSCR se mesure échéance par échéance. | P21: 2 · Exposition de la banque (MMAD) | Q21: B26 | R21: =IF(ISNUMBER($B$26),1,0) -> 0
A22: A — Famille de financement | B22: PF-FLUX | C22: SPV dédiée, remboursement par les flux du projet (R5 vente d'actifs : hors outil). | P22: 2 · Recettes, coûts et dette en dirhams ? | Q22: B27 | R22: =IF($B$27<>"",1,0) -> 0
P23: 2 · Durée du financement (ans) | Q23: B28 | R23: =IF(ISNUMBER($B$28),1,0) -> 0
A24: 2 · RÉGIME DE PROPORTIONNALITÉ — calculé, jamais choisi | P24: 2 · Technologie éprouvée ? | Q24: B29 | R24: =IF($B$29<>"",1,0) -> 0
A25: CAPEX du projet économique complet (MMAD) | B25: =B50 -> 0 | C25: Repris du total des emplois (section 3). | P25: 2 · EPC clé-en-main de moins de 18 mois ? (phase P1) | Q25: B30 | R25: =IF(OR(NOT($B$20="P1"),$B$30<>""),1,0) -> 0
A26: Exposition de la banque (MMAD) | B26: 465 | P26: 2 · Acheteur principal unique ? | Q26: B31 | R26: =IF($B$31<>"",1,0) -> 0
A27: Recettes, coûts et dette intégralement en dirhams | B27: Oui | P27: 2 · Première référence technologique ? | Q27: B32 | R27: =IF($B$32<>"",1,0) -> 0
A28: Durée du financement (ans) | B28: 20 | P28: 2 · Opération consortiale ? | Q28: B33 | R28: =IF($B$33<>"",1,0) -> 0
A29: Technologie : ≥ 3 références industrielles de plus de 3 ans | B29: Oui | P29: 2 · Contrat de revenus de plus de 20 ans ? | Q29: B34 | R29: =IF($B$34<>"",1,0) -> 0
A30: En P1 : EPC clé-en-main forfaitaire, prix et délai garantis, < 18 mois | B30: Non | P30: 2 · Site à risque climatique élevé ? | Q30: B35 | R30: =IF($B$35<>"",1,0) -> 0
A31: Acheteur principal unique et identifié | B31: Oui | P31: 2 · Nombre de contreparties clés | Q31: B36 | R31: =IF(ISNUMBER($B$36),1,0) -> 0
A32: Technologie constituant une première référence dans la juridiction | B32: Non | P32: 3 · Emplois : montants du besoin à terminaison | Q32: B42 | R32: =IF(N($B$50)>0,1,0) -> 0
A33: Opération consortiale relevant de la directive 3/W/2025 | B33: Non | P33: 3 · Ressources engagées : montants | Q33: E42 | R33: =IF(N($E$50)>0,1,0) -> 0
A34: Concession ou contrat de revenus de plus de 20 ans | B34: Oui | P34: 3 · Nature de chaque ressource | Q34: F42 | R34: =IF(SUMPRODUCT(ISNUMBER($E$42:$E$49)*($F$42:$F$49=""))=0,1,0) -> 0
A35: Site classé à risque climatique physique élevé | B35: Non | P35: 3 · Plan de remédiation (couverture entre 95 et 100 %) | Q35: B53 | R35: =IF(OR(NOT(AND($B$20="P1",ISNUMBER($B$51),N($B$51)>=P_N3_V,N($B$51)<P_N3_F)),$B$53<>""),1,0) -> 0
A36: Nombre de contreparties clés | B36: 3 | P36: 6 · Choc du scénario défavorable (%) | Q36: B91 | R36: =IF(ISNUMBER($B$91),1,0) -> 0
A37: Régime calculé (avant escalade) | B37: =IF(OR(B25="",B25=0,B18=""),"",IF(OR(B25>P_L_CAPEX,N(B26)>P_L_EXPO,B18="R4",B32="Oui",N(B174)>0,B33="Oui",B34="Oui",B35="Oui",N(B36)>P_L_NBCP),"L",IF(AND(B25<=P_S_CAPEX,B26<>"",N(B26)<=P_S_EXPO,OR(B18="R1",B18="R2"),B29="Oui",B27="Oui",B28<>"",N(B28)<=P_S_DUREE,OR(B20<>"P1",B30="Oui"),B31="Oui",COUNTIF($F$243:$F$254,"Oui")=0),"S","M"))) -> 0 | C37: =IF(B37="","",IF(B37="L","Escalade : "&IF(B25>P_L_CAPEX,"CAPEX > "&P_L_CAPEX&" MMAD ; ","")&IF(N(B26)>P_L_EXPO,"exposition > "&P_L_EXPO&" MMAD ; ","")&IF(B18="R4","régime de revenus R4 ; ","")&IF(B32="Oui","première référence technologique ; ","")&IF(N(B174)>0,"devises non intégralement couvertes ; ","")&IF(B33="Oui","opération consortiale ; ","")&IF(B34="Oui","contrat de revenus > 20 ans ; ","")&IF(B35="Oui","risque climatique élevé ; ","")&IF(N(B36)>P_L_NBCP,"plus de "&P_L_NBCP&" contreparties clés ; ",""),IF(B37="S","Toutes les conditions du régime simplifié sont réunies.","Régime standard par défaut : une condition du régime S manque, aucune condition d'escalade."))) -> 0 | P37: 6 · Échéancier : CFADS d'au moins deux périodes | Q37: B93 | R37: =IF(COUNT($B$93:$B$152)>=2,1,0) -> 0
A38: RÉGIME RETENU (après escalade automatique) | B38: =IF(B37="","",IF(AND(IF(AND(B37="S",COUNTIF($F$243:$F$254,"Oui")>0),"M",B37)="M",COUNTIF($E$258:$E$272,"Oui")>0),"L",IF(AND(B37="S",COUNTIF($F$243:$F$254,"Oui")>0),"M",B37))) -> 0 | C38: =IF(B38=B37,"Aucune escalade.",IF(B38="L","Escalade : un plafond de note est actif (M passe en L).","Escalade : un verrou est actif (S passe en M).")) -> 0 | P38: 6 · Service de la dette de chaque période | Q38: C93 | R38: =IF(SUMPRODUCT(ISNUMBER($B$93:$B$152)*(1-ISNUMBER($C$93:$C$152)))=0,1,0) -> 0
P39: 7 · N4 — Liquidité : situation à choisir | Q39: E166 | R39: =IF($B$166<>"",1,0) -> 0
A40: 3 · SOURCES ET EMPLOIS (MMAD) — test de financement à terminaison ; crédits de la banque | P40: 7 · N5 — Levier : situation à choisir | Q40: E167 | R40: =IF($B$167<>"",1,0) -> 0
A41: Emplois | B41: Montant | D41: Ressources | E41: Montant | F41: Nature | P41: 7 · N6 — Exposition résiduelle : situation à choisir | Q41: E168 | R41: =IF($B$168<>"",1,0) -> 0
A42: Contrat EPC (modules, structures, postes) | B42: 590 | D42: Dette senior (20 ans, 5,5 %) | E42: 465 | F42: Dette senior | P42: 7 · Justification exigée (N4 à N6 Critique ou Info. insuffisante) | Q42: ="H"&IF(COUNT($T$166:$T$168)=0,166,MIN($T$166:$T$168)) -> 0 | R42: =IF(COUNT($T$166:$T$168)=0,1,0) -> 0
A43: Raccordement au réseau | B43: 25 | D43: Fonds propres et quasi-fonds propres | E43: 242 | F43: Quasi-fonds propres | P43: 7 · N3 hors phase P1 : note LLCR | Q43: B171 | R43: =IF(OR($B$20="P1",$B$171<>""),1,0) -> 0
A44: Développement, frais et assurances | B44: 20 | D44: Engagement sponsor de dépassement (engagé, non tiré) | E44: 40 | F44: Engagement sponsor | P44: 7 · LLCR (plafond C4) | Q44: B172 | R44: =IF(ISNUMBER($B$172),1,0) -> 0
A45: Contingence | B45: 30 | P45: 7 · DSRA en mois (plafond C7) | Q45: B173 | R45: =IF(ISNUMBER($B$173),1,0) -> 0
A46: Intérêts intercalaires | B46: 18 | P46: 7 · Exposition nette en devises (plafond C6) | Q46: B174 | R46: =IF(ISNUMBER($B$174),1,0) -> 0
A47: Dotation initiale DSRA | B47: 20 | P47: 7 · Dette à refinancer à maturité (plafond C8) | Q47: B175 | R47: =IF(ISNUMBER($B$175),1,0) -> 0
A48: BFR de démarrage | B48: 4 | P48: 7 · Stratégie de refinancement approuvée ? | Q48: B176 | R48: =IF(OR(N($B$175)<=P_C8,$B$176<>""),1,0) -> 0
P49: 7 · Part des recettes de l'acheteur principal (C10) | Q49: B177 | R49: =IF(ISNUMBER($B$177),1,0) -> 0
A50: Total emplois (besoin à terminaison) | B50: =SUM(B42:B49) -> 0 | D50: Total ressources engagées | E50: =SUM(E42:E49) -> 0 | P50: 7 · Qualité de crédit de l'acheteur principal | Q50: B178 | R50: =IF($B$178<>"",1,0) -> 0
A51: Couverture du besoin à terminaison (ressources / emplois) | B51: =IF(N(B50)=0,"",E50/B50) -> 0 | P51: 7 · Durée résiduelle du contrat de revenus (C5) | Q51: B179 | R51: =IF(OR($B$18="R4",ISNUMBER($B$179)),1,0) -> 0
A52: Quote-part de dette (dette / besoin à terminaison) | B52: =IF(N(B50)=0,"",(SUMIF(F42:F49,"Dette senior",E42:E49)+SUMIF(F42:F49,"Dette subordonnée",E42:E49))/B50) -> 0 | P52: 7 · Durée résiduelle de la dette | Q52: B180 | R52: =IF(ISNUMBER($B$180),1,0) -> 0
A53: Plan de remédiation approuvé (couverture entre 95 % et 100 %) | B53: Non | P53: 7 · Solution documentée (contrat plus court que la dette) ? | Q53: B181 | R53: =IF(OR(NOT(AND(ISNUMBER($B$179),ISNUMBER($B$180))),N($B$179)>=N($B$180),$B$181<>""),1,0) -> 0
P54: 7 · Plan d'adaptation climatique financé ? (C11) | Q54: B182 | R54: =IF(OR($B$35<>"Oui",$B$182<>""),1,0) -> 0
A55: Crédits de la banque sur le projet — un projet peut porter plusieurs dossiers de crédit | P55: 7 · Capacité résiduelle du sponsor (C12) | Q55: B183 | R55: =IF($B$183<>"",1,0) -> 0
A56: Numéro du dossier de crédit | B56: Nature | E56: Montant (MMAD) | F56: Devise | G56: Durée (ans) | H56: Observation | P56: 7 · Opérateur remplaçable ? (C13) | Q56: B184 | R56: =IF($B$184<>"",1,0) -> 0
A57: CR-26-0101 | B57: Crédit d'investissement (moyen et long terme) | E57: 425 | F57: MAD | G57: 20 | P57: 7 · Écart fin O&M / fin de dette (opérateur non remplaçable) | Q57: B185 | R57: =IF(OR($B$184<>"Non",ISNUMBER($B$185)),1,0) -> 0
A58: CR-26-0102 | B58: Crédit relais (TVA, subventions) | E58: 40 | F58: MAD | G58: 2 | P58: 7 · Facteur commun au-delà de la limite interne (C14) | Q58: B186 | R58: =IF($B$186<>"",1,0) -> 0
P59: 8 · Grille : sous-critère requis sans situation choisie | Q59: ="E"&IF(COUNT($P$190:$P$222)=0,191,MIN($P$190:$P$222)) -> 0 | R59: =IF(COUNT($P$190:$P$222)=0,1,0) -> 0
P60: 8 · Commentaire exigé (situation Critique ou Info. insuffisante) | Q60: ="H"&IF(COUNT($T$190:$T$222)=0,191,MIN($T$190:$T$222)) -> 0 | R60: =IF(COUNT($T$190:$T$222)=0,1,0) -> 0
P61: 10 · Verrous X1 à B8 : répondre Oui ou Non | Q61: E243 | R61: =IF(COUNTBLANK($E$243:$E$254)=0,1,0) -> 0
P62: 13 · Synthèse de l'analyste | Q62: B280 | R62: =IF($B$280<>"",1,0) -> 0
A63: Total des crédits de la banque (MMAD, contre-valeur) | E63: =SUM(E57:E62) -> 0 | F63: Écart avec l'exposition (bloc 2) | H63: =IF(OR(N(E63)=0,NOT(ISNUMBER($B$26))),"",E63-$B$26) -> 0 | P63: 13 · Justification des écarts (plafond, verrou ou info. insuffisante) | Q63: B284 | R63: =IF(OR(NOT(OR(COUNTIF($E$258:$E$272,"Oui")>0,COUNTIF($F$243:$F$254,"Oui")>0,SUMPRODUCT(($J$190:$J$222="SC")*($K$190:$K$222=1)*($S$190:$S$222=5))>0,COUNTIF($S$166:$S$168,5)>0)),$B$284<>""),1,0) -> 0
A65: 4 · DONNÉES SECTORIELLES ET HYPOTHÈSES D'EXPLOITATION (information, non calculées)
A66: ="Données du secteur "&IF($B$19="","(choisissez le secteur au bloc 1)",$B$19) -> 0 | B66: Valeur | C66: Unité | D66: Observation ou source
A67: =IF($B$19="",IF(0=0,"Choisissez d'abord le secteur (bloc 1)",""),IFERROR(IF(T(INDEX(R_SecChamps,MATCH($B$19,R_SecCodes,0),1))="","Sans objet pour ce secteur",T(INDEX(R_SecChamps,MATCH($B$19,R_SecCodes,0),1))),"")) -> 0 | B67: 80 | C67: =IFERROR(T(INDEX(R_SecUnites,MATCH($B$19,R_SecCodes,0),1)),"") -> 0
A68: =IF($B$19="",IF(1=0,"Choisissez d'abord le secteur (bloc 1)",""),IFERROR(IF(T(INDEX(R_SecChamps,MATCH($B$19,R_SecCodes,0),2))="","Sans objet pour ce secteur",T(INDEX(R_SecChamps,MATCH($B$19,R_SecCodes,0),2))),"")) -> 0 | B68: 152 | C68: =IFERROR(T(INDEX(R_SecUnites,MATCH($B$19,R_SecCodes,0),2)),"") -> 0
A69: =IF($B$19="",IF(2=0,"Choisissez d'abord le secteur (bloc 1)",""),IFERROR(IF(T(INDEX(R_SecChamps,MATCH($B$19,R_SecCodes,0),3))="","Sans objet pour ce secteur",T(INDEX(R_SecChamps,MATCH($B$19,R_SecCodes,0),3))),"")) -> 0 | B69: 140 | C69: =IFERROR(T(INDEX(R_SecUnites,MATCH($B$19,R_SecCodes,0),3)),"") -> 0
A70: =IF($B$19="",IF(3=0,"Choisissez d'abord le secteur (bloc 1)",""),IFERROR(IF(T(INDEX(R_SecChamps,MATCH($B$19,R_SecCodes,0),4))="","Sans objet pour ce secteur",T(INDEX(R_SecChamps,MATCH($B$19,R_SecCodes,0),4))),"")) -> 0 | B70: 25 | C70: =IFERROR(T(INDEX(R_SecUnites,MATCH($B$19,R_SecCodes,0),4)),"") -> 0
A71: =IF($B$19="",IF(4=0,"Choisissez d'abord le secteur (bloc 1)",""),IFERROR(IF(T(INDEX(R_SecChamps,MATCH($B$19,R_SecCodes,0),5))="","Sans objet pour ce secteur",T(INDEX(R_SecChamps,MATCH($B$19,R_SecCodes,0),5))),"")) -> 0 | B71: 0.48 | C71: =IFERROR(T(INDEX(R_SecUnites,MATCH($B$19,R_SecCodes,0),5)),"") -> 0
A72: =IF($B$19="",IF(5=0,"Choisissez d'abord le secteur (bloc 1)",""),IFERROR(IF(T(INDEX(R_SecChamps,MATCH($B$19,R_SecCodes,0),6))="","Sans objet pour ce secteur",T(INDEX(R_SecChamps,MATCH($B$19,R_SecCodes,0),6))),"")) -> 0 | B72: 0.4 | C72: =IFERROR(T(INDEX(R_SecUnites,MATCH($B$19,R_SecCodes,0),6)),"") -> 0
A73: Autres hypothèses d'exploitation | B73: Valeur
A74: Chiffre d'affaires | B74: 73 MMAD/an
A75: Charges d'exploitation | B75: 11 MMAD/an
A76: EBITDA | B76: 62 MMAD/an
A77: CFADS de référence | B77: 54 MMAD/an
A78: Service de la dette | B78: 38,9 MMAD/an, semestriel
A83: 5 · SEUILS DSCR APPLICABLES = base du régime + Δ secteur + majoration de phase
A84: Seuil critique de base du régime | B84: =IFERROR(INDEX(P_Crit,MATCH($B$18,P_Regimes,0)),"") -> 0
A85: Écart sectoriel Δ | B85: =IFERROR(INDEX(P_SecDelta,MATCH($B$19,P_SecCodes,0)),"") -> 0
A86: Majoration de phase | B86: =IFERROR(INDEX(P_PhaseMaj,MATCH($B$20,P_PhaseCodes,0)),"") -> 0
A87: Seuils applicables | B87: Critique < | C87: Vigilance < | D87: Favorable < | E87: Très favorable ≥
A88: Seuil = base + Δ + majoration | B88: =IFERROR(INDEX(P_Crit,MATCH($B$18,P_Regimes,0))+$B$85+$B$86,"") -> 0 | C88: =IFERROR(INDEX(P_Vig,MATCH($B$18,P_Regimes,0))+$B$85+$B$86,"") -> 0 | D88: =IFERROR(INDEX(P_Fav,MATCH($B$18,P_Regimes,0))+$B$85+$B$86,"") -> 0 | E88: =D88 -> 0
A90: 6 · ÉCHÉANCIER DATÉ ET DSCR PAR ÉCHÉANCE (jusqu'à 60 périodes)
A91: Scénario défavorable : baisse du CFADS appliquée à chaque période | B91: 0.137871 | C91: Production P90 (− 8 %) et charges d’exploitation + 10 %
A92: Période | B92: CFADS central | C92: Service de la dette | D92: DSCR | E92: Classement | F92: CFADS stressé (saisie facultative) | G92: DSCR stressé | H92: DSCR annuel (paire de semestres)
A93: An 1 · S1 | B93: 25.9 | C93: 19.45 | D93: =IF(OR(B93="",C93=""),"",IF(C93=0,"",B93/C93)) -> 0 | E93: =IF(B93="","",IF(C93=0,"Différé",IF(B93<0,"Critique",IF(D93<$B$88,"Critique",IF(D93<$C$88,"Vigilance",IF(D93<$D$88,"Favorable","Très favorable")))))) -> 0 | G93: =IF(OR(B93="",C93="",C93=0),"",IF(F93<>"",F93,B93*(1-$B$91))/C93) -> 0
A94: An 1 · S2 | B94: 28.1 | C94: 19.45 | D94: =IF(OR(B94="",C94=""),"",IF(C94=0,"",B94/C94)) -> 0 | E94: =IF(B94="","",IF(C94=0,"Différé",IF(B94<0,"Critique",IF(D94<$B$88,"Critique",IF(D94<$C$88,"Vigilance",IF(D94<$D$88,"Favorable","Très favorable")))))) -> 0 | G94: =IF(OR(B94="",C94="",C94=0),"",IF(F94<>"",F94,B94*(1-$B$91))/C94) -> 0 | H94: =IF(AND($B$21="Semestrielle",B94<>"",B93<>"",N(C94)+N(C93)>0),(B94+B93)/(C94+C93),"") -> 0
A95: An 10 · S1 | B95: 25.5 | C95: 19.45 | D95: =IF(OR(B95="",C95=""),"",IF(C95=0,"",B95/C95)) -> 0 | E95: =IF(B95="","",IF(C95=0,"Différé",IF(B95<0,"Critique",IF(D95<$B$88,"Critique",IF(D95<$C$88,"Vigilance",IF(D95<$D$88,"Favorable","Très favorable")))))) -> 0 | G95: =IF(OR(B95="",C95="",C95=0),"",IF(F95<>"",F95,B95*(1-$B$91))/C95) -> 0
A96: An 10 · S2 | B96: 27.7 | C96: 19.45 | D96: =IF(OR(B96="",C96=""),"",IF(C96=0,"",B96/C96)) -> 0 | E96: =IF(B96="","",IF(C96=0,"Différé",IF(B96<0,"Critique",IF(D96<$B$88,"Critique",IF(D96<$C$88,"Vigilance",IF(D96<$D$88,"Favorable","Très favorable")))))) -> 0 | G96: =IF(OR(B96="",C96="",C96=0),"",IF(F96<>"",F96,B96*(1-$B$91))/C96) -> 0 | H96: =IF(AND($B$21="Semestrielle",B96<>"",B95<>"",N(C96)+N(C95)>0),(B96+B95)/(C96+C95),"") -> 0
A97: An 20 · S1 | B97: 25.2 | C97: 19.45 | D97: =IF(OR(B97="",C97=""),"",IF(C97=0,"",B97/C97)) -> 0 | E97: =IF(B97="","",IF(C97=0,"Différé",IF(B97<0,"Critique",IF(D97<$B$88,"Critique",IF(D97<$C$88,"Vigilance",IF(D97<$D$88,"Favorable","Très favorable")))))) -> 0 | G97: =IF(OR(B97="",C97="",C97=0),"",IF(F97<>"",F97,B97*(1-$B$91))/C97) -> 0
A98: An 20 · S2 | B98: 27.2 | C98: 19.45 | D98: =IF(OR(B98="",C98=""),"",IF(C98=0,"",B98/C98)) -> 0 | E98: =IF(B98="","",IF(C98=0,"Différé",IF(B98<0,"Critique",IF(D98<$B$88,"Critique",IF(D98<$C$88,"Vigilance",IF(D98<$D$88,"Favorable","Très favorable")))))) -> 0 | G98: =IF(OR(B98="",C98="",C98=0),"",IF(F98<>"",F98,B98*(1-$B$91))/C98) -> 0 | H98: =IF(AND($B$21="Semestrielle",B98<>"",B97<>"",N(C98)+N(C97)>0),(B98+B97)/(C98+C97),"") -> 0
D99: =IF(OR(B99="",C99=""),"",IF(C99=0,"",B99/C99)) -> 0 | E99: =IF(B99="","",IF(C99=0,"Différé",IF(B99<0,"Critique",IF(D99<$B$88,"Critique",IF(D99<$C$88,"Vigilance",IF(D99<$D$88,"Favorable","Très favorable")))))) -> 0 | G99: =IF(OR(B99="",C99="",C99=0),"",IF(F99<>"",F99,B99*(1-$B$91))/C99) -> 0
D100: =IF(OR(B100="",C100=""),"",IF(C100=0,"",B100/C100)) -> 0 | E100: =IF(B100="","",IF(C100=0,"Différé",IF(B100<0,"Critique",IF(D100<$B$88,"Critique",IF(D100<$C$88,"Vigilance",IF(D100<$D$88,"Favorable","Très favorable")))))) -> 0 | G100: =IF(OR(B100="",C100="",C100=0),"",IF(F100<>"",F100,B100*(1-$B$91))/C100) -> 0 | H100: =IF(AND($B$21="Semestrielle",B100<>"",B99<>"",N(C100)+N(C99)>0),(B100+B99)/(C100+C99),"") -> 0
D101: =IF(OR(B101="",C101=""),"",IF(C101=0,"",B101/C101)) -> 0 | E101: =IF(B101="","",IF(C101=0,"Différé",IF(B101<0,"Critique",IF(D101<$B$88,"Critique",IF(D101<$C$88,"Vigilance",IF(D101<$D$88,"Favorable","Très favorable")))))) -> 0 | G101: =IF(OR(B101="",C101="",C101=0),"",IF(F101<>"",F101,B101*(1-$B$91))/C101) -> 0
D102: =IF(OR(B102="",C102=""),"",IF(C102=0,"",B102/C102)) -> 0 | E102: =IF(B102="","",IF(C102=0,"Différé",IF(B102<0,"Critique",IF(D102<$B$88,"Critique",IF(D102<$C$88,"Vigilance",IF(D102<$D$88,"Favorable","Très favorable")))))) -> 0 | G102: =IF(OR(B102="",C102="",C102=0),"",IF(F102<>"",F102,B102*(1-$B$91))/C102) -> 0 | H102: =IF(AND($B$21="Semestrielle",B102<>"",B101<>"",N(C102)+N(C101)>0),(B102+B101)/(C102+C101),"") -> 0
D103: =IF(OR(B103="",C103=""),"",IF(C103=0,"",B103/C103)) -> 0 | E103: =IF(B103="","",IF(C103=0,"Différé",IF(B103<0,"Critique",IF(D103<$B$88,"Critique",IF(D103<$C$88,"Vigilance",IF(D103<$D$88,"Favorable","Très favorable")))))) -> 0 | G103: =IF(OR(B103="",C103="",C103=0),"",IF(F103<>"",F103,B103*(1-$B$91))/C103) -> 0
D104: =IF(OR(B104="",C104=""),"",IF(C104=0,"",B104/C104)) -> 0 | E104: =IF(B104="","",IF(C104=0,"Différé",IF(B104<0,"Critique",IF(D104<$B$88,"Critique",IF(D104<$C$88,"Vigilance",IF(D104<$D$88,"Favorable","Très favorable")))))) -> 0 | G104: =IF(OR(B104="",C104="",C104=0),"",IF(F104<>"",F104,B104*(1-$B$91))/C104) -> 0 | H104: =IF(AND($B$21="Semestrielle",B104<>"",B103<>"",N(C104)+N(C103)>0),(B104+B103)/(C104+C103),"") -> 0
D105: =IF(OR(B105="",C105=""),"",IF(C105=0,"",B105/C105)) -> 0 | E105: =IF(B105="","",IF(C105=0,"Différé",IF(B105<0,"Critique",IF(D105<$B$88,"Critique",IF(D105<$C$88,"Vigilance",IF(D105<$D$88,"Favorable","Très favorable")))))) -> 0 | G105: =IF(OR(B105="",C105="",C105=0),"",IF(F105<>"",F105,B105*(1-$B$91))/C105) -> 0
D106: =IF(OR(B106="",C106=""),"",IF(C106=0,"",B106/C106)) -> 0 | E106: =IF(B106="","",IF(C106=0,"Différé",IF(B106<0,"Critique",IF(D106<$B$88,"Critique",IF(D106<$C$88,"Vigilance",IF(D106<$D$88,"Favorable","Très favorable")))))) -> 0 | G106: =IF(OR(B106="",C106="",C106=0),"",IF(F106<>"",F106,B106*(1-$B$91))/C106) -> 0 | H106: =IF(AND($B$21="Semestrielle",B106<>"",B105<>"",N(C106)+N(C105)>0),(B106+B105)/(C106+C105),"") -> 0
...

Sheet C2
A1: CAS 2 · Usine de dessalement 100 000 m³/jour | J1: DOSSIER_V8 | K1: V3
A2: SPV « Aqua Souss » SA (fictive) — Littoral de Souss-Massa
A3: Usine d'osmose inverse rémunérée par une redevance de capacité versée par l'acheteur public, assortie d'une redevance variable répercutant le coût de l'énergie dans une limite plafonnée.
A4: À SAISIR (cellules orange) | B4: =COUNTIF($R$14:$R$63,0) -> 0 | C4: =IF(B4=0,"Saisie complète : lisez la note ci-dessous, puis « Fiche comité ».","Prochaine saisie : "&INDEX($P$14:$P$63,MATCH(0,$R$14:$R$63,0))) -> 0 | G4: =IF(B4=0,"",HYPERLINK("#"&INDEX($Q$14:$Q$63,MATCH(0,$R$14:$R$63,0)),"→ Aller à la cellule "&INDEX($Q$14:$Q$63,MATCH(0,$R$14:$R$63,0)))) -> 0
A5: ="TABLEAU DE BORD — "&IF($B$17="","code projet à saisir",$B$17)&" · client "&IF($B$15="","—",$B$15)&" · radical "&IF($B$16="","—",$B$16) -> 0
A6: NOTE APPROUVÉE (1 à 10) | B6: =B276 -> 0 | C6: Libellé | D6: =IFERROR(INDEX(P_ConvLib,MATCH(B276,P_ConvNote,0)),"") -> 0 | E6: Statut | F6: =B277 -> 0
A7: Score global (sur 100) | B7: =B238 -> 0 | C7: Note calculée | D7: =B239 -> 0 | E7: Plafond applicable | F7: =IF(B273>=10,"Aucun (10)",B273) -> 0
A8: Plafonds actifs | B8: =IF(TRIM(IF(E258="Oui","C1 ("&F258&") ","")&IF(E259="Oui","C2 ("&F259&") ","")&IF(E260="Oui","C3 ("&F260&") ","")&IF(E261="Oui","C4 ("&F261&") ","")&IF(E262="Oui","C5 ("&F262&") ","")&IF(E263="Oui","C6 ("&F263&") ","")&IF(E264="Oui","C7 ("&F264&") ","")&IF(E265="Oui","C8 ("&F265&") ","")&IF(E266="Oui","C9 ("&F266&") ","")&IF(E267="Oui","C10 ("&F267&") ","")&IF(E268="Oui","C11 ("&F268&") ","")&IF(E269="Oui","C12 ("&F269&") ","")&IF(E270="Oui","C13 ("&F270&") ","")&IF(E271="Oui","C14 ("&F271&") ","")&IF(E272="Oui","C15 ("&F272&") ",""))="","Aucun",TRIM(IF(E258="Oui","C1 ("&F258&") ","")&IF(E259="Oui","C2 ("&F259&") ","")&IF(E260="Oui","C3 ("&F260&") ","")&IF(E261="Oui","C4 ("&F261&") ","")&IF(E262="Oui","C5 ("&F262&") ","")&IF(E263="Oui","C6 ("&F263&") ","")&IF(E264="Oui","C7 ("&F264&") ","")&IF(E265="Oui","C8 ("&F265&") ","")&IF(E266="Oui","C9 ("&F266&") ","")&IF(E267="Oui","C10 ("&F267&") ","")&IF(E268="Oui","C11 ("&F268&") ","")&IF(E269="Oui","C12 ("&F269&") ","")&IF(E270="Oui","C13 ("&F270&") ","")&IF(E271="Oui","C14 ("&F271&") ","")&IF(E272="Oui","C15 ("&F272&") ","")))&IF(COUNTIF(E258:E272,"n.r.")>0," — "&COUNTIF(E258:E272,"n.r.")&" plafond(s) non évalué(s) faute de donnée","") -> 0
A9: Verrous actifs (exclusions X, blocages B) | B9: =IF(TRIM(IF(F243="Oui","X1 ","")&IF(F244="Oui","X2 ","")&IF(F245="Oui","X3 ","")&IF(F246="Oui","X4 ","")&IF(F247="Oui","B1 ","")&IF(F248="Oui","B2 ","")&IF(F249="Oui","B3 ","")&IF(F250="Oui","B4 ","")&IF(F251="Oui","B5 ","")&IF(F252="Oui","B6 ","")&IF(F253="Oui","B7 ","")&IF(F254="Oui","B8 ",""))="","Aucun",TRIM(IF(F243="Oui","X1 ","")&IF(F244="Oui","X2 ","")&IF(F245="Oui","X3 ","")&IF(F246="Oui","X4 ","")&IF(F247="Oui","B1 ","")&IF(F248="Oui","B2 ","")&IF(F249="Oui","B3 ","")&IF(F250="Oui","B4 ","")&IF(F251="Oui","B5 ","")&IF(F252="Oui","B6 ","")&IF(F253="Oui","B7 ","")&IF(F254="Oui","B8 ",""))) -> 0
A10: Régime de proportionnalité retenu | B10: =B38 -> 0 | C10: DSCR minimum | D10: =D154 -> 0 | E10: DSCR stressé min. | F10: =D155 -> 0
A11: Complétude (noyau N1-N6 et grille) | B11: =B225 -> 0 | C11: Noyau financier D7 | D11: =D169 -> 0 | E11: Orientation | F11: =IFERROR(INDEX(P_ConvOrient,MATCH(B276,P_ConvNote,0)),"") -> 0
A12: Aller à la section : | B12: =HYPERLINK("#A13","1 · Identification") -> 0 | C12: =HYPERLINK("#A40","3 · Sources") -> 0 | D12: =HYPERLINK("#A90","6 · Échéancier") -> 0 | E12: =HYPERLINK("#A161","7 · Noyau") -> 0 | F12: =HYPERLINK("#A188","8 · Grille") -> 0 | G12: =HYPERLINK("#A256","11 · Plafonds") -> 0 | H12: =HYPERLINK("#A279","13 · Commentaires") -> 0
A13: 1 · IDENTIFICATION ET ROUTAGE — codes du client et du projet ; le routage pilote seuils et poids
A14: Axe | B14: Valeur | C14: Libellé, contrôle | P14: 1 · Code client T24 | Q14: B15 | R14: =IF(AND(LEN(TRIM($B$15))>=1,LEN($B$15)<=20),1,0) -> 0
A15: Code client T24 (société de projet) | B15: 20058316 | C15: =IF(B15="","À saisir — Texte, zéros de tête conservés.",IF(AND(LEN(TRIM(B15))>=1,LEN(B15)<=20),"Format conforme.","Format non conforme : Texte, zéros de tête conservés.")) -> 0 | P15: 1 · Radical du client (7 chiffres) | Q15: B16 | R15: =IF(AND(LEN($B$16)=7,SUMPRODUCT(--ISNUMBER(FIND(MID($B$16,ROW(INDIRECT("1:7"))+0,1),"0123456789")))=7),1,0) -> 0
A16: Radical du client (7 chiffres) | B16: 0058316 | C16: =IF(B16="","À saisir — Exactement 7 chiffres, zéros de tête compris.",IF(AND(LEN(B16)=7,SUMPRODUCT(--ISNUMBER(FIND(MID(B16,ROW(INDIRECT("1:7"))+0,1),"0123456789")))=7),"Format conforme.","Format non conforme : Exactement 7 chiffres, zéros de tête compris.")) -> 0 | P16: 1 · Code projet (PF-AAAA-NNNN) | Q16: B17 | R16: =IF(AND(LEN($B$17)=12,EXACT(LEFT($B$17,3),"PF-"),MID($B$17,8,1)="-",SUMPRODUCT(--ISNUMBER(FIND(MID($B$17,ROW(INDIRECT("1:4"))+3,1),"0123456789")))=4,SUMPRODUCT(--ISNUMBER(FIND(MID($B$17,ROW(INDIRECT("1:4"))+8,1),"0123456789")))=4),1,0) -> 0
A17: Code projet | B17: PF-2026-0002 | C17: =IF(B17="","À saisir — Format PF-AAAA-NNNN.",IF(AND(LEN(B17)=12,EXACT(LEFT(B17,3),"PF-"),MID(B17,8,1)="-",SUMPRODUCT(--ISNUMBER(FIND(MID(B17,ROW(INDIRECT("1:4"))+3,1),"0123456789")))=4,SUMPRODUCT(--ISNUMBER(FIND(MID(B17,ROW(INDIRECT("1:4"))+8,1),"0123456789")))=4),"Format conforme.","Format non conforme : Format PF-AAAA-NNNN.")) -> 0 | P17: 1 · Régime de revenus | Q17: B18 | R17: =IF($B$18<>"",1,0) -> 0
A18: C — Régime de revenus | B18: R2 | C18: =IFERROR(INDEX(P_RegLib,MATCH(B18,P_Regimes,0)),"") -> 0 | P18: 1 · Secteur du projet | Q18: B19 | R18: =IF($B$19<>"",1,0) -> 0
A19: D — Secteur du projet | B19: EAU | C19: =IFERROR(INDEX(P_SecLib,MATCH(B19,P_SecCodes,0)),"") -> 0 | P19: 1 · Phase du projet | Q19: B20 | R19: =IF($B$20<>"",1,0) -> 0
A20: B — Phase | B20: P2 | C20: =IFERROR(INDEX(P_PhaseLib,MATCH(B20,P_PhaseCodes,0)),"") -> 0 | P20: 1 · Périodicité des échéances | Q20: B21 | R20: =IF($B$21<>"",1,0) -> 0
A21: Périodicité du service de la dette | B21: Semestrielle | C21: Jamais annuelle : le DSCR se mesure échéance par échéance. | P21: 2 · Exposition de la banque (MMAD) | Q21: B26 | R21: =IF(ISNUMBER($B$26),1,0) -> 0
A22: A — Famille de financement | B22: PF-FLUX | C22: SPV dédiée, remboursement par les flux du projet (R5 vente d'actifs : hors outil). | P22: 2 · Recettes, coûts et dette en dirhams ? | Q22: B27 | R22: =IF($B$27<>"",1,0) -> 0
P23: 2 · Durée du financement (ans) | Q23: B28 | R23: =IF(ISNUMBER($B$28),1,0) -> 0
A24: 2 · RÉGIME DE PROPORTIONNALITÉ — calculé, jamais choisi | P24: 2 · Technologie éprouvée ? | Q24: B29 | R24: =IF($B$29<>"",1,0) -> 0
A25: CAPEX du projet économique complet (MMAD) | B25: =B50 -> 0 | C25: Repris du total des emplois (section 3). | P25: 2 · EPC clé-en-main de moins de 18 mois ? (phase P1) | Q25: B30 | R25: =IF(OR(NOT($B$20="P1"),$B$30<>""),1,0) -> 0
A26: Exposition de la banque (MMAD) | B26: 420 | P26: 2 · Acheteur principal unique ? | Q26: B31 | R26: =IF($B$31<>"",1,0) -> 0
A27: Recettes, coûts et dette intégralement en dirhams | B27: Non | P27: 2 · Première référence technologique ? | Q27: B32 | R27: =IF($B$32<>"",1,0) -> 0
A28: Durée du financement (ans) | B28: 20 | P28: 2 · Opération consortiale ? | Q28: B33 | R28: =IF($B$33<>"",1,0) -> 0
A29: Technologie : ≥ 3 références industrielles de plus de 3 ans | B29: Oui | P29: 2 · Contrat de revenus de plus de 20 ans ? | Q29: B34 | R29: =IF($B$34<>"",1,0) -> 0
A30: En P1 : EPC clé-en-main forfaitaire, prix et délai garantis, < 18 mois | B30: Non | P30: 2 · Site à risque climatique élevé ? | Q30: B35 | R30: =IF($B$35<>"",1,0) -> 0
A31: Acheteur principal unique et identifié | B31: Oui | P31: 2 · Nombre de contreparties clés | Q31: B36 | R31: =IF(ISNUMBER($B$36),1,0) -> 0
A32: Technologie constituant une première référence dans la juridiction | B32: Non | P32: 3 · Emplois : montants du besoin à terminaison | Q32: B42 | R32: =IF(N($B$50)>0,1,0) -> 0
A33: Opération consortiale relevant de la directive 3/W/2025 | B33: Oui | P33: 3 · Ressources engagées : montants | Q33: E42 | R33: =IF(N($E$50)>0,1,0) -> 0
A34: Concession ou contrat de revenus de plus de 20 ans | B34: Oui | P34: 3 · Nature de chaque ressource | Q34: F42 | R34: =IF(SUMPRODUCT(ISNUMBER($E$42:$E$49)*($F$42:$F$49=""))=0,1,0) -> 0
A35: Site classé à risque climatique physique élevé | B35: Non | P35: 3 · Plan de remédiation (couverture entre 95 et 100 %) | Q35: B53 | R35: =IF(OR(NOT(AND($B$20="P1",ISNUMBER($B$51),N($B$51)>=P_N3_V,N($B$51)<P_N3_F)),$B$53<>""),1,0) -> 0
A36: Nombre de contreparties clés | B36: 4 | P36: 6 · Choc du scénario défavorable (%) | Q36: B91 | R36: =IF(ISNUMBER($B$91),1,0) -> 0
A37: Régime calculé (avant escalade) | B37: =IF(OR(B25="",B25=0,B18=""),"",IF(OR(B25>P_L_CAPEX,N(B26)>P_L_EXPO,B18="R4",B32="Oui",N(B174)>0,B33="Oui",B34="Oui",B35="Oui",N(B36)>P_L_NBCP),"L",IF(AND(B25<=P_S_CAPEX,B26<>"",N(B26)<=P_S_EXPO,OR(B18="R1",B18="R2"),B29="Oui",B27="Oui",B28<>"",N(B28)<=P_S_DUREE,OR(B20<>"P1",B30="Oui"),B31="Oui",COUNTIF($F$243:$F$254,"Oui")=0),"S","M"))) -> 0 | C37: =IF(B37="","",IF(B37="L","Escalade : "&IF(B25>P_L_CAPEX,"CAPEX > "&P_L_CAPEX&" MMAD ; ","")&IF(N(B26)>P_L_EXPO,"exposition > "&P_L_EXPO&" MMAD ; ","")&IF(B18="R4","régime de revenus R4 ; ","")&IF(B32="Oui","première référence technologique ; ","")&IF(N(B174)>0,"devises non intégralement couvertes ; ","")&IF(B33="Oui","opération consortiale ; ","")&IF(B34="Oui","contrat de revenus > 20 ans ; ","")&IF(B35="Oui","risque climatique élevé ; ","")&IF(N(B36)>P_L_NBCP,"plus de "&P_L_NBCP&" contreparties clés ; ",""),IF(B37="S","Toutes les conditions du régime simplifié sont réunies.","Régime standard par défaut : une condition du régime S manque, aucune condition d'escalade."))) -> 0 | P37: 6 · Échéancier : CFADS d'au moins deux périodes | Q37: B93 | R37: =IF(COUNT($B$93:$B$152)>=2,1,0) -> 0
A38: RÉGIME RETENU (après escalade automatique) | B38: =IF(B37="","",IF(AND(IF(AND(B37="S",COUNTIF($F$243:$F$254,"Oui")>0),"M",B37)="M",COUNTIF($E$258:$E$272,"Oui")>0),"L",IF(AND(B37="S",COUNTIF($F$243:$F$254,"Oui")>0),"M",B37))) -> 0 | C38: =IF(B38=B37,"Aucune escalade.",IF(B38="L","Escalade : un plafond de note est actif (M passe en L).","Escalade : un verrou est actif (S passe en M).")) -> 0 | P38: 6 · Service de la dette de chaque période | Q38: C93 | R38: =IF(SUMPRODUCT(ISNUMBER($B$93:$B$152)*(1-ISNUMBER($C$93:$C$152)))=0,1,0) -> 0
P39: 7 · N4 — Liquidité : situation à choisir | Q39: E166 | R39: =IF($B$166<>"",1,0) -> 0
A40: 3 · SOURCES ET EMPLOIS (MMAD) — test de financement à terminaison ; crédits de la banque | P40: 7 · N5 — Levier : situation à choisir | Q40: E167 | R40: =IF($B$167<>"",1,0) -> 0
A41: Emplois | B41: Montant | D41: Ressources | E41: Montant | F41: Nature | P41: 7 · N6 — Exposition résiduelle : situation à choisir | Q41: E168 | R41: =IF($B$168<>"",1,0) -> 0
A42: Contrat EPC (prise d’eau, osmose inverse, rejet) | B42: 1780 | D42: Dette senior (20 ans, 6,0 %), dont 35 % en euros | E42: 1680 | F42: Dette senior | P42: 7 · Justification exigée (N4 à N6 Critique ou Info. insuffisante) | Q42: ="H"&IF(COUNT($T$166:$T$168)=0,166,MIN($T$166:$T$168)) -> 0 | R42: =IF(COUNT($T$166:$T$168)=0,1,0) -> 0
A43: Canalisations et raccordement électrique | B43: 240 | D43: Fonds propres | E43: 720 | F43: Fonds propres | P43: 7 · N3 hors phase P1 : note LLCR | Q43: B171 | R43: =IF(OR($B$20="P1",$B$171<>""),1,0) -> 0
A44: Développement, frais et assurances | B44: 95 | P44: 7 · LLCR (plafond C4) | Q44: B172 | R44: =IF(ISNUMBER($B$172),1,0) -> 0
A45: Contingence | B45: 110 | P45: 7 · DSRA en mois (plafond C7) | Q45: B173 | R45: =IF(ISNUMBER($B$173),1,0) -> 0
A46: Intérêts intercalaires | B46: 100 | P46: 7 · Exposition nette en devises (plafond C6) | Q46: B174 | R46: =IF(ISNUMBER($B$174),1,0) -> 0
A47: Dotation initiale DSRA | B47: 50 | P47: 7 · Dette à refinancer à maturité (plafond C8) | Q47: B175 | R47: =IF(ISNUMBER($B$175),1,0) -> 0
A48: BFR de démarrage | B48: 25 | P48: 7 · Stratégie de refinancement approuvée ? | Q48: B176 | R48: =IF(OR(N($B$175)<=P_C8,$B$176<>""),1,0) -> 0
P49: 7 · Part des recettes de l'acheteur principal (C10) | Q49: B177 | R49: =IF(ISNUMBER($B$177),1,0) -> 0
A50: Total emplois (besoin à terminaison) | B50: =SUM(B42:B49) -> 0 | D50: Total ressources engagées | E50: =SUM(E42:E49) -> 0 | P50: 7 · Qualité de crédit de l'acheteur principal | Q50: B178 | R50: =IF($B$178<>"",1,0) -> 0
A51: Couverture du besoin à terminaison (ressources / emplois) | B51: =IF(N(B50)=0,"",E50/B50) -> 0 | P51: 7 · Durée résiduelle du contrat de revenus (C5) | Q51: B179 | R51: =IF(OR($B$18="R4",ISNUMBER($B$179)),1,0) -> 0
A52: Quote-part de dette (dette / besoin à terminaison) | B52: =IF(N(B50)=0,"",(SUMIF(F42:F49,"Dette senior",E42:E49)+SUMIF(F42:F49,"Dette subordonnée",E42:E49))/B50) -> 0 | P52: 7 · Durée résiduelle de la dette | Q52: B180 | R52: =IF(ISNUMBER($B$180),1,0) -> 0
A53: Plan de remédiation approuvé (couverture entre 95 % et 100 %) | B53: Non | P53: 7 · Solution documentée (contrat plus court que la dette) ? | Q53: B181 | R53: =IF(OR(NOT(AND(ISNUMBER($B$179),ISNUMBER($B$180))),N($B$179)>=N($B$180),$B$181<>""),1,0) -> 0
P54: 7 · Plan d'adaptation climatique financé ? (C11) | Q54: B182 | R54: =IF(OR($B$35<>"Oui",$B$182<>""),1,0) -> 0
A55: Crédits de la banque sur le projet — un projet peut porter plusieurs dossiers de crédit | P55: 7 · Capacité résiduelle du sponsor (C12) | Q55: B183 | R55: =IF($B$183<>"",1,0) -> 0
A56: Numéro du dossier de crédit | B56: Nature | E56: Montant (MMAD) | F56: Devise | G56: Durée (ans) | H56: Observation | P56: 7 · Opérateur remplaçable ? (C13) | Q56: B184 | R56: =IF($B$184<>"",1,0) -> 0
A57: CR-26-0201 | B57: Crédit d'investissement (moyen et long terme) | E57: 270 | F57: MAD | G57: 20 | P57: 7 · Écart fin O&M / fin de dette (opérateur non remplaçable) | Q57: B185 | R57: =IF(OR($B$184<>"Non",ISNUMBER($B$185)),1,0) -> 0
A58: CR-26-0202 | B58: Crédit d'investissement (moyen et long terme) | E58: 150 | F58: EUR | G58: 20 | P58: 7 · Facteur commun au-delà de la limite interne (C14) | Q58: B186 | R58: =IF($B$186<>"",1,0) -> 0
P59: 8 · Grille : sous-critère requis sans situation choisie | Q59: ="E"&IF(COUNT($P$190:$P$222)=0,191,MIN($P$190:$P$222)) -> 0 | R59: =IF(COUNT($P$190:$P$222)=0,1,0) -> 0
P60: 8 · Commentaire exigé (situation Critique ou Info. insuffisante) | Q60: ="H"&IF(COUNT($T$190:$T$222)=0,191,MIN($T$190:$T$222)) -> 0 | R60: =IF(COUNT($T$190:$T$222)=0,1,0) -> 0
P61: 10 · Verrous X1 à B8 : répondre Oui ou Non | Q61: E243 | R61: =IF(COUNTBLANK($E$243:$E$254)=0,1,0) -> 0
P62: 13 · Synthèse de l'analyste | Q62: B280 | R62: =IF($B$280<>"",1,0) -> 0
A63: Total des crédits de la banque (MMAD, contre-valeur) | E63: =SUM(E57:E62) -> 0 | F63: Écart avec l'exposition (bloc 2) | H63: =IF(OR(N(E63)=0,NOT(ISNUMBER($B$26))),"",E63-$B$26) -> 0 | P63: 13 · Justification des écarts (plafond, verrou ou info. insuffisante) | Q63: B284 | R63: =IF(OR(NOT(OR(COUNTIF($E$258:$E$272,"Oui")>0,COUNTIF($F$243:$F$254,"Oui")>0,SUMPRODUCT(($J$190:$J$222="SC")*($K$190:$K$222=1)*($S$190:$S$222=5))>0,COUNTIF($S$166:$S$168,5)>0)),$B$284<>""),1,0) -> 0
A65: 4 · DONNÉES SECTORIELLES ET HYPOTHÈSES D'EXPLOITATION (information, non calculées)
A66: ="Données du secteur "&IF($B$19="","(choisissez le secteur au bloc 1)",$B$19) -> 0 | B66: Valeur | C66: Unité | D66: Observation ou source
A67: =IF($B$19="",IF(0=0,"Choisissez d'abord le secteur (bloc 1)",""),IFERROR(IF(T(INDEX(R_SecChamps,MATCH($B$19,R_SecCodes,0),1))="","Sans objet pour ce secteur",T(INDEX(R_SecChamps,MATCH($B$19,R_SecCodes,0),1))),"")) -> 0 | B67: 100000 | C67: =IFERROR(T(INDEX(R_SecUnites,MATCH($B$19,R_SecCodes,0),1)),"") -> 0
A68: =IF($B$19="",IF(1=0,"Choisissez d'abord le secteur (bloc 1)",""),IFERROR(IF(T(INDEX(R_SecChamps,MATCH($B$19,R_SecCodes,0),2))="","Sans objet pour ce secteur",T(INDEX(R_SecChamps,MATCH($B$19,R_SecCodes,0),2))),"")) -> 0 | B68: 3.6 | C68: =IFERROR(T(INDEX(R_SecUnites,MATCH($B$19,R_SecCodes,0),2)),"") -> 0
A69: =IF($B$19="",IF(2=0,"Choisissez d'abord le secteur (bloc 1)",""),IFERROR(IF(T(INDEX(R_SecChamps,MATCH($B$19,R_SecCodes,0),3))="","Sans objet pour ce secteur",T(INDEX(R_SecChamps,MATCH($B$19,R_SecCodes,0),3))),"")) -> 0 | B69: 83 | C69: =IFERROR(T(INDEX(R_SecUnites,MATCH($B$19,R_SecCodes,0),3)),"") -> 0
A70: =IF($B$19="",IF(3=0,"Choisissez d'abord le secteur (bloc 1)",""),IFERROR(IF(T(INDEX(R_SecChamps,MATCH($B$19,R_SecCodes,0),4))="","Sans objet pour ce secteur",T(INDEX(R_SecChamps,MATCH($B$19,R_SecCodes,0),4))),"")) -> 0 | B70: 60 | C70: =IFERROR(T(INDEX(R_SecUnites,MATCH($B$19,R_SecCodes,0),4)),"") -> 0
A71: =IF($B$19="",IF(4=0,"Choisissez d'abord le secteur (bloc 1)",""),IFERROR(IF(T(INDEX(R_SecChamps,MATCH($B$19,R_SecCodes,0),5))="","Sans objet pour ce secteur",T(INDEX(R_SecChamps,MATCH($B$19,R_SecCodes,0),5))),"")) -> 0 | B71: 25 | C71: =IFERROR(T(INDEX(R_SecUnites,MATCH($B$19,R_SecCodes,0),5)),"") -> 0
A72: =IF($B$19="",IF(5=0,"Choisissez d'abord le secteur (bloc 1)",""),IFERROR(IF(T(INDEX(R_SecChamps,MATCH($B$19,R_SecCodes,0),6))="","Sans objet pour ce secteur",T(INDEX(R_SecChamps,MATCH($B$19,R_SecCodes,0),6))),"")) -> 0 | C72: =IFERROR(T(INDEX(R_SecUnites,MATCH($B$19,R_SecCodes,0),6)),"") -> 0
A73: Autres hypothèses d'exploitation | B73: Valeur
A74: Redevance de capacité | B74: 290 MMAD/an
A75: Charges hors énergie | B75: 60 MMAD/an
A76: EBITDA | B76: 230 MMAD/an
A77: CFADS à régime établi | B77: 196 MMAD/an
A78: Service de la dette | B78: 146,5 MMAD/an, semestriel
A83: 5 · SEUILS DSCR APPLICABLES = base du régime + Δ secteur + majoration de phase
A84: Seuil critique de base du régime | B84: =IFERROR(INDEX(P_Crit,MATCH($B$18,P_Regimes,0)),"") -> 0
A85: Écart sectoriel Δ | B85: =IFERROR(INDEX(P_SecDelta,MATCH($B$19,P_SecCodes,0)),"") -> 0
A86: Majoration de phase | B86: =IFERROR(INDEX(P_PhaseMaj,MATCH($B$20,P_PhaseCodes,0)),"") -> 0
A87: Seuils applicables | B87: Critique < | C87: Vigilance < | D87: Favorable < | E87: Très favorable ≥
A88: Seuil = base + Δ + majoration | B88: =IFERROR(INDEX(P_Crit,MATCH($B$18,P_Regimes,0))+$B$85+$B$86,"") -> 0 | C88: =IFERROR(INDEX(P_Vig,MATCH($B$18,P_Regimes,0))+$B$85+$B$86,"") -> 0 | D88: =IFERROR(INDEX(P_Fav,MATCH($B$18,P_Regimes,0))+$B$85+$B$86,"") -> 0 | E88: =D88 -> 0
A90: 6 · ÉCHÉANCIER DATÉ ET DSCR PAR ÉCHÉANCE (jusqu'à 60 périodes)
A91: Scénario défavorable : baisse du CFADS appliquée à chaque période | B91: 0.109606 | C91: Coût de l’énergie + 15 % répercuté à 60 % seulement, disponibilité ramenée à 92 %
A92: Période | B92: CFADS central | C92: Service de la dette | D92: DSCR | E92: Classement | F92: CFADS stressé (saisie facultative) | G92: DSCR stressé | H92: DSCR annuel (paire de semestres)
A93: An 1 · S1 (disponibilité 94 %) | B93: 90 | C93: 73.25 | D93: =IF(OR(B93="",C93=""),"",IF(C93=0,"",B93/C93)) -> 0 | E93: =IF(B93="","",IF(C93=0,"Différé",IF(B93<0,"Critique",IF(D93<$B$88,"Critique",IF(D93<$C$88,"Vigilance",IF(D93<$D$88,"Favorable","Très favorable")))))) -> 0 | G93: =IF(OR(B93="",C93="",C93=0),"",IF(F93<>"",F93,B93*(1-$B$91))/C93) -> 0
A94: An 1 · S2 (disponibilité 95 %) | B94: 93 | C94: 73.25 | D94: =IF(OR(B94="",C94=""),"",IF(C94=0,"",B94/C94)) -> 0 | E94: =IF(B94="","",IF(C94=0,"Différé",IF(B94<0,"Critique",IF(D94<$B$88,"Critique",IF(D94<$C$88,"Vigilance",IF(D94<$D$88,"Favorable","Très favorable")))))) -> 0 | G94: =IF(OR(B94="",C94="",C94=0),"",IF(F94<>"",F94,B94*(1-$B$91))/C94) -> 0 | H94: =IF(AND($B$21="Semestrielle",B94<>"",B93<>"",N(C94)+N(C93)>0),(B94+B93)/(C94+C93),"") -> 0
A95: An 3 · S1 (régime établi) | B95: 97 | C95: 73.25 | D95: =IF(OR(B95="",C95=""),"",IF(C95=0,"",B95/C95)) -> 0 | E95: =IF(B95="","",IF(C95=0,"Différé",IF(B95<0,"Critique",IF(D95<$B$88,"Critique",IF(D95<$C$88,"Vigilance",IF(D95<$D$88,"Favorable","Très favorable")))))) -> 0 | G95: =IF(OR(B95="",C95="",C95=0),"",IF(F95<>"",F95,B95*(1-$B$91))/C95) -> 0
A96: An 3 · S2 (régime établi) | B96: 99 | C96: 73.25 | D96: =IF(OR(B96="",C96=""),"",IF(C96=0,"",B96/C96)) -> 0 | E96: =IF(B96="","",IF(C96=0,"Différé",IF(B96<0,"Critique",IF(D96<$B$88,"Critique",IF(D96<$C$88,"Vigilance",IF(D96<$D$88,"Favorable","Très favorable")))))) -> 0 | G96: =IF(OR(B96="",C96="",C96=0),"",IF(F96<>"",F96,B96*(1-$B$91))/C96) -> 0 | H96: =IF(AND($B$21="Semestrielle",B96<>"",B95<>"",N(C96)+N(C95)>0),(B96+B95)/(C96+C95),"") -> 0
D97: =IF(OR(B97="",C97=""),"",IF(C97=0,"",B97/C97)) -> 0 | E97: =IF(B97="","",IF(C97=0,"Différé",IF(B97<0,"Critique",IF(D97<$B$88,"Critique",IF(D97<$C$88,"Vigilance",IF(D97<$D$88,"Favorable","Très favorable")))))) -> 0 | G97: =IF(OR(B97="",C97="",C97=0),"",IF(F97<>"",F97,B97*(1-$B$91))/C97) -> 0
D98: =IF(OR(B98="",C98=""),"",IF(C98=0,"",B98/C98)) -> 0 | E98: =IF(B98="","",IF(C98=0,"Différé",IF(B98<0,"Critique",IF(D98<$B$88,"Critique",IF(D98<$C$88,"Vigilance",IF(D98<$D$88,"Favorable","Très favorable")))))) -> 0 | G98: =IF(OR(B98="",C98="",C98=0),"",IF(F98<>"",F98,B98*(1-$B$91))/C98) -> 0 | H98: =IF(AND($B$21="Semestrielle",B98<>"",B97<>"",N(C98)+N(C97)>0),(B98+B97)/(C98+C97),"") -> 0
D99: =IF(OR(B99="",C99=""),"",IF(C99=0,"",B99/C99)) -> 0 | E99: =IF(B99="","",IF(C99=0,"Différé",IF(B99<0,"Critique",IF(D99<$B$88,"Critique",IF(D99<$C$88,"Vigilance",IF(D99<$D$88,"Favorable","Très favorable")))))) -> 0 | G99: =IF(OR(B99="",C99="",C99=0),"",IF(F99<>"",F99,B99*(1-$B$91))/C99) -> 0
D100: =IF(OR(B100="",C100=""),"",IF(C100=0,"",B100/C100)) -> 0 | E100: =IF(B100="","",IF(C100=0,"Différé",IF(B100<0,"Critique",IF(D100<$B$88,"Critique",IF(D100<$C$88,"Vigilance",IF(D100<$D$88,"Favorable","Très favorable")))))) -> 0 | G100: =IF(OR(B100="",C100="",C100=0),"",IF(F100<>"",F100,B100*(1-$B$91))/C100) -> 0 | H100: =IF(AND($B$21="Semestrielle",B100<>"",B99<>"",N(C100)+N(C99)>0),(B100+B99)/(C100+C99),"") -> 0
D101: =IF(OR(B101="",C101=""),"",IF(C101=0,"",B101/C101)) -> 0 | E101: =IF(B101="","",IF(C101=0,"Différé",IF(B101<0,"Critique",IF(D101<$B$88,"Critique",IF(D101<$C$88,"Vigilance",IF(D101<$D$88,"Favorable","Très favorable")))))) -> 0 | G101: =IF(OR(B101="",C101="",C101=0),"",IF(F101<>"",F101,B101*(1-$B$91))/C101) -> 0
D102: =IF(OR(B102="",C102=""),"",IF(C102=0,"",B102/C102)) -> 0 | E102: =IF(B102="","",IF(C102=0,"Différé",IF(B102<0,"Critique",IF(D102<$B$88,"Critique",IF(D102<$C$88,"Vigilance",IF(D102<$D$88,"Favorable","Très favorable")))))) -> 0 | G102: =IF(OR(B102="",C102="",C102=0),"",IF(F102<>"",F102,B102*(1-$B$91))/C102) -> 0 | H102: =IF(AND($B$21="Semestrielle",B102<>"",B101<>"",N(C102)+N(C101)>0),(B102+B101)/(C102+C101),"") -> 0
D103: =IF(OR(B103="",C103=""),"",IF(C103=0,"",B103/C103)) -> 0 | E103: =IF(B103="","",IF(C103=0,"Différé",IF(B103<0,"Critique",IF(D103<$B$88,"Critique",IF(D103<$C$88,"Vigilance",IF(D103<$D$88,"Favorable","Très favorable")))))) -> 0 | G103: =IF(OR(B103="",C103="",C103=0),"",IF(F103<>"",F103,B103*(1-$B$91))/C103) -> 0
D104: =IF(OR(B104="",C104=""),"",IF(C104=0,"",B104/C104)) -> 0 | E104: =IF(B104="","",IF(C104=0,"Différé",IF(B104<0,"Critique",IF(D104<$B$88,"Critique",IF(D104<$C$88,"Vigilance",IF(D104<$D$88,"Favorable","Très favorable")))))) -> 0 | G104: =IF(OR(B104="",C104="",C104=0),"",IF(F104<>"",F104,B104*(1-$B$91))/C104) -> 0 | H104: =IF(AND($B$21="Semestrielle",B104<>"",B103<>"",N(C104)+N(C103)>0),(B104+B103)/(C104+C103),"") -> 0
D105: =IF(OR(B105="",C105=""),"",IF(C105=0,"",B105/C105)) -> 0 | E105: =IF(B105="","",IF(C105=0,"Différé",IF(B105<0,"Critique",IF(D105<$B$88,"Critique",IF(D105<$C$88,"Vigilance",IF(D105<$D$88,"Favorable","Très favorable")))))) -> 0 | G105: =IF(OR(B105="",C105="",C105=0),"",IF(F105<>"",F105,B105*(1-$B$91))/C105) -> 0
D106: =IF(OR(B106="",C106=""),"",IF(C106=0,"",B106/C106)) -> 0 | E106: =IF(B106="","",IF(C106=0,"Différé",IF(B106<0,"Critique",IF(D106<$B$88,"Critique",IF(D106<$C$88,"Vigilance",IF(D106<$D$88,"Favorable","Très favorable")))))) -> 0 | G106: =IF(OR(B106="",C106="",C106=0),"",IF(F106<>"",F106,B106*(1-$B$91))/C106) -> 0 | H106: =IF(AND($B$21="Semestrielle",B106<>"",B105<>"",N(C106)+N(C105)>0),(B106+B105)/(C106+C105),"") -> 0
...

Sheet C3
A1: CAS 3 · Hôtel 4 étoiles, 220 clés | J1: DOSSIER_V8 | K1: V3
A2: SPV « Atlas Hospitality » SA (fictive) — Marrakech
A3: Hôtel exploité sous contrat de gestion par un groupe international. Aucun contrat de revenus : prix et volume sont intégralement portés par le projet.
A4: À SAISIR (cellules orange) | B4: =COUNTIF($R$14:$R$63,0) -> 0 | C4: =IF(B4=0,"Saisie complète : lisez la note ci-dessous, puis « Fiche comité ».","Prochaine saisie : "&INDEX($P$14:$P$63,MATCH(0,$R$14:$R$63,0))) -> 0 | G4: =IF(B4=0,"",HYPERLINK("#"&INDEX($Q$14:$Q$63,MATCH(0,$R$14:$R$63,0)),"→ Aller à la cellule "&INDEX($Q$14:$Q$63,MATCH(0,$R$14:$R$63,0)))) -> 0
A5: ="TABLEAU DE BORD — "&IF($B$17="","code projet à saisir",$B$17)&" · client "&IF($B$15="","—",$B$15)&" · radical "&IF($B$16="","—",$B$16) -> 0
A6: NOTE APPROUVÉE (1 à 10) | B6: =B276 -> 0 | C6: Libellé | D6: =IFERROR(INDEX(P_ConvLib,MATCH(B276,P_ConvNote,0)),"") -> 0 | E6: Statut | F6: =B277 -> 0
A7: Score global (sur 100) | B7: =B238 -> 0 | C7: Note calculée | D7: =B239 -> 0 | E7: Plafond applicable | F7: =IF(B273>=10,"Aucun (10)",B273) -> 0
A8: Plafonds actifs | B8: =IF(TRIM(IF(E258="Oui","C1 ("&F258&") ","")&IF(E259="Oui","C2 ("&F259&") ","")&IF(E260="Oui","C3 ("&F260&") ","")&IF(E261="Oui","C4 ("&F261&") ","")&IF(E262="Oui","C5 ("&F262&") ","")&IF(E263="Oui","C6 ("&F263&") ","")&IF(E264="Oui","C7 ("&F264&") ","")&IF(E265="Oui","C8 ("&F265&") ","")&IF(E266="Oui","C9 ("&F266&") ","")&IF(E267="Oui","C10 ("&F267&") ","")&IF(E268="Oui","C11 ("&F268&") ","")&IF(E269="Oui","C12 ("&F269&") ","")&IF(E270="Oui","C13 ("&F270&") ","")&IF(E271="Oui","C14 ("&F271&") ","")&IF(E272="Oui","C15 ("&F272&") ",""))="","Aucun",TRIM(IF(E258="Oui","C1 ("&F258&") ","")&IF(E259="Oui","C2 ("&F259&") ","")&IF(E260="Oui","C3 ("&F260&") ","")&IF(E261="Oui","C4 ("&F261&") ","")&IF(E262="Oui","C5 ("&F262&") ","")&IF(E263="Oui","C6 ("&F263&") ","")&IF(E264="Oui","C7 ("&F264&") ","")&IF(E265="Oui","C8 ("&F265&") ","")&IF(E266="Oui","C9 ("&F266&") ","")&IF(E267="Oui","C10 ("&F267&") ","")&IF(E268="Oui","C11 ("&F268&") ","")&IF(E269="Oui","C12 ("&F269&") ","")&IF(E270="Oui","C13 ("&F270&") ","")&IF(E271="Oui","C14 ("&F271&") ","")&IF(E272="Oui","C15 ("&F272&") ","")))&IF(COUNTIF(E258:E272,"n.r.")>0," — "&COUNTIF(E258:E272,"n.r.")&" plafond(s) non évalué(s) faute de donnée","") -> 0
A9: Verrous actifs (exclusions X, blocages B) | B9: =IF(TRIM(IF(F243="Oui","X1 ","")&IF(F244="Oui","X2 ","")&IF(F245="Oui","X3 ","")&IF(F246="Oui","X4 ","")&IF(F247="Oui","B1 ","")&IF(F248="Oui","B2 ","")&IF(F249="Oui","B3 ","")&IF(F250="Oui","B4 ","")&IF(F251="Oui","B5 ","")&IF(F252="Oui","B6 ","")&IF(F253="Oui","B7 ","")&IF(F254="Oui","B8 ",""))="","Aucun",TRIM(IF(F243="Oui","X1 ","")&IF(F244="Oui","X2 ","")&IF(F245="Oui","X3 ","")&IF(F246="Oui","X4 ","")&IF(F247="Oui","B1 ","")&IF(F248="Oui","B2 ","")&IF(F249="Oui","B3 ","")&IF(F250="Oui","B4 ","")&IF(F251="Oui","B5 ","")&IF(F252="Oui","B6 ","")&IF(F253="Oui","B7 ","")&IF(F254="Oui","B8 ",""))) -> 0
A10: Régime de proportionnalité retenu | B10: =B38 -> 0 | C10: DSCR minimum | D10: =D154 -> 0 | E10: DSCR stressé min. | F10: =D155 -> 0
A11: Complétude (noyau N1-N6 et grille) | B11: =B225 -> 0 | C11: Noyau financier D7 | D11: =D169 -> 0 | E11: Orientation | F11: =IFERROR(INDEX(P_ConvOrient,MATCH(B276,P_ConvNote,0)),"") -> 0
A12: Aller à la section : | B12: =HYPERLINK("#A13","1 · Identification") -> 0 | C12: =HYPERLINK("#A40","3 · Sources") -> 0 | D12: =HYPERLINK("#A90","6 · Échéancier") -> 0 | E12: =HYPERLINK("#A161","7 · Noyau") -> 0 | F12: =HYPERLINK("#A188","8 · Grille") -> 0 | G12: =HYPERLINK("#A256","11 · Plafonds") -> 0 | H12: =HYPERLINK("#A279","13 · Commentaires") -> 0
A13: 1 · IDENTIFICATION ET ROUTAGE — codes du client et du projet ; le routage pilote seuils et poids
A14: Axe | B14: Valeur | C14: Libellé, contrôle | P14: 1 · Code client T24 | Q14: B15 | R14: =IF(AND(LEN(TRIM($B$15))>=1,LEN($B$15)<=20),1,0) -> 0
A15: Code client T24 (société de projet) | B15: 20063902 | C15: =IF(B15="","À saisir — Texte, zéros de tête conservés.",IF(AND(LEN(TRIM(B15))>=1,LEN(B15)<=20),"Format conforme.","Format non conforme : Texte, zéros de tête conservés.")) -> 0 | P15: 1 · Radical du client (7 chiffres) | Q15: B16 | R15: =IF(AND(LEN($B$16)=7,SUMPRODUCT(--ISNUMBER(FIND(MID($B$16,ROW(INDIRECT("1:7"))+0,1),"0123456789")))=7),1,0) -> 0
A16: Radical du client (7 chiffres) | B16: 0063902 | C16: =IF(B16="","À saisir — Exactement 7 chiffres, zéros de tête compris.",IF(AND(LEN(B16)=7,SUMPRODUCT(--ISNUMBER(FIND(MID(B16,ROW(INDIRECT("1:7"))+0,1),"0123456789")))=7),"Format conforme.","Format non conforme : Exactement 7 chiffres, zéros de tête compris.")) -> 0 | P16: 1 · Code projet (PF-AAAA-NNNN) | Q16: B17 | R16: =IF(AND(LEN($B$17)=12,EXACT(LEFT($B$17,3),"PF-"),MID($B$17,8,1)="-",SUMPRODUCT(--ISNUMBER(FIND(MID($B$17,ROW(INDIRECT("1:4"))+3,1),"0123456789")))=4,SUMPRODUCT(--ISNUMBER(FIND(MID($B$17,ROW(INDIRECT("1:4"))+8,1),"0123456789")))=4),1,0) -> 0
A17: Code projet | B17: PF-2026-0003 | C17: =IF(B17="","À saisir — Format PF-AAAA-NNNN.",IF(AND(LEN(B17)=12,EXACT(LEFT(B17,3),"PF-"),MID(B17,8,1)="-",SUMPRODUCT(--ISNUMBER(FIND(MID(B17,ROW(INDIRECT("1:4"))+3,1),"0123456789")))=4,SUMPRODUCT(--ISNUMBER(FIND(MID(B17,ROW(INDIRECT("1:4"))+8,1),"0123456789")))=4),"Format conforme.","Format non conforme : Format PF-AAAA-NNNN.")) -> 0 | P17: 1 · Régime de revenus | Q17: B18 | R17: =IF($B$18<>"",1,0) -> 0
A18: C — Régime de revenus | B18: R4 | C18: =IFERROR(INDEX(P_RegLib,MATCH(B18,P_Regimes,0)),"") -> 0 | P18: 1 · Secteur du projet | Q18: B19 | R18: =IF($B$19<>"",1,0) -> 0
A19: D — Secteur du projet | B19: TOU | C19: =IFERROR(INDEX(P_SecLib,MATCH(B19,P_SecCodes,0)),"") -> 0 | P19: 1 · Phase du projet | Q19: B20 | R19: =IF($B$20<>"",1,0) -> 0
A20: B — Phase | B20: P2 | C20: =IFERROR(INDEX(P_PhaseLib,MATCH(B20,P_PhaseCodes,0)),"") -> 0 | P20: 1 · Périodicité des échéances | Q20: B21 | R20: =IF($B$21<>"",1,0) -> 0
A21: Périodicité du service de la dette | B21: Semestrielle | C21: Jamais annuelle : le DSCR se mesure échéance par échéance. | P21: 2 · Exposition de la banque (MMAD) | Q21: B26 | R21: =IF(ISNUMBER($B$26),1,0) -> 0
A22: A — Famille de financement | B22: PF-FLUX | C22: SPV dédiée, remboursement par les flux du projet (R5 vente d'actifs : hors outil). | P22: 2 · Recettes, coûts et dette en dirhams ? | Q22: B27 | R22: =IF($B$27<>"",1,0) -> 0
P23: 2 · Durée du financement (ans) | Q23: B28 | R23: =IF(ISNUMBER($B$28),1,0) -> 0
A24: 2 · RÉGIME DE PROPORTIONNALITÉ — calculé, jamais choisi | P24: 2 · Technologie éprouvée ? | Q24: B29 | R24: =IF($B$29<>"",1,0) -> 0
A25: CAPEX du projet économique complet (MMAD) | B25: =B50 -> 0 | C25: Repris du total des emplois (section 3). | P25: 2 · EPC clé-en-main de moins de 18 mois ? (phase P1) | Q25: B30 | R25: =IF(OR(NOT($B$20="P1"),$B$30<>""),1,0) -> 0
A26: Exposition de la banque (MMAD) | B26: 240 | P26: 2 · Acheteur principal unique ? | Q26: B31 | R26: =IF($B$31<>"",1,0) -> 0
A27: Recettes, coûts et dette intégralement en dirhams | B27: Oui | P27: 2 · Première référence technologique ? | Q27: B32 | R27: =IF($B$32<>"",1,0) -> 0
A28: Durée du financement (ans) | B28: 15 | P28: 2 · Opération consortiale ? | Q28: B33 | R28: =IF($B$33<>"",1,0) -> 0
A29: Technologie : ≥ 3 références industrielles de plus de 3 ans | B29: Oui | P29: 2 · Contrat de revenus de plus de 20 ans ? | Q29: B34 | R29: =IF($B$34<>"",1,0) -> 0
A30: En P1 : EPC clé-en-main forfaitaire, prix et délai garantis, < 18 mois | B30: Non | P30: 2 · Site à risque climatique élevé ? | Q30: B35 | R30: =IF($B$35<>"",1,0) -> 0
A31: Acheteur principal unique et identifié | B31: Non | P31: 2 · Nombre de contreparties clés | Q31: B36 | R31: =IF(ISNUMBER($B$36),1,0) -> 0
A32: Technologie constituant une première référence dans la juridiction | B32: Non | P32: 3 · Emplois : montants du besoin à terminaison | Q32: B42 | R32: =IF(N($B$50)>0,1,0) -> 0
A33: Opération consortiale relevant de la directive 3/W/2025 | B33: Non | P33: 3 · Ressources engagées : montants | Q33: E42 | R33: =IF(N($E$50)>0,1,0) -> 0
A34: Concession ou contrat de revenus de plus de 20 ans | B34: Non | P34: 3 · Nature de chaque ressource | Q34: F42 | R34: =IF(SUMPRODUCT(ISNUMBER($E$42:$E$49)*($F$42:$F$49=""))=0,1,0) -> 0
A35: Site classé à risque climatique physique élevé | B35: Non | P35: 3 · Plan de remédiation (couverture entre 95 et 100 %) | Q35: B53 | R35: =IF(OR(NOT(AND($B$20="P1",ISNUMBER($B$51),N($B$51)>=P_N3_V,N($B$51)<P_N3_F)),$B$53<>""),1,0) -> 0
A36: Nombre de contreparties clés | B36: 3 | P36: 6 · Choc du scénario défavorable (%) | Q36: B91 | R36: =IF(ISNUMBER($B$91),1,0) -> 0
A37: Régime calculé (avant escalade) | B37: =IF(OR(B25="",B25=0,B18=""),"",IF(OR(B25>P_L_CAPEX,N(B26)>P_L_EXPO,B18="R4",B32="Oui",N(B174)>0,B33="Oui",B34="Oui",B35="Oui",N(B36)>P_L_NBCP),"L",IF(AND(B25<=P_S_CAPEX,B26<>"",N(B26)<=P_S_EXPO,OR(B18="R1",B18="R2"),B29="Oui",B27="Oui",B28<>"",N(B28)<=P_S_DUREE,OR(B20<>"P1",B30="Oui"),B31="Oui",COUNTIF($F$243:$F$254,"Oui")=0),"S","M"))) -> 0 | C37: =IF(B37="","",IF(B37="L","Escalade : "&IF(B25>P_L_CAPEX,"CAPEX > "&P_L_CAPEX&" MMAD ; ","")&IF(N(B26)>P_L_EXPO,"exposition > "&P_L_EXPO&" MMAD ; ","")&IF(B18="R4","régime de revenus R4 ; ","")&IF(B32="Oui","première référence technologique ; ","")&IF(N(B174)>0,"devises non intégralement couvertes ; ","")&IF(B33="Oui","opération consortiale ; ","")&IF(B34="Oui","contrat de revenus > 20 ans ; ","")&IF(B35="Oui","risque climatique élevé ; ","")&IF(N(B36)>P_L_NBCP,"plus de "&P_L_NBCP&" contreparties clés ; ",""),IF(B37="S","Toutes les conditions du régime simplifié sont réunies.","Régime standard par défaut : une condition du régime S manque, aucune condition d'escalade."))) -> 0 | P37: 6 · Échéancier : CFADS d'au moins deux périodes | Q37: B93 | R37: =IF(COUNT($B$93:$B$152)>=2,1,0) -> 0
A38: RÉGIME RETENU (après escalade automatique) | B38: =IF(B37="","",IF(AND(IF(AND(B37="S",COUNTIF($F$243:$F$254,"Oui")>0),"M",B37)="M",COUNTIF($E$258:$E$272,"Oui")>0),"L",IF(AND(B37="S",COUNTIF($F$243:$F$254,"Oui")>0),"M",B37))) -> 0 | C38: =IF(B38=B37,"Aucune escalade.",IF(B38="L","Escalade : un plafond de note est actif (M passe en L).","Escalade : un verrou est actif (S passe en M).")) -> 0 | P38: 6 · Service de la dette de chaque période | Q38: C93 | R38: =IF(SUMPRODUCT(ISNUMBER($B$93:$B$152)*(1-ISNUMBER($C$93:$C$152)))=0,1,0) -> 0
P39: 7 · N4 — Liquidité : situation à choisir | Q39: E166 | R39: =IF($B$166<>"",1,0) -> 0
A40: 3 · SOURCES ET EMPLOIS (MMAD) — test de financement à terminaison ; crédits de la banque | P40: 7 · N5 — Levier : situation à choisir | Q40: E167 | R40: =IF($B$167<>"",1,0) -> 0
A41: Emplois | B41: Montant | D41: Ressources | E41: Montant | F41: Nature | P41: 7 · N6 — Exposition résiduelle : situation à choisir | Q41: E168 | R41: =IF($B$168<>"",1,0) -> 0
A42: Construction et second œuvre | B42: 330 | D42: Dette senior (15 ans, 6,5 %) | E42: 240 | F42: Dette senior | P42: 7 · Justification exigée (N4 à N6 Critique ou Info. insuffisante) | Q42: ="H"&IF(COUNT($T$166:$T$168)=0,166,MIN($T$166:$T$168)) -> 0 | R42: =IF(COUNT($T$166:$T$168)=0,1,0) -> 0
A43: Terrain | B43: 60 | D43: Fonds propres | E43: 240 | F43: Fonds propres | P43: 7 · N3 hors phase P1 : note LLCR | Q43: B171 | R43: =IF(OR($B$20="P1",$B$171<>""),1,0) -> 0
A44: Mobilier et équipements | B44: 45 | P44: 7 · LLCR (plafond C4) | Q44: B172 | R44: =IF(ISNUMBER($B$172),1,0) -> 0
A45: Frais, intérêts intercalaires et pré-ouverture | B45: 30 | P45: 7 · DSRA en mois (plafond C7) | Q45: B173 | R45: =IF(ISNUMBER($B$173),1,0) -> 0
A46: Dotation initiale DSRA | B46: 15 | P46: 7 · Exposition nette en devises (plafond C6) | Q46: B174 | R46: =IF(ISNUMBER($B$174),1,0) -> 0
P47: 7 · Dette à refinancer à maturité (plafond C8) | Q47: B175 | R47: =IF(ISNUMBER($B$175),1,0) -> 0
P48: 7 · Stratégie de refinancement approuvée ? | Q48: B176 | R48: =IF(OR(N($B$175)<=P_C8,$B$176<>""),1,0) -> 0
P49: 7 · Part des recettes de l'acheteur principal (C10) | Q49: B177 | R49: =IF(ISNUMBER($B$177),1,0) -> 0
A50: Total emplois (besoin à terminaison) | B50: =SUM(B42:B49) -> 0 | D50: Total ressources engagées | E50: =SUM(E42:E49) -> 0 | P50: 7 · Qualité de crédit de l'acheteur principal | Q50: B178 | R50: =IF($B$178<>"",1,0) -> 0
A51: Couverture du besoin à terminaison (ressources / emplois) | B51: =IF(N(B50)=0,"",E50/B50) -> 0 | P51: 7 · Durée résiduelle du contrat de revenus (C5) | Q51: B179 | R51: =IF(OR($B$18="R4",ISNUMBER($B$179)),1,0) -> 0
A52: Quote-part de dette (dette / besoin à terminaison) | B52: =IF(N(B50)=0,"",(SUMIF(F42:F49,"Dette senior",E42:E49)+SUMIF(F42:F49,"Dette subordonnée",E42:E49))/B50) -> 0 | P52: 7 · Durée résiduelle de la dette | Q52: B180 | R52: =IF(ISNUMBER($B$180),1,0) -> 0
A53: Plan de remédiation approuvé (couverture entre 95 % et 100 %) | B53: Non | P53: 7 · Solution documentée (contrat plus court que la dette) ? | Q53: B181 | R53: =IF(OR(NOT(AND(ISNUMBER($B$179),ISNUMBER($B$180))),N($B$179)>=N($B$180),$B$181<>""),1,0) -> 0
P54: 7 · Plan d'adaptation climatique financé ? (C11) | Q54: B182 | R54: =IF(OR($B$35<>"Oui",$B$182<>""),1,0) -> 0
A55: Crédits de la banque sur le projet — un projet peut porter plusieurs dossiers de crédit | P55: 7 · Capacité résiduelle du sponsor (C12) | Q55: B183 | R55: =IF($B$183<>"",1,0) -> 0
A56: Numéro du dossier de crédit | B56: Nature | E56: Montant (MMAD) | F56: Devise | G56: Durée (ans) | H56: Observation | P56: 7 · Opérateur remplaçable ? (C13) | Q56: B184 | R56: =IF($B$184<>"",1,0) -> 0
A57: CR-26-0301 | B57: Crédit d'investissement (moyen et long terme) | E57: 240 | F57: MAD | G57: 15 | P57: 7 · Écart fin O&M / fin de dette (opérateur non remplaçable) | Q57: B185 | R57: =IF(OR($B$184<>"Non",ISNUMBER($B$185)),1,0) -> 0
P58: 7 · Facteur commun au-delà de la limite interne (C14) | Q58: B186 | R58: =IF($B$186<>"",1,0) -> 0
P59: 8 · Grille : sous-critère requis sans situation choisie | Q59: ="E"&IF(COUNT($P$190:$P$222)=0,191,MIN($P$190:$P$222)) -> 0 | R59: =IF(COUNT($P$190:$P$222)=0,1,0) -> 0
P60: 8 · Commentaire exigé (situation Critique ou Info. insuffisante) | Q60: ="H"&IF(COUNT($T$190:$T$222)=0,191,MIN($T$190:$T$222)) -> 0 | R60: =IF(COUNT($T$190:$T$222)=0,1,0) -> 0
P61: 10 · Verrous X1 à B8 : répondre Oui ou Non | Q61: E243 | R61: =IF(COUNTBLANK($E$243:$E$254)=0,1,0) -> 0
P62: 13 · Synthèse de l'analyste | Q62: B280 | R62: =IF($B$280<>"",1,0) -> 0
A63: Total des crédits de la banque (MMAD, contre-valeur) | E63: =SUM(E57:E62) -> 0 | F63: Écart avec l'exposition (bloc 2) | H63: =IF(OR(N(E63)=0,NOT(ISNUMBER($B$26))),"",E63-$B$26) -> 0 | P63: 13 · Justification des écarts (plafond, verrou ou info. insuffisante) | Q63: B284 | R63: =IF(OR(NOT(OR(COUNTIF($E$258:$E$272,"Oui")>0,COUNTIF($F$243:$F$254,"Oui")>0,SUMPRODUCT(($J$190:$J$222="SC")*($K$190:$K$222=1)*($S$190:$S$222=5))>0,COUNTIF($S$166:$S$168,5)>0)),$B$284<>""),1,0) -> 0
A65: 4 · DONNÉES SECTORIELLES ET HYPOTHÈSES D'EXPLOITATION (information, non calculées)
A66: ="Données du secteur "&IF($B$19="","(choisissez le secteur au bloc 1)",$B$19) -> 0 | B66: Valeur | C66: Unité | D66: Observation ou source
A67: =IF($B$19="",IF(0=0,"Choisissez d'abord le secteur (bloc 1)",""),IFERROR(IF(T(INDEX(R_SecChamps,MATCH($B$19,R_SecCodes,0),1))="","Sans objet pour ce secteur",T(INDEX(R_SecChamps,MATCH($B$19,R_SecCodes,0),1))),"")) -> 0 | B67: 220 | C67: =IFERROR(T(INDEX(R_SecUnites,MATCH($B$19,R_SecCodes,0),1)),"") -> 0
A68: =IF($B$19="",IF(1=0,"Choisissez d'abord le secteur (bloc 1)",""),IFERROR(IF(T(INDEX(R_SecChamps,MATCH($B$19,R_SecCodes,0),2))="","Sans objet pour ce secteur",T(INDEX(R_SecChamps,MATCH($B$19,R_SecCodes,0),2))),"")) -> 0 | B68: 65 | C68: =IFERROR(T(INDEX(R_SecUnites,MATCH($B$19,R_SecCodes,0),2)),"") -> 0
A69: =IF($B$19="",IF(2=0,"Choisissez d'abord le secteur (bloc 1)",""),IFERROR(IF(T(INDEX(R_SecChamps,MATCH($B$19,R_SecCodes,0),3))="","Sans objet pour ce secteur",T(INDEX(R_SecChamps,MATCH($B$19,R_SecCodes,0),3))),"")) -> 0 | B69: 1350 | C69: =IFERROR(T(INDEX(R_SecUnites,MATCH($B$19,R_SecCodes,0),3)),"") -> 0
A70: =IF($B$19="",IF(3=0,"Choisissez d'abord le secteur (bloc 1)",""),IFERROR(IF(T(INDEX(R_SecChamps,MATCH($B$19,R_SecCodes,0),4))="","Sans objet pour ce secteur",T(INDEX(R_SecChamps,MATCH($B$19,R_SecCodes,0),4))),"")) -> 0 | B70: 878 | C70: =IFERROR(T(INDEX(R_SecUnites,MATCH($B$19,R_SecCodes,0),4)),"") -> 0
A71: =IF($B$19="",IF(4=0,"Choisissez d'abord le secteur (bloc 1)",""),IFERROR(IF(T(INDEX(R_SecChamps,MATCH($B$19,R_SecCodes,0),5))="","Sans objet pour ce secteur",T(INDEX(R_SecChamps,MATCH($B$19,R_SecCodes,0),5))),"")) -> 0 | B71: 55 | C71: =IFERROR(T(INDEX(R_SecUnites,MATCH($B$19,R_SecCodes,0),5)),"") -> 0
A72: =IF($B$19="",IF(5=0,"Choisissez d'abord le secteur (bloc 1)",""),IFERROR(IF(T(INDEX(R_SecChamps,MATCH($B$19,R_SecCodes,0),6))="","Sans objet pour ce secteur",T(INDEX(R_SecChamps,MATCH($B$19,R_SecCodes,0),6))),"")) -> 0 | B72: Contrat de gestion, 15 ans | C72: =IFERROR(T(INDEX(R_SecUnites,MATCH($B$19,R_SecCodes,0),6)),"") -> 0
A73: Autres hypothèses d'exploitation | B73: Valeur
A74: Chiffre d’affaires | B74: 98 MMAD/an
A75: Charges d’exploitation | B75: 62 MMAD/an
A76: EBITDA (GOP après loyer de gestion) | B76: 36 MMAD/an
A77: CFADS | B77: 30 MMAD/an
A78: Service de la dette | B78: 25,5 MMAD/an, semestriel
A83: 5 · SEUILS DSCR APPLICABLES = base du régime + Δ secteur + majoration de phase
A84: Seuil critique de base du régime | B84: =IFERROR(INDEX(P_Crit,MATCH($B$18,P_Regimes,0)),"") -> 0
A85: Écart sectoriel Δ | B85: =IFERROR(INDEX(P_SecDelta,MATCH($B$19,P_SecCodes,0)),"") -> 0
A86: Majoration de phase | B86: =IFERROR(INDEX(P_PhaseMaj,MATCH($B$20,P_PhaseCodes,0)),"") -> 0
A87: Seuils applicables | B87: Critique < | C87: Vigilance < | D87: Favorable < | E87: Très favorable ≥
A88: Seuil = base + Δ + majoration | B88: =IFERROR(INDEX(P_Crit,MATCH($B$18,P_Regimes,0))+$B$85+$B$86,"") -> 0 | C88: =IFERROR(INDEX(P_Vig,MATCH($B$18,P_Regimes,0))+$B$85+$B$86,"") -> 0 | D88: =IFERROR(INDEX(P_Fav,MATCH($B$18,P_Regimes,0))+$B$85+$B$86,"") -> 0 | E88: =D88 -> 0
A90: 6 · ÉCHÉANCIER DATÉ ET DSCR PAR ÉCHÉANCE (jusqu'à 60 périodes)
A91: Scénario défavorable : baisse du CFADS appliquée à chaque période | B91: 0.289778 | C91: Occupation ramenée de 65 % à 55 %, soit un chiffre d’affaires en recul de 15 %
A92: Période | B92: CFADS central | C92: Service de la dette | D92: DSCR | E92: Classement | F92: CFADS stressé (saisie facultative) | G92: DSCR stressé | H92: DSCR annuel (paire de semestres)
A93: An 2 · S1 (haute saison) | B93: 16.5 | C93: 12.75 | D93: =IF(OR(B93="",C93=""),"",IF(C93=0,"",B93/C93)) -> 0 | E93: =IF(B93="","",IF(C93=0,"Différé",IF(B93<0,"Critique",IF(D93<$B$88,"Critique",IF(D93<$C$88,"Vigilance",IF(D93<$D$88,"Favorable","Très favorable")))))) -> 0 | G93: =IF(OR(B93="",C93="",C93=0),"",IF(F93<>"",F93,B93*(1-$B$91))/C93) -> 0
A94: An 2 · S2 (creux estival) | B94: 13.5 | C94: 12.75 | D94: =IF(OR(B94="",C94=""),"",IF(C94=0,"",B94/C94)) -> 0 | E94: =IF(B94="","",IF(C94=0,"Différé",IF(B94<0,"Critique",IF(D94<$B$88,"Critique",IF(D94<$C$88,"Vigilance",IF(D94<$D$88,"Favorable","Très favorable")))))) -> 0 | G94: =IF(OR(B94="",C94="",C94=0),"",IF(F94<>"",F94,B94*(1-$B$91))/C94) -> 0 | H94: =IF(AND($B$21="Semestrielle",B94<>"",B93<>"",N(C94)+N(C93)>0),(B94+B93)/(C94+C93),"") -> 0
A95: An 5 · S1 | B95: 17.2 | C95: 12.75 | D95: =IF(OR(B95="",C95=""),"",IF(C95=0,"",B95/C95)) -> 0 | E95: =IF(B95="","",IF(C95=0,"Différé",IF(B95<0,"Critique",IF(D95<$B$88,"Critique",IF(D95<$C$88,"Vigilance",IF(D95<$D$88,"Favorable","Très favorable")))))) -> 0 | G95: =IF(OR(B95="",C95="",C95=0),"",IF(F95<>"",F95,B95*(1-$B$91))/C95) -> 0
A96: An 5 · S2 | B96: 14.1 | C96: 12.75 | D96: =IF(OR(B96="",C96=""),"",IF(C96=0,"",B96/C96)) -> 0 | E96: =IF(B96="","",IF(C96=0,"Différé",IF(B96<0,"Critique",IF(D96<$B$88,"Critique",IF(D96<$C$88,"Vigilance",IF(D96<$D$88,"Favorable","Très favorable")))))) -> 0 | G96: =IF(OR(B96="",C96="",C96=0),"",IF(F96<>"",F96,B96*(1-$B$91))/C96) -> 0 | H96: =IF(AND($B$21="Semestrielle",B96<>"",B95<>"",N(C96)+N(C95)>0),(B96+B95)/(C96+C95),"") -> 0
D97: =IF(OR(B97="",C97=""),"",IF(C97=0,"",B97/C97)) -> 0 | E97: =IF(B97="","",IF(C97=0,"Différé",IF(B97<0,"Critique",IF(D97<$B$88,"Critique",IF(D97<$C$88,"Vigilance",IF(D97<$D$88,"Favorable","Très favorable")))))) -> 0 | G97: =IF(OR(B97="",C97="",C97=0),"",IF(F97<>"",F97,B97*(1-$B$91))/C97) -> 0
D98: =IF(OR(B98="",C98=""),"",IF(C98=0,"",B98/C98)) -> 0 | E98: =IF(B98="","",IF(C98=0,"Différé",IF(B98<0,"Critique",IF(D98<$B$88,"Critique",IF(D98<$C$88,"Vigilance",IF(D98<$D$88,"Favorable","Très favorable")))))) -> 0 | G98: =IF(OR(B98="",C98="",C98=0),"",IF(F98<>"",F98,B98*(1-$B$91))/C98) -> 0 | H98: =IF(AND($B$21="Semestrielle",B98<>"",B97<>"",N(C98)+N(C97)>0),(B98+B97)/(C98+C97),"") -> 0
D99: =IF(OR(B99="",C99=""),"",IF(C99=0,"",B99/C99)) -> 0 | E99: =IF(B99="","",IF(C99=0,"Différé",IF(B99<0,"Critique",IF(D99<$B$88,"Critique",IF(D99<$C$88,"Vigilance",IF(D99<$D$88,"Favorable","Très favorable")))))) -> 0 | G99: =IF(OR(B99="",C99="",C99=0),"",IF(F99<>"",F99,B99*(1-$B$91))/C99) -> 0
D100: =IF(OR(B100="",C100=""),"",IF(C100=0,"",B100/C100)) -> 0 | E100: =IF(B100="","",IF(C100=0,"Différé",IF(B100<0,"Critique",IF(D100<$B$88,"Critique",IF(D100<$C$88,"Vigilance",IF(D100<$D$88,"Favorable","Très favorable")))))) -> 0 | G100: =IF(OR(B100="",C100="",C100=0),"",IF(F100<>"",F100,B100*(1-$B$91))/C100) -> 0 | H100: =IF(AND($B$21="Semestrielle",B100<>"",B99<>"",N(C100)+N(C99)>0),(B100+B99)/(C100+C99),"") -> 0
D101: =IF(OR(B101="",C101=""),"",IF(C101=0,"",B101/C101)) -> 0 | E101: =IF(B101="","",IF(C101=0,"Différé",IF(B101<0,"Critique",IF(D101<$B$88,"Critique",IF(D101<$C$88,"Vigilance",IF(D101<$D$88,"Favorable","Très favorable")))))) -> 0 | G101: =IF(OR(B101="",C101="",C101=0),"",IF(F101<>"",F101,B101*(1-$B$91))/C101) -> 0
D102: =IF(OR(B102="",C102=""),"",IF(C102=0,"",B102/C102)) -> 0 | E102: =IF(B102="","",IF(C102=0,"Différé",IF(B102<0,"Critique",IF(D102<$B$88,"Critique",IF(D102<$C$88,"Vigilance",IF(D102<$D$88,"Favorable","Très favorable")))))) -> 0 | G102: =IF(OR(B102="",C102="",C102=0),"",IF(F102<>"",F102,B102*(1-$B$91))/C102) -> 0 | H102: =IF(AND($B$21="Semestrielle",B102<>"",B101<>"",N(C102)+N(C101)>0),(B102+B101)/(C102+C101),"") -> 0
D103: =IF(OR(B103="",C103=""),"",IF(C103=0,"",B103/C103)) -> 0 | E103: =IF(B103="","",IF(C103=0,"Différé",IF(B103<0,"Critique",IF(D103<$B$88,"Critique",IF(D103<$C$88,"Vigilance",IF(D103<$D$88,"Favorable","Très favorable")))))) -> 0 | G103: =IF(OR(B103="",C103="",C103=0),"",IF(F103<>"",F103,B103*(1-$B$91))/C103) -> 0
D104: =IF(OR(B104="",C104=""),"",IF(C104=0,"",B104/C104)) -> 0 | E104: =IF(B104="","",IF(C104=0,"Différé",IF(B104<0,"Critique",IF(D104<$B$88,"Critique",IF(D104<$C$88,"Vigilance",IF(D104<$D$88,"Favorable","Très favorable")))))) -> 0 | G104: =IF(OR(B104="",C104="",C104=0),"",IF(F104<>"",F104,B104*(1-$B$91))/C104) -> 0 | H104: =IF(AND($B$21="Semestrielle",B104<>"",B103<>"",N(C104)+N(C103)>0),(B104+B103)/(C104+C103),"") -> 0
D105: =IF(OR(B105="",C105=""),"",IF(C105=0,"",B105/C105)) -> 0 | E105: =IF(B105="","",IF(C105=0,"Différé",IF(B105<0,"Critique",IF(D105<$B$88,"Critique",IF(D105<$C$88,"Vigilance",IF(D105<$D$88,"Favorable","Très favorable")))))) -> 0 | G105: =IF(OR(B105="",C105="",C105=0),"",IF(F105<>"",F105,B105*(1-$B$91))/C105) -> 0
D106: =IF(OR(B106="",C106=""),"",IF(C106=0,"",B106/C106)) -> 0 | E106: =IF(B106="","",IF(C106=0,"Différé",IF(B106<0,"Critique",IF(D106<$B$88,"Critique",IF(D106<$C$88,"Vigilance",IF(D106<$D$88,"Favorable","Très favorable")))))) -> 0 | G106: =IF(OR(B106="",C106="",C106=0),"",IF(F106<>"",F106,B106*(1-$B$91))/C106) -> 0 | H106: =IF(AND($B$21="Semestrielle",B106<>"",B105<>"",N(C106)+N(C105)>0),(B106+B105)/(C106+C105),"") -> 0
...

Sheet C4A
A1: CAS 4 — variante A · Unité agro-industrielle de trituration et conditionnement | J1: DOSSIER_V8 | K1: V3
A2: SPV « Doukkala Agro » SA (fictive) — Région de Doukkala-Abda
A3: Unité transformant une production agricole locale sous contrats d'enlèvement à prix convenu mais volume exposé. Structure initiale : amortissement semestriel linéaire, change non couvert.
A4: À SAISIR (cellules orange) | B4: =COUNTIF($R$14:$R$63,0) -> 0 | C4: =IF(B4=0,"Saisie complète : lisez la note ci-dessous, puis « Fiche comité ».","Prochaine saisie : "&INDEX($P$14:$P$63,MATCH(0,$R$14:$R$63,0))) -> 0 | G4: =IF(B4=0,"",HYPERLINK("#"&INDEX($Q$14:$Q$63,MATCH(0,$R$14:$R$63,0)),"→ Aller à la cellule "&INDEX($Q$14:$Q$63,MATCH(0,$R$14:$R$63,0)))) -> 0
A5: ="TABLEAU DE BORD — "&IF($B$17="","code projet à saisir",$B$17)&" · client "&IF($B$15="","—",$B$15)&" · radical "&IF($B$16="","—",$B$16) -> 0
A6: NOTE APPROUVÉE (1 à 10) | B6: =B276 -> 0 | C6: Libellé | D6: =IFERROR(INDEX(P_ConvLib,MATCH(B276,P_ConvNote,0)),"") -> 0 | E6: Statut | F6: =B277 -> 0
A7: Score global (sur 100) | B7: =B238 -> 0 | C7: Note calculée | D7: =B239 -> 0 | E7: Plafond applicable | F7: =IF(B273>=10,"Aucun (10)",B273) -> 0
A8: Plafonds actifs | B8: =IF(TRIM(IF(E258="Oui","C1 ("&F258&") ","")&IF(E259="Oui","C2 ("&F259&") ","")&IF(E260="Oui","C3 ("&F260&") ","")&IF(E261="Oui","C4 ("&F261&") ","")&IF(E262="Oui","C5 ("&F262&") ","")&IF(E263="Oui","C6 ("&F263&") ","")&IF(E264="Oui","C7 ("&F264&") ","")&IF(E265="Oui","C8 ("&F265&") ","")&IF(E266="Oui","C9 ("&F266&") ","")&IF(E267="Oui","C10 ("&F267&") ","")&IF(E268="Oui","C11 ("&F268&") ","")&IF(E269="Oui","C12 ("&F269&") ","")&IF(E270="Oui","C13 ("&F270&") ","")&IF(E271="Oui","C14 ("&F271&") ","")&IF(E272="Oui","C15 ("&F272&") ",""))="","Aucun",TRIM(IF(E258="Oui","C1 ("&F258&") ","")&IF(E259="Oui","C2 ("&F259&") ","")&IF(E260="Oui","C3 ("&F260&") ","")&IF(E261="Oui","C4 ("&F261&") ","")&IF(E262="Oui","C5 ("&F262&") ","")&IF(E263="Oui","C6 ("&F263&") ","")&IF(E264="Oui","C7 ("&F264&") ","")&IF(E265="Oui","C8 ("&F265&") ","")&IF(E266="Oui","C9 ("&F266&") ","")&IF(E267="Oui","C10 ("&F267&") ","")&IF(E268="Oui","C11 ("&F268&") ","")&IF(E269="Oui","C12 ("&F269&") ","")&IF(E270="Oui","C13 ("&F270&") ","")&IF(E271="Oui","C14 ("&F271&") ","")&IF(E272="Oui","C15 ("&F272&") ","")))&IF(COUNTIF(E258:E272,"n.r.")>0," — "&COUNTIF(E258:E272,"n.r.")&" plafond(s) non évalué(s) faute de donnée","") -> 0
A9: Verrous actifs (exclusions X, blocages B) | B9: =IF(TRIM(IF(F243="Oui","X1 ","")&IF(F244="Oui","X2 ","")&IF(F245="Oui","X3 ","")&IF(F246="Oui","X4 ","")&IF(F247="Oui","B1 ","")&IF(F248="Oui","B2 ","")&IF(F249="Oui","B3 ","")&IF(F250="Oui","B4 ","")&IF(F251="Oui","B5 ","")&IF(F252="Oui","B6 ","")&IF(F253="Oui","B7 ","")&IF(F254="Oui","B8 ",""))="","Aucun",TRIM(IF(F243="Oui","X1 ","")&IF(F244="Oui","X2 ","")&IF(F245="Oui","X3 ","")&IF(F246="Oui","X4 ","")&IF(F247="Oui","B1 ","")&IF(F248="Oui","B2 ","")&IF(F249="Oui","B3 ","")&IF(F250="Oui","B4 ","")&IF(F251="Oui","B5 ","")&IF(F252="Oui","B6 ","")&IF(F253="Oui","B7 ","")&IF(F254="Oui","B8 ",""))) -> 0
A10: Régime de proportionnalité retenu | B10: =B38 -> 0 | C10: DSCR minimum | D10: =D154 -> 0 | E10: DSCR stressé min. | F10: =D155 -> 0
A11: Complétude (noyau N1-N6 et grille) | B11: =B225 -> 0 | C11: Noyau financier D7 | D11: =D169 -> 0 | E11: Orientation | F11: =IFERROR(INDEX(P_ConvOrient,MATCH(B276,P_ConvNote,0)),"") -> 0
A12: Aller à la section : | B12: =HYPERLINK("#A13","1 · Identification") -> 0 | C12: =HYPERLINK("#A40","3 · Sources") -> 0 | D12: =HYPERLINK("#A90","6 · Échéancier") -> 0 | E12: =HYPERLINK("#A161","7 · Noyau") -> 0 | F12: =HYPERLINK("#A188","8 · Grille") -> 0 | G12: =HYPERLINK("#A256","11 · Plafonds") -> 0 | H12: =HYPERLINK("#A279","13 · Commentaires") -> 0
A13: 1 · IDENTIFICATION ET ROUTAGE — codes du client et du projet ; le routage pilote seuils et poids
A14: Axe | B14: Valeur | C14: Libellé, contrôle | P14: 1 · Code client T24 | Q14: B15 | R14: =IF(AND(LEN(TRIM($B$15))>=1,LEN($B$15)<=20),1,0) -> 0
A15: Code client T24 (société de projet) | B15: 20077415 | C15: =IF(B15="","À saisir — Texte, zéros de tête conservés.",IF(AND(LEN(TRIM(B15))>=1,LEN(B15)<=20),"Format conforme.","Format non conforme : Texte, zéros de tête conservés.")) -> 0 | P15: 1 · Radical du client (7 chiffres) | Q15: B16 | R15: =IF(AND(LEN($B$16)=7,SUMPRODUCT(--ISNUMBER(FIND(MID($B$16,ROW(INDIRECT("1:7"))+0,1),"0123456789")))=7),1,0) -> 0
A16: Radical du client (7 chiffres) | B16: 0077415 | C16: =IF(B16="","À saisir — Exactement 7 chiffres, zéros de tête compris.",IF(AND(LEN(B16)=7,SUMPRODUCT(--ISNUMBER(FIND(MID(B16,ROW(INDIRECT("1:7"))+0,1),"0123456789")))=7),"Format conforme.","Format non conforme : Exactement 7 chiffres, zéros de tête compris.")) -> 0 | P16: 1 · Code projet (PF-AAAA-NNNN) | Q16: B17 | R16: =IF(AND(LEN($B$17)=12,EXACT(LEFT($B$17,3),"PF-"),MID($B$17,8,1)="-",SUMPRODUCT(--ISNUMBER(FIND(MID($B$17,ROW(INDIRECT("1:4"))+3,1),"0123456789")))=4,SUMPRODUCT(--ISNUMBER(FIND(MID($B$17,ROW(INDIRECT("1:4"))+8,1),"0123456789")))=4),1,0) -> 0
A17: Code projet | B17: PF-2026-0004 | C17: =IF(B17="","À saisir — Format PF-AAAA-NNNN.",IF(AND(LEN(B17)=12,EXACT(LEFT(B17,3),"PF-"),MID(B17,8,1)="-",SUMPRODUCT(--ISNUMBER(FIND(MID(B17,ROW(INDIRECT("1:4"))+3,1),"0123456789")))=4,SUMPRODUCT(--ISNUMBER(FIND(MID(B17,ROW(INDIRECT("1:4"))+8,1),"0123456789")))=4),"Format conforme.","Format non conforme : Format PF-AAAA-NNNN.")) -> 0 | P17: 1 · Régime de revenus | Q17: B18 | R17: =IF($B$18<>"",1,0) -> 0
A18: C — Régime de revenus | B18: R3 | C18: =IFERROR(INDEX(P_RegLib,MATCH(B18,P_Regimes,0)),"") -> 0 | P18: 1 · Secteur du projet | Q18: B19 | R18: =IF($B$19<>"",1,0) -> 0
A19: D — Secteur du projet | B19: AGR | C19: =IFERROR(INDEX(P_SecLib,MATCH(B19,P_SecCodes,0)),"") -> 0 | P19: 1 · Phase du projet | Q19: B20 | R19: =IF($B$20<>"",1,0) -> 0
A20: B — Phase | B20: P3 | C20: =IFERROR(INDEX(P_PhaseLib,MATCH(B20,P_PhaseCodes,0)),"") -> 0 | P20: 1 · Périodicité des échéances | Q20: B21 | R20: =IF($B$21<>"",1,0) -> 0
A21: Périodicité du service de la dette | B21: Semestrielle | C21: Jamais annuelle : le DSCR se mesure échéance par échéance. | P21: 2 · Exposition de la banque (MMAD) | Q21: B26 | R21: =IF(ISNUMBER($B$26),1,0) -> 0
A22: A — Famille de financement | B22: PF-FLUX | C22: SPV dédiée, remboursement par les flux du projet (R5 vente d'actifs : hors outil). | P22: 2 · Recettes, coûts et dette en dirhams ? | Q22: B27 | R22: =IF($B$27<>"",1,0) -> 0
P23: 2 · Durée du financement (ans) | Q23: B28 | R23: =IF(ISNUMBER($B$28),1,0) -> 0
A24: 2 · RÉGIME DE PROPORTIONNALITÉ — calculé, jamais choisi | P24: 2 · Technologie éprouvée ? | Q24: B29 | R24: =IF($B$29<>"",1,0) -> 0
A25: CAPEX du projet économique complet (MMAD) | B25: =B50 -> 0 | C25: Repris du total des emplois (section 3). | P25: 2 · EPC clé-en-main de moins de 18 mois ? (phase P1) | Q25: B30 | R25: =IF(OR(NOT($B$20="P1"),$B$30<>""),1,0) -> 0
A26: Exposition de la banque (MMAD) | B26: 250 | P26: 2 · Acheteur principal unique ? | Q26: B31 | R26: =IF($B$31<>"",1,0) -> 0
A27: Recettes, coûts et dette intégralement en dirhams | B27: Non | P27: 2 · Première référence technologique ? | Q27: B32 | R27: =IF($B$32<>"",1,0) -> 0
A28: Durée du financement (ans) | B28: 10 | P28: 2 · Opération consortiale ? | Q28: B33 | R28: =IF($B$33<>"",1,0) -> 0
A29: Technologie : ≥ 3 références industrielles de plus de 3 ans | B29: Oui | P29: 2 · Contrat de revenus de plus de 20 ans ? | Q29: B34 | R29: =IF($B$34<>"",1,0) -> 0
A30: En P1 : EPC clé-en-main forfaitaire, prix et délai garantis, < 18 mois | B30: Non | P30: 2 · Site à risque climatique élevé ? | Q30: B35 | R30: =IF($B$35<>"",1,0) -> 0
A31: Acheteur principal unique et identifié | B31: Non | P31: 2 · Nombre de contreparties clés | Q31: B36 | R31: =IF(ISNUMBER($B$36),1,0) -> 0
A32: Technologie constituant une première référence dans la juridiction | B32: Non | P32: 3 · Emplois : montants du besoin à terminaison | Q32: B42 | R32: =IF(N($B$50)>0,1,0) -> 0
A33: Opération consortiale relevant de la directive 3/W/2025 | B33: Non | P33: 3 · Ressources engagées : montants | Q33: E42 | R33: =IF(N($E$50)>0,1,0) -> 0
A34: Concession ou contrat de revenus de plus de 20 ans | B34: Non | P34: 3 · Nature de chaque ressource | Q34: F42 | R34: =IF(SUMPRODUCT(ISNUMBER($E$42:$E$49)*($F$42:$F$49=""))=0,1,0) -> 0
A35: Site classé à risque climatique physique élevé | B35: Non | P35: 3 · Plan de remédiation (couverture entre 95 et 100 %) | Q35: B53 | R35: =IF(OR(NOT(AND($B$20="P1",ISNUMBER($B$51),N($B$51)>=P_N3_V,N($B$51)<P_N3_F)),$B$53<>""),1,0) -> 0
A36: Nombre de contreparties clés | B36: 3 | P36: 6 · Choc du scénario défavorable (%) | Q36: B91 | R36: =IF(ISNUMBER($B$91),1,0) -> 0
A37: Régime calculé (avant escalade) | B37: =IF(OR(B25="",B25=0,B18=""),"",IF(OR(B25>P_L_CAPEX,N(B26)>P_L_EXPO,B18="R4",B32="Oui",N(B174)>0,B33="Oui",B34="Oui",B35="Oui",N(B36)>P_L_NBCP),"L",IF(AND(B25<=P_S_CAPEX,B26<>"",N(B26)<=P_S_EXPO,OR(B18="R1",B18="R2"),B29="Oui",B27="Oui",B28<>"",N(B28)<=P_S_DUREE,OR(B20<>"P1",B30="Oui"),B31="Oui",COUNTIF($F$243:$F$254,"Oui")=0),"S","M"))) -> 0 | C37: =IF(B37="","",IF(B37="L","Escalade : "&IF(B25>P_L_CAPEX,"CAPEX > "&P_L_CAPEX&" MMAD ; ","")&IF(N(B26)>P_L_EXPO,"exposition > "&P_L_EXPO&" MMAD ; ","")&IF(B18="R4","régime de revenus R4 ; ","")&IF(B32="Oui","première référence technologique ; ","")&IF(N(B174)>0,"devises non intégralement couvertes ; ","")&IF(B33="Oui","opération consortiale ; ","")&IF(B34="Oui","contrat de revenus > 20 ans ; ","")&IF(B35="Oui","risque climatique élevé ; ","")&IF(N(B36)>P_L_NBCP,"plus de "&P_L_NBCP&" contreparties clés ; ",""),IF(B37="S","Toutes les conditions du régime simplifié sont réunies.","Régime standard par défaut : une condition du régime S manque, aucune condition d'escalade."))) -> 0 | P37: 6 · Échéancier : CFADS d'au moins deux périodes | Q37: B93 | R37: =IF(COUNT($B$93:$B$152)>=2,1,0) -> 0
A38: RÉGIME RETENU (après escalade automatique) | B38: =IF(B37="","",IF(AND(IF(AND(B37="S",COUNTIF($F$243:$F$254,"Oui")>0),"M",B37)="M",COUNTIF($E$258:$E$272,"Oui")>0),"L",IF(AND(B37="S",COUNTIF($F$243:$F$254,"Oui")>0),"M",B37))) -> 0 | C38: =IF(B38=B37,"Aucune escalade.",IF(B38="L","Escalade : un plafond de note est actif (M passe en L).","Escalade : un verrou est actif (S passe en M).")) -> 0 | P38: 6 · Service de la dette de chaque période | Q38: C93 | R38: =IF(SUMPRODUCT(ISNUMBER($B$93:$B$152)*(1-ISNUMBER($C$93:$C$152)))=0,1,0) -> 0
P39: 7 · N4 — Liquidité : situation à choisir | Q39: E166 | R39: =IF($B$166<>"",1,0) -> 0
A40: 3 · SOURCES ET EMPLOIS (MMAD) — test de financement à terminaison ; crédits de la banque | P40: 7 · N5 — Levier : situation à choisir | Q40: E167 | R40: =IF($B$167<>"",1,0) -> 0
A41: Emplois | B41: Montant | D41: Ressources | E41: Montant | F41: Nature | P41: 7 · N6 — Exposition résiduelle : situation à choisir | Q41: E168 | R41: =IF($B$168<>"",1,0) -> 0
A42: Ligne de production et bâtiments | B42: 300 | D42: Dette senior (10 ans, 6,0 %), amortissement linéaire | E42: 250 | F42: Dette senior | P42: 7 · Justification exigée (N4 à N6 Critique ou Info. insuffisante) | Q42: ="H"&IF(COUNT($T$166:$T$168)=0,166,MIN($T$166:$T$168)) -> 0 | R42: =IF(COUNT($T$166:$T$168)=0,1,0) -> 0
A43: Stockage et froid | B43: 70 | D43: Fonds propres | E43: 170 | F43: Fonds propres | P43: 7 · N3 hors phase P1 : note LLCR | Q43: B171 | R43: =IF(OR($B$20="P1",$B$171<>""),1,0) -> 0
A44: Terrain et aménagements | B44: 25 | P44: 7 · LLCR (plafond C4) | Q44: B172 | R44: =IF(ISNUMBER($B$172),1,0) -> 0
A45: Frais et intérêts intercalaires | B45: 17 | P45: 7 · DSRA en mois (plafond C7) | Q45: B173 | R45: =IF(ISNUMBER($B$173),1,0) -> 0
A46: Dotation DSRA | B46: 8 | P46: 7 · Exposition nette en devises (plafond C6) | Q46: B174 | R46: =IF(ISNUMBER($B$174),1,0) -> 0
P47: 7 · Dette à refinancer à maturité (plafond C8) | Q47: B175 | R47: =IF(ISNUMBER($B$175),1,0) -> 0
P48: 7 · Stratégie de refinancement approuvée ? | Q48: B176 | R48: =IF(OR(N($B$175)<=P_C8,$B$176<>""),1,0) -> 0
P49: 7 · Part des recettes de l'acheteur principal (C10) | Q49: B177 | R49: =IF(ISNUMBER($B$177),1,0) -> 0
A50: Total emplois (besoin à terminaison) | B50: =SUM(B42:B49) -> 0 | D50: Total ressources engagées | E50: =SUM(E42:E49) -> 0 | P50: 7 · Qualité de crédit de l'acheteur principal | Q50: B178 | R50: =IF($B$178<>"",1,0) -> 0
A51: Couverture du besoin à terminaison (ressources / emplois) | B51: =IF(N(B50)=0,"",E50/B50) -> 0 | P51: 7 · Durée résiduelle du contrat de revenus (C5) | Q51: B179 | R51: =IF(OR($B$18="R4",ISNUMBER($B$179)),1,0) -> 0
A52: Quote-part de dette (dette / besoin à terminaison) | B52: =IF(N(B50)=0,"",(SUMIF(F42:F49,"Dette senior",E42:E49)+SUMIF(F42:F49,"Dette subordonnée",E42:E49))/B50) -> 0 | P52: 7 · Durée résiduelle de la dette | Q52: B180 | R52: =IF(ISNUMBER($B$180),1,0) -> 0
A53: Plan de remédiation approuvé (couverture entre 95 % et 100 %) | B53: Non | P53: 7 · Solution documentée (contrat plus court que la dette) ? | Q53: B181 | R53: =IF(OR(NOT(AND(ISNUMBER($B$179),ISNUMBER($B$180))),N($B$179)>=N($B$180),$B$181<>""),1,0) -> 0
P54: 7 · Plan d'adaptation climatique financé ? (C11) | Q54: B182 | R54: =IF(OR($B$35<>"Oui",$B$182<>""),1,0) -> 0
A55: Crédits de la banque sur le projet — un projet peut porter plusieurs dossiers de crédit | P55: 7 · Capacité résiduelle du sponsor (C12) | Q55: B183 | R55: =IF($B$183<>"",1,0) -> 0
A56: Numéro du dossier de crédit | B56: Nature | E56: Montant (MMAD) | F56: Devise | G56: Durée (ans) | H56: Observation | P56: 7 · Opérateur remplaçable ? (C13) | Q56: B184 | R56: =IF($B$184<>"",1,0) -> 0
A57: CR-26-0401 | B57: Crédit d'investissement (moyen et long terme) | E57: 250 | F57: MAD | G57: 10 | P57: 7 · Écart fin O&M / fin de dette (opérateur non remplaçable) | Q57: B185 | R57: =IF(OR($B$184<>"Non",ISNUMBER($B$185)),1,0) -> 0
P58: 7 · Facteur commun au-delà de la limite interne (C14) | Q58: B186 | R58: =IF($B$186<>"",1,0) -> 0
P59: 8 · Grille : sous-critère requis sans situation choisie | Q59: ="E"&IF(COUNT($P$190:$P$222)=0,191,MIN($P$190:$P$222)) -> 0 | R59: =IF(COUNT($P$190:$P$222)=0,1,0) -> 0
P60: 8 · Commentaire exigé (situation Critique ou Info. insuffisante) | Q60: ="H"&IF(COUNT($T$190:$T$222)=0,191,MIN($T$190:$T$222)) -> 0 | R60: =IF(COUNT($T$190:$T$222)=0,1,0) -> 0
P61: 10 · Verrous X1 à B8 : répondre Oui ou Non | Q61: E243 | R61: =IF(COUNTBLANK($E$243:$E$254)=0,1,0) -> 0
P62: 13 · Synthèse de l'analyste | Q62: B280 | R62: =IF($B$280<>"",1,0) -> 0
A63: Total des crédits de la banque (MMAD, contre-valeur) | E63: =SUM(E57:E62) -> 0 | F63: Écart avec l'exposition (bloc 2) | H63: =IF(OR(N(E63)=0,NOT(ISNUMBER($B$26))),"",E63-$B$26) -> 0 | P63: 13 · Justification des écarts (plafond, verrou ou info. insuffisante) | Q63: B284 | R63: =IF(OR(NOT(OR(COUNTIF($E$258:$E$272,"Oui")>0,COUNTIF($F$243:$F$254,"Oui")>0,SUMPRODUCT(($J$190:$J$222="SC")*($K$190:$K$222=1)*($S$190:$S$222=5))>0,COUNTIF($S$166:$S$168,5)>0)),$B$284<>""),1,0) -> 0
A65: 4 · DONNÉES SECTORIELLES ET HYPOTHÈSES D'EXPLOITATION (information, non calculées)
A66: ="Données du secteur "&IF($B$19="","(choisissez le secteur au bloc 1)",$B$19) -> 0 | B66: Valeur | C66: Unité | D66: Observation ou source
A67: =IF($B$19="",IF(0=0,"Choisissez d'abord le secteur (bloc 1)",""),IFERROR(IF(T(INDEX(R_SecChamps,MATCH($B$19,R_SecCodes,0),1))="","Sans objet pour ce secteur",T(INDEX(R_SecChamps,MATCH($B$19,R_SecCodes,0),1))),"")) -> 0 | B67: 60 | C67: =IFERROR(T(INDEX(R_SecUnites,MATCH($B$19,R_SecCodes,0),1)),"") -> 0
A68: =IF($B$19="",IF(1=0,"Choisissez d'abord le secteur (bloc 1)",""),IFERROR(IF(T(INDEX(R_SecChamps,MATCH($B$19,R_SecCodes,0),2))="","Sans objet pour ce secteur",T(INDEX(R_SecChamps,MATCH($B$19,R_SecCodes,0),2))),"")) -> 0 | B68: 3.2 | C68: =IFERROR(T(INDEX(R_SecUnites,MATCH($B$19,R_SecCodes,0),2)),"") -> 0
A69: =IF($B$19="",IF(2=0,"Choisissez d'abord le secteur (bloc 1)",""),IFERROR(IF(T(INDEX(R_SecChamps,MATCH($B$19,R_SecCodes,0),3))="","Sans objet pour ce secteur",T(INDEX(R_SecChamps,MATCH($B$19,R_SecCodes,0),3))),"")) -> 0 | B69: 70 | C69: =IFERROR(T(INDEX(R_SecUnites,MATCH($B$19,R_SecCodes,0),3)),"") -> 0
A70: =IF($B$19="",IF(3=0,"Choisissez d'abord le secteur (bloc 1)",""),IFERROR(IF(T(INDEX(R_SecChamps,MATCH($B$19,R_SecCodes,0),4))="","Sans objet pour ce secteur",T(INDEX(R_SecChamps,MATCH($B$19,R_SecCodes,0),4))),"")) -> 0 | B70: 40 | C70: =IFERROR(T(INDEX(R_SecUnites,MATCH($B$19,R_SecCodes,0),4)),"") -> 0
A71: =IF($B$19="",IF(4=0,"Choisissez d'abord le secteur (bloc 1)",""),IFERROR(IF(T(INDEX(R_SecChamps,MATCH($B$19,R_SecCodes,0),5))="","Sans objet pour ce secteur",T(INDEX(R_SecChamps,MATCH($B$19,R_SecCodes,0),5))),"")) -> 0 | C71: =IFERROR(T(INDEX(R_SecUnites,MATCH($B$19,R_SecCodes,0),5)),"") -> 0
A72: =IF($B$19="",IF(5=0,"Choisissez d'abord le secteur (bloc 1)",""),IFERROR(IF(T(INDEX(R_SecChamps,MATCH($B$19,R_SecCodes,0),6))="","Sans objet pour ce secteur",T(INDEX(R_SecChamps,MATCH($B$19,R_SecCodes,0),6))),"")) -> 0 | C72: =IFERROR(T(INDEX(R_SecUnites,MATCH($B$19,R_SecCodes,0),6)),"") -> 0
A73: Autres hypothèses d'exploitation | B73: Valeur
A74: Chiffre d’affaires | B74: 380 MMAD/an
A75: Charges d’exploitation | B75: 320 MMAD/an
A76: EBITDA | B76: 60 MMAD/an
A77: CFADS | B77: 52 MMAD/an
A78: Saisonnalité | B78: Campagne concentrée sur le premier semestre : 42 MMAD contre 10 MMAD
A79: Service de la dette | B79: 34 MMAD/an, soit 17 MMAD par semestre
A80: Achats importés non couverts | B80: 45 MMAD/an nets des recettes à l’export
A83: 5 · SEUILS DSCR APPLICABLES = base du régime + Δ secteur + majoration de phase
A84: Seuil critique de base du régime | B84: =IFERROR(INDEX(P_Crit,MATCH($B$18,P_Regimes,0)),"") -> 0
A85: Écart sectoriel Δ | B85: =IFERROR(INDEX(P_SecDelta,MATCH($B$19,P_SecCodes,0)),"") -> 0
A86: Majoration de phase | B86: =IFERROR(INDEX(P_PhaseMaj,MATCH($B$20,P_PhaseCodes,0)),"") -> 0
A87: Seuils applicables | B87: Critique < | C87: Vigilance < | D87: Favorable < | E87: Très favorable ≥
A88: Seuil = base + Δ + majoration | B88: =IFERROR(INDEX(P_Crit,MATCH($B$18,P_Regimes,0))+$B$85+$B$86,"") -> 0 | C88: =IFERROR(INDEX(P_Vig,MATCH($B$18,P_Regimes,0))+$B$85+$B$86,"") -> 0 | D88: =IFERROR(INDEX(P_Fav,MATCH($B$18,P_Regimes,0))+$B$85+$B$86,"") -> 0 | E88: =D88 -> 0
A90: 6 · ÉCHÉANCIER DATÉ ET DSCR PAR ÉCHÉANCE (jusqu'à 60 périodes)
A91: Scénario défavorable : baisse du CFADS appliquée à chaque période | B91: 0.3285 | C91: Récolte en recul de 20 % sous stress hydrique, soit un chiffre d’affaires en baisse de 15 %
A92: Période | B92: CFADS central | C92: Service de la dette | D92: DSCR | E92: Classement | F92: CFADS stressé (saisie facultative) | G92: DSCR stressé | H92: DSCR annuel (paire de semestres)
A93: An 3 · S1 (campagne) | B93: 42 | C93: 17 | D93: =IF(OR(B93="",C93=""),"",IF(C93=0,"",B93/C93)) -> 0 | E93: =IF(B93="","",IF(C93=0,"Différé",IF(B93<0,"Critique",IF(D93<$B$88,"Critique",IF(D93<$C$88,"Vigilance",IF(D93<$D$88,"Favorable","Très favorable")))))) -> 0 | G93: =IF(OR(B93="",C93="",C93=0),"",IF(F93<>"",F93,B93*(1-$B$91))/C93) -> 0
A94: An 3 · S2 (intercampagne) | B94: 10 | C94: 17 | D94: =IF(OR(B94="",C94=""),"",IF(C94=0,"",B94/C94)) -> 0 | E94: =IF(B94="","",IF(C94=0,"Différé",IF(B94<0,"Critique",IF(D94<$B$88,"Critique",IF(D94<$C$88,"Vigilance",IF(D94<$D$88,"Favorable","Très favorable")))))) -> 0 | G94: =IF(OR(B94="",C94="",C94=0),"",IF(F94<>"",F94,B94*(1-$B$91))/C94) -> 0 | H94: =IF(AND($B$21="Semestrielle",B94<>"",B93<>"",N(C94)+N(C93)>0),(B94+B93)/(C94+C93),"") -> 0
A95: An 6 · S1 (campagne) | B95: 43 | C95: 17 | D95: =IF(OR(B95="",C95=""),"",IF(C95=0,"",B95/C95)) -> 0 | E95: =IF(B95="","",IF(C95=0,"Différé",IF(B95<0,"Critique",IF(D95<$B$88,"Critique",IF(D95<$C$88,"Vigilance",IF(D95<$D$88,"Favorable","Très favorable")))))) -> 0 | G95: =IF(OR(B95="",C95="",C95=0),"",IF(F95<>"",F95,B95*(1-$B$91))/C95) -> 0
A96: An 6 · S2 (intercampagne) | B96: 10.5 | C96: 17 | D96: =IF(OR(B96="",C96=""),"",IF(C96=0,"",B96/C96)) -> 0 | E96: =IF(B96="","",IF(C96=0,"Différé",IF(B96<0,"Critique",IF(D96<$B$88,"Critique",IF(D96<$C$88,"Vigilance",IF(D96<$D$88,"Favorable","Très favorable")))))) -> 0 | G96: =IF(OR(B96="",C96="",C96=0),"",IF(F96<>"",F96,B96*(1-$B$91))/C96) -> 0 | H96: =IF(AND($B$21="Semestrielle",B96<>"",B95<>"",N(C96)+N(C95)>0),(B96+B95)/(C96+C95),"") -> 0
D97: =IF(OR(B97="",C97=""),"",IF(C97=0,"",B97/C97)) -> 0 | E97: =IF(B97="","",IF(C97=0,"Différé",IF(B97<0,"Critique",IF(D97<$B$88,"Critique",IF(D97<$C$88,"Vigilance",IF(D97<$D$88,"Favorable","Très favorable")))))) -> 0 | G97: =IF(OR(B97="",C97="",C97=0),"",IF(F97<>"",F97,B97*(1-$B$91))/C97) -> 0
D98: =IF(OR(B98="",C98=""),"",IF(C98=0,"",B98/C98)) -> 0 | E98: =IF(B98="","",IF(C98=0,"Différé",IF(B98<0,"Critique",IF(D98<$B$88,"Critique",IF(D98<$C$88,"Vigilance",IF(D98<$D$88,"Favorable","Très favorable")))))) -> 0 | G98: =IF(OR(B98="",C98="",C98=0),"",IF(F98<>"",F98,B98*(1-$B$91))/C98) -> 0 | H98: =IF(AND($B$21="Semestrielle",B98<>"",B97<>"",N(C98)+N(C97)>0),(B98+B97)/(C98+C97),"") -> 0
D99: =IF(OR(B99="",C99=""),"",IF(C99=0,"",B99/C99)) -> 0 | E99: =IF(B99="","",IF(C99=0,"Différé",IF(B99<0,"Critique",IF(D99<$B$88,"Critique",IF(D99<$C$88,"Vigilance",IF(D99<$D$88,"Favorable","Très favorable")))))) -> 0 | G99: =IF(OR(B99="",C99="",C99=0),"",IF(F99<>"",F99,B99*(1-$B$91))/C99) -> 0
D100: =IF(OR(B100="",C100=""),"",IF(C100=0,"",B100/C100)) -> 0 | E100: =IF(B100="","",IF(C100=0,"Différé",IF(B100<0,"Critique",IF(D100<$B$88,"Critique",IF(D100<$C$88,"Vigilance",IF(D100<$D$88,"Favorable","Très favorable")))))) -> 0 | G100: =IF(OR(B100="",C100="",C100=0),"",IF(F100<>"",F100,B100*(1-$B$91))/C100) -> 0 | H100: =IF(AND($B$21="Semestrielle",B100<>"",B99<>"",N(C100)+N(C99)>0),(B100+B99)/(C100+C99),"") -> 0
D101: =IF(OR(B101="",C101=""),"",IF(C101=0,"",B101/C101)) -> 0 | E101: =IF(B101="","",IF(C101=0,"Différé",IF(B101<0,"Critique",IF(D101<$B$88,"Critique",IF(D101<$C$88,"Vigilance",IF(D101<$D$88,"Favorable","Très favorable")))))) -> 0 | G101: =IF(OR(B101="",C101="",C101=0),"",IF(F101<>"",F101,B101*(1-$B$91))/C101) -> 0
D102: =IF(OR(B102="",C102=""),"",IF(C102=0,"",B102/C102)) -> 0 | E102: =IF(B102="","",IF(C102=0,"Différé",IF(B102<0,"Critique",IF(D102<$B$88,"Critique",IF(D102<$C$88,"Vigilance",IF(D102<$D$88,"Favorable","Très favorable")))))) -> 0 | G102: =IF(OR(B102="",C102="",C102=0),"",IF(F102<>"",F102,B102*(1-$B$91))/C102) -> 0 | H102: =IF(AND($B$21="Semestrielle",B102<>"",B101<>"",N(C102)+N(C101)>0),(B102+B101)/(C102+C101),"") -> 0
D103: =IF(OR(B103="",C103=""),"",IF(C103=0,"",B103/C103)) -> 0 | E103: =IF(B103="","",IF(C103=0,"Différé",IF(B103<0,"Critique",IF(D103<$B$88,"Critique",IF(D103<$C$88,"Vigilance",IF(D103<$D$88,"Favorable","Très favorable")))))) -> 0 | G103: =IF(OR(B103="",C103="",C103=0),"",IF(F103<>"",F103,B103*(1-$B$91))/C103) -> 0
D104: =IF(OR(B104="",C104=""),"",IF(C104=0,"",B104/C104)) -> 0 | E104: =IF(B104="","",IF(C104=0,"Différé",IF(B104<0,"Critique",IF(D104<$B$88,"Critique",IF(D104<$C$88,"Vigilance",IF(D104<$D$88,"Favorable","Très favorable")))))) -> 0 | G104: =IF(OR(B104="",C104="",C104=0),"",IF(F104<>"",F104,B104*(1-$B$91))/C104) -> 0 | H104: =IF(AND($B$21="Semestrielle",B104<>"",B103<>"",N(C104)+N(C103)>0),(B104+B103)/(C104+C103),"") -> 0
...

Sheet C4B
A1: CAS 4 — variante B · Unité agro-industrielle — structure restructurée | J1: DOSSIER_V8 | K1: V3
A2: SPV « Doukkala Agro » SA (fictive) — Région de Doukkala-Abda
A3: Même actif, même marché, même grille qualitative. Trois corrections de montage : amortissement sculpté sur la campagne, apport complémentaire de 40 MMAD, couverture de change portée à 90 %.
A4: À SAISIR (cellules orange) | B4: =COUNTIF($R$14:$R$63,0) -> 0 | C4: =IF(B4=0,"Saisie complète : lisez la note ci-dessous, puis « Fiche comité ».","Prochaine saisie : "&INDEX($P$14:$P$63,MATCH(0,$R$14:$R$63,0))) -> 0 | G4: =IF(B4=0,"",HYPERLINK("#"&INDEX($Q$14:$Q$63,MATCH(0,$R$14:$R$63,0)),"→ Aller à la cellule "&INDEX($Q$14:$Q$63,MATCH(0,$R$14:$R$63,0)))) -> 0
A5: ="TABLEAU DE BORD — "&IF($B$17="","code projet à saisir",$B$17)&" · client "&IF($B$15="","—",$B$15)&" · radical "&IF($B$16="","—",$B$16) -> 0
A6: NOTE APPROUVÉE (1 à 10) | B6: =B276 -> 0 | C6: Libellé | D6: =IFERROR(INDEX(P_ConvLib,MATCH(B276,P_ConvNote,0)),"") -> 0 | E6: Statut | F6: =B277 -> 0
A7: Score global (sur 100) | B7: =B238 -> 0 | C7: Note calculée | D7: =B239 -> 0 | E7: Plafond applicable | F7: =IF(B273>=10,"Aucun (10)",B273) -> 0
A8: Plafonds actifs | B8: =IF(TRIM(IF(E258="Oui","C1 ("&F258&") ","")&IF(E259="Oui","C2 ("&F259&") ","")&IF(E260="Oui","C3 ("&F260&") ","")&IF(E261="Oui","C4 ("&F261&") ","")&IF(E262="Oui","C5 ("&F262&") ","")&IF(E263="Oui","C6 ("&F263&") ","")&IF(E264="Oui","C7 ("&F264&") ","")&IF(E265="Oui","C8 ("&F265&") ","")&IF(E266="Oui","C9 ("&F266&") ","")&IF(E267="Oui","C10 ("&F267&") ","")&IF(E268="Oui","C11 ("&F268&") ","")&IF(E269="Oui","C12 ("&F269&") ","")&IF(E270="Oui","C13 ("&F270&") ","")&IF(E271="Oui","C14 ("&F271&") ","")&IF(E272="Oui","C15 ("&F272&") ",""))="","Aucun",TRIM(IF(E258="Oui","C1 ("&F258&") ","")&IF(E259="Oui","C2 ("&F259&") ","")&IF(E260="Oui","C3 ("&F260&") ","")&IF(E261="Oui","C4 ("&F261&") ","")&IF(E262="Oui","C5 ("&F262&") ","")&IF(E263="Oui","C6 ("&F263&") ","")&IF(E264="Oui","C7 ("&F264&") ","")&IF(E265="Oui","C8 ("&F265&") ","")&IF(E266="Oui","C9 ("&F266&") ","")&IF(E267="Oui","C10 ("&F267&") ","")&IF(E268="Oui","C11 ("&F268&") ","")&IF(E269="Oui","C12 ("&F269&") ","")&IF(E270="Oui","C13 ("&F270&") ","")&IF(E271="Oui","C14 ("&F271&") ","")&IF(E272="Oui","C15 ("&F272&") ","")))&IF(COUNTIF(E258:E272,"n.r.")>0," — "&COUNTIF(E258:E272,"n.r.")&" plafond(s) non évalué(s) faute de donnée","") -> 0
A9: Verrous actifs (exclusions X, blocages B) | B9: =IF(TRIM(IF(F243="Oui","X1 ","")&IF(F244="Oui","X2 ","")&IF(F245="Oui","X3 ","")&IF(F246="Oui","X4 ","")&IF(F247="Oui","B1 ","")&IF(F248="Oui","B2 ","")&IF(F249="Oui","B3 ","")&IF(F250="Oui","B4 ","")&IF(F251="Oui","B5 ","")&IF(F252="Oui","B6 ","")&IF(F253="Oui","B7 ","")&IF(F254="Oui","B8 ",""))="","Aucun",TRIM(IF(F243="Oui","X1 ","")&IF(F244="Oui","X2 ","")&IF(F245="Oui","X3 ","")&IF(F246="Oui","X4 ","")&IF(F247="Oui","B1 ","")&IF(F248="Oui","B2 ","")&IF(F249="Oui","B3 ","")&IF(F250="Oui","B4 ","")&IF(F251="Oui","B5 ","")&IF(F252="Oui","B6 ","")&IF(F253="Oui","B7 ","")&IF(F254="Oui","B8 ",""))) -> 0
A10: Régime de proportionnalité retenu | B10: =B38 -> 0 | C10: DSCR minimum | D10: =D154 -> 0 | E10: DSCR stressé min. | F10: =D155 -> 0
A11: Complétude (noyau N1-N6 et grille) | B11: =B225 -> 0 | C11: Noyau financier D7 | D11: =D169 -> 0 | E11: Orientation | F11: =IFERROR(INDEX(P_ConvOrient,MATCH(B276,P_ConvNote,0)),"") -> 0
A12: Aller à la section : | B12: =HYPERLINK("#A13","1 · Identification") -> 0 | C12: =HYPERLINK("#A40","3 · Sources") -> 0 | D12: =HYPERLINK("#A90","6 · Échéancier") -> 0 | E12: =HYPERLINK("#A161","7 · Noyau") -> 0 | F12: =HYPERLINK("#A188","8 · Grille") -> 0 | G12: =HYPERLINK("#A256","11 · Plafonds") -> 0 | H12: =HYPERLINK("#A279","13 · Commentaires") -> 0
A13: 1 · IDENTIFICATION ET ROUTAGE — codes du client et du projet ; le routage pilote seuils et poids
A14: Axe | B14: Valeur | C14: Libellé, contrôle | P14: 1 · Code client T24 | Q14: B15 | R14: =IF(AND(LEN(TRIM($B$15))>=1,LEN($B$15)<=20),1,0) -> 0
A15: Code client T24 (société de projet) | B15: 20077415 | C15: =IF(B15="","À saisir — Texte, zéros de tête conservés.",IF(AND(LEN(TRIM(B15))>=1,LEN(B15)<=20),"Format conforme.","Format non conforme : Texte, zéros de tête conservés.")) -> 0 | P15: 1 · Radical du client (7 chiffres) | Q15: B16 | R15: =IF(AND(LEN($B$16)=7,SUMPRODUCT(--ISNUMBER(FIND(MID($B$16,ROW(INDIRECT("1:7"))+0,1),"0123456789")))=7),1,0) -> 0
A16: Radical du client (7 chiffres) | B16: 0077415 | C16: =IF(B16="","À saisir — Exactement 7 chiffres, zéros de tête compris.",IF(AND(LEN(B16)=7,SUMPRODUCT(--ISNUMBER(FIND(MID(B16,ROW(INDIRECT("1:7"))+0,1),"0123456789")))=7),"Format conforme.","Format non conforme : Exactement 7 chiffres, zéros de tête compris.")) -> 0 | P16: 1 · Code projet (PF-AAAA-NNNN) | Q16: B17 | R16: =IF(AND(LEN($B$17)=12,EXACT(LEFT($B$17,3),"PF-"),MID($B$17,8,1)="-",SUMPRODUCT(--ISNUMBER(FIND(MID($B$17,ROW(INDIRECT("1:4"))+3,1),"0123456789")))=4,SUMPRODUCT(--ISNUMBER(FIND(MID($B$17,ROW(INDIRECT("1:4"))+8,1),"0123456789")))=4),1,0) -> 0
A17: Code projet | B17: PF-2026-0004 | C17: =IF(B17="","À saisir — Format PF-AAAA-NNNN.",IF(AND(LEN(B17)=12,EXACT(LEFT(B17,3),"PF-"),MID(B17,8,1)="-",SUMPRODUCT(--ISNUMBER(FIND(MID(B17,ROW(INDIRECT("1:4"))+3,1),"0123456789")))=4,SUMPRODUCT(--ISNUMBER(FIND(MID(B17,ROW(INDIRECT("1:4"))+8,1),"0123456789")))=4),"Format conforme.","Format non conforme : Format PF-AAAA-NNNN.")) -> 0 | P17: 1 · Régime de revenus | Q17: B18 | R17: =IF($B$18<>"",1,0) -> 0
A18: C — Régime de revenus | B18: R3 | C18: =IFERROR(INDEX(P_RegLib,MATCH(B18,P_Regimes,0)),"") -> 0 | P18: 1 · Secteur du projet | Q18: B19 | R18: =IF($B$19<>"",1,0) -> 0
A19: D — Secteur du projet | B19: AGR | C19: =IFERROR(INDEX(P_SecLib,MATCH(B19,P_SecCodes,0)),"") -> 0 | P19: 1 · Phase du projet | Q19: B20 | R19: =IF($B$20<>"",1,0) -> 0
A20: B — Phase | B20: P3 | C20: =IFERROR(INDEX(P_PhaseLib,MATCH(B20,P_PhaseCodes,0)),"") -> 0 | P20: 1 · Périodicité des échéances | Q20: B21 | R20: =IF($B$21<>"",1,0) -> 0
A21: Périodicité du service de la dette | B21: Semestrielle | C21: Jamais annuelle : le DSCR se mesure échéance par échéance. | P21: 2 · Exposition de la banque (MMAD) | Q21: B26 | R21: =IF(ISNUMBER($B$26),1,0) -> 0
A22: A — Famille de financement | B22: PF-FLUX | C22: SPV dédiée, remboursement par les flux du projet (R5 vente d'actifs : hors outil). | P22: 2 · Recettes, coûts et dette en dirhams ? | Q22: B27 | R22: =IF($B$27<>"",1,0) -> 0
P23: 2 · Durée du financement (ans) | Q23: B28 | R23: =IF(ISNUMBER($B$28),1,0) -> 0
A24: 2 · RÉGIME DE PROPORTIONNALITÉ — calculé, jamais choisi | P24: 2 · Technologie éprouvée ? | Q24: B29 | R24: =IF($B$29<>"",1,0) -> 0
A25: CAPEX du projet économique complet (MMAD) | B25: =B50 -> 0 | C25: Repris du total des emplois (section 3). | P25: 2 · EPC clé-en-main de moins de 18 mois ? (phase P1) | Q25: B30 | R25: =IF(OR(NOT($B$20="P1"),$B$30<>""),1,0) -> 0
A26: Exposition de la banque (MMAD) | B26: 210 | P26: 2 · Acheteur principal unique ? | Q26: B31 | R26: =IF($B$31<>"",1,0) -> 0
A27: Recettes, coûts et dette intégralement en dirhams | B27: Non | P27: 2 · Première référence technologique ? | Q27: B32 | R27: =IF($B$32<>"",1,0) -> 0
A28: Durée du financement (ans) | B28: 10 | P28: 2 · Opération consortiale ? | Q28: B33 | R28: =IF($B$33<>"",1,0) -> 0
A29: Technologie : ≥ 3 références industrielles de plus de 3 ans | B29: Oui | P29: 2 · Contrat de revenus de plus de 20 ans ? | Q29: B34 | R29: =IF($B$34<>"",1,0) -> 0
A30: En P1 : EPC clé-en-main forfaitaire, prix et délai garantis, < 18 mois | B30: Non | P30: 2 · Site à risque climatique élevé ? | Q30: B35 | R30: =IF($B$35<>"",1,0) -> 0
A31: Acheteur principal unique et identifié | B31: Non | P31: 2 · Nombre de contreparties clés | Q31: B36 | R31: =IF(ISNUMBER($B$36),1,0) -> 0
A32: Technologie constituant une première référence dans la juridiction | B32: Non | P32: 3 · Emplois : montants du besoin à terminaison | Q32: B42 | R32: =IF(N($B$50)>0,1,0) -> 0
A33: Opération consortiale relevant de la directive 3/W/2025 | B33: Non | P33: 3 · Ressources engagées : montants | Q33: E42 | R33: =IF(N($E$50)>0,1,0) -> 0
A34: Concession ou contrat de revenus de plus de 20 ans | B34: Non | P34: 3 · Nature de chaque ressource | Q34: F42 | R34: =IF(SUMPRODUCT(ISNUMBER($E$42:$E$49)*($F$42:$F$49=""))=0,1,0) -> 0
A35: Site classé à risque climatique physique élevé | B35: Non | P35: 3 · Plan de remédiation (couverture entre 95 et 100 %) | Q35: B53 | R35: =IF(OR(NOT(AND($B$20="P1",ISNUMBER($B$51),N($B$51)>=P_N3_V,N($B$51)<P_N3_F)),$B$53<>""),1,0) -> 0
A36: Nombre de contreparties clés | B36: 3 | P36: 6 · Choc du scénario défavorable (%) | Q36: B91 | R36: =IF(ISNUMBER($B$91),1,0) -> 0
A37: Régime calculé (avant escalade) | B37: =IF(OR(B25="",B25=0,B18=""),"",IF(OR(B25>P_L_CAPEX,N(B26)>P_L_EXPO,B18="R4",B32="Oui",N(B174)>0,B33="Oui",B34="Oui",B35="Oui",N(B36)>P_L_NBCP),"L",IF(AND(B25<=P_S_CAPEX,B26<>"",N(B26)<=P_S_EXPO,OR(B18="R1",B18="R2"),B29="Oui",B27="Oui",B28<>"",N(B28)<=P_S_DUREE,OR(B20<>"P1",B30="Oui"),B31="Oui",COUNTIF($F$243:$F$254,"Oui")=0),"S","M"))) -> 0 | C37: =IF(B37="","",IF(B37="L","Escalade : "&IF(B25>P_L_CAPEX,"CAPEX > "&P_L_CAPEX&" MMAD ; ","")&IF(N(B26)>P_L_EXPO,"exposition > "&P_L_EXPO&" MMAD ; ","")&IF(B18="R4","régime de revenus R4 ; ","")&IF(B32="Oui","première référence technologique ; ","")&IF(N(B174)>0,"devises non intégralement couvertes ; ","")&IF(B33="Oui","opération consortiale ; ","")&IF(B34="Oui","contrat de revenus > 20 ans ; ","")&IF(B35="Oui","risque climatique élevé ; ","")&IF(N(B36)>P_L_NBCP,"plus de "&P_L_NBCP&" contreparties clés ; ",""),IF(B37="S","Toutes les conditions du régime simplifié sont réunies.","Régime standard par défaut : une condition du régime S manque, aucune condition d'escalade."))) -> 0 | P37: 6 · Échéancier : CFADS d'au moins deux périodes | Q37: B93 | R37: =IF(COUNT($B$93:$B$152)>=2,1,0) -> 0
A38: RÉGIME RETENU (après escalade automatique) | B38: =IF(B37="","",IF(AND(IF(AND(B37="S",COUNTIF($F$243:$F$254,"Oui")>0),"M",B37)="M",COUNTIF($E$258:$E$272,"Oui")>0),"L",IF(AND(B37="S",COUNTIF($F$243:$F$254,"Oui")>0),"M",B37))) -> 0 | C38: =IF(B38=B37,"Aucune escalade.",IF(B38="L","Escalade : un plafond de note est actif (M passe en L).","Escalade : un verrou est actif (S passe en M).")) -> 0 | P38: 6 · Service de la dette de chaque période | Q38: C93 | R38: =IF(SUMPRODUCT(ISNUMBER($B$93:$B$152)*(1-ISNUMBER($C$93:$C$152)))=0,1,0) -> 0
P39: 7 · N4 — Liquidité : situation à choisir | Q39: E166 | R39: =IF($B$166<>"",1,0) -> 0
A40: 3 · SOURCES ET EMPLOIS (MMAD) — test de financement à terminaison ; crédits de la banque | P40: 7 · N5 — Levier : situation à choisir | Q40: E167 | R40: =IF($B$167<>"",1,0) -> 0
A41: Emplois | B41: Montant | D41: Ressources | E41: Montant | F41: Nature | P41: 7 · N6 — Exposition résiduelle : situation à choisir | Q41: E168 | R41: =IF($B$168<>"",1,0) -> 0
A42: Ligne de production et bâtiments | B42: 300 | D42: Dette senior (10 ans, 6,0 %), amortissement sculpté | E42: 210 | F42: Dette senior | P42: 7 · Justification exigée (N4 à N6 Critique ou Info. insuffisante) | Q42: ="H"&IF(COUNT($T$166:$T$168)=0,166,MIN($T$166:$T$168)) -> 0 | R42: =IF(COUNT($T$166:$T$168)=0,1,0) -> 0
A43: Stockage et froid | B43: 70 | D43: Fonds propres | E43: 210 | F43: Fonds propres | P43: 7 · N3 hors phase P1 : note LLCR | Q43: B171 | R43: =IF(OR($B$20="P1",$B$171<>""),1,0) -> 0
A44: Terrain et aménagements | B44: 25 | D44: Ligne de campagne dédiée (engagée) | E44: 25 | F44: Ligne dédiée engagée | P44: 7 · LLCR (plafond C4) | Q44: B172 | R44: =IF(ISNUMBER($B$172),1,0) -> 0
A45: Frais et intérêts intercalaires | B45: 17 | P45: 7 · DSRA en mois (plafond C7) | Q45: B173 | R45: =IF(ISNUMBER($B$173),1,0) -> 0
A46: Dotation DSRA | B46: 8 | P46: 7 · Exposition nette en devises (plafond C6) | Q46: B174 | R46: =IF(ISNUMBER($B$174),1,0) -> 0
P47: 7 · Dette à refinancer à maturité (plafond C8) | Q47: B175 | R47: =IF(ISNUMBER($B$175),1,0) -> 0
P48: 7 · Stratégie de refinancement approuvée ? | Q48: B176 | R48: =IF(OR(N($B$175)<=P_C8,$B$176<>""),1,0) -> 0
P49: 7 · Part des recettes de l'acheteur principal (C10) | Q49: B177 | R49: =IF(ISNUMBER($B$177),1,0) -> 0
A50: Total emplois (besoin à terminaison) | B50: =SUM(B42:B49) -> 0 | D50: Total ressources engagées | E50: =SUM(E42:E49) -> 0 | P50: 7 · Qualité de crédit de l'acheteur principal | Q50: B178 | R50: =IF($B$178<>"",1,0) -> 0
A51: Couverture du besoin à terminaison (ressources / emplois) | B51: =IF(N(B50)=0,"",E50/B50) -> 0 | P51: 7 · Durée résiduelle du contrat de revenus (C5) | Q51: B179 | R51: =IF(OR($B$18="R4",ISNUMBER($B$179)),1,0) -> 0
A52: Quote-part de dette (dette / besoin à terminaison) | B52: =IF(N(B50)=0,"",(SUMIF(F42:F49,"Dette senior",E42:E49)+SUMIF(F42:F49,"Dette subordonnée",E42:E49))/B50) -> 0 | P52: 7 · Durée résiduelle de la dette | Q52: B180 | R52: =IF(ISNUMBER($B$180),1,0) -> 0
A53: Plan de remédiation approuvé (couverture entre 95 % et 100 %) | B53: Non | P53: 7 · Solution documentée (contrat plus court que la dette) ? | Q53: B181 | R53: =IF(OR(NOT(AND(ISNUMBER($B$179),ISNUMBER($B$180))),N($B$179)>=N($B$180),$B$181<>""),1,0) -> 0
P54: 7 · Plan d'adaptation climatique financé ? (C11) | Q54: B182 | R54: =IF(OR($B$35<>"Oui",$B$182<>""),1,0) -> 0
A55: Crédits de la banque sur le projet — un projet peut porter plusieurs dossiers de crédit | P55: 7 · Capacité résiduelle du sponsor (C12) | Q55: B183 | R55: =IF($B$183<>"",1,0) -> 0
A56: Numéro du dossier de crédit | B56: Nature | E56: Montant (MMAD) | F56: Devise | G56: Durée (ans) | H56: Observation | P56: 7 · Opérateur remplaçable ? (C13) | Q56: B184 | R56: =IF($B$184<>"",1,0) -> 0
A57: CR-26-0402 | B57: Crédit d'investissement (moyen et long terme) | E57: 210 | F57: MAD | G57: 10 | P57: 7 · Écart fin O&M / fin de dette (opérateur non remplaçable) | Q57: B185 | R57: =IF(OR($B$184<>"Non",ISNUMBER($B$185)),1,0) -> 0
A58: CR-26-0403 | B58: Ligne de fonctionnement (BFR) | E58: 25 | F58: MAD | G58: 1 | P58: 7 · Facteur commun au-delà de la limite interne (C14) | Q58: B186 | R58: =IF($B$186<>"",1,0) -> 0
P59: 8 · Grille : sous-critère requis sans situation choisie | Q59: ="E"&IF(COUNT($P$190:$P$222)=0,191,MIN($P$190:$P$222)) -> 0 | R59: =IF(COUNT($P$190:$P$222)=0,1,0) -> 0
P60: 8 · Commentaire exigé (situation Critique ou Info. insuffisante) | Q60: ="H"&IF(COUNT($T$190:$T$222)=0,191,MIN($T$190:$T$222)) -> 0 | R60: =IF(COUNT($T$190:$T$222)=0,1,0) -> 0
P61: 10 · Verrous X1 à B8 : répondre Oui ou Non | Q61: E243 | R61: =IF(COUNTBLANK($E$243:$E$254)=0,1,0) -> 0
P62: 13 · Synthèse de l'analyste | Q62: B280 | R62: =IF($B$280<>"",1,0) -> 0
A63: Total des crédits de la banque (MMAD, contre-valeur) | E63: =SUM(E57:E62) -> 0 | F63: Écart avec l'exposition (bloc 2) | H63: =IF(OR(N(E63)=0,NOT(ISNUMBER($B$26))),"",E63-$B$26) -> 0 | P63: 13 · Justification des écarts (plafond, verrou ou info. insuffisante) | Q63: B284 | R63: =IF(OR(NOT(OR(COUNTIF($E$258:$E$272,"Oui")>0,COUNTIF($F$243:$F$254,"Oui")>0,SUMPRODUCT(($J$190:$J$222="SC")*($K$190:$K$222=1)*($S$190:$S$222=5))>0,COUNTIF($S$166:$S$168,5)>0)),$B$284<>""),1,0) -> 0
A65: 4 · DONNÉES SECTORIELLES ET HYPOTHÈSES D'EXPLOITATION (information, non calculées)
A66: ="Données du secteur "&IF($B$19="","(choisissez le secteur au bloc 1)",$B$19) -> 0 | B66: Valeur | C66: Unité | D66: Observation ou source
A67: =IF($B$19="",IF(0=0,"Choisissez d'abord le secteur (bloc 1)",""),IFERROR(IF(T(INDEX(R_SecChamps,MATCH($B$19,R_SecCodes,0),1))="","Sans objet pour ce secteur",T(INDEX(R_SecChamps,MATCH($B$19,R_SecCodes,0),1))),"")) -> 0 | B67: 60 | C67: =IFERROR(T(INDEX(R_SecUnites,MATCH($B$19,R_SecCodes,0),1)),"") -> 0
A68: =IF($B$19="",IF(1=0,"Choisissez d'abord le secteur (bloc 1)",""),IFERROR(IF(T(INDEX(R_SecChamps,MATCH($B$19,R_SecCodes,0),2))="","Sans objet pour ce secteur",T(INDEX(R_SecChamps,MATCH($B$19,R_SecCodes,0),2))),"")) -> 0 | B68: 3.2 | C68: =IFERROR(T(INDEX(R_SecUnites,MATCH($B$19,R_SecCodes,0),2)),"") -> 0
A69: =IF($B$19="",IF(2=0,"Choisissez d'abord le secteur (bloc 1)",""),IFERROR(IF(T(INDEX(R_SecChamps,MATCH($B$19,R_SecCodes,0),3))="","Sans objet pour ce secteur",T(INDEX(R_SecChamps,MATCH($B$19,R_SecCodes,0),3))),"")) -> 0 | B69: 70 | C69: =IFERROR(T(INDEX(R_SecUnites,MATCH($B$19,R_SecCodes,0),3)),"") -> 0
A70: =IF($B$19="",IF(3=0,"Choisissez d'abord le secteur (bloc 1)",""),IFERROR(IF(T(INDEX(R_SecChamps,MATCH($B$19,R_SecCodes,0),4))="","Sans objet pour ce secteur",T(INDEX(R_SecChamps,MATCH($B$19,R_SecCodes,0),4))),"")) -> 0 | B70: 40 | C70: =IFERROR(T(INDEX(R_SecUnites,MATCH($B$19,R_SecCodes,0),4)),"") -> 0
A71: =IF($B$19="",IF(4=0,"Choisissez d'abord le secteur (bloc 1)",""),IFERROR(IF(T(INDEX(R_SecChamps,MATCH($B$19,R_SecCodes,0),5))="","Sans objet pour ce secteur",T(INDEX(R_SecChamps,MATCH($B$19,R_SecCodes,0),5))),"")) -> 0 | C71: =IFERROR(T(INDEX(R_SecUnites,MATCH($B$19,R_SecCodes,0),5)),"") -> 0
A72: =IF($B$19="",IF(5=0,"Choisissez d'abord le secteur (bloc 1)",""),IFERROR(IF(T(INDEX(R_SecChamps,MATCH($B$19,R_SecCodes,0),6))="","Sans objet pour ce secteur",T(INDEX(R_SecChamps,MATCH($B$19,R_SecCodes,0),6))),"")) -> 0 | C72: =IFERROR(T(INDEX(R_SecUnites,MATCH($B$19,R_SecCodes,0),6)),"") -> 0
A73: Autres hypothèses d'exploitation | B73: Valeur
A74: Chiffre d’affaires | B74: 380 MMAD/an — inchangé
A75: CFADS | B75: 52 MMAD/an — inchangé
A76: Service sculpté | B76: 25 MMAD en campagne, 3,5 MMAD en intercampagne
A77: Couverture de change | B77: 90 % des achats importés
A78: Exposition nette résiduelle | B78: 4,5 MMAD, soit 16 % du service annuel
A83: 5 · SEUILS DSCR APPLICABLES = base du régime + Δ secteur + majoration de phase
A84: Seuil critique de base du régime | B84: =IFERROR(INDEX(P_Crit,MATCH($B$18,P_Regimes,0)),"") -> 0
A85: Écart sectoriel Δ | B85: =IFERROR(INDEX(P_SecDelta,MATCH($B$19,P_SecCodes,0)),"") -> 0
A86: Majoration de phase | B86: =IFERROR(INDEX(P_PhaseMaj,MATCH($B$20,P_PhaseCodes,0)),"") -> 0
A87: Seuils applicables | B87: Critique < | C87: Vigilance < | D87: Favorable < | E87: Très favorable ≥
A88: Seuil = base + Δ + majoration | B88: =IFERROR(INDEX(P_Crit,MATCH($B$18,P_Regimes,0))+$B$85+$B$86,"") -> 0 | C88: =IFERROR(INDEX(P_Vig,MATCH($B$18,P_Regimes,0))+$B$85+$B$86,"") -> 0 | D88: =IFERROR(INDEX(P_Fav,MATCH($B$18,P_Regimes,0))+$B$85+$B$86,"") -> 0 | E88: =D88 -> 0
A90: 6 · ÉCHÉANCIER DATÉ ET DSCR PAR ÉCHÉANCE (jusqu'à 60 périodes)
A91: Scénario défavorable : baisse du CFADS appliquée à chaque période | B91: 0.32619 | C91: Même choc : récolte en recul de 20 % sous stress hydrique
A92: Période | B92: CFADS central | C92: Service de la dette | D92: DSCR | E92: Classement | F92: CFADS stressé (saisie facultative) | G92: DSCR stressé | H92: DSCR annuel (paire de semestres)
A93: An 3 · S1 (campagne) | B93: 42 | C93: 25 | D93: =IF(OR(B93="",C93=""),"",IF(C93=0,"",B93/C93)) -> 0 | E93: =IF(B93="","",IF(C93=0,"Différé",IF(B93<0,"Critique",IF(D93<$B$88,"Critique",IF(D93<$C$88,"Vigilance",IF(D93<$D$88,"Favorable","Très favorable")))))) -> 0 | G93: =IF(OR(B93="",C93="",C93=0),"",IF(F93<>"",F93,B93*(1-$B$91))/C93) -> 0
A94: An 3 · S2 (intercampagne) | B94: 10 | C94: 3.5 | D94: =IF(OR(B94="",C94=""),"",IF(C94=0,"",B94/C94)) -> 0 | E94: =IF(B94="","",IF(C94=0,"Différé",IF(B94<0,"Critique",IF(D94<$B$88,"Critique",IF(D94<$C$88,"Vigilance",IF(D94<$D$88,"Favorable","Très favorable")))))) -> 0 | G94: =IF(OR(B94="",C94="",C94=0),"",IF(F94<>"",F94,B94*(1-$B$91))/C94) -> 0 | H94: =IF(AND($B$21="Semestrielle",B94<>"",B93<>"",N(C94)+N(C93)>0),(B94+B93)/(C94+C93),"") -> 0
A95: An 6 · S1 (campagne) | B95: 43 | C95: 25 | D95: =IF(OR(B95="",C95=""),"",IF(C95=0,"",B95/C95)) -> 0 | E95: =IF(B95="","",IF(C95=0,"Différé",IF(B95<0,"Critique",IF(D95<$B$88,"Critique",IF(D95<$C$88,"Vigilance",IF(D95<$D$88,"Favorable","Très favorable")))))) -> 0 | G95: =IF(OR(B95="",C95="",C95=0),"",IF(F95<>"",F95,B95*(1-$B$91))/C95) -> 0
A96: An 6 · S2 (intercampagne) | B96: 10.5 | C96: 3.5 | D96: =IF(OR(B96="",C96=""),"",IF(C96=0,"",B96/C96)) -> 0 | E96: =IF(B96="","",IF(C96=0,"Différé",IF(B96<0,"Critique",IF(D96<$B$88,"Critique",IF(D96<$C$88,"Vigilance",IF(D96<$D$88,"Favorable","Très favorable")))))) -> 0 | G96: =IF(OR(B96="",C96="",C96=0),"",IF(F96<>"",F96,B96*(1-$B$91))/C96) -> 0 | H96: =IF(AND($B$21="Semestrielle",B96<>"",B95<>"",N(C96)+N(C95)>0),(B96+B95)/(C96+C95),"") -> 0
D97: =IF(OR(B97="",C97=""),"",IF(C97=0,"",B97/C97)) -> 0 | E97: =IF(B97="","",IF(C97=0,"Différé",IF(B97<0,"Critique",IF(D97<$B$88,"Critique",IF(D97<$C$88,"Vigilance",IF(D97<$D$88,"Favorable","Très favorable")))))) -> 0 | G97: =IF(OR(B97="",C97="",C97=0),"",IF(F97<>"",F97,B97*(1-$B$91))/C97) -> 0
D98: =IF(OR(B98="",C98=""),"",IF(C98=0,"",B98/C98)) -> 0 | E98: =IF(B98="","",IF(C98=0,"Différé",IF(B98<0,"Critique",IF(D98<$B$88,"Critique",IF(D98<$C$88,"Vigilance",IF(D98<$D$88,"Favorable","Très favorable")))))) -> 0 | G98: =IF(OR(B98="",C98="",C98=0),"",IF(F98<>"",F98,B98*(1-$B$91))/C98) -> 0 | H98: =IF(AND($B$21="Semestrielle",B98<>"",B97<>"",N(C98)+N(C97)>0),(B98+B97)/(C98+C97),"") -> 0
D99: =IF(OR(B99="",C99=""),"",IF(C99=0,"",B99/C99)) -> 0 | E99: =IF(B99="","",IF(C99=0,"Différé",IF(B99<0,"Critique",IF(D99<$B$88,"Critique",IF(D99<$C$88,"Vigilance",IF(D99<$D$88,"Favorable","Très favorable")))))) -> 0 | G99: =IF(OR(B99="",C99="",C99=0),"",IF(F99<>"",F99,B99*(1-$B$91))/C99) -> 0
D100: =IF(OR(B100="",C100=""),"",IF(C100=0,"",B100/C100)) -> 0 | E100: =IF(B100="","",IF(C100=0,"Différé",IF(B100<0,"Critique",IF(D100<$B$88,"Critique",IF(D100<$C$88,"Vigilance",IF(D100<$D$88,"Favorable","Très favorable")))))) -> 0 | G100: =IF(OR(B100="",C100="",C100=0),"",IF(F100<>"",F100,B100*(1-$B$91))/C100) -> 0 | H100: =IF(AND($B$21="Semestrielle",B100<>"",B99<>"",N(C100)+N(C99)>0),(B100+B99)/(C100+C99),"") -> 0
D101: =IF(OR(B101="",C101=""),"",IF(C101=0,"",B101/C101)) -> 0 | E101: =IF(B101="","",IF(C101=0,"Différé",IF(B101<0,"Critique",IF(D101<$B$88,"Critique",IF(D101<$C$88,"Vigilance",IF(D101<$D$88,"Favorable","Très favorable")))))) -> 0 | G101: =IF(OR(B101="",C101="",C101=0),"",IF(F101<>"",F101,B101*(1-$B$91))/C101) -> 0
D102: =IF(OR(B102="",C102=""),"",IF(C102=0,"",B102/C102)) -> 0 | E102: =IF(B102="","",IF(C102=0,"Différé",IF(B102<0,"Critique",IF(D102<$B$88,"Critique",IF(D102<$C$88,"Vigilance",IF(D102<$D$88,"Favorable","Très favorable")))))) -> 0 | G102: =IF(OR(B102="",C102="",C102=0),"",IF(F102<>"",F102,B102*(1-$B$91))/C102) -> 0 | H102: =IF(AND($B$21="Semestrielle",B102<>"",B101<>"",N(C102)+N(C101)>0),(B102+B101)/(C102+C101),"") -> 0
D103: =IF(OR(B103="",C103=""),"",IF(C103=0,"",B103/C103)) -> 0 | E103: =IF(B103="","",IF(C103=0,"Différé",IF(B103<0,"Critique",IF(D103<$B$88,"Critique",IF(D103<$C$88,"Vigilance",IF(D103<$D$88,"Favorable","Très favorable")))))) -> 0 | G103: =IF(OR(B103="",C103="",C103=0),"",IF(F103<>"",F103,B103*(1-$B$91))/C103) -> 0
D104: =IF(OR(B104="",C104=""),"",IF(C104=0,"",B104/C104)) -> 0 | E104: =IF(B104="","",IF(C104=0,"Différé",IF(B104<0,"Critique",IF(D104<$B$88,"Critique",IF(D104<$C$88,"Vigilance",IF(D104<$D$88,"Favorable","Très favorable")))))) -> 0 | G104: =IF(OR(B104="",C104="",C104=0),"",IF(F104<>"",F104,B104*(1-$B$91))/C104) -> 0 | H104: =IF(AND($B$21="Semestrielle",B104<>"",B103<>"",N(C104)+N(C103)>0),(B104+B103)/(C104+C103),"") -> 0
D105: =IF(OR(B105="",C105=""),"",IF(C105=0,"",B105/C105)) -> 0 | E105: =IF(B105="","",IF(C105=0,"Différé",IF(B105<0,"Critique",IF(D105<$B$88,"Critique",IF(D105<$C$88,"Vigilance",IF(D105<$D$88,"Favorable","Très favorable")))))) -> 0 | G105: =IF(OR(B105="",C105="",C105=0),"",IF(F105<>"",F105,B105*(1-$B$91))/C105) -> 0
D106: =IF(OR(B106="",C106=""),"",IF(C106=0,"",B106/C106)) -> 0 | E106: =IF(B106="","",IF(C106=0,"Différé",IF(B106<0,"Critique",IF(D106<$B$88,"Critique",IF(D106<$C$88,"Vigilance",IF(D106<$D$88,"Favorable","Très favorable")))))) -> 0 | G106: =IF(OR(B106="",C106="",C106=0),"",IF(F106<>"",F106,B106*(1-$B$91))/C106) -> 0 | H106: =IF(AND($B$21="Semestrielle",B106<>"",B105<>"",N(C106)+N(C105)>0),(B106+B105)/(C106+C105),"") -> 0
...

Sheet C5
A1: CAS 5 · Centrale PV d’autoproduction 12 MWc | J1: DOSSIER_V8 | K1: V3
A2: SPV « Gharb Énergie » SARL (fictive) — Zone industrielle de Kénitra
A3: Centrale vendant sa production à un industriel privé voisin sous contrat ferme de 15 ans. Petit ticket éligible au régime d'instruction simplifié.
A4: À SAISIR (cellules orange) | B4: =COUNTIF($R$14:$R$63,0) -> 0 | C4: =IF(B4=0,"Saisie complète : lisez la note ci-dessous, puis « Fiche comité ».","Prochaine saisie : "&INDEX($P$14:$P$63,MATCH(0,$R$14:$R$63,0))) -> 0 | G4: =IF(B4=0,"",HYPERLINK("#"&INDEX($Q$14:$Q$63,MATCH(0,$R$14:$R$63,0)),"→ Aller à la cellule "&INDEX($Q$14:$Q$63,MATCH(0,$R$14:$R$63,0)))) -> 0
A5: ="TABLEAU DE BORD — "&IF($B$17="","code projet à saisir",$B$17)&" · client "&IF($B$15="","—",$B$15)&" · radical "&IF($B$16="","—",$B$16) -> 0
A6: NOTE APPROUVÉE (1 à 10) | B6: =B276 -> 0 | C6: Libellé | D6: =IFERROR(INDEX(P_ConvLib,MATCH(B276,P_ConvNote,0)),"") -> 0 | E6: Statut | F6: =B277 -> 0
A7: Score global (sur 100) | B7: =B238 -> 0 | C7: Note calculée | D7: =B239 -> 0 | E7: Plafond applicable | F7: =IF(B273>=10,"Aucun (10)",B273) -> 0
A8: Plafonds actifs | B8: =IF(TRIM(IF(E258="Oui","C1 ("&F258&") ","")&IF(E259="Oui","C2 ("&F259&") ","")&IF(E260="Oui","C3 ("&F260&") ","")&IF(E261="Oui","C4 ("&F261&") ","")&IF(E262="Oui","C5 ("&F262&") ","")&IF(E263="Oui","C6 ("&F263&") ","")&IF(E264="Oui","C7 ("&F264&") ","")&IF(E265="Oui","C8 ("&F265&") ","")&IF(E266="Oui","C9 ("&F266&") ","")&IF(E267="Oui","C10 ("&F267&") ","")&IF(E268="Oui","C11 ("&F268&") ","")&IF(E269="Oui","C12 ("&F269&") ","")&IF(E270="Oui","C13 ("&F270&") ","")&IF(E271="Oui","C14 ("&F271&") ","")&IF(E272="Oui","C15 ("&F272&") ",""))="","Aucun",TRIM(IF(E258="Oui","C1 ("&F258&") ","")&IF(E259="Oui","C2 ("&F259&") ","")&IF(E260="Oui","C3 ("&F260&") ","")&IF(E261="Oui","C4 ("&F261&") ","")&IF(E262="Oui","C5 ("&F262&") ","")&IF(E263="Oui","C6 ("&F263&") ","")&IF(E264="Oui","C7 ("&F264&") ","")&IF(E265="Oui","C8 ("&F265&") ","")&IF(E266="Oui","C9 ("&F266&") ","")&IF(E267="Oui","C10 ("&F267&") ","")&IF(E268="Oui","C11 ("&F268&") ","")&IF(E269="Oui","C12 ("&F269&") ","")&IF(E270="Oui","C13 ("&F270&") ","")&IF(E271="Oui","C14 ("&F271&") ","")&IF(E272="Oui","C15 ("&F272&") ","")))&IF(COUNTIF(E258:E272,"n.r.")>0," — "&COUNTIF(E258:E272,"n.r.")&" plafond(s) non évalué(s) faute de donnée","") -> 0
A9: Verrous actifs (exclusions X, blocages B) | B9: =IF(TRIM(IF(F243="Oui","X1 ","")&IF(F244="Oui","X2 ","")&IF(F245="Oui","X3 ","")&IF(F246="Oui","X4 ","")&IF(F247="Oui","B1 ","")&IF(F248="Oui","B2 ","")&IF(F249="Oui","B3 ","")&IF(F250="Oui","B4 ","")&IF(F251="Oui","B5 ","")&IF(F252="Oui","B6 ","")&IF(F253="Oui","B7 ","")&IF(F254="Oui","B8 ",""))="","Aucun",TRIM(IF(F243="Oui","X1 ","")&IF(F244="Oui","X2 ","")&IF(F245="Oui","X3 ","")&IF(F246="Oui","X4 ","")&IF(F247="Oui","B1 ","")&IF(F248="Oui","B2 ","")&IF(F249="Oui","B3 ","")&IF(F250="Oui","B4 ","")&IF(F251="Oui","B5 ","")&IF(F252="Oui","B6 ","")&IF(F253="Oui","B7 ","")&IF(F254="Oui","B8 ",""))) -> 0
A10: Régime de proportionnalité retenu | B10: =B38 -> 0 | C10: DSCR minimum | D10: =D154 -> 0 | E10: DSCR stressé min. | F10: =D155 -> 0
A11: Complétude (noyau N1-N6 et grille) | B11: =B225 -> 0 | C11: Noyau financier D7 | D11: =D169 -> 0 | E11: Orientation | F11: =IFERROR(INDEX(P_ConvOrient,MATCH(B276,P_ConvNote,0)),"") -> 0
A12: Aller à la section : | B12: =HYPERLINK("#A13","1 · Identification") -> 0 | C12: =HYPERLINK("#A40","3 · Sources") -> 0 | D12: =HYPERLINK("#A90","6 · Échéancier") -> 0 | E12: =HYPERLINK("#A161","7 · Noyau") -> 0 | F12: =HYPERLINK("#A188","8 · Grille") -> 0 | G12: =HYPERLINK("#A256","11 · Plafonds") -> 0 | H12: =HYPERLINK("#A279","13 · Commentaires") -> 0
A13: 1 · IDENTIFICATION ET ROUTAGE — codes du client et du projet ; le routage pilote seuils et poids
A14: Axe | B14: Valeur | C14: Libellé, contrôle | P14: 1 · Code client T24 | Q14: B15 | R14: =IF(AND(LEN(TRIM($B$15))>=1,LEN($B$15)<=20),1,0) -> 0
A15: Code client T24 (société de projet) | B15: 20089133 | C15: =IF(B15="","À saisir — Texte, zéros de tête conservés.",IF(AND(LEN(TRIM(B15))>=1,LEN(B15)<=20),"Format conforme.","Format non conforme : Texte, zéros de tête conservés.")) -> 0 | P15: 1 · Radical du client (7 chiffres) | Q15: B16 | R15: =IF(AND(LEN($B$16)=7,SUMPRODUCT(--ISNUMBER(FIND(MID($B$16,ROW(INDIRECT("1:7"))+0,1),"0123456789")))=7),1,0) -> 0
A16: Radical du client (7 chiffres) | B16: 0089133 | C16: =IF(B16="","À saisir — Exactement 7 chiffres, zéros de tête compris.",IF(AND(LEN(B16)=7,SUMPRODUCT(--ISNUMBER(FIND(MID(B16,ROW(INDIRECT("1:7"))+0,1),"0123456789")))=7),"Format conforme.","Format non conforme : Exactement 7 chiffres, zéros de tête compris.")) -> 0 | P16: 1 · Code projet (PF-AAAA-NNNN) | Q16: B17 | R16: =IF(AND(LEN($B$17)=12,EXACT(LEFT($B$17,3),"PF-"),MID($B$17,8,1)="-",SUMPRODUCT(--ISNUMBER(FIND(MID($B$17,ROW(INDIRECT("1:4"))+3,1),"0123456789")))=4,SUMPRODUCT(--ISNUMBER(FIND(MID($B$17,ROW(INDIRECT("1:4"))+8,1),"0123456789")))=4),1,0) -> 0
A17: Code projet | B17: PF-2026-0005 | C17: =IF(B17="","À saisir — Format PF-AAAA-NNNN.",IF(AND(LEN(B17)=12,EXACT(LEFT(B17,3),"PF-"),MID(B17,8,1)="-",SUMPRODUCT(--ISNUMBER(FIND(MID(B17,ROW(INDIRECT("1:4"))+3,1),"0123456789")))=4,SUMPRODUCT(--ISNUMBER(FIND(MID(B17,ROW(INDIRECT("1:4"))+8,1),"0123456789")))=4),"Format conforme.","Format non conforme : Format PF-AAAA-NNNN.")) -> 0 | P17: 1 · Régime de revenus | Q17: B18 | R17: =IF($B$18<>"",1,0) -> 0
A18: C — Régime de revenus | B18: R1 | C18: =IFERROR(INDEX(P_RegLib,MATCH(B18,P_Regimes,0)),"") -> 0 | P18: 1 · Secteur du projet | Q18: B19 | R18: =IF($B$19<>"",1,0) -> 0
A19: D — Secteur du projet | B19: ENR | C19: =IFERROR(INDEX(P_SecLib,MATCH(B19,P_SecCodes,0)),"") -> 0 | P19: 1 · Phase du projet | Q19: B20 | R19: =IF($B$20<>"",1,0) -> 0
A20: B — Phase | B20: P1 | C20: =IFERROR(INDEX(P_PhaseLib,MATCH(B20,P_PhaseCodes,0)),"") -> 0 | P20: 1 · Périodicité des échéances | Q20: B21 | R20: =IF($B$21<>"",1,0) -> 0
A21: Périodicité du service de la dette | B21: Semestrielle | C21: Jamais annuelle : le DSCR se mesure échéance par échéance. | P21: 2 · Exposition de la banque (MMAD) | Q21: B26 | R21: =IF(ISNUMBER($B$26),1,0) -> 0
A22: A — Famille de financement | B22: PF-FLUX | C22: SPV dédiée, remboursement par les flux du projet (R5 vente d'actifs : hors outil). | P22: 2 · Recettes, coûts et dette en dirhams ? | Q22: B27 | R22: =IF($B$27<>"",1,0) -> 0
P23: 2 · Durée du financement (ans) | Q23: B28 | R23: =IF(ISNUMBER($B$28),1,0) -> 0
A24: 2 · RÉGIME DE PROPORTIONNALITÉ — calculé, jamais choisi | P24: 2 · Technologie éprouvée ? | Q24: B29 | R24: =IF($B$29<>"",1,0) -> 0
A25: CAPEX du projet économique complet (MMAD) | B25: =B50 -> 0 | C25: Repris du total des emplois (section 3). | P25: 2 · EPC clé-en-main de moins de 18 mois ? (phase P1) | Q25: B30 | R25: =IF(OR(NOT($B$20="P1"),$B$30<>""),1,0) -> 0
A26: Exposition de la banque (MMAD) | B26: 60 | P26: 2 · Acheteur principal unique ? | Q26: B31 | R26: =IF($B$31<>"",1,0) -> 0
A27: Recettes, coûts et dette intégralement en dirhams | B27: Oui | P27: 2 · Première référence technologique ? | Q27: B32 | R27: =IF($B$32<>"",1,0) -> 0
A28: Durée du financement (ans) | B28: 12 | P28: 2 · Opération consortiale ? | Q28: B33 | R28: =IF($B$33<>"",1,0) -> 0
A29: Technologie : ≥ 3 références industrielles de plus de 3 ans | B29: Oui | P29: 2 · Contrat de revenus de plus de 20 ans ? | Q29: B34 | R29: =IF($B$34<>"",1,0) -> 0
A30: En P1 : EPC clé-en-main forfaitaire, prix et délai garantis, < 18 mois | B30: Oui | P30: 2 · Site à risque climatique élevé ? | Q30: B35 | R30: =IF($B$35<>"",1,0) -> 0
A31: Acheteur principal unique et identifié | B31: Oui | P31: 2 · Nombre de contreparties clés | Q31: B36 | R31: =IF(ISNUMBER($B$36),1,0) -> 0
A32: Technologie constituant une première référence dans la juridiction | B32: Non | P32: 3 · Emplois : montants du besoin à terminaison | Q32: B42 | R32: =IF(N($B$50)>0,1,0) -> 0
A33: Opération consortiale relevant de la directive 3/W/2025 | B33: Non | P33: 3 · Ressources engagées : montants | Q33: E42 | R33: =IF(N($E$50)>0,1,0) -> 0
A34: Concession ou contrat de revenus de plus de 20 ans | B34: Non | P34: 3 · Nature de chaque ressource | Q34: F42 | R34: =IF(SUMPRODUCT(ISNUMBER($E$42:$E$49)*($F$42:$F$49=""))=0,1,0) -> 0
A35: Site classé à risque climatique physique élevé | B35: Non | P35: 3 · Plan de remédiation (couverture entre 95 et 100 %) | Q35: B53 | R35: =IF(OR(NOT(AND($B$20="P1",ISNUMBER($B$51),N($B$51)>=P_N3_V,N($B$51)<P_N3_F)),$B$53<>""),1,0) -> 0
A36: Nombre de contreparties clés | B36: 2 | P36: 6 · Choc du scénario défavorable (%) | Q36: B91 | R36: =IF(ISNUMBER($B$91),1,0) -> 0
A37: Régime calculé (avant escalade) | B37: =IF(OR(B25="",B25=0,B18=""),"",IF(OR(B25>P_L_CAPEX,N(B26)>P_L_EXPO,B18="R4",B32="Oui",N(B174)>0,B33="Oui",B34="Oui",B35="Oui",N(B36)>P_L_NBCP),"L",IF(AND(B25<=P_S_CAPEX,B26<>"",N(B26)<=P_S_EXPO,OR(B18="R1",B18="R2"),B29="Oui",B27="Oui",B28<>"",N(B28)<=P_S_DUREE,OR(B20<>"P1",B30="Oui"),B31="Oui",COUNTIF($F$243:$F$254,"Oui")=0),"S","M"))) -> 0 | C37: =IF(B37="","",IF(B37="L","Escalade : "&IF(B25>P_L_CAPEX,"CAPEX > "&P_L_CAPEX&" MMAD ; ","")&IF(N(B26)>P_L_EXPO,"exposition > "&P_L_EXPO&" MMAD ; ","")&IF(B18="R4","régime de revenus R4 ; ","")&IF(B32="Oui","première référence technologique ; ","")&IF(N(B174)>0,"devises non intégralement couvertes ; ","")&IF(B33="Oui","opération consortiale ; ","")&IF(B34="Oui","contrat de revenus > 20 ans ; ","")&IF(B35="Oui","risque climatique élevé ; ","")&IF(N(B36)>P_L_NBCP,"plus de "&P_L_NBCP&" contreparties clés ; ",""),IF(B37="S","Toutes les conditions du régime simplifié sont réunies.","Régime standard par défaut : une condition du régime S manque, aucune condition d'escalade."))) -> 0 | P37: 6 · Échéancier : CFADS d'au moins deux périodes | Q37: B93 | R37: =IF(COUNT($B$93:$B$152)>=2,1,0) -> 0
A38: RÉGIME RETENU (après escalade automatique) | B38: =IF(B37="","",IF(AND(IF(AND(B37="S",COUNTIF($F$243:$F$254,"Oui")>0),"M",B37)="M",COUNTIF($E$258:$E$272,"Oui")>0),"L",IF(AND(B37="S",COUNTIF($F$243:$F$254,"Oui")>0),"M",B37))) -> 0 | C38: =IF(B38=B37,"Aucune escalade.",IF(B38="L","Escalade : un plafond de note est actif (M passe en L).","Escalade : un verrou est actif (S passe en M).")) -> 0 | P38: 6 · Service de la dette de chaque période | Q38: C93 | R38: =IF(SUMPRODUCT(ISNUMBER($B$93:$B$152)*(1-ISNUMBER($C$93:$C$152)))=0,1,0) -> 0
P39: 7 · N4 — Liquidité : situation à choisir | Q39: E166 | R39: =IF($B$166<>"",1,0) -> 0
A40: 3 · SOURCES ET EMPLOIS (MMAD) — test de financement à terminaison ; crédits de la banque | P40: 7 · N5 — Levier : situation à choisir | Q40: E167 | R40: =IF($B$167<>"",1,0) -> 0
A41: Emplois | B41: Montant | D41: Ressources | E41: Montant | F41: Nature | P41: 7 · N6 — Exposition résiduelle : situation à choisir | Q41: E168 | R41: =IF($B$168<>"",1,0) -> 0
A42: Contrat EPC clé-en-main | B42: 88 | D42: Dette senior (12 ans, 6,0 %) | E42: 60 | F42: Dette senior | P42: 7 · Justification exigée (N4 à N6 Critique ou Info. insuffisante) | Q42: ="H"&IF(COUNT($T$166:$T$168)=0,166,MIN($T$166:$T$168)) -> 0 | R42: =IF(COUNT($T$166:$T$168)=0,1,0) -> 0
A43: Raccordement et poste de livraison | B43: 7 | D43: Fonds propres | E43: 48 | F43: Fonds propres | P43: 7 · N3 hors phase P1 : note LLCR | Q43: B171 | R43: =IF(OR($B$20="P1",$B$171<>""),1,0) -> 0
A44: Frais et contingence | B44: 5 | P44: 7 · LLCR (plafond C4) | Q44: B172 | R44: =IF(ISNUMBER($B$172),1,0) -> 0
A45: Intérêts intercalaires | B45: 2 | P45: 7 · DSRA en mois (plafond C7) | Q45: B173 | R45: =IF(ISNUMBER($B$173),1,0) -> 0
A46: Dotation DSRA | B46: 3.6 | P46: 7 · Exposition nette en devises (plafond C6) | Q46: B174 | R46: =IF(ISNUMBER($B$174),1,0) -> 0
P47: 7 · Dette à refinancer à maturité (plafond C8) | Q47: B175 | R47: =IF(ISNUMBER($B$175),1,0) -> 0
P48: 7 · Stratégie de refinancement approuvée ? | Q48: B176 | R48: =IF(OR(N($B$175)<=P_C8,$B$176<>""),1,0) -> 0
P49: 7 · Part des recettes de l'acheteur principal (C10) | Q49: B177 | R49: =IF(ISNUMBER($B$177),1,0) -> 0
A50: Total emplois (besoin à terminaison) | B50: =SUM(B42:B49) -> 0 | D50: Total ressources engagées | E50: =SUM(E42:E49) -> 0 | P50: 7 · Qualité de crédit de l'acheteur principal | Q50: B178 | R50: =IF($B$178<>"",1,0) -> 0
A51: Couverture du besoin à terminaison (ressources / emplois) | B51: =IF(N(B50)=0,"",E50/B50) -> 0 | P51: 7 · Durée résiduelle du contrat de revenus (C5) | Q51: B179 | R51: =IF(OR($B$18="R4",ISNUMBER($B$179)),1,0) -> 0
A52: Quote-part de dette (dette / besoin à terminaison) | B52: =IF(N(B50)=0,"",(SUMIF(F42:F49,"Dette senior",E42:E49)+SUMIF(F42:F49,"Dette subordonnée",E42:E49))/B50) -> 0 | P52: 7 · Durée résiduelle de la dette | Q52: B180 | R52: =IF(ISNUMBER($B$180),1,0) -> 0
A53: Plan de remédiation approuvé (couverture entre 95 % et 100 %) | B53: Non | P53: 7 · Solution documentée (contrat plus court que la dette) ? | Q53: B181 | R53: =IF(OR(NOT(AND(ISNUMBER($B$179),ISNUMBER($B$180))),N($B$179)>=N($B$180),$B$181<>""),1,0) -> 0
P54: 7 · Plan d'adaptation climatique financé ? (C11) | Q54: B182 | R54: =IF(OR($B$35<>"Oui",$B$182<>""),1,0) -> 0
A55: Crédits de la banque sur le projet — un projet peut porter plusieurs dossiers de crédit | P55: 7 · Capacité résiduelle du sponsor (C12) | Q55: B183 | R55: =IF($B$183<>"",1,0) -> 0
A56: Numéro du dossier de crédit | B56: Nature | E56: Montant (MMAD) | F56: Devise | G56: Durée (ans) | H56: Observation | P56: 7 · Opérateur remplaçable ? (C13) | Q56: B184 | R56: =IF($B$184<>"",1,0) -> 0
A57: CR-26-0501 | B57: Crédit d'investissement (moyen et long terme) | E57: 60 | F57: MAD | G57: 12 | P57: 7 · Écart fin O&M / fin de dette (opérateur non remplaçable) | Q57: B185 | R57: =IF(OR($B$184<>"Non",ISNUMBER($B$185)),1,0) -> 0
P58: 7 · Facteur commun au-delà de la limite interne (C14) | Q58: B186 | R58: =IF($B$186<>"",1,0) -> 0
P59: 8 · Grille : sous-critère requis sans situation choisie | Q59: ="E"&IF(COUNT($P$190:$P$222)=0,191,MIN($P$190:$P$222)) -> 0 | R59: =IF(COUNT($P$190:$P$222)=0,1,0) -> 0
